Workbook

Sheet 1 Balance sheet
A1: BILAN PREVISIONNEL
A3: ALL AMOUNTS IN KEUR | B3: Actual 08/2020 | C3: Estimé 2020 | D3: 2021 | E3: 2022 | F3: 2023
A4: Immobilisations corporelles/ incorporelles | B4: =SUM(B5:B6) -> 1870.4446 | C4: =SUM(C5:C6) -> 1881.4578 | D4: =SUM(D5:D6) -> 2111.6055 | E4: =SUM(E5:E6) -> 2634.0101 | F4: =SUM(F5:F6) -> 2950.6057
A5: Immobilisations | B5: 2987.6658 | C5: 3129.3648 | D5: =C5+400/3+'2 P&L'!D45+'2 P&L'!E45+'2 P&L'!F45+'2 P&L'!G45 -> 3863.4731 | E5: =D5+400/3+'2 P&L'!H45+'2 P&L'!I45+'2 P&L'!J45+'2 P&L'!K45 -> 5025.5815 | F5: =E5+400/3+'2 P&L'!L45+'2 P&L'!M45+'2 P&L'!N45+'2 P&L'!O45 -> 6077.6898 | G5: =F5-C5 -> 2948.325
A6: Amortissement | B6: -1117.2212 | C6: -1247.907 | D6: =C6+'[1]Recap Amortissement'!$E$10 -> -1751.8676 | E6: =D6+'[1]Recap Amortissement'!$I$10 -> -2391.5713 | F6: =E6+'[1]Recap Amortissement'!$M$10 -> -3127.0841 | G6: =F6-C6 -> -1879.1771
A7: Immobilisations financières | B7: 7.05 | C7: =B7 -> 7.05 | D7: =C7 -> 7.05 | E7: =D7 -> 7.05 | F7: =E7 -> 7.05 | G7: =D6-C6 -> -503.96067
A8: Actifs immobilisés | B8: =B4+B7 -> 1877.4946 | C8: =C4+C7 -> 1888.5078 | D8: =D4+D7 -> 2118.6555 | E8: =E4+E7 -> 2641.0601 | F8: =F4+F7 -> 2957.6557 | G8: =D5-C5 -> 734.10833
A9: Stocks | B9: 7.37821 | C9: 7.37821 | D9: =C9 -> 7.37821 | E9: =D9 -> 7.37821 | F9: =E9 -> 7.37821
A10: Créances commerciales | B10: 5.83226 | C10: 5.83226 | D10: =C10-'3 Cash Flow'!G4 -> 582.6619 | E10: =C10-'3 Cash Flow'!L4 -> 353.986 | F10: =C10-'3 Cash Flow'!Q4 -> 542.90593
A11: Autres créances | B11: 36.4293 | C11: 36.4293 | D11: =C11 -> 36.4293 | E11: =D11 -> 36.4293 | F11: =E11 -> 36.4293
A12: Cash & équivalents | B12: =SUM(B13:B22) -> 523.59175 | C12: =SUM(C13:C22) -> 129.3068 | D12: =SUM(D13:D22) -> 1515.034 | E12: =SUM(E13:E22) -> 2876.1213 | F12: =SUM(F13:F22) -> 4998.983
A13: Opening cash | B13: 523.59175 | C13: =B13 -> 523.59175 | D13: =C12 -> 129.3068 | E13: =D12 -> 1515.034 | F13: =E12 -> 2876.1213
A14: Apport capital | B14: 0 | C14: 0 | D14: 4000 | E14: 2000 | F14: 0
A15: Revenus | B15: 0 | C15: 67.824 | D15: =SUM('2 P&L'!D12:G12) -> 1298.3469 | E15: =SUM('2 P&L'!H12:K12)-D16 -> 5051.8169 | F15: =SUM('2 P&L'!L12:O12)-E16 -> 9120.496
A16: Revenus non perçus | B16: 0 | C16: 0 | D16: ='3 Cash Flow'!G4 -> -576.82964 | E16: ='3 Cash Flow'!L4 -> -348.15374 | F16: ='3 Cash Flow'!Q4 -> -537.07367
A17: Acquisitions immobilisations | B17: 0 | C17: 0 | D17: =-400/3 -> -133.33333 | E17: =-400/3 -> -133.33333 | F17: =-400/3 -> -133.33333
A18: Subsides reçus | B18: 0 | C18: 0 | D18: 0 | E18: 0 | F18: 0
A19: Payroll & OPEX & coûts financiers | B19: 0 | C19: -462.10895 | D19: =SUM('2 P&L'!D47:G48)+SUM('2 P&L'!D54:G54) -> -3044.5721 | E19: =SUM('2 P&L'!H47:K48)+SUM('2 P&L'!H54:K54)-D20 -> -4441.7749 | F19: =SUM('2 P&L'!L47:O48)+SUM('2 P&L'!L54:O54)-E20 -> -4976.5772
A20: Report des paiements OPEX | B20: 0 | C20: 0 | D20: ='3 Cash Flow'!G3 -> 86.776689 | E20: ='3 Cash Flow'!L3 -> -8.6664991 | F20: ='3 Cash Flow'!Q3 -> 4.8749216
A21: Achat stock | B21: 0 | C21: 0 | D21: =SUM('2 P&L'!D13:G13) -> -244.66123 | E21: =SUM('2 P&L'!H13:K13) -> -758.80113 | F21: =SUM('2 P&L'!L13:O13) -> -1355.525
A22: Impôts sur le résultat | B22: ='[2]P&L'!B38 -> 0 | C22: 0 | D22: 0 | E22: 0 | F22: 0
A23: Comptes de régularisation | B23: 0 | C23: 0 | D23: 0 | E23: 0 | F23: 0
A24: Actifs circulants | B24: =+B12+B11+B23+B10+B9 -> 573.23152 | C24: =+C12+C11+C23+C10+C9 -> 178.94657 | D24: =+D12+D11+D23+D10+D9 -> 2141.5034 | E24: =+E12+E11+E23+E10+E9 -> 3273.9148 | F24: =+F12+F11+F23+F10+F9 -> 5585.6965
A25: TOTAL ACTIF | B25: =B8+B24 -> 2450.7261 | C25: =C8+C24 -> 2067.4544 | D25: =D8+D24 -> 4260.1589 | E25: =E8+E24 -> 5914.9749 | F25: =F8+F24 -> 8543.3522
A27: Capital | B27: 4650.315 | C27: =B27 -> 4650.315 | D27: =C27+4000 -> 8650.315 | E27: =D27+2000 -> 10650.315 | F27: =E27 -> 10650.315
A28: Réserves & résultat reporté | B28: -2386.6292 | C28: =B28+C15+C19+C4-B4 -> -2769.9009 | D28: =C28+SUM('2 P&L'!D62:G62) -> -4663.973 | E28: =D28+SUM('2 P&L'!H62:K62) -> -4913.7139 | F28: =E28+SUM('2 P&L'!L62:O62) -> -2298.878 | G28: =F28-C28 -> 471.02285
A29: Subsides | B29: 0 | C29: =B29 -> 0 | D29: =C29 -> 0 | E29: =D29 -> 0 | F29: =E29 -> 0
A30: Fonds propres | B30: =SUM(B27:B29) -> 2263.6859 | C30: =SUM(C27:C29) -> 1880.4142 | D30: =SUM(D27:D29) -> 3986.342 | E30: =SUM(E27:E29) -> 5736.6012 | F30: =SUM(F27:F29) -> 8351.437
A31: Provisions pour risques et charges | B31: 0 | C31: =B31 -> 0 | D31: =C31 -> 0 | E31: =D31 -> 0 | F31: =E31 -> 0
A32: Dettes financières long terme | B32: 94.28986 | C32: =B32 -> 94.28986 | D32: =C32 -> 94.28986 | E32: =D32 -> 94.28986 | F32: =E32 -> 94.28986
A33: Dettes financières court terme | B33: 0 | C33: =B33 -> 0 | D33: =C33 -> 0 | E33: =D33 -> 0 | F33: =E33 -> 0
A34: Dettes commerciales | B34: 107.13429 | C34: =B34 -> 107.13429 | D34: =C34+'3 Cash Flow'!G3 -> 193.91098 | E34: =C34+'3 Cash Flow'!L3 -> 98.467791 | F34: =C34+'3 Cash Flow'!Q3 -> 112.00921
A35: Dettes fiscales, salariales et sociales | B35: 32.62096 | C35: =B35 -> 32.62096 | D35: =C35 -> 32.62096 | E35: =D35 -> 32.62096 | F35: =E35 -> 32.62096
A36: Autres dettes | B36: -47.00488 | C36: =B36 -> -47.00488 | D36: =C36 -> -47.00488 | E36: =D36 -> -47.00488 | F36: =E36 -> -47.00488
A37: Comptes de régularisation | B37: 0 | C37: =B37 -> 0 | D37: =C37 -> 0 | E37: =D37 -> 0 | F37: =E37 -> 0
A38: Autres passifs | B38: =SUM(B31:B36,B37) -> 187.04023 | C38: =SUM(C31:C36,C37) -> 187.04023 | D38: =SUM(D31:D36,D37) -> 273.81692 | E38: =SUM(E31:E36,E37) -> 178.37373 | F38: =SUM(F31:F36,F37) -> 191.91515
A39: TOTAL PASSIF | B39: =+B38+B30 -> 2450.7261 | C39: =+C38+C30 -> 2067.4544 | D39: =+D38+D30 -> 4260.1589 | E39: =+E38+E30 -> 5914.9749 | F39: =+F38+F30 -> 8543.3522
B40: =+B39-B25 -> 0 | C40: =+C39-C25 -> 0 | D40: =+D39-D25 -> 0 | E40: =+E39-E25 -> 0 | F40: =+F39-F25 -> 0

Sheet 2 P&L
B2: DATA FROM sales V8.4 / somme corrections in 8.6 not included
C4: PROFIT AND LOSS | D4: YEAR 1 | H4: Year2 | L4: Year3
C5: ALL AMOUNTS IN KEUR | D5: Q1 | E5: Q2 | F5: Q3 | G5: Q4 | H5: Q1 | I5: Q2 | J5: Q3 | K5: Q4 | L5: Q1 | M5: Q2 | N5: Q3 | O5: Q4 | P5: TOTAL | Q5: Comments
C6: T1 -Hospital market | D6: ='Tableau recap'!E4 -> 23.585794 | E6: ='Tableau recap'!F4 -> 47.171589 | F6: ='Tableau recap'!G4 -> 99.51492 | G6: ='Tableau recap'!H4 -> 373.10071 | H6: ='Tableau recap'!I4 -> 280.07969 | I6: ='Tableau recap'!J4 -> 402.23186 | J6: ='Tableau recap'!K4 -> 524.38404 | K6: ='Tableau recap'!L4 -> 646.53622 | ... O6: ='Tableau recap'!P4 -> 1210.0564 | P6: =SUM(D6:O6) -> 7236.8303
C7: T2 - Homecare market | D7: ='Tableau recap'!E14 -> 12.018168 | E7: ='Tableau recap'!F14 -> 35.574767 | F7: ='Tableau recap'!G14 -> 53.362151 | G7: ='Tableau recap'!H14 -> 76.918751 | H7: ='Tableau recap'!I14 -> 238.18886 | I7: ='Tableau recap'!J14 -> 238.18886 | J7: ='Tableau recap'!K14 -> 238.18886 | K7: ='Tableau recap'!L14 -> 238.18886 | ... O7: ='Tableau recap'!P14 -> 485.3042 | P7: =SUM(D7:O7) -> 3071.8461
C8: T3 - Nutrow & Feedim evolution | D8: ='Tableau recap'!E24 -> 0 | E8: ='Tableau recap'!F24 -> 0 | F8: ='Tableau recap'!G24 -> 0 | G8: ='Tableau recap'!H24 -> 0 | H8: ='Tableau recap'!I24 -> 0 | I8: ='Tableau recap'!J24 -> 0 | J8: ='Tableau recap'!K24 -> 0 | K8: ='Tableau recap'!L24 -> 0 | ... O8: ='Tableau recap'!P24 -> 0 | P8: =SUM(D8:O8) -> 0
C9: T4 - Oncology development | D9: ='Tableau recap'!E34 -> 0 | E9: ='Tableau recap'!F34 -> 0 | F9: ='Tableau recap'!G34 -> 0 | G9: ='Tableau recap'!H34 -> 0 | H9: ='Tableau recap'!I34 -> 0 | I9: ='Tableau recap'!J34 -> 0 | J9: ='Tableau recap'!K34 -> 0 | K9: ='Tableau recap'!L34 -> 0 | ... O9: ='Tableau recap'!P34 -> 0 | P9: =SUM(D9:O9) -> 0
C10: T5 - Operations | D10: ='Tableau recap'!E44 -> 48.125 | E10: ='Tableau recap'!F44 -> 20.625 | F10: ='Tableau recap'!G44 -> 48.125 | G10: ='Tableau recap'!H44 -> 20.625 | H10: ='Tableau recap'!I44 -> 90.75 | I10: ='Tableau recap'!J44 -> 140.25 | J10: ='Tableau recap'!K44 -> 189.75 | K10: ='Tableau recap'!L44 -> 239.25 | ... O10: ='Tableau recap'!P44 -> 103.125 | P10: =SUM(D10:O10) -> 1210
C11: T6 - OEM Feedim | D11: ='Tableau recap'!E54 -> 0 | E11: ='Tableau recap'!F54 -> 45 | F11: ='Tableau recap'!G54 -> 0 | G11: ='Tableau recap'!H54 -> 394.6 | H11: ='Tableau recap'!I54 -> 218.5 | I11: ='Tableau recap'!J54 -> 263.5 | J11: ='Tableau recap'!K54 -> 263.5 | K11: ='Tableau recap'!L54 -> 263.5 | ... O11: ='Tableau recap'!P54 -> 394.6 | P11: =SUM(D11:O11) -> 3027
C12: TOTAL REVENUE | D12: =SUM(D6:D11) -> 83.728962 | E12: =SUM(E6:E11) -> 148.37136 | F12: =SUM(F6:F11) -> 201.00207 | G12: =SUM(G6:G11) -> 865.24447 | H12: =SUM(H6:H11) -> 827.51854 | I12: =SUM(I6:I11) -> 1044.1707 | J12: =SUM(J6:J11) -> 1215.8229 | K12: =SUM(K6:K11) -> 1387.4751 | ... P12: =SUM(P6:P11) -> 14545.676
A13: 22 | C13: COGS | D13: =-'Tableau recap'!E93 -> -2.3482652 | E13: =-'Tableau recap'!F93 -> -8.6851811 | F13: =-'Tableau recap'!G93 -> -14.029459 | G13: =-'Tableau recap'!H93 -> -219.59833 | H13: =-'Tableau recap'!I93 -> -184.37366 | I13: =-'Tableau recap'!J93 -> -187.92474 | J13: =-'Tableau recap'!K93 -> -191.47582 | K13: =-'Tableau recap'!L93 -> -195.02691 | ... O13: =-'Tableau recap'!P93 -> -338.88125 | P13: =SUM(D13:O13) -> -2358.9874
C14: Variation de stock | D14: =COGS!C21/1000 -> 0 | E14: =COGS!D21/1000 -> 0 | F14: =COGS!E21/1000 -> 0 | G14: =COGS!F21/1000 -> 0 | H14: =COGS!G21/1000 -> 0 | I14: =COGS!H21/1000 -> 0 | J14: =COGS!I21/1000 -> 0 | K14: =COGS!J21/1000 -> 0 | ... O14: =COGS!N21/1000 -> 0 | P14: =SUM(D14:O14) -> 0
C15: TOTAL COGS | D15: =SUM(D13:D14) -> -2.3482652 | E15: =SUM(E13:E14) -> -8.6851811 | F15: =SUM(F13:F14) -> -14.029459 | G15: =SUM(G13:G14) -> -219.59833 | H15: =SUM(H13:H14) -> -184.37366 | I15: =SUM(I13:I14) -> -187.92474 | J15: =SUM(J13:J14) -> -191.47582 | K15: =SUM(K13:K14) -> -195.02691 | ... P15: =SUM(P13:P14) -> -2358.9874
C16: GROSS MARGIN | D16: =D12+D15 -> 81.380697 | E16: =E12+E15 -> 139.68617 | F16: =F12+F15 -> 186.97261 | G16: =G12+G15 -> 645.64614 | H16: =H12+H15 -> 643.14489 | I16: =I12+I15 -> 856.24598 | J16: =J12+J15 -> 1024.3471 | K16: =K12+K15 -> 1192.4482 | ... P16: =P12+P15 -> 12186.689
C17: GROSS MARGIN Rate | D17: =D16/D12 -> 0.97195397 | E17: =E16/E12 -> 0.94146322 | F17: =F16/F12 -> 0.93020242 | G17: =G16/G12 -> 0.74620083 | H17: =H16/H12 -> 0.77719695 | I17: =I16/I12 -> 0.82002489 | J17: =J16/J12 -> 0.84251339 | K17: =K16/K12 -> 0.85943754 | ... P17: =P16/P12 -> 0.83782209
A18: 10 | B18: HR/Admin | C18: Directors | D18: =-'Recap costs'!H33/1000 -> -9 | E18: =-'Recap costs'!I33/1000 -> -9 | F18: =-'Recap costs'!J33/1000 -> -9 | G18: =-'Recap costs'!K33/1000 -> -9 | H18: =-'Recap costs'!L33/1000 -> -9 | I18: =-'Recap costs'!M33/1000 -> -9 | J18: =-'Recap costs'!N33/1000 -> -9 | K18: =-'Recap costs'!O33/1000 -> -9 | ... O18: =-'Recap costs'!S33/1000 -> -9 | P18: =SUM(D18:O18) -> -108
A19: 11 | C19: Employees & Freelances | D19: =SUM(D20:D26) -> -327.61809 | E19: =SUM(E20:E26) -> -514.49309 | F19: =SUM(F20:F26) -> -551.59309 | G19: =SUM(G20:G26) -> -706.44309 | H19: =SUM(H20:H26) -> -867.84309 | I19: =SUM(I20:I26) -> -837.59309 | J19: =SUM(J20:J26) -> -864.34309 | K19: =SUM(K20:K26) -> -922.09309 | ... O19: =SUM(O20:O26) -> -1041.6931 | P19: =SUM(D19:O19) -> -9573.442
C20: T1 -Hospital market: Baxter & DIM 3 Pilot | D20: =-('PT Recap costs'!B48+'PT Recap costs'!B49)/1000 -> -13.47309 | E20: =-('PT Recap costs'!C48+'PT Recap costs'!C49)/1000 -> -82.91059 | F20: =-('PT Recap costs'!D48+'PT Recap costs'!D49)/1000 -> -82.91059 | G20: =-('PT Recap costs'!E48+'PT Recap costs'!E49)/1000 -> -105.46059 | H20: =-('PT Recap costs'!F48+'PT Recap costs'!F49)/1000 -> -109.03559 | I20: =-('PT Recap costs'!G48+'PT Recap costs'!G49)/1000 -> -109.03559 | J20: =-('PT Recap costs'!H48+'PT Recap costs'!H49)/1000 -> -109.03559 | K20: =-('PT Recap costs'!I48+'PT Recap costs'!I49)/1000 -> -109.03559 | ... O20: =-('PT Recap costs'!M48+'PT Recap costs'!M49)/1000 -> -120.31059 | P20: =SUM(D20:O20) -> -1190.8646
C21: T2 - Homecare market: Vivisol | D21: =-('PT Recap costs'!B52+'PT Recap costs'!B53)/1000 -> -13.47309 | E21: =-('PT Recap costs'!C52+'PT Recap costs'!C53)/1000 -> -82.91059 | F21: =-('PT Recap costs'!D52+'PT Recap costs'!D53)/1000 -> -82.91059 | G21: =-('PT Recap costs'!E52+'PT Recap costs'!E53)/1000 -> -105.46059 | H21: =-('PT Recap costs'!F52+'PT Recap costs'!F53)/1000 -> -109.03559 | I21: =-('PT Recap costs'!G52+'PT Recap costs'!G53)/1000 -> -109.03559 | J21: =-('PT Recap costs'!H52+'PT Recap costs'!H53)/1000 -> -109.03559 | K21: =-('PT Recap costs'!I52+'PT Recap costs'!I53)/1000 -> -109.03559 | ... O21: =-('PT Recap costs'!M52+'PT Recap costs'!M53)/1000 -> -120.31059 | P21: =SUM(D21:O21) -> -1190.8646
C22: T3 - Nutrow & Feedim evolution | D22: =-('PT Recap costs'!B56+'PT Recap costs'!B57)/1000 -> -100.67891 | E22: =-('PT Recap costs'!C56+'PT Recap costs'!C57)/1000 -> -103.42891 | F22: =-('PT Recap costs'!D56+'PT Recap costs'!D57)/1000 -> -98.715611 | G22: =-('PT Recap costs'!E56+'PT Recap costs'!E57)/1000 -> -178.46561 | H22: =-('PT Recap costs'!F56+'PT Recap costs'!F57)/1000 -> -213.42891 | I22: =-('PT Recap costs'!G56+'PT Recap costs'!G57)/1000 -> -183.17891 | J22: =-('PT Recap costs'!H56+'PT Recap costs'!H57)/1000 -> -106.17891 | K22: =-('PT Recap costs'!I56+'PT Recap costs'!I57)/1000 -> -144.67891 | ... O22: =-('PT Recap costs'!M56+'PT Recap costs'!M57)/1000 -> -235.42891 | P22: =SUM(D22:O22) -> -1930.2203
C23: T4 - Oncology: development | D23: =-('PT Recap costs'!B60+'PT Recap costs'!B61)/1000 -> -11.25 | E23: =-('PT Recap costs'!C60+'PT Recap costs'!C61)/1000 -> -41.5 | F23: =-('PT Recap costs'!D60+'PT Recap costs'!D61)/1000 -> -46.213295 | G23: =-('PT Recap costs'!E60+'PT Recap costs'!E61)/1000 -> -76.213295 | H23: =-('PT Recap costs'!F60+'PT Recap costs'!F61)/1000 -> -60.25 | I23: =-('PT Recap costs'!G60+'PT Recap costs'!G61)/1000 -> -60.25 | J23: =-('PT Recap costs'!H60+'PT Recap costs'!H61)/1000 -> -90.5 | K23: =-('PT Recap costs'!I60+'PT Recap costs'!I61)/1000 -> -109.75 | ... O23: =-('PT Recap costs'!M60+'PT Recap costs'!M61)/1000 -> -93.5 | P23: =SUM(D23:O23) -> -869.92659
C24: T5 - Operations organisation (Services): Installation & Interfaçage | D24: =-('PT Recap costs'!B64+'PT Recap costs'!B65)/1000 -> -27 | E24: =-('PT Recap costs'!C64+'PT Recap costs'!C65)/1000 -> -27 | F24: =-('PT Recap costs'!D64+'PT Recap costs'!D65)/1000 -> -27 | G24: =-('PT Recap costs'!E64+'PT Recap costs'!E65)/1000 -> -27 | H24: =-('PT Recap costs'!F64+'PT Recap costs'!F65)/1000 -> -134.25 | I24: =-('PT Recap costs'!G64+'PT Recap costs'!G65)/1000 -> -134.25 | J24: =-('PT Recap costs'!H64+'PT Recap costs'!H65)/1000 -> -117.75 | K24: =-('PT Recap costs'!I64+'PT Recap costs'!I65)/1000 -> -117.75 | ... O24: =-('PT Recap costs'!M64+'PT Recap costs'!M65)/1000 -> -129.025 | P24: =SUM(D24:O24) -> -1116.825
C25: T6 - OEM Feedim | D25: =-('PT Recap costs'!B68+'PT Recap costs'!B69)/1000 -> 0 | E25: =-('PT Recap costs'!C68+'PT Recap costs'!C69)/1000 -> -15 | F25: =-('PT Recap costs'!D68+'PT Recap costs'!D69)/1000 -> -30 | G25: =-('PT Recap costs'!E68+'PT Recap costs'!E69)/1000 -> -30 | H25: =-('PT Recap costs'!F68+'PT Recap costs'!F69)/1000 -> -30 | I25: =-('PT Recap costs'!G68+'PT Recap costs'!G69)/1000 -> -30 | J25: =-('PT Recap costs'!H68+'PT Recap costs'!H69)/1000 -> -120 | K25: =-('PT Recap costs'!I68+'PT Recap costs'!I69)/1000 -> -120 | ... O25: =-('PT Recap costs'!M68+'PT Recap costs'!M69)/1000 -> -131.275 | P25: =SUM(D25:O25) -> -888.825
C26: Other | D26: =-('PT Recap costs'!B72+'PT Recap costs'!B73)/1000-'Recap costs'!H31/1000-'Recap costs'!H60/1000-'Recap costs'!H61/1000 -> -161.743 | E26: =-('PT Recap costs'!C72+'PT Recap costs'!C73)/1000-'Recap costs'!I31/1000-'Recap costs'!I60/1000-'Recap costs'!I61/1000 -> -161.743 | F26: =-('PT Recap costs'!D72+'PT Recap costs'!D73)/1000-'Recap costs'!J31/1000-'Recap costs'!J60/1000-'Recap costs'!J61/1000 -> -183.843 | G26: =-('PT Recap costs'!E72+'PT Recap costs'!E73)/1000-'Recap costs'!K31/1000-'Recap costs'!K60/1000-'Recap costs'!K61/1000 -> -183.843 | H26: =-('PT Recap costs'!F72+'PT Recap costs'!F73)/1000-'Recap costs'!L31/1000-'Recap costs'!L60/1000-'Recap costs'!L61/1000 -> -211.843 | I26: =-('PT Recap costs'!G72+'PT Recap costs'!G73)/1000-'Recap costs'!M31/1000-'Recap costs'!M60/1000-'Recap costs'!M61/1000 -> -211.843 | J26: =-('PT Recap costs'!H72+'PT Recap costs'!H73)/1000-'Recap costs'!N31/1000-'Recap costs'!N60/1000-'Recap costs'!N61/1000 -> -211.843 | K26: =-('PT Recap costs'!I72+'PT Recap costs'!I73)/1000-'Recap costs'!O31/1000-'Recap costs'!O60/1000-'Recap costs'!O61/1000 -> -211.843 | ... O26: =-('PT Recap costs'!M72+'PT Recap costs'!M73)/1000-'Recap costs'!S31/1000-'Recap costs'!S60/1000-'Recap costs'!S61/1000 -> -211.843 | P26: =SUM(D26:O26) -> -2385.916
A27: 13 | B27: HR/Admin | C27: Recruitment | D27: =-'Recap costs'!H34/1000 -> -30 | E27: =-'Recap costs'!I34/1000 -> -60 | F27: =-'Recap costs'!J34/1000 -> 0 | G27: =-'Recap costs'!K34/1000 -> -40 | H27: =-'Recap costs'!L34/1000 -> -40 | I27: =-'Recap costs'!M34/1000 -> 0 | J27: =-'Recap costs'!N34/1000 -> -10 | K27: =-'Recap costs'!O34/1000 -> -30 | ... O27: =-'Recap costs'!S34/1000 -> -10 | P27: =SUM(D27:O27) -> -250
A28: 14 | B28: HR/Admin | C28: Training | D28: =-'Recap costs'!H35/1000 -> -10.5 | E28: =-'Recap costs'!I35/1000 -> -12.5 | F28: =-'Recap costs'!J35/1000 -> -13.5 | G28: =-'Recap costs'!K35/1000 -> -13.5 | H28: =-'Recap costs'!L35/1000 -> -12.5 | I28: =-'Recap costs'!M35/1000 -> -12.5 | J28: =-'Recap costs'!N35/1000 -> -12.5 | K28: =-'Recap costs'!O35/1000 -> -12.5 | ... O28: =-'Recap costs'!S35/1000 -> -13 | P28: =SUM(D28:O28) -> -152
A29: 15 | B29: Travel | C29: Travel | D29: =-('Recap costs'!H75+'Recap costs'!H76+'Recap costs'!H77+'Recap costs'!H78+'Recap costs'!H79+'Recap costs'!H80)/1000 -> -22.5 | E29: =-('Recap costs'!I75+'Recap costs'!I76+'Recap costs'!I77+'Recap costs'!I78+'Recap costs'!I79+'Recap costs'!I80)/1000 -> -22.5 | F29: =-('Recap costs'!J75+'Recap costs'!J76+'Recap costs'!J77+'Recap costs'!J78+'Recap costs'!J79+'Recap costs'!J80)/1000 -> -22.5 | G29: =-('Recap costs'!K75+'Recap costs'!K76+'Recap costs'!K77+'Recap costs'!K78+'Recap costs'!K79+'Recap costs'!K80)/1000 -> -22.5 | H29: =-('Recap costs'!L75+'Recap costs'!L76+'Recap costs'!L77+'Recap costs'!L78+'Recap costs'!L79+'Recap costs'!L80)/1000 -> -30 | I29: =-('Recap costs'!M75+'Recap costs'!M76+'Recap costs'!M77+'Recap costs'!M78+'Recap costs'!M79+'Recap costs'!M80)/1000 -> -30 | J29: =-('Recap costs'!N75+'Recap costs'!N76+'Recap costs'!N77+'Recap costs'!N78+'Recap costs'!N79+'Recap costs'!N80)/1000 -> -30 | K29: =-('Recap costs'!O75+'Recap costs'!O76+'Recap costs'!O77+'Recap costs'!O78+'Recap costs'!O79+'Recap costs'!O80)/1000 -> -30 | ... O29: =-('Recap costs'!S75+'Recap costs'!S76+'Recap costs'!S77+'Recap costs'!S78+'Recap costs'!S79+'Recap costs'!S80)/1000 -> -30 | P29: =SUM(D29:O29) -> -330
A30: 16 | C30: Consultancies | D30: =SUM(D31:D37) -> -137.86433 | E30: =SUM(E31:E37) -> -137.86433 | F30: =SUM(F31:F37) -> -130.86433 | G30: =SUM(G31:G37) -> -130.86433 | H30: =SUM(H31:H37) -> -85.864333 | I30: =SUM(I31:I37) -> -85.864333 | J30: =SUM(J31:J37) -> -85.864333 | K30: =SUM(K31:K37) -> -85.864333 | ... O30: =SUM(O31:O37) -> -85.864333 | P30: =SUM(D30:O30) -> -1224.372
C31: T1 -Hospital market: Baxter & DIM 3 Pilot | D31: =-'PT Recap costs'!B47/1000-'PT Recap costs'!B34/1000 -> -8.0615556 | E31: =-'PT Recap costs'!C47/1000-'PT Recap costs'!C34/1000 -> -8.0615556 | F31: =-'PT Recap costs'!D47/1000-'PT Recap costs'!D34/1000 -> -8.0615556 | G31: =-'PT Recap costs'!E47/1000-'PT Recap costs'!E34/1000 -> -8.0615556 | H31: =-'PT Recap costs'!F47/1000-'PT Recap costs'!F34/1000 -> -8.0615556 | I31: =-'PT Recap costs'!G47/1000-'PT Recap costs'!G34/1000 -> -8.0615556 | J31: =-'PT Recap costs'!H47/1000-'PT Recap costs'!H34/1000 -> -8.0615556 | K31: =-'PT Recap costs'!I47/1000-'PT Recap costs'!I34/1000 -> -8.0615556 | ... O31: =-'PT Recap costs'!M47/1000-'PT Recap costs'!M34/1000 -> -8.0615556 | P31: =SUM(D31:O31) -> -96.738667
C32: T2 - Homecare market: Vivisol | D32: =-'PT Recap costs'!B51/1000-'PT Recap costs'!B37/1000 -> -5.0555556 | E32: =-'PT Recap costs'!C51/1000-'PT Recap costs'!C37/1000 -> -5.0555556 | F32: =-'PT Recap costs'!D51/1000-'PT Recap costs'!D37/1000 -> -5.0555556 | G32: =-'PT Recap costs'!E51/1000-'PT Recap costs'!E37/1000 -> -5.0555556 | H32: =-'PT Recap costs'!F51/1000-'PT Recap costs'!F37/1000 -> -5.0555556 | I32: =-'PT Recap costs'!G51/1000-'PT Recap costs'!G37/1000 -> -5.0555556 | J32: =-'PT Recap costs'!H51/1000-'PT Recap costs'!H37/1000 -> -5.0555556 | K32: =-'PT Recap costs'!I51/1000-'PT Recap costs'!I37/1000 -> -5.0555556 | ... O32: =-'PT Recap costs'!M51/1000-'PT Recap costs'!M37/1000 -> -5.0555556 | P32: =SUM(D32:O32) -> -60.666667
C33: T3 - Nutrow & Feedim evolution | D33: =-'PT Recap costs'!B55/1000-'PT Recap costs'!B29/1000 -> -75.555556 | E33: =-'PT Recap costs'!C55/1000-'PT Recap costs'!C29/1000 -> -75.555556 | F33: =-'PT Recap costs'!D55/1000-'PT Recap costs'!D29/1000 -> -75.555556 | G33: =-'PT Recap costs'!E55/1000-'PT Recap costs'!E29/1000 -> -75.555556 | H33: =-'PT Recap costs'!F55/1000-'PT Recap costs'!F29/1000 -> -30.555556 | I33: =-'PT Recap costs'!G55/1000-'PT Recap costs'!G29/1000 -> -30.555556 | J33: =-'PT Recap costs'!H55/1000-'PT Recap costs'!H29/1000 -> -30.555556 | K33: =-'PT Recap costs'!I55/1000-'PT Recap costs'!I29/1000 -> -30.555556 | ... O33: =-'PT Recap costs'!M55/1000-'PT Recap costs'!M29/1000 -> -30.555556 | P33: =SUM(D33:O33) -> -546.66667
C34: T4 - Oncology: development | D34: =-'PT Recap costs'!B59/1000-'PT Recap costs'!B40/1000 -> -0.55555556 | E34: =-'PT Recap costs'!C59/1000-'PT Recap costs'!C40/1000 -> -0.55555556 | F34: =-'PT Recap costs'!D59/1000-'PT Recap costs'!D40/1000 -> -0.55555556 | G34: =-'PT Recap costs'!E59/1000-'PT Recap costs'!E40/1000 -> -0.55555556 | H34: =-'PT Recap costs'!F59/1000-'PT Recap costs'!F40/1000 -> -0.55555556 | I34: =-'PT Recap costs'!G59/1000-'PT Recap costs'!G40/1000 -> -0.55555556 | J34: =-'PT Recap costs'!H59/1000-'PT Recap costs'!H40/1000 -> -0.55555556 | K34: =-'PT Recap costs'!I59/1000-'PT Recap costs'!I40/1000 -> -0.55555556 | ... O34: =-'PT Recap costs'!M59/1000-'PT Recap costs'!M40/1000 -> -0.55555556 | P34: =SUM(D34:O34) -> -6.6666667
C35: T5 - Operations organisation (Services): Installation & Interfaçage | D35: =-'PT Recap costs'!B63/1000-'PT Recap costs'!B13/1000 -> -1.5555556 | E35: =-'PT Recap costs'!C63/1000-'PT Recap costs'!C13/1000 -> -1.5555556 | F35: =-'PT Recap costs'!D63/1000-'PT Recap costs'!D13/1000 -> -1.5555556 | G35: =-'PT Recap costs'!E63/1000-'PT Recap costs'!E13/1000 -> -1.5555556 | H35: =-'PT Recap costs'!F63/1000-'PT Recap costs'!F13/1000 -> -1.5555556 | I35: =-'PT Recap costs'!G63/1000-'PT Recap costs'!G13/1000 -> -1.5555556 | J35: =-'PT Recap costs'!H63/1000-'PT Recap costs'!H13/1000 -> -1.5555556 | K35: =-'PT Recap costs'!I63/1000-'PT Recap costs'!I13/1000 -> -1.5555556 | ... O35: =-'PT Recap costs'!M63/1000-'PT Recap costs'!M13/1000 -> -1.5555556 | P35: =SUM(D35:O35) -> -18.666667
C36: T6 - OEM Feedim | D36: =-'PT Recap costs'!B67/1000-'PT Recap costs'!B25/1000 -> -0.55555556 | E36: =-'PT Recap costs'!C67/1000-'PT Recap costs'!C25/1000 -> -0.55555556 | F36: =-'PT Recap costs'!D67/1000-'PT Recap costs'!D25/1000 -> -0.55555556 | G36: =-'PT Recap costs'!E67/1000-'PT Recap costs'!E25/1000 -> -0.55555556 | H36: =-'PT Recap costs'!F67/1000-'PT Recap costs'!F25/1000 -> -0.55555556 | I36: =-'PT Recap costs'!G67/1000-'PT Recap costs'!G25/1000 -> -0.55555556 | J36: =-'PT Recap costs'!H67/1000-'PT Recap costs'!H25/1000 -> -0.55555556 | K36: =-'PT Recap costs'!I67/1000-'PT Recap costs'!I25/1000 -> -0.55555556 | ... O36: =-'PT Recap costs'!M67/1000-'PT Recap costs'!M25/1000 -> -0.55555556 | P36: =SUM(D36:O36) -> -6.6666667
C37: Other | D37: =-'PT Recap costs'!B71/1000-('Recap costs'!H24+'Recap costs'!H26+'Recap costs'!H27+'Recap costs'!H32+'Recap costs'!H2)/1000 -> -46.525 | E37: =-'PT Recap costs'!C71/1000-('Recap costs'!I24+'Recap costs'!I26+'Recap costs'!I27+'Recap costs'!I32+'Recap costs'!I2)/1000 -> -46.525 | F37: =-'PT Recap costs'!D71/1000-('Recap costs'!J24+'Recap costs'!J26+'Recap costs'!J27+'Recap costs'!J32+'Recap costs'!J2)/1000 -> -39.525 | G37: =-'PT Recap costs'!E71/1000-('Recap costs'!K24+'Recap costs'!K26+'Recap costs'!K27+'Recap costs'!K32+'Recap costs'!K2)/1000 -> -39.525 | H37: =-'PT Recap costs'!F71/1000-('Recap costs'!L24+'Recap costs'!L26+'Recap costs'!L27+'Recap costs'!L32+'Recap costs'!L2)/1000 -> -39.525 | I37: =-'PT Recap costs'!G71/1000-('Recap costs'!M24+'Recap costs'!M26+'Recap costs'!M27+'Recap costs'!M32+'Recap costs'!M2)/1000 -> -39.525 | J37: =-'PT Recap costs'!H71/1000-('Recap costs'!N24+'Recap costs'!N26+'Recap costs'!N27+'Recap costs'!N32+'Recap costs'!N2)/1000 -> -39.525 | K37: =-'PT Recap costs'!I71/1000-('Recap costs'!O24+'Recap costs'!O26+'Recap costs'!O27+'Recap costs'!O32+'Recap costs'!O2)/1000 -> -39.525 | ... O37: =-'PT Recap costs'!M71/1000-('Recap costs'!S24+'Recap costs'!S26+'Recap costs'!S27+'Recap costs'!S32+'Recap costs'!S2)/1000 -> -39.525 | P37: =SUM(D37:O37) -> -488.3
A38: 17 | B38: Other costs | C38: IP & patents costs | D38: =-'Recap costs'!H54/1000 -> -0.3453767 | E38: =-'Recap costs'!I54/1000 -> -0.61202251 | F38: =-'Recap costs'!J54/1000 -> -0.8291209 | G38: =-'Recap costs'!K54/1000 -> -3.569079 | H38: =-'Recap costs'!L54/1000 -> -3.4134619 | I38: =-'Recap costs'!M54/1000 -> -4.3071385 | J38: =-'Recap costs'!N54/1000 -> -5.015193 | K38: =-'Recap costs'!O54/1000 -> -5.7232474 | ... O38: =-'Recap costs'!S54/1000 -> -9.04634 | P38: =SUM(D38:O38) -> -60
A39: 18 | B39: Marketing | C39: Marketing & communication | D39: =-'Recap costs'!H62/1000 -> -1.7268835 | E39: =-'Recap costs'!I62/1000 -> -3.0601125 | F39: =-'Recap costs'!J62/1000 -> -4.1456045 | G39: =-'Recap costs'!K62/1000 -> -17.845395 | H39: =-'Recap costs'!L62/1000 -> -17.06731 | I39: =-'Recap costs'!M62/1000 -> -21.535693 | J39: =-'Recap costs'!N62/1000 -> -25.075965 | K39: =-'Recap costs'!O62/1000 -> -28.616237 | ... O39: =-'Recap costs'!S62/1000 -> -45.2317 | P39: =SUM(D39:O39) -> -300
A40: 19 | B40: Other costs | C40: Shipment in & out | D40: =-'Recap costs'!H55/1000 -> -0.06907534 | E40: =-'Recap costs'!I55/1000 -> -0.1224045 | F40: =-'Recap costs'!J55/1000 -> -0.16582418 | G40: =-'Recap costs'!K55/1000 -> -0.7138158 | H40: =-'Recap costs'!L55/1000 -> -0.68269239 | I40: =-'Recap costs'!M55/1000 -> -0.86142771 | J40: =-'Recap costs'!N55/1000 -> -1.0030386 | K40: =-'Recap costs'!O55/1000 -> -1.1446495 | ... O40: =-'Recap costs'!S55/1000 -> -1.809268 | P40: =SUM(D40:O40) -> -12
A41: 20 | B41: Other costs | C41: Small equipment | D41: =-'Recap costs'!H56/1000 -> -0.12951626 | E41: =-'Recap costs'!I56/1000 -> -0.22950844 | F41: =-'Recap costs'!J56/1000 -> -0.31092034 | G41: =-'Recap costs'!K56/1000 -> -1.3384046 | H41: =-'Recap costs'!L56/1000 -> -1.2800482 | I41: =-'Recap costs'!M56/1000 -> -1.6151769 | J41: =-'Recap costs'!N56/1000 -> -1.8806974 | K41: =-'Recap costs'!O56/1000 -> -2.1462178 | ... O41: =-'Recap costs'!S56/1000 -> -3.3923775 | P41: =SUM(D41:O41) -> -22.5
A42: 21 | B42: Other costs | C42: Software & licences | D42: =-'Recap costs'!H57/1000 -> -0.86344175 | E42: =-'Recap costs'!I57/1000 -> -1.5300563 | F42: =-'Recap costs'!J57/1000 -> -2.0728022 | G42: =-'Recap costs'!K57/1000 -> -8.9226975 | H42: =-'Recap costs'!L57/1000 -> -8.5336548 | I42: =-'Recap costs'!M57/1000 -> -10.767846 | J42: =-'Recap costs'!N57/1000 -> -12.537982 | K42: =-'Recap costs'!O57/1000 -> -14.308118 | ... O42: =-'Recap costs'!S57/1000 -> -22.61585 | P42: =SUM(D42:O42) -> -150
A43: 23 | B43: Facilities | C43: Facilities | D43: =-'Recap costs'!H25/1000 -> -10.5 | E43: =-'Recap costs'!I25/1000 -> -10.5 | F43: =-'Recap costs'!J25/1000 -> -10.5 | G43: =-'Recap costs'!K25/1000 -> -10.5 | H43: =-'Recap costs'!L25/1000 -> -12.5 | I43: =-'Recap costs'!M25/1000 -> -12.5 | J43: =-'Recap costs'!N25/1000 -> -12.5 | K43: =-'Recap costs'!O25/1000 -> -12.5 | ... O43: =-'Recap costs'!S25/1000 -> -15 | P43: =SUM(D43:O43) -> -152
A44: 24 | B44: HR/Admin | C44: Admin costs | D44: =-'Recap costs'!H36/1000 -> -0.15254138 | E44: =-'Recap costs'!I36/1000 -> -0.27030994 | F44: =-'Recap costs'!J36/1000 -> -0.36619506 | G44: =-'Recap costs'!K36/1000 -> -1.5763432 | H44: =-'Recap costs'!L36/1000 -> -1.5076124 | I44: =-'Recap costs'!M36/1000 -> -1.9023195 | J44: =-'Recap costs'!N36/1000 -> -2.2150436 | K44: =-'Recap costs'!O36/1000 -> -2.5277676 | ... O44: =-'Recap costs'!S36/1000 -> -3.9954668 | P44: =SUM(D44:O44) -> -26.5
C45: Capitalized costs | D45: 138.50625 | E45: 138.50625 | F45: 138.50625 | G45: 185.25625 | H45: 311.50625 | I45: 281.25625 | J45: 218.00625 | K45: 218.00625 | L45: 218.00625 | M45: 218.00625 | N45: 218.00625 | O45: 264.75625 | P45: =SUM(D45:O45) -> 2548.325 | Q45: File "BP 21-23 - Amortissements"
C46: TOTAL OVERHEAD | D46: =SUM(D18:D19)+SUM(D27:D30)+SUM(D38:D45) -> -412.76301 | E46: =SUM(E18:E19)+SUM(E27:E30)+SUM(E38:E45) -> -634.17558 | F46: =SUM(F18:F19)+SUM(F27:F30)+SUM(F38:F45) -> -607.34164 | G46: =SUM(G18:G19)+SUM(G27:G30)+SUM(G38:G45) -> -781.51691 | H46: =SUM(H18:H19)+SUM(H27:H30)+SUM(H38:H45) -> -778.68595 | I46: =SUM(I18:I19)+SUM(I27:I30)+SUM(I38:I45) -> -747.19077 | J46: =SUM(J18:J19)+SUM(J27:J30)+SUM(J38:J45) -> -853.92909 | K46: =SUM(K18:K19)+SUM(K27:K30)+SUM(K38:K45) -> -938.41741 | ... P46: =SUM(P18:P19)+SUM(P27:P30)+SUM(P38:P45) -> -9812.489
C47: Total payroll | D47: =D19 -> -327.61809 | E47: =E19 -> -514.49309 | F47: =F19 -> -551.59309 | G47: =G19 -> -706.44309 | H47: =H19 -> -867.84309 | I47: =I19 -> -837.59309 | J47: =J19 -> -864.34309 | K47: =K19 -> -922.09309 | ... P47: =P19 -> -9573.442
C48: Total Opex | D48: =D18+SUM(D27:D30)+SUM(D38:D44) -> -223.65117 | E48: =E18+SUM(E27:E30)+SUM(E38:E44) -> -258.18875 | F48: =F18+SUM(F27:F30)+SUM(F38:F44) -> -194.2548 | G48: =G18+SUM(G27:G30)+SUM(G38:G44) -> -260.33007 | H48: =H18+SUM(H27:H30)+SUM(H38:H44) -> -222.34911 | I48: =I18+SUM(I27:I30)+SUM(I38:I44) -> -190.85394 | J48: =J18+SUM(J27:J30)+SUM(J38:J44) -> -207.59225 | K48: =K18+SUM(K27:K30)+SUM(K38:K44) -> -234.33057 | ... P48: =P18+SUM(P27:P30)+SUM(P38:P44) -> -2787.372
C50: EBITDA | D50: =+D46+D16 -> -331.38231 | E50: =+E46+E16 -> -494.48941 | F50: =+F46+F16 -> -420.36903 | G50: =+G46+G16 -> -135.87077 | H50: =+H46+H16 -> -135.54106 | I50: =+I46+I16 -> 109.05521 | J50: =+J46+J16 -> 170.41798 | K50: =+K46+K16 -> 254.03076 | ... P50: =+P46+P16 -> 2374.2
C51: EBITDA rate | D51: =D50/D12 -> -3.9577979 | E51: =E50/E12 -> -3.3327822 | F51: =F50/F12 -> -2.0913666 | G51: =G50/G12 -> -0.15703165 | H51: =H50/H12 -> -0.16379218 | I51: =I50/I12 -> 0.10444193 | J51: =J50/J12 -> 0.14016678 | K51: =K50/K12 -> 0.18308852 | ... P51: =P50/P12 -> 0.16322376
C53: Depreciation & Amortization | D53: -115.65278 | E53: -122.2661 | F53: -128.87942 | G53: -137.16238 | H53: -144.05282 | I53: -155.76436 | J53: -165.21696 | K53: -174.66956 | L53: -169.28187 | M53: -178.73447 | N53: -188.18707 | O53: -199.30932 | P53: =SUM(D53:O53) -> -1879.1771 | Q53: File "BP 21-23 - Amortissements"
C54: Financial costs | D54: =-'Recap costs'!H28/1000 -> -2 | E54: =-'Recap costs'!I28/1000 -> -2 | F54: =-'Recap costs'!J28/1000 -> -2 | G54: =-'Recap costs'!K28/1000 -> -2 | H54: =-'Recap costs'!L28/1000 -> -2 | I54: =-'Recap costs'!M28/1000 -> -2 | J54: =-'Recap costs'!N28/1000 -> -2 | K54: =-'Recap costs'!O28/1000 -> -2 | ... O54: =-'Recap costs'!S28/1000 -> -2 | P54: =SUM(D54:O54) -> -24
C55: Financial income | D55: 0 | E55: 0 | F55: 0 | G55: 0 | H55: 0 | I55: 0 | J55: 0 | K55: 0 | L55: 0 | M55: 0 | N55: 0 | O55: 0 | P55: =SUM(D55:O55) -> 0
C56: Extraordinary costs | D56: 0 | E56: 0 | F56: 0 | G56: 0 | H56: 0 | I56: 0 | J56: 0 | K56: 0 | L56: 0 | M56: 0 | N56: 0 | O56: 0 | P56: =SUM(D56:O56) -> 0
C57: Extraordinary income | D57: 0 | E57: 0 | F57: 0 | G57: 0 | H57: 0 | I57: 0 | J57: 0 | K57: 0 | L57: 0 | M57: 0 | N57: 0 | O57: 0 | P57: =SUM(D57:O57) -> 0
C58: PROFIT BEFORE TAXES | D58: =D50+SUM(D53:D55) -> -449.03509 | E58: =E50+SUM(E53:E55) -> -618.75551 | F58: =F50+SUM(F53:F55) -> -551.24844 | G58: =G50+SUM(G53:G55) -> -275.03315 | H58: =H50+SUM(H53:H55) -> -281.59389 | I58: =I50+SUM(I53:I55) -> -48.70915 | J58: =J50+SUM(J53:J55) -> 3.2010216 | K58: =K50+SUM(K53:K55) -> 77.361193 | ... P58: =P50+SUM(P53:P55) -> 471.02285
C60: Income tax
C62: NET PROFIT | D62: =+D60+D58 -> -449.03509 | E62: =+E60+E58 -> -618.75551 | F62: =+F60+F58 -> -551.24844 | G62: =+G60+G58 -> -275.03315 | H62: =+H60+H58 -> -281.59389 | I62: =+I60+I58 -> -48.70915 | J62: =+J60+J58 -> 3.2010216 | K62: =+K60+K58 -> 77.361193 | ... P62: =+P60+P58 -> 471.02285
C64: OPERATING CASH FLOW | D64: =D62-D53-D54-D55 -> -331.38231 | E64: =E62-E53-E54-E55 -> -494.48941 | F64: =F62-F53-F54-F55 -> -420.36903 | G64: =G62-G53-G54-G55 -> -135.87077 | H64: =H62-H53-H54-H55 -> -135.54106 | I64: =I62-I53-I54-I55 -> 109.05521 | J64: =J62-J53-J54-J55 -> 170.41798 | K64: =K62-K53-K54-K55 -> 254.03076 | ... P64: =P62-P53-P54-P55 -> 2374.2
C66: CAPEX | D66: =-400/12 -> -33.333333 | E66: =-400/12 -> -33.333333 | F66: =-400/12 -> -33.333333 | G66: =-400/12 -> -33.333333 | H66: =-400/12 -> -33.333333 | I66: =-400/12 -> -33.333333 | J66: =-400/12 -> -33.333333 | K66: =-400/12 -> -33.333333 | ... O66: =-400/12 -> -33.333333 | P66: =SUM(D66:O66) -> -400
C67: Capitalized costs | D67: =-D45 -> -138.50625 | E67: =-E45 -> -138.50625 | F67: =-F45 -> -138.50625 | G67: =-G45 -> -185.25625 | H67: =-H45 -> -311.50625 | I67: =-I45 -> -281.25625 | J67: =-J45 -> -218.00625 | K67: =-K45 -> -218.00625 | ... O67: =-O45 -> -264.75625 | P67: =SUM(D67:O67) -> -2548.325
C68: INVESTING CASH FLOW | D68: =SUM(D66:D67) -> -171.83958 | E68: =SUM(E66:E67) -> -171.83958 | F68: =SUM(F66:F67) -> -171.83958 | G68: =SUM(G66:G67) -> -218.58958 | H68: =SUM(H66:H67) -> -344.83958 | I68: =SUM(I66:I67) -> -314.58958 | J68: =SUM(J66:J67) -> -251.33958 | K68: =SUM(K66:K67) -> -251.33958 | ... P68: =SUM(P66:P67) -> -2948.325
C70: Capital increase | P70: =SUM(D70:O70) -> 0
C71: New funding | P71: =SUM(D71:O71) -> 0
C72: Loan reimbursement | D72: 0 | E72: 0 | F72: 0 | G72: 0 | H72: 0 | I72: 0 | J72: 0 | K72: 0 | L72: 0 | M72: 0 | N72: 0 | O72: 0 | P72: =SUM(D72:O72) -> 0
C73: Financial costs/ income | D73: =D54+D55 -> -2 | E73: =E54+E55 -> -2 | F73: =F54+F55 -> -2 | G73: =G54+G55 -> -2 | H73: =H54+H55 -> -2 | I73: =I54+I55 -> -2 | J73: =J54+J55 -> -2 | K73: =K54+K55 -> -2 | ... O73: =O54+O55 -> -2 | P73: =SUM(D73:O73) -> -24
C74: Subsidies | D74: 0 | E74: 0 | F74: 0 | G74: 0 | H74: 0 | I74: 0 | J74: 0 | K74: 0 | L74: 0 | M74: 0 | N74: 0 | O74: 0 | P74: =SUM(D74:O74) -> 0 | Q74: Explained in the text
C75: FINANCING CASH FLOW | D75: =SUM(D70:D74) -> -2 | E75: =SUM(E70:E74) -> -2 | F75: =SUM(F70:F74) -> -2 | G75: =SUM(G70:G74) -> -2 | H75: =SUM(H70:H74) -> -2 | I75: =SUM(I70:I74) -> -2 | J75: =SUM(J70:J74) -> -2 | K75: =SUM(K70:K74) -> -2 | ... P75: =SUM(P70:P74) -> -24
C77: NET CASH FLOW | D77: =D64+D68+D75 -> -505.22189 | E77: =E64+E68+E75 -> -668.32899 | F77: =F64+F68+F75 -> -594.20861 | G77: =G64+G68+G75 -> -356.46035 | H77: =H64+H68+H75 -> -482.38065 | I77: =I64+I68+I75 -> -207.53438 | J77: =J64+J68+J75 -> -82.921601 | K77: =K64+K68+K75 -> 0.69117406 | ... P77: =P64+P68+P75 -> -598.12504
C78: NET CUMULATIVE CASH FLOW | D78: =D77 -> -505.22189 | E78: =D78+E77 -> -1173.5509 | F78: =E78+F77 -> -1767.7595 | G78: =F78+G77 -> -2124.2198 | H78: =G78+H77 -> -2606.6005 | I78: =H78+I77 -> -2814.1349 | J78: =I78+J77 -> -2897.0565 | K78: =J78+K77 -> -2896.3653 | L78: =K78+L77 -> -2286.2927 | ... O78: =N78+O77 -> -598.12504
D79: =D77-D14-D66-'Tableau recap'!E105 -> 0 | E79: =E77-E14-E66-'Tableau recap'!F105 -> 0 | F79: =F77-F14-F66-'Tableau recap'!G105 -> 0 | G79: =G77-G14-G66-'Tableau recap'!H105 -> 0 | H79: =H77-H14-H66-'Tableau recap'!I105 -> 0 | I79: =I77-I14-I66-'Tableau recap'!J105 -> 0 | J79: =J77-J14-J66-'Tableau recap'!K105 -> -3.1974423e-13 | K79: =K77-K14-K66-'Tableau recap'!L105 -> -2.0605739e-13 | ... O79: =O77-O14-O66-'Tableau recap'!P105 -> 0

Sheet 3 Cash Flow
A1: ALL AMOUNTS IN KEUR | B1: BP 21-23 | C1: Q1 21 | D1: Q2 21 | E1: Q3 21 | F1: Q4 21 | G1: BP 2021 | H1: Q1 22 | I1: Q2 22 | J1: Q3 22 | K1: Q4 22 | L1: BP 2022 | M1: Q1 23 | N1: Q2 23 | O1: Q3 23 | P1: Q4 23 | Q1: BP 2023 | R1: TOTAL
A2: Gross cash flow (EBITDA) | B2: ='2 P&L'!P50 -> 2374.2 | C2: ='2 P&L'!D50 -> -331.38231 | D2: ='2 P&L'!E50 -> -494.48941 | E2: ='2 P&L'!F50 -> -420.36903 | F2: ='2 P&L'!G50 -> -135.87077 | G2: =SUM(C2:F2) -> -1382.1115 | H2: ='2 P&L'!H50 -> -135.54106 | I2: ='2 P&L'!I50 -> 109.05521 | J2: ='2 P&L'!J50 -> 170.41798 | K2: ='2 P&L'!K50 -> 254.03076 | L2: =SUM(H2:K2) -> 397.96288 | M2: ='2 P&L'!L50 -> 863.41215 | N2: ='2 P&L'!M50 -> 828.31215 | O2: ='2 P&L'!N50 -> 838.31215 | P2: ='2 P&L'!O50 -> 828.31215 | Q2: =SUM(M2:P2) -> 3358.3486 | R2: =G2+L2+Q2 -> 2374.2
A3: Suppliers - WK changes (30 days) | B3: =-'2 P&L'!O48/3 -> 82.985112 | C3: =-'2 P&L'!D48/3 -> 74.550389 | D3: ='2 P&L'!D48/3-'2 P&L'!E48/3 -> 11.512526 | E3: ='2 P&L'!E48/3-'2 P&L'!F48/3 -> -21.311316 | F3: ='2 P&L'!F48/3-'2 P&L'!G48/3 -> 22.025089 | G3: =SUM(C3:F3) -> 86.776689 | H3: ='2 P&L'!G48/3-'2 P&L'!H48/3 -> -12.660319 | I3: ='2 P&L'!H48/3-'2 P&L'!I48/3 -> -10.498393 | J3: ='2 P&L'!I48/3-'2 P&L'!J48/3 -> 5.5794393 | K3: ='2 P&L'!J48/3-'2 P&L'!K48/3 -> 8.9127727 | L3: =SUM(H3:K3) -> -8.6664991 | M3: ='2 P&L'!K48/3-'2 P&L'!L48/3 -> 8.208255 | N3: ='2 P&L'!L48/3-'2 P&L'!M48/3 -> -3.3333333 | O3: ='2 P&L'!M48/3-'2 P&L'!N48/3 -> -3.3333333 | P3: ='2 P&L'!N48/3-'2 P&L'!O48/3 -> 3.3333333 | Q3: =SUM(M3:P3) -> 4.8749216 | R3: =G3+L3+Q3 -> 82.985112
A4: Clients - WK changes (60 days) | B4: =-'2 P&L'!O12*2/3 -> -1462.057 | C4: =-'2 P&L'!D12*2/3 -> -55.819308 | D4: =-C4-'2 P&L'!E12/3*2 -> -43.094929 | E4: ='2 P&L'!E12/3*2-'2 P&L'!F12/3*2 -> -35.087144 | F4: ='2 P&L'!F12/3*2-'2 P&L'!G12/3*2 -> -442.82826 | G4: =SUM(C4:F4) -> -576.82964 | H4: ='2 P&L'!G12/3*2-'2 P&L'!H12/3*2 -> 25.150614 | I4: ='2 P&L'!H12/3*2-'2 P&L'!I12/3*2 -> -144.43478 | J4: ='2 P&L'!I12/3*2-'2 P&L'!J12/3*2 -> -114.43478 | K4: ='2 P&L'!J12/3*2-'2 P&L'!K12/3*2 -> -114.43478 | L4: =SUM(H4:K4) -> -348.15374 | M4: ='2 P&L'!K12/3*2-'2 P&L'!L12/3*2 -> -537.07367 | N4: ='2 P&L'!L12/3*2-'2 P&L'!M12/3*2 -> 0 | O4: ='2 P&L'!M12/3*2-'2 P&L'!N12/3*2 -> 0 | P4: ='2 P&L'!N12/3*2-'2 P&L'!O12/3*2 -> 0 | Q4: =SUM(M4:P4) -> -537.07367 | R4: =G4+L4+Q4 -> -1462.057
A5: Inventory | B5: =-'2 P&L'!P14 -> 0 | C5: =-'2 P&L'!D14 -> 0 | D5: =-'2 P&L'!E14 -> 0 | E5: =-'2 P&L'!F14 -> 0 | F5: =-'2 P&L'!G14 -> 0 | G5: =SUM(C5:F5) -> 0 | H5: =-'2 P&L'!H14 -> 0 | I5: =-'2 P&L'!I14 -> 0 | J5: =-'2 P&L'!J14 -> 0 | K5: =-'2 P&L'!K14 -> 0 | L5: =SUM(H5:K5) -> 0 | M5: =-'2 P&L'!L14 -> 0 | N5: =-'2 P&L'!M14 -> 0 | O5: =-'2 P&L'!N14 -> 0 | P5: =-'2 P&L'!O14 -> 0 | Q5: =SUM(M5:P5) -> 0 | R5: =G5+L5+Q5 -> 0
A6: CASH FROM OPERATING ACTIVITIES | B6: =SUM(B2:B5) -> 995.12802 | C6: =SUM(C2:C5) -> -312.65123 | D6: =SUM(D2:D5) -> -526.07181 | E6: =SUM(E2:E5) -> -476.76748 | F6: =SUM(F2:F5) -> -556.67394 | G6: =SUM(G2:G5) -> -1872.1645 | H6: =SUM(H2:H5) -> -123.05077 | I6: =SUM(I2:I5) -> -45.87797 | ... Q6: =SUM(Q2:Q5) -> 2826.1498 | R6: =G6+L6+Q6 -> 995.12802
A7: CAPEX | B7: ='2 P&L'!P66 -> -400 | C7: ='2 P&L'!D66 -> -33.333333 | D7: ='2 P&L'!E66 -> -33.333333 | E7: ='2 P&L'!F66 -> -33.333333 | F7: ='2 P&L'!G66 -> -33.333333 | G7: =SUM(C7:F7) -> -133.33333 | H7: ='2 P&L'!H66 -> -33.333333 | I7: ='2 P&L'!I66 -> -33.333333 | J7: ='2 P&L'!J66 -> -33.333333 | K7: ='2 P&L'!K66 -> -33.333333 | L7: =SUM(H7:K7) -> -133.33333 | M7: ='2 P&L'!L66 -> -33.333333 | N7: ='2 P&L'!M66 -> -33.333333 | O7: ='2 P&L'!N66 -> -33.333333 | P7: ='2 P&L'!O66 -> -33.333333 | Q7: =SUM(M7:P7) -> -133.33333 | R7: =G7+L7+Q7 -> -400
A8: R&D and other capitalised costs | B8: ='2 P&L'!P67 -> -2548.325 | C8: ='2 P&L'!D67 -> -138.50625 | D8: ='2 P&L'!E67 -> -138.50625 | E8: ='2 P&L'!F67 -> -138.50625 | F8: ='2 P&L'!G67 -> -185.25625 | G8: =SUM(C8:F8) -> -600.775 | H8: ='2 P&L'!H67 -> -311.50625 | I8: ='2 P&L'!I67 -> -281.25625 | J8: ='2 P&L'!J67 -> -218.00625 | K8: ='2 P&L'!K67 -> -218.00625 | L8: =SUM(H8:K8) -> -1028.775 | M8: ='2 P&L'!L67 -> -218.00625 | N8: ='2 P&L'!M67 -> -218.00625 | O8: ='2 P&L'!N67 -> -218.00625 | P8: ='2 P&L'!O67 -> -264.75625 | Q8: =SUM(M8:P8) -> -918.775 | R8: =G8+L8+Q8 -> -2548.325
A9: CASH FROM INVESTING ACTIVITIES | B9: =SUM(B7:B8) -> -2948.325 | C9: =SUM(C7:C8) -> -171.83958 | D9: =SUM(D7:D8) -> -171.83958 | E9: =SUM(E7:E8) -> -171.83958 | F9: =SUM(F7:F8) -> -218.58958 | G9: =SUM(G7:G8) -> -734.10833 | H9: =SUM(H7:H8) -> -344.83958 | I9: =SUM(I7:I8) -> -314.58958 | ... Q9: =SUM(Q7:Q8) -> -1052.1083 | R9: =G9+L9+Q9 -> -2948.325
A10: Capital increase | B10: 6000 | C10: 3000 | D10: 0 | E10: 0 | F10: 1000 | G10: =SUM(C10:F10) -> 4000 | H10: 0 | I10: 2000 | J10: 0 | K10: 0 | L10: =SUM(H10:K10) -> 2000 | M10: 0 | N10: 0 | O10: 0 | P10: 0 | Q10: =SUM(M10:P10) -> 0 | R10: =G10+L10+Q10 -> 6000
A11: New funding | B11: ='2 P&L'!P71 -> 0 | C11: ='2 P&L'!D71 -> 0 | D11: ='2 P&L'!E71 -> 0 | E11: ='2 P&L'!F71 -> 0 | F11: ='2 P&L'!G71 -> 0 | G11: =SUM(C11:F11) -> 0 | H11: ='2 P&L'!H71 -> 0 | I11: ='2 P&L'!I71 -> 0 | J11: ='2 P&L'!J71 -> 0 | K11: ='2 P&L'!K71 -> 0 | L11: =SUM(H11:K11) -> 0 | M11: ='2 P&L'!L71 -> 0 | N11: ='2 P&L'!M71 -> 0 | O11: ='2 P&L'!N71 -> 0 | P11: ='2 P&L'!O71 -> 0 | Q11: =SUM(M11:P11) -> 0 | R11: =G11+L11+Q11 -> 0
A12: Loan reimbursement | B12: ='2 P&L'!P72 -> 0 | C12: ='2 P&L'!D72 -> 0 | D12: ='2 P&L'!E72 -> 0 | E12: ='2 P&L'!F72 -> 0 | F12: ='2 P&L'!G72 -> 0 | G12: =SUM(C12:F12) -> 0 | H12: ='2 P&L'!H72 -> 0 | I12: ='2 P&L'!I72 -> 0 | J12: ='2 P&L'!J72 -> 0 | K12: ='2 P&L'!K72 -> 0 | L12: =SUM(H12:K12) -> 0 | M12: ='2 P&L'!L72 -> 0 | N12: ='2 P&L'!M72 -> 0 | O12: ='2 P&L'!N72 -> 0 | P12: ='2 P&L'!O72 -> 0 | Q12: =SUM(M12:P12) -> 0 | R12: =G12+L12+Q12 -> 0
A13: Financial costs/ income | B13: ='2 P&L'!P73 -> -24 | C13: ='2 P&L'!D73 -> -2 | D13: ='2 P&L'!E73 -> -2 | E13: ='2 P&L'!F73 -> -2 | F13: ='2 P&L'!G73 -> -2 | G13: =SUM(C13:F13) -> -8 | H13: ='2 P&L'!H73 -> -2 | I13: ='2 P&L'!I73 -> -2 | J13: ='2 P&L'!J73 -> -2 | K13: ='2 P&L'!K73 -> -2 | L13: =SUM(H13:K13) -> -8 | M13: ='2 P&L'!L73 -> -2 | N13: ='2 P&L'!M73 -> -2 | O13: ='2 P&L'!N73 -> -2 | P13: ='2 P&L'!O73 -> -2 | Q13: =SUM(M13:P13) -> -8 | R13: =G13+L13+Q13 -> -24
A14: Subsidies | B14: ='2 P&L'!P74 -> 0 | C14: ='2 P&L'!D74 -> 0 | D14: ='2 P&L'!E74 -> 0 | E14: ='2 P&L'!F74 -> 0 | F14: ='2 P&L'!G74 -> 0 | G14: =SUM(C14:F14) -> 0 | H14: ='2 P&L'!H74 -> 0 | I14: ='2 P&L'!I74 -> 0 | J14: ='2 P&L'!J74 -> 0 | K14: ='2 P&L'!K74 -> 0 | L14: =SUM(H14:K14) -> 0 | M14: ='2 P&L'!L74 -> 0 | N14: ='2 P&L'!M74 -> 0 | O14: ='2 P&L'!N74 -> 0 | P14: ='2 P&L'!O74 -> 0 | Q14: =SUM(M14:P14) -> 0 | R14: =G14+L14+Q14 -> 0
A15: CASH FROM FINANCING ACTIVITIES | B15: =SUM(B10:B14) -> 5976 | C15: =SUM(C10:C14) -> 2998 | D15: =SUM(D10:D14) -> -2 | E15: =SUM(E10:E14) -> -2 | F15: =SUM(F10:F14) -> 998 | G15: =SUM(G10:G14) -> 3992 | H15: =SUM(H10:H14) -> -2 | I15: =SUM(I10:I14) -> 1998 | ... Q15: =SUM(Q10:Q14) -> -8 | R15: =G15+L15+Q15 -> 5976
A17: NET CASH VARIATION | B17: =B6+B9+B15 -> 4022.803 | C17: =C6+C9+C15 -> 2513.5092 | D17: =D6+D9+D15 -> -699.9114 | E17: =E6+E9+E15 -> -650.60707 | F17: =F6+F9+F15 -> 222.73647 | G17: =G6+G9+G15 -> 1385.7272 | H17: =H6+H9+H15 -> -469.89035 | I17: =I6+I9+I15 -> 1637.5324 | ... Q17: =Q6+Q9+Q15 -> 1766.0415 | R17: =G17+L17+Q17 -> 4022.803
A19: OPENING CASH 01/01/2021 | B19: 0 | C19: =B19 -> 0 | D19: =C20 -> 2513.5092 | E19: =D20 -> 1813.5978 | F19: =E20 -> 1162.9907 | G19: =B19 -> 0 | H19: =F20 -> 1385.7272 | I19: =H20 -> 915.83685 | J19: =I20 -> 2553.3693 | K19: =J20 -> 2361.5923 | L19: =G20 -> 1385.7272 | M19: =K20 -> 2256.7615 | N19: =M20 -> 2337.9687 | O19: =N20 -> 2909.6079 | P19: =O20 -> 3491.2471 | Q19: =L20 -> 2256.7615 | R19: 0
A20: CLOSING CASH 31/12/2023 | B20: =B17+B19 -> 4022.803 | C20: =C17+C19 -> 2513.5092 | D20: =D17+D19 -> 1813.5978 | E20: =E17+E19 -> 1162.9907 | F20: =F17+F19 -> 1385.7272 | G20: =G17+G19 -> 1385.7272 | H20: =H17+H19 -> 915.83685 | I20: =I17+I19 -> 2553.3693 | ... R20: =R17+R19 -> 4022.803
B21: =B20-B3-B4-B5-B10-'2 P&L'!P77 -> 0

Sheet Tableau recap
E3: Q1 21 | F3: Q2 21 | G3: Q3 21 | H3: Q4 21 | I3: Q1 22 | J3: Q2 22 | K3: Q3 22 | L3: Q4 22 | M3: Q1 23 | N3: Q2 23 | O3: Q3 23 | P3: Q4 23 | Q3: Total
B4: T1 | C4: Hospital market: Baxter & DIM 3 Pilot | D4: Cash in from Revenue | E4: 23.585794 | F4: 47.171589 | G4: 99.51492 | H4: 373.10071 | I4: 280.07969 | J4: 402.23186 | K4: 524.38404 | L4: 646.53622 | M4: 1210.0564 | N4: 1210.0564 | O4: 1210.0564 | P4: 1210.0564 | Q4: =SUM(E4:P4) -> 7236.8303
D5: COSTS | E5: =-SUM(E6:E11) -> -25.42976 | F5: =-SUM(F6:F11) -> -95.429041 | G5: =-SUM(G6:G11) -> -96.992509 | H5: =-SUM(H6:H11) -> -120.10429 | I5: =-SUM(I6:I11) -> -129.17574 | J5: =-SUM(J6:J11) -> -132.72682 | K5: =-SUM(K6:K11) -> -136.27791 | L5: =-SUM(L6:L11) -> -139.82899 | ... Q5: =-SUM(Q6:Q11) -> -1505.898
D6: COGS | E6: =COGS!C8/1000 -> 0.56178083 | F6: =COGS!D8/1000 -> 1.1235617 | G6: =COGS!E8/1000 -> 2.68703 | H6: =COGS!F8/1000 -> 3.2488108 | I6: =COGS!G8/1000 -> 8.7452615 | J6: =COGS!H8/1000 -> 12.296344 | K6: =COGS!I8/1000 -> 15.847427 | L6: =COGS!J8/1000 -> 19.39851 | ... P6: =COGS!N8/1000 -> 28.596518 | Q6: =SUM(E6:P6) -> 178.2948
D7: Consultancies | E7: ='PT Recap costs'!B47/1000 -> 7.506 | F7: ='PT Recap costs'!C47/1000 -> 7.506 | G7: ='PT Recap costs'!D47/1000 -> 7.506 | H7: ='PT Recap costs'!E47/1000 -> 7.506 | I7: ='PT Recap costs'!F47/1000 -> 7.506 | J7: ='PT Recap costs'!G47/1000 -> 7.506 | K7: ='PT Recap costs'!H47/1000 -> 7.506 | L7: ='PT Recap costs'!I47/1000 -> 7.506 | ... P7: ='PT Recap costs'!M47/1000 -> 7.506 | Q7: =SUM(E7:P7) -> 90.072
D8: Development & op. | E8: ='PT Recap costs'!B48/1000 -> 0 | F8: ='PT Recap costs'!C48/1000 -> 0 | G8: ='PT Recap costs'!D48/1000 -> 0 | H8: ='PT Recap costs'!E48/1000 -> 0 | I8: ='PT Recap costs'!F48/1000 -> 0 | J8: ='PT Recap costs'!G48/1000 -> 0 | K8: ='PT Recap costs'!H48/1000 -> 0 | L8: ='PT Recap costs'!I48/1000 -> 0 | ... P8: ='PT Recap costs'!M48/1000 -> 0 | Q8: =SUM(E8:P8) -> 0
D9: E&F | E9: ='PT Recap costs'!B49/1000 -> 13.47309 | F9: ='PT Recap costs'!C49/1000 -> 82.91059 | G9: ='PT Recap costs'!D49/1000 -> 82.91059 | H9: ='PT Recap costs'!E49/1000 -> 105.46059 | I9: ='PT Recap costs'!F49/1000 -> 109.03559 | J9: ='PT Recap costs'!G49/1000 -> 109.03559 | K9: ='PT Recap costs'!H49/1000 -> 109.03559 | L9: ='PT Recap costs'!I49/1000 -> 109.03559 | ... P9: ='PT Recap costs'!M49/1000 -> 120.31059 | Q9: =SUM(E9:P9) -> 1190.8646
D10: Legal | E10: ='PT Recap costs'!B34/1000 -> 0.55555556 | F10: ='PT Recap costs'!C34/1000 -> 0.55555556 | G10: ='PT Recap costs'!D34/1000 -> 0.55555556 | H10: ='PT Recap costs'!E34/1000 -> 0.55555556 | I10: ='PT Recap costs'!F34/1000 -> 0.55555556 | J10: ='PT Recap costs'!G34/1000 -> 0.55555556 | K10: ='PT Recap costs'!H34/1000 -> 0.55555556 | L10: ='PT Recap costs'!I34/1000 -> 0.55555556 | ... P10: ='PT Recap costs'!M34/1000 -> 0.55555556 | Q10: =SUM(E10:P10) -> 6.6666667
D11: T&E | E11: ='PT Recap costs'!B35/1000 -> 3.3333333 | F11: ='PT Recap costs'!C35/1000 -> 3.3333333 | G11: ='PT Recap costs'!D35/1000 -> 3.3333333 | H11: ='PT Recap costs'!E35/1000 -> 3.3333333 | I11: ='PT Recap costs'!F35/1000 -> 3.3333333 | J11: ='PT Recap costs'!G35/1000 -> 3.3333333 | K11: ='PT Recap costs'!H35/1000 -> 3.3333333 | L11: ='PT Recap costs'!I35/1000 -> 3.3333333 | ... P11: ='PT Recap costs'!M35/1000 -> 3.3333333 | Q11: =SUM(E11:P11) -> 40
D12: NET | E12: =E4+E5 -> -1.8439657 | F12: =F4+F5 -> -48.257452 | G12: =G4+G5 -> 2.5224112 | H12: =H4+H5 -> 252.99642 | I12: =I4+I5 -> 150.90395 | J12: =J4+J5 -> 269.50504 | K12: =K4+K5 -> 388.10613 | L12: =L4+L5 -> 506.70723 | ... Q12: =Q4+Q5 -> 5730.9323
B14: T2 | C14: Homecare market: Vivisol | D14: Cash in from Revenue | E14: 12.018168 | F14: 35.574767 | G14: 53.362151 | H14: 76.918751 | I14: 238.18886 | J14: 238.18886 | K14: 238.18886 | L14: 238.18886 | M14: 485.3042 | N14: 485.3042 | O14: 485.3042 | P14: 485.3042 | Q14: =SUM(E14:P14) -> 3071.8461
D15: COSTS | E15: =-SUM(E16:E21) -> -23.648463 | F15: =-SUM(F16:F21) -> -98.861098 | G15: =-SUM(G16:G21) -> -102.64191 | H15: =-SUM(H16:H21) -> -130.199 | I15: =-SUM(I16:I21) -> -168.05288 | J15: =-SUM(J16:J21) -> -168.05288 | K15: =-SUM(K16:K21) -> -168.05288 | L15: =-SUM(L16:L21) -> -168.05288 | ... Q15: =-SUM(Q16:Q21) -> -1972.2238
D16: COGS | E16: =COGS!C10/1000 -> 1.7864844 | F16: =COGS!D10/1000 -> 7.5616194 | G16: =COGS!E10/1000 -> 11.342429 | H16: =COGS!F10/1000 -> 16.349519 | I16: =COGS!G10/1000 -> 50.628398 | J16: =COGS!H10/1000 -> 50.628398 | K16: =COGS!I10/1000 -> 50.628398 | L16: =COGS!J10/1000 -> 50.628398 | ... P16: =COGS!N10/1000 -> 110.28474 | Q16: =SUM(E16:P16) -> 680.69259
D17: Consultancies | E17: ='PT Recap costs'!B51/1000 -> 4.5 | F17: ='PT Recap costs'!C51/1000 -> 4.5 | G17: ='PT Recap costs'!D51/1000 -> 4.5 | H17: ='PT Recap costs'!E51/1000 -> 4.5 | I17: ='PT Recap costs'!F51/1000 -> 4.5 | J17: ='PT Recap costs'!G51/1000 -> 4.5 | K17: ='PT Recap costs'!H51/1000 -> 4.5 | L17: ='PT Recap costs'!I51/1000 -> 4.5 | ... P17: ='PT Recap costs'!M51/1000 -> 4.5 | Q17: =SUM(E17:P17) -> 54
D18: Development & op. | E18: ='PT Recap costs'!B52/1000 -> 0 | F18: ='PT Recap costs'!C52/1000 -> 0 | G18: ='PT Recap costs'!D52/1000 -> 0 | H18: ='PT Recap costs'!E52/1000 -> 0 | I18: ='PT Recap costs'!F52/1000 -> 0 | J18: ='PT Recap costs'!G52/1000 -> 0 | K18: ='PT Recap costs'!H52/1000 -> 0 | L18: ='PT Recap costs'!I52/1000 -> 0 | ... P18: ='PT Recap costs'!M52/1000 -> 0 | Q18: =SUM(E18:P18) -> 0
D19: E&F | E19: ='PT Recap costs'!B53/1000 -> 13.47309 | F19: ='PT Recap costs'!C53/1000 -> 82.91059 | G19: ='PT Recap costs'!D53/1000 -> 82.91059 | H19: ='PT Recap costs'!E53/1000 -> 105.46059 | I19: ='PT Recap costs'!F53/1000 -> 109.03559 | J19: ='PT Recap costs'!G53/1000 -> 109.03559 | K19: ='PT Recap costs'!H53/1000 -> 109.03559 | L19: ='PT Recap costs'!I53/1000 -> 109.03559 | ... P19: ='PT Recap costs'!M53/1000 -> 120.31059 | Q19: =SUM(E19:P19) -> 1190.8646
D20: Legal | E20: ='PT Recap costs'!B37/1000 -> 0.55555556 | F20: ='PT Recap costs'!C37/1000 -> 0.55555556 | G20: ='PT Recap costs'!D37/1000 -> 0.55555556 | H20: ='PT Recap costs'!E37/1000 -> 0.55555556 | I20: ='PT Recap costs'!F37/1000 -> 0.55555556 | J20: ='PT Recap costs'!G37/1000 -> 0.55555556 | K20: ='PT Recap costs'!H37/1000 -> 0.55555556 | L20: ='PT Recap costs'!I37/1000 -> 0.55555556 | ... P20: ='PT Recap costs'!M37/1000 -> 0.55555556 | Q20: =SUM(E20:P20) -> 6.6666667
D21: T&E | E21: ='PT Recap costs'!B38/1000 -> 3.3333333 | F21: ='PT Recap costs'!C38/1000 -> 3.3333333 | G21: ='PT Recap costs'!D38/1000 -> 3.3333333 | H21: ='PT Recap costs'!E38/1000 -> 3.3333333 | I21: ='PT Recap costs'!F38/1000 -> 3.3333333 | J21: ='PT Recap costs'!G38/1000 -> 3.3333333 | K21: ='PT Recap costs'!H38/1000 -> 3.3333333 | L21: ='PT Recap costs'!I38/1000 -> 3.3333333 | ... P21: ='PT Recap costs'!M38/1000 -> 3.3333333 | Q21: =SUM(E21:P21) -> 40
D22: NET | E22: =E14+E15 -> -11.630296 | F22: =F14+F15 -> -63.286331 | G22: =G14+G15 -> -49.279757 | H22: =H14+H15 -> -53.280247 | I22: =I14+I15 -> 70.135979 | J22: =J14+J15 -> 70.135979 | K22: =K14+K15 -> 70.135979 | L22: =L14+L15 -> 70.135979 | ... Q22: =Q14+Q15 -> 1099.6222
B24: T3 | C24: Nutrow & Feedim evolution | D24: Cash in from Revenue | E24: 0 | F24: 0 | G24: 0 | H24: 0 | I24: 0 | J24: 0 | K24: 0 | L24: 0 | M24: 0 | N24: 0 | O24: 0 | P24: 0 | Q24: =SUM(E24:P24) -> 0
D25: COSTS | E25: =-SUM(E26:E31) -> -181.23446 | F25: =-SUM(F26:F31) -> -183.98446 | G25: =-SUM(G26:G31) -> -179.27117 | H25: =-SUM(H26:H31) -> -259.02117 | I25: =-SUM(I26:I31) -> -248.98446 | J25: =-SUM(J26:J31) -> -218.73446 | K25: =-SUM(K26:K31) -> -141.73446 | L25: =-SUM(L26:L31) -> -180.23446 | ... Q25: =-SUM(Q26:Q31) -> -2536.887
D26: COGS | E26: =COGS!C12/1000 -> 0 | F26: =COGS!D12/1000 -> 0 | G26: =COGS!E12/1000 -> 0 | H26: =COGS!F12/1000 -> 0 | I26: =COGS!G12/1000 -> 0 | J26: =COGS!H12/1000 -> 0 | K26: =COGS!I12/1000 -> 0 | L26: =COGS!J12/1000 -> 0 | ... P26: =COGS!N12/1000 -> 0 | Q26: =SUM(E26:P26) -> 0
D27: Consultancies | E27: ='PT Recap costs'!B55/1000 -> 75 | F27: ='PT Recap costs'!C55/1000 -> 75 | G27: ='PT Recap costs'!D55/1000 -> 75 | H27: ='PT Recap costs'!E55/1000 -> 75 | I27: ='PT Recap costs'!F55/1000 -> 30 | J27: ='PT Recap costs'!G55/1000 -> 30 | K27: ='PT Recap costs'!H55/1000 -> 30 | L27: ='PT Recap costs'!I55/1000 -> 30 | ... P27: ='PT Recap costs'!M55/1000 -> 30 | Q27: =SUM(E27:P27) -> 540
D28: Development & op. | E28: ='PT Recap costs'!B56/1000 -> 100.67891 | F28: ='PT Recap costs'!C56/1000 -> 100.67891 | G28: ='PT Recap costs'!D56/1000 -> 95.965611 | H28: ='PT Recap costs'!E56/1000 -> 172.96561 | I28: ='PT Recap costs'!F56/1000 -> 207.92891 | J28: ='PT Recap costs'!G56/1000 -> 177.67891 | K28: ='PT Recap costs'!H56/1000 -> 100.67891 | L28: ='PT Recap costs'!I56/1000 -> 139.17891 | ... P28: ='PT Recap costs'!M56/1000 -> 229.92891 | Q28: =SUM(E28:P28) -> 1875.2203
D29: E&F | E29: ='PT Recap costs'!B57/1000 -> 0 | F29: ='PT Recap costs'!C57/1000 -> 2.75 | G29: ='PT Recap costs'!D57/1000 -> 2.75 | H29: ='PT Recap costs'!E57/1000 -> 5.5 | I29: ='PT Recap costs'!F57/1000 -> 5.5 | J29: ='PT Recap costs'!G57/1000 -> 5.5 | K29: ='PT Recap costs'!H57/1000 -> 5.5 | L29: ='PT Recap costs'!I57/1000 -> 5.5 | ... P29: ='PT Recap costs'!M57/1000 -> 5.5 | Q29: =SUM(E29:P29) -> 55
D30: Legal | E30: ='PT Recap costs'!B29/1000 -> 0.55555556 | F30: ='PT Recap costs'!C29/1000 -> 0.55555556 | G30: ='PT Recap costs'!D29/1000 -> 0.55555556 | H30: ='PT Recap costs'!E29/1000 -> 0.55555556 | I30: ='PT Recap costs'!F29/1000 -> 0.55555556 | J30: ='PT Recap costs'!G29/1000 -> 0.55555556 | K30: ='PT Recap costs'!H29/1000 -> 0.55555556 | L30: ='PT Recap costs'!I29/1000 -> 0.55555556 | ... P30: ='PT Recap costs'!M29/1000 -> 0.55555556 | Q30: =SUM(E30:P30) -> 6.6666667
D31: T&E | E31: ='PT Recap costs'!B30/1000 -> 5 | F31: ='PT Recap costs'!C30/1000 -> 5 | G31: ='PT Recap costs'!D30/1000 -> 5 | H31: ='PT Recap costs'!E30/1000 -> 5 | I31: ='PT Recap costs'!F30/1000 -> 5 | J31: ='PT Recap costs'!G30/1000 -> 5 | K31: ='PT Recap costs'!H30/1000 -> 5 | L31: ='PT Recap costs'!I30/1000 -> 5 | ... P31: ='PT Recap costs'!M30/1000 -> 5 | Q31: =SUM(E31:P31) -> 60
D32: NET | E32: =E24+E25 -> -181.23446 | F32: =F24+F25 -> -183.98446 | G32: =G24+G25 -> -179.27117 | H32: =H24+H25 -> -259.02117 | I32: =I24+I25 -> -248.98446 | J32: =J24+J25 -> -218.73446 | K32: =K24+K25 -> -141.73446 | L32: =L24+L25 -> -180.23446 | ... Q32: =Q24+Q25 -> -2536.887
B34: T4 | C34: Oncology: development | D34: Cash in from Revenue | E34: 0 | F34: 0 | G34: 0 | H34: 0 | I34: 0 | J34: 0 | K34: 0 | L34: 0 | M34: 0 | N34: 0 | O34: 0 | P34: 0 | Q34: =SUM(E34:P34) -> 0
D35: COSTS | E35: =-SUM(E36:E41) -> -11.805556 | F35: =-SUM(F36:F41) -> -42.055556 | G35: =-SUM(G36:G41) -> -46.768851 | H35: =-SUM(H36:H41) -> -76.768851 | I35: =-SUM(I36:I41) -> -60.805556 | J35: =-SUM(J36:J41) -> -60.805556 | K35: =-SUM(K36:K41) -> -91.055556 | L35: =-SUM(L36:L41) -> -110.30556 | ... Q35: =-SUM(Q36:Q41) -> -876.59326
D36: COGS | E36: =COGS!C14/1000 -> 0 | F36: =COGS!D14/1000 -> 0 | G36: =COGS!E14/1000 -> 0 | H36: =COGS!F14/1000 -> 0 | I36: =COGS!G14/1000 -> 0 | J36: =COGS!H14/1000 -> 0 | K36: =COGS!I14/1000 -> 0 | L36: =COGS!J14/1000 -> 0 | ... P36: =COGS!N14/1000 -> 0 | Q36: =SUM(E36:P36) -> 0
D37: Consultancies | E37: ='PT Recap costs'!B59/1000 -> 0 | F37: ='PT Recap costs'!C59/1000 -> 0 | G37: ='PT Recap costs'!D59/1000 -> 0 | H37: ='PT Recap costs'!E59/1000 -> 0 | I37: ='PT Recap costs'!F59/1000 -> 0 | J37: ='PT Recap costs'!G59/1000 -> 0 | K37: ='PT Recap costs'!H59/1000 -> 0 | L37: ='PT Recap costs'!I59/1000 -> 0 | ... P37: ='PT Recap costs'!M59/1000 -> 0 | Q37: =SUM(E37:P37) -> 0
D38: Development & op. | E38: ='PT Recap costs'!B60/1000 -> 0 | F38: ='PT Recap costs'!C60/1000 -> 30.25 | G38: ='PT Recap costs'!D60/1000 -> 34.963295 | H38: ='PT Recap costs'!E60/1000 -> 64.963295 | I38: ='PT Recap costs'!F60/1000 -> 60.25 | J38: ='PT Recap costs'!G60/1000 -> 60.25 | K38: ='PT Recap costs'!H60/1000 -> 90.5 | L38: ='PT Recap costs'!I60/1000 -> 109.75 | ... P38: ='PT Recap costs'!M60/1000 -> 93.5 | Q38: =SUM(E38:P38) -> 824.92659
D39: E&F | E39: ='PT Recap costs'!B61/1000 -> 11.25 | F39: ='PT Recap costs'!C61/1000 -> 11.25 | G39: ='PT Recap costs'!D61/1000 -> 11.25 | H39: ='PT Recap costs'!E61/1000 -> 11.25 | I39: ='PT Recap costs'!F61/1000 -> 0 | J39: ='PT Recap costs'!G61/1000 -> 0 | K39: ='PT Recap costs'!H61/1000 -> 0 | L39: ='PT Recap costs'!I61/1000 -> 0 | ... P39: ='PT Recap costs'!M61/1000 -> 0 | Q39: =SUM(E39:P39) -> 45
D40: Legal | E40: ='PT Recap costs'!B40/1000 -> 0.55555556 | F40: ='PT Recap costs'!C40/1000 -> 0.55555556 | G40: ='PT Recap costs'!D40/1000 -> 0.55555556 | H40: ='PT Recap costs'!E40/1000 -> 0.55555556 | I40: ='PT Recap costs'!F40/1000 -> 0.55555556 | J40: ='PT Recap costs'!G40/1000 -> 0.55555556 | K40: ='PT Recap costs'!H40/1000 -> 0.55555556 | L40: ='PT Recap costs'!I40/1000 -> 0.55555556 | ... P40: ='PT Recap costs'!M40/1000 -> 0.55555556 | Q40: =SUM(E40:P40) -> 6.6666667
D41: T&E | E41: ='PT Recap costs'!B41/1000 -> 0 | F41: ='PT Recap costs'!C41/1000 -> 0 | G41: ='PT Recap costs'!D41/1000 -> 0 | H41: ='PT Recap costs'!E41/1000 -> 0 | I41: ='PT Recap costs'!F41/1000 -> 0 | J41: ='PT Recap costs'!G41/1000 -> 0 | K41: ='PT Recap costs'!H41/1000 -> 0 | L41: ='PT Recap costs'!I41/1000 -> 0 | ... P41: ='PT Recap costs'!M41/1000 -> 0 | Q41: =SUM(E41:P41) -> 0
D42: NET | E42: =E34+E35 -> -11.805556 | F42: =F34+F35 -> -42.055556 | G42: =G34+G35 -> -46.768851 | H42: =H34+H35 -> -76.768851 | I42: =I34+I35 -> -60.805556 | J42: =J34+J35 -> -60.805556 | K42: =K34+K35 -> -91.055556 | L42: =L34+L35 -> -110.30556 | ... Q42: =Q34+Q35 -> -876.59326
B44: T5 | C44: Operations organisation (Services): Installation & Interfaçage | D44: Cash in from Revenue | E44: 48.125 | F44: 20.625 | G44: 48.125 | H44: 20.625 | I44: 90.75 | J44: 140.25 | K44: 189.75 | L44: 239.25 | M44: 103.125 | N44: 103.125 | O44: 103.125 | P44: 103.125 | Q44: =SUM(E44:P44) -> 1210
D45: COSTS | E45: =-SUM(E46:E51) -> -36.055556 | F45: =-SUM(F46:F51) -> -36.055556 | G45: =-SUM(G46:G51) -> -36.055556 | H45: =-SUM(H46:H51) -> -36.055556 | I45: =-SUM(I46:I51) -> -150.80556 | J45: =-SUM(J46:J51) -> -150.80556 | K45: =-SUM(K46:K51) -> -134.30556 | L45: =-SUM(L46:L51) -> -134.30556 | ... Q45: =-SUM(Q46:Q51) -> -1285.4917
D46: COGS | E46: =COGS!C16/1000 -> 0 | F46: =COGS!D16/1000 -> 0 | G46: =COGS!E16/1000 -> 0 | H46: =COGS!F16/1000 -> 0 | I46: =COGS!G16/1000 -> 0 | J46: =COGS!H16/1000 -> 0 | K46: =COGS!I16/1000 -> 0 | L46: =COGS!J16/1000 -> 0 | ... P46: =COGS!N16/1000 -> 0 | Q46: =SUM(E46:P46) -> 0
D47: Consultancies | E47: ='PT Recap costs'!B63/1000 -> 1 | F47: ='PT Recap costs'!C63/1000 -> 1 | G47: ='PT Recap costs'!D63/1000 -> 1 | H47: ='PT Recap costs'!E63/1000 -> 1 | I47: ='PT Recap costs'!F63/1000 -> 1 | J47: ='PT Recap costs'!G63/1000 -> 1 | K47: ='PT Recap costs'!H63/1000 -> 1 | L47: ='PT Recap costs'!I63/1000 -> 1 | ... P47: ='PT Recap costs'!M63/1000 -> 1 | Q47: =SUM(E47:P47) -> 12
D48: Development & op. | E48: ='PT Recap costs'!B64/1000 -> 27 | F48: ='PT Recap costs'!C64/1000 -> 27 | G48: ='PT Recap costs'!D64/1000 -> 27 | H48: ='PT Recap costs'!E64/1000 -> 27 | I48: ='PT Recap costs'!F64/1000 -> 134.25 | J48: ='PT Recap costs'!G64/1000 -> 134.25 | K48: ='PT Recap costs'!H64/1000 -> 87.5 | L48: ='PT Recap costs'!I64/1000 -> 87.5 | ... P48: ='PT Recap costs'!M64/1000 -> 87.5 | Q48: =SUM(E48:P48) -> 901.5
D49: E&F | E49: ='PT Recap costs'!B65/1000 -> 0 | F49: ='PT Recap costs'!C65/1000 -> 0 | G49: ='PT Recap costs'!D65/1000 -> 0 | H49: ='PT Recap costs'!E65/1000 -> 0 | I49: ='PT Recap costs'!F65/1000 -> 0 | J49: ='PT Recap costs'!G65/1000 -> 0 | K49: ='PT Recap costs'!H65/1000 -> 30.25 | L49: ='PT Recap costs'!I65/1000 -> 30.25 | ... P49: ='PT Recap costs'!M65/1000 -> 41.525 | Q49: =SUM(E49:P49) -> 215.325
D50: Legal | E50: ='PT Recap costs'!B13/1000 -> 0.55555556 | F50: ='PT Recap costs'!C13/1000 -> 0.55555556 | G50: ='PT Recap costs'!D13/1000 -> 0.55555556 | H50: ='PT Recap costs'!E13/1000 -> 0.55555556 | I50: ='PT Recap costs'!F13/1000 -> 0.55555556 | J50: ='PT Recap costs'!G13/1000 -> 0.55555556 | K50: ='PT Recap costs'!H13/1000 -> 0.55555556 | L50: ='PT Recap costs'!I13/1000 -> 0.55555556 | ... P50: ='PT Recap costs'!M13/1000 -> 0.55555556 | Q50: =SUM(E50:P50) -> 6.6666667
D51: T&E | E51: ='PT Recap costs'!B14/1000 -> 7.5 | F51: ='PT Recap costs'!C14/1000 -> 7.5 | G51: ='PT Recap costs'!D14/1000 -> 7.5 | H51: ='PT Recap costs'!E14/1000 -> 7.5 | I51: ='PT Recap costs'!F14/1000 -> 15 | J51: ='PT Recap costs'!G14/1000 -> 15 | K51: ='PT Recap costs'!H14/1000 -> 15 | L51: ='PT Recap costs'!I14/1000 -> 15 | ... P51: ='PT Recap costs'!M14/1000 -> 15 | Q51: =SUM(E51:P51) -> 150
D52: NET | E52: =E44+E45 -> 12.069444 | F52: =F44+F45 -> -15.430556 | G52: =G44+G45 -> 12.069444 | H52: =H44+H45 -> -15.430556 | I52: =I44+I45 -> -60.055556 | J52: =J44+J45 -> -10.555556 | K52: =K44+K45 -> 55.444444 | L52: =L44+L45 -> 104.94444 | ... Q52: =Q44+Q45 -> -75.491667
B54: T6 | C54: OEM Feedim | D54: Cash in from Revenue | E54: 0 | F54: 45 | G54: 0 | H54: 394.6 | I54: 218.5 | J54: 263.5 | K54: 263.5 | L54: 263.5 | M54: 394.6 | N54: 394.6 | O54: 394.6 | P54: 394.6 | Q54: =SUM(E54:P54) -> 3027
D55: COSTS | E55: =-SUM(E56:E61) -> -3.8888889 | F55: =-SUM(F56:F61) -> -18.888889 | G55: =-SUM(G56:G61) -> -33.888889 | H55: =-SUM(H56:H61) -> -233.88889 | I55: =-SUM(I56:I61) -> -158.88889 | J55: =-SUM(J56:J61) -> -158.88889 | K55: =-SUM(K56:K61) -> -248.88889 | L55: =-SUM(L56:L61) -> -248.88889 | ... Q55: =-SUM(Q56:Q61) -> -2435.4917
D56: COGS | E56: =COGS!C18/1000 -> 0 | F56: =COGS!D18/1000 -> 0 | G56: =COGS!E18/1000 -> 0 | H56: =COGS!F18/1000 -> 200 | I56: =COGS!G18/1000 -> 125 | J56: =COGS!H18/1000 -> 125 | K56: =COGS!I18/1000 -> 125 | L56: =COGS!J18/1000 -> 125 | ... P56: =COGS!N18/1000 -> 200 | Q56: =SUM(E56:P56) -> 1500
D57: Consultancies | E57: ='PT Recap costs'!B67/1000 -> 0 | F57: ='PT Recap costs'!C67/1000 -> 0 | G57: ='PT Recap costs'!D67/1000 -> 0 | H57: ='PT Recap costs'!E67/1000 -> 0 | I57: ='PT Recap costs'!F67/1000 -> 0 | J57: ='PT Recap costs'!G67/1000 -> 0 | K57: ='PT Recap costs'!H67/1000 -> 0 | L57: ='PT Recap costs'!I67/1000 -> 0 | ... P57: ='PT Recap costs'!M67/1000 -> 0 | Q57: =SUM(E57:P57) -> 0
D58: Development & op. | E58: ='PT Recap costs'!B68/1000 -> 0 | F58: ='PT Recap costs'!C68/1000 -> 0 | G58: ='PT Recap costs'!D68/1000 -> 0 | H58: ='PT Recap costs'!E68/1000 -> 0 | I58: ='PT Recap costs'!F68/1000 -> 0 | J58: ='PT Recap costs'!G68/1000 -> 0 | K58: ='PT Recap costs'!H68/1000 -> 0 | L58: ='PT Recap costs'!I68/1000 -> 0 | ... P58: ='PT Recap costs'!M68/1000 -> 0 | Q58: =SUM(E58:P58) -> 0
D59: E&F | E59: ='PT Recap costs'!B69/1000 -> 0 | F59: ='PT Recap costs'!C69/1000 -> 15 | G59: ='PT Recap costs'!D69/1000 -> 30 | H59: ='PT Recap costs'!E69/1000 -> 30 | I59: ='PT Recap costs'!F69/1000 -> 30 | J59: ='PT Recap costs'!G69/1000 -> 30 | K59: ='PT Recap costs'!H69/1000 -> 120 | L59: ='PT Recap costs'!I69/1000 -> 120 | ... P59: ='PT Recap costs'!M69/1000 -> 131.275 | Q59: =SUM(E59:P59) -> 888.825
D60: Legal | E60: ='PT Recap costs'!B25/1000 -> 0.55555556 | F60: ='PT Recap costs'!C25/1000 -> 0.55555556 | G60: ='PT Recap costs'!D25/1000 -> 0.55555556 | H60: ='PT Recap costs'!E25/1000 -> 0.55555556 | I60: ='PT Recap costs'!F25/1000 -> 0.55555556 | J60: ='PT Recap costs'!G25/1000 -> 0.55555556 | K60: ='PT Recap costs'!H25/1000 -> 0.55555556 | L60: ='PT Recap costs'!I25/1000 -> 0.55555556 | ... P60: ='PT Recap costs'!M25/1000 -> 0.55555556 | Q60: =SUM(E60:P60) -> 6.6666667
D61: T&E | E61: ='PT Recap costs'!B26/1000 -> 3.3333333 | F61: ='PT Recap costs'!C26/1000 -> 3.3333333 | G61: ='PT Recap costs'!D26/1000 -> 3.3333333 | H61: ='PT Recap costs'!E26/1000 -> 3.3333333 | I61: ='PT Recap costs'!F26/1000 -> 3.3333333 | J61: ='PT Recap costs'!G26/1000 -> 3.3333333 | K61: ='PT Recap costs'!H26/1000 -> 3.3333333 | L61: ='PT Recap costs'!I26/1000 -> 3.3333333 | ... P61: ='PT Recap costs'!M26/1000 -> 3.3333333 | Q61: =SUM(E61:P61) -> 40
D62: NET | E62: =E54+E55 -> -3.8888889 | F62: =F54+F55 -> 26.111111 | G62: =G54+G55 -> -33.888889 | H62: =H54+H55 -> 160.71111 | I62: =I54+I55 -> 59.611111 | J62: =J54+J55 -> 104.61111 | K62: =K54+K55 -> 14.611111 | L62: =L54+L55 -> 14.611111 | ... Q62: =Q54+Q55 -> 591.50833
B64: TARGETS | D64: Cash in from Revenue | E64: =E4+E14+E24+E34+E44+E54 -> 83.728962 | F64: =F4+F14+F24+F34+F44+F54 -> 148.37136 | G64: =G4+G14+G24+G34+G44+G54 -> 201.00207 | H64: =H4+H14+H24+H34+H44+H54 -> 865.24447 | I64: =I4+I14+I24+I34+I44+I54 -> 827.51854 | J64: =J4+J14+J24+J34+J44+J54 -> 1044.1707 | K64: =K4+K14+K24+K34+K44+K54 -> 1215.8229 | L64: =L4+L14+L24+L34+L44+L54 -> 1387.4751 | ... P64: =P4+P14+P24+P34+P44+P54 -> 2193.0856 | Q64: =SUM(E64:P64) -> 14545.676
D65: COSTS | E65: =-SUM(E66:E71) -> -282.06269 | F65: =-SUM(F66:F71) -> -475.2746 | G65: =-SUM(G66:G71) -> -495.61888 | H65: =-SUM(H66:H71) -> -856.03775 | I65: =-SUM(I66:I71) -> -916.71308 | J65: =-SUM(J66:J71) -> -890.01416 | K65: =-SUM(K66:K71) -> -920.31525 | L65: =-SUM(L66:L71) -> -981.61633 | ... P65: =-SUM(P66:P71) -> -1245.0707 | Q65: =SUM(E65:P65) -> -10612.585
D66: COGS | E66: =E6+E16+E26+E36+E46+E56 -> 2.3482652 | F66: =F6+F16+F26+F36+F46+F56 -> 8.6851811 | G66: =G6+G16+G26+G36+G46+G56 -> 14.029459 | H66: =H6+H16+H26+H36+H46+H56 -> 219.59833 | I66: =I6+I16+I26+I36+I46+I56 -> 184.37366 | J66: =J6+J16+J26+J36+J46+J56 -> 187.92474 | K66: =K6+K16+K26+K36+K46+K56 -> 191.47582 | L66: =L6+L16+L26+L36+L46+L56 -> 195.02691 | ... P66: =P6+P16+P26+P36+P46+P56 -> 338.88125 | Q66: =SUM(E66:P66) -> 2358.9874
D67: Consultancies | E67: =E7+E17+E27+E37+E47+E57 -> 88.006 | F67: =F7+F17+F27+F37+F47+F57 -> 88.006 | G67: =G7+G17+G27+G37+G47+G57 -> 88.006 | H67: =H7+H17+H27+H37+H47+H57 -> 88.006 | I67: =I7+I17+I27+I37+I47+I57 -> 43.006 | J67: =J7+J17+J27+J37+J47+J57 -> 43.006 | K67: =K7+K17+K27+K37+K47+K57 -> 43.006 | L67: =L7+L17+L27+L37+L47+L57 -> 43.006 | ... P67: =P7+P17+P27+P37+P47+P57 -> 43.006 | Q67: =SUM(E67:P67) -> 696.072
D68: Development & op. | E68: =E8+E18+E28+E38+E48+E58 -> 127.67891 | F68: =F8+F18+F28+F38+F48+F58 -> 157.92891 | G68: =G8+G18+G28+G38+G48+G58 -> 157.92891 | H68: =H8+H18+H28+H38+H48+H58 -> 264.92891 | I68: =I8+I18+I28+I38+I48+I58 -> 402.42891 | J68: =J8+J18+J28+J38+J48+J58 -> 372.17891 | K68: =K8+K18+K28+K38+K48+K58 -> 278.67891 | L68: =L8+L18+L28+L38+L48+L58 -> 336.42891 | ... P68: =P8+P18+P28+P38+P48+P58 -> 410.92891 | Q68: =SUM(E68:P68) -> 3601.6469
D69: E&F | E69: =E9+E19+E29+E39+E49+E59 -> 38.19618 | F69: =F9+F19+F29+F39+F49+F59 -> 194.82118 | G69: =G9+G19+G29+G39+G49+G59 -> 209.82118 | H69: =H9+H19+H29+H39+H49+H59 -> 257.67118 | I69: =I9+I19+I29+I39+I49+I59 -> 253.57118 | J69: =J9+J19+J29+J39+J49+J59 -> 253.57118 | K69: =K9+K19+K29+K39+K49+K59 -> 373.82118 | L69: =L9+L19+L29+L39+L49+L59 -> 373.82118 | ... P69: =P9+P19+P29+P39+P49+P59 -> 418.92118 | Q69: =SUM(E69:P69) -> 3585.8792
D70: Legal | E70: =E10+E20+E30+E40+E50+E60 -> 3.3333333 | F70: =F10+F20+F30+F40+F50+F60 -> 3.3333333 | G70: =G10+G20+G30+G40+G50+G60 -> 3.3333333 | H70: =H10+H20+H30+H40+H50+H60 -> 3.3333333 | I70: =I10+I20+I30+I40+I50+I60 -> 3.3333333 | J70: =J10+J20+J30+J40+J50+J60 -> 3.3333333 | K70: =K10+K20+K30+K40+K50+K60 -> 3.3333333 | L70: =L10+L20+L30+L40+L50+L60 -> 3.3333333 | ... P70: =P10+P20+P30+P40+P50+P60 -> 3.3333333 | Q70: =SUM(E70:P70) -> 40
D71: T&E | E71: =E11+E21+E31+E41+E51+E61 -> 22.5 | F71: =F11+F21+F31+F41+F51+F61 -> 22.5 | G71: =G11+G21+G31+G41+G51+G61 -> 22.5 | H71: =H11+H21+H31+H41+H51+H61 -> 22.5 | I71: =I11+I21+I31+I41+I51+I61 -> 30 | J71: =J11+J21+J31+J41+J51+J61 -> 30 | K71: =K11+K21+K31+K41+K51+K61 -> 30 | L71: =L11+L21+L31+L41+L51+L61 -> 30 | ... P71: =P11+P21+P31+P41+P51+P61 -> 30 | Q71: =SUM(E71:P71) -> 330
D72: NET | E72: =E64+E65 -> -198.33372 | F72: =F64+F65 -> -326.90325 | G72: =G64+G65 -> -294.61681 | H72: =H64+H65 -> 9.2067159 | I72: =I64+I65 -> -89.194535 | J72: =J64+J65 -> 154.15656 | K72: =K64+K65 -> 295.50765 | L72: =L64+L65 -> 405.85875 | ... Q72: =Q64+Q65 -> 3933.091
B74: Costs not allocated to targets | D74: COSTS | E74: =-SUM(E75:E80) -> -170.34563 | F74: =-SUM(F75:F80) -> -171.67886 | G74: =-SUM(G75:G80) -> -194.86435 | H74: =-SUM(H75:H80) -> -208.56414 | I74: =-SUM(I75:I80) -> -235.78606 | J74: =-SUM(J75:J80) -> -240.25444 | K74: =-SUM(K75:K80) -> -243.79471 | L74: =-SUM(L75:L80) -> -247.33499 | ... Q74: =-SUM(Q75:Q80) -> -2768.425
D75: Consultancies | E75: ='PT Recap costs'!B71/1000 -> 22.2 | F75: ='PT Recap costs'!C71/1000 -> 22.2 | G75: ='PT Recap costs'!D71/1000 -> 22.2 | H75: ='PT Recap costs'!E71/1000 -> 22.2 | I75: ='PT Recap costs'!F71/1000 -> 22.2 | J75: ='PT Recap costs'!G71/1000 -> 22.2 | K75: ='PT Recap costs'!H71/1000 -> 22.2 | L75: ='PT Recap costs'!I71/1000 -> 22.2 | ... P75: ='PT Recap costs'!M71/1000 -> 22.2 | Q75: =SUM(E75:P75) -> 266.4
D76: Development & op. | E76: ='PT Recap costs'!B72/1000 -> 0 | F76: ='PT Recap costs'!C72/1000 -> 0 | G76: ='PT Recap costs'!D72/1000 -> 0 | H76: ='PT Recap costs'!E72/1000 -> 0 | I76: ='PT Recap costs'!F72/1000 -> 0 | J76: ='PT Recap costs'!G72/1000 -> 0 | K76: ='PT Recap costs'!H72/1000 -> 0 | L76: ='PT Recap costs'!I72/1000 -> 0 | ... P76: ='PT Recap costs'!M72/1000 -> 0 | Q76: =SUM(E76:P76) -> 0
D77: E&F | E77: ='PT Recap costs'!B73/1000 -> 135.41875 | F77: ='PT Recap costs'!C73/1000 -> 135.41875 | G77: ='PT Recap costs'!D73/1000 -> 146.51875 | H77: ='PT Recap costs'!E73/1000 -> 146.51875 | I77: ='PT Recap costs'!F73/1000 -> 152.51875 | J77: ='PT Recap costs'!G73/1000 -> 152.51875 | K77: ='PT Recap costs'!H73/1000 -> 152.51875 | L77: ='PT Recap costs'!I73/1000 -> 152.51875 | ... P77: ='PT Recap costs'!M73/1000 -> 152.51875 | Q77: =SUM(E77:P77) -> 1784.025
D78: Legal | E78: 0 | F78: 0 | G78: 0 | H78: 0 | I78: 0 | J78: 0 | K78: 0 | L78: 0 | M78: 0 | N78: 0 | O78: 0 | P78: 0 | Q78: =SUM(E78:P78) -> 0
D79: T&E | E79: 0 | F79: 0 | G79: 0 | H79: 0 | I79: 0 | J79: 0 | K79: 0 | L79: 0 | M79: 0 | N79: 0 | O79: 0 | P79: 0 | Q79: =SUM(E79:P79) -> 0
D80: Marketing | E80: ='PT Recap costs'!B5/1000 -> 12.726883 | F80: ='PT Recap costs'!C5/1000 -> 14.060113 | G80: ='PT Recap costs'!D5/1000 -> 26.145604 | H80: ='PT Recap costs'!E5/1000 -> 39.845395 | I80: ='PT Recap costs'!F5/1000 -> 61.06731 | J80: ='PT Recap costs'!G5/1000 -> 65.535693 | K80: ='PT Recap costs'!H5/1000 -> 69.075965 | L80: ='PT Recap costs'!I5/1000 -> 72.616237 | ... P80: ='PT Recap costs'!M5/1000 -> 89.2317 | Q80: =SUM(E80:P80) -> 718
D81: NET | E81: =E74 -> -170.34563 | F81: =F74 -> -171.67886 | G81: =G74 -> -194.86435 | H81: =H74 -> -208.56414 | I81: =I74 -> -235.78606 | J81: =J74 -> -240.25444 | K81: =K74 -> -243.79471 | L81: =L74 -> -247.33499 | ... Q81: =Q74 -> -2768.425
B83: G&A | D83: COSTS | E83: =-SUM(E84:E88) -> -103.2092 | F83: =-SUM(F84:F88) -> -136.41355 | G83: =-SUM(G84:G88) -> -71.394113 | H83: =-SUM(H84:H88) -> -123.76959 | I83: =-SUM(I84:I88) -> -124.06672 | J83: =-SUM(J84:J88) -> -88.103159 | K83: =-SUM(K84:K88) -> -101.3012 | L83: =-SUM(L84:L88) -> -124.49925 | ... P83: =-SUM(P84:P88) -> -122.50855 | Q83: =SUM(E83:P83) -> -1362.791
D84: Facilities | E84: ='PT Recap costs'!B7/1000 -> 11.85 | F84: ='PT Recap costs'!C7/1000 -> 11.85 | G84: ='PT Recap costs'!D7/1000 -> 11.85 | H84: ='PT Recap costs'!E7/1000 -> 11.85 | I84: ='PT Recap costs'!F7/1000 -> 13.85 | J84: ='PT Recap costs'!G7/1000 -> 13.85 | K84: ='PT Recap costs'!H7/1000 -> 13.85 | L84: ='PT Recap costs'!I7/1000 -> 13.85 | ... P84: ='PT Recap costs'!M7/1000 -> 16.35 | Q84: =SUM(E84:P84) -> 168.2
D85: Finance | E85: ='PT Recap costs'!B8/1000 -> 16 | F85: ='PT Recap costs'!C8/1000 -> 16 | G85: ='PT Recap costs'!D8/1000 -> 16 | H85: ='PT Recap costs'!E8/1000 -> 16 | I85: ='PT Recap costs'!F8/1000 -> 16 | J85: ='PT Recap costs'!G8/1000 -> 16 | K85: ='PT Recap costs'!H8/1000 -> 16 | L85: ='PT Recap costs'!I8/1000 -> 16 | ... P85: ='PT Recap costs'!M8/1000 -> 16 | Q85: =SUM(E85:P85) -> 192
D86: HR/Admin | E86: ='PT Recap costs'!B9/1000 -> 66.951791 | F86: ='PT Recap costs'!C9/1000 -> 99.06956 | G86: ='PT Recap costs'!D9/1000 -> 40.165445 | H86: ='PT Recap costs'!E9/1000 -> 81.375593 | I86: ='PT Recap costs'!F9/1000 -> 80.306862 | J86: ='PT Recap costs'!G9/1000 -> 40.70157 | K86: ='PT Recap costs'!H9/1000 -> 51.014294 | L86: ='PT Recap costs'!I9/1000 -> 71.327018 | ... P86: ='PT Recap costs'!M9/1000 -> 53.294717 | Q86: =SUM(E86:P86) -> 744.091
D87: Other costs | E87: ='PT Recap costs'!B10/1000 -> 1.4074101 | F87: ='PT Recap costs'!C10/1000 -> 2.4939917 | G87: ='PT Recap costs'!D10/1000 -> 3.3786677 | H87: ='PT Recap costs'!E10/1000 -> 14.543997 | I87: ='PT Recap costs'!F10/1000 -> 13.909857 | J87: ='PT Recap costs'!G10/1000 -> 17.55159 | K87: ='PT Recap costs'!H10/1000 -> 20.436911 | L87: ='PT Recap costs'!I10/1000 -> 23.322233 | ... P87: ='PT Recap costs'!M10/1000 -> 36.863836 | Q87: =SUM(E87:P87) -> 244.5
D88: Capital increase | E88: ='PT Recap costs'!B11/1000 -> 7 | F88: ='PT Recap costs'!C11/1000 -> 7 | G88: ='PT Recap costs'!D11/1000 -> 0 | H88: ='PT Recap costs'!E11/1000 -> 0 | I88: ='PT Recap costs'!F11/1000 -> 0 | J88: ='PT Recap costs'!G11/1000 -> 0 | K88: ='PT Recap costs'!H11/1000 -> 0 | L88: ='PT Recap costs'!I11/1000 -> 0 | ... P88: ='PT Recap costs'!M11/1000 -> 0 | Q88: =SUM(E88:P88) -> 14
D89: NET | E89: =E83 -> -103.2092 | F89: =F83 -> -136.41355 | G89: =G83 -> -71.394113 | H89: =H83 -> -123.76959 | I89: =I83 -> -124.06672 | J89: =J83 -> -88.103159 | K89: =K83 -> -101.3012 | L89: =L83 -> -124.49925 | ... Q89: =Q83 -> -1362.791
B91: TOTAL | D91: Cash in from Revenue | E91: =E64 -> 83.728962 | F91: =F64 -> 148.37136 | G91: =G64 -> 201.00207 | H91: =H64 -> 865.24447 | I91: =I64 -> 827.51854 | J91: =J64 -> 1044.1707 | K91: =K64 -> 1215.8229 | L91: =L64 -> 1387.4751 | ... P91: =P64 -> 2193.0856 | Q91: =SUM(E91:P91) -> 14545.676
D92: COSTS | E92: =-SUM(E93:E104) -> -555.61752 | F92: =-SUM(F93:F104) -> -783.36702 | G92: =-SUM(G93:G104) -> -761.87735 | H92: =-SUM(H93:H104) -> -1188.3715 | I92: =-SUM(I93:I104) -> -1276.5659 | J92: =-SUM(J93:J104) -> -1218.3718 | K92: =-SUM(K93:K104) -> -1265.4112 | L92: =-SUM(L93:L104) -> -1353.4506 | ... P92: =-SUM(P93:P104) -> -1631.5297 | Q92: =SUM(E92:P92) -> -14743.801
D93: COGS | E93: =E66 -> 2.3482652 | F93: =F66 -> 8.6851811 | G93: =G66 -> 14.029459 | H93: =H66 -> 219.59833 | I93: =I66 -> 184.37366 | J93: =J66 -> 187.92474 | K93: =K66 -> 191.47582 | L93: =L66 -> 195.02691 | ... P93: =P66 -> 338.88125 | Q93: =SUM(E93:P93) -> 2358.9874
D94: Consultancies | E94: =E67+E75 -> 110.206 | F94: =F67+F75 -> 110.206 | G94: =G67+G75 -> 110.206 | H94: =H67+H75 -> 110.206 | I94: =I67+I75 -> 65.206 | J94: =J67+J75 -> 65.206 | K94: =K67+K75 -> 65.206 | L94: =L67+L75 -> 65.206 | ... P94: =P67+P75 -> 65.206 | Q94: =SUM(E94:P94) -> 962.472
D95: Development & op. | E95: =E68+E76 -> 127.67891 | F95: =F68+F76 -> 157.92891 | G95: =G68+G76 -> 157.92891 | H95: =H68+H76 -> 264.92891 | I95: =I68+I76 -> 402.42891 | J95: =J68+J76 -> 372.17891 | K95: =K68+K76 -> 278.67891 | L95: =L68+L76 -> 336.42891 | ... P95: =P68+P76 -> 410.92891 | Q95: =SUM(E95:P95) -> 3601.6469
D96: E&F | E96: =E69+E77 -> 173.61493 | F96: =F69+F77 -> 330.23993 | G96: =G69+G77 -> 356.33993 | H96: =H69+H77 -> 404.18993 | I96: =I69+I77 -> 406.08993 | J96: =J69+J77 -> 406.08993 | K96: =K69+K77 -> 526.33993 | L96: =L69+L77 -> 526.33993 | ... P96: =P69+P77 -> 571.43993 | Q96: =SUM(E96:P96) -> 5369.9042
D97: Legal | E97: =E70+E78 -> 3.3333333 | F97: =F70+F78 -> 3.3333333 | G97: =G70+G78 -> 3.3333333 | H97: =H70+H78 -> 3.3333333 | I97: =I70+I78 -> 3.3333333 | J97: =J70+J78 -> 3.3333333 | K97: =K70+K78 -> 3.3333333 | L97: =L70+L78 -> 3.3333333 | ... P97: =P70+P78 -> 3.3333333 | Q97: =SUM(E97:P97) -> 40
D98: T&E | E98: =E71+E79 -> 22.5 | F98: =F71+F79 -> 22.5 | G98: =G71+G79 -> 22.5 | H98: =H71+H79 -> 22.5 | I98: =I71+I79 -> 30 | J98: =J71+J79 -> 30 | K98: =K71+K79 -> 30 | L98: =L71+L79 -> 30 | ... P98: =P71+P79 -> 30 | Q98: =SUM(E98:P98) -> 330
D99: Marketing | E99: =+E80 -> 12.726883 | F99: =+F80 -> 14.060113 | G99: =+G80 -> 26.145604 | H99: =+H80 -> 39.845395 | I99: =+I80 -> 61.06731 | J99: =+J80 -> 65.535693 | K99: =+K80 -> 69.075965 | L99: =+L80 -> 72.616237 | ... P99: =+P80 -> 89.2317 | Q99: =SUM(E99:P99) -> 718
D100: Facilities | E100: =E84 -> 11.85 | F100: =F84 -> 11.85 | G100: =G84 -> 11.85 | H100: =H84 -> 11.85 | I100: =I84 -> 13.85 | J100: =J84 -> 13.85 | K100: =K84 -> 13.85 | L100: =L84 -> 13.85 | ... P100: =P84 -> 16.35 | Q100: =SUM(E100:P100) -> 168.2
D101: Finance | E101: =E85 -> 16 | F101: =F85 -> 16 | G101: =G85 -> 16 | H101: =H85 -> 16 | I101: =I85 -> 16 | J101: =J85 -> 16 | K101: =K85 -> 16 | L101: =L85 -> 16 | ... P101: =P85 -> 16 | Q101: =SUM(E101:P101) -> 192
D102: HR/Admin | E102: =E86 -> 66.951791 | F102: =F86 -> 99.06956 | G102: =G86 -> 40.165445 | H102: =H86 -> 81.375593 | I102: =I86 -> 80.306862 | J102: =J86 -> 40.70157 | K102: =K86 -> 51.014294 | L102: =L86 -> 71.327018 | ... P102: =P86 -> 53.294717 | Q102: =SUM(E102:P102) -> 744.091
D103: Other costs | E103: =E87 -> 1.4074101 | F103: =F87 -> 2.4939917 | G103: =G87 -> 3.3786677 | H103: =H87 -> 14.543997 | I103: =I87 -> 13.909857 | J103: =J87 -> 17.55159 | K103: =K87 -> 20.436911 | L103: =L87 -> 23.322233 | ... P103: =P87 -> 36.863836 | Q103: =SUM(E103:P103) -> 244.5
D104: Capital increase | E104: =E88 -> 7 | F104: =F88 -> 7 | G104: =G88 -> 0 | H104: =H88 -> 0 | I104: =I88 -> 0 | J104: =J88 -> 0 | K104: =K88 -> 0 | L104: =L88 -> 0 | ... P104: =P88 -> 0 | Q104: =SUM(E104:P104) -> 14
D105: NET | E105: =E91+E92 -> -471.88856 | F105: =F91+F92 -> -634.99566 | G105: =G91+G92 -> -560.87528 | H105: =H91+H92 -> -323.12702 | I105: =I91+I92 -> -449.04731 | J105: =J91+J92 -> -174.20104 | K105: =K91+K92 -> -49.588268 | L105: =L91+L92 -> 34.024507 | ... Q105: =Q91+Q92 -> -198.12504
D106: Cumulated | E106: =E105 -> -471.88856 | F106: =E106+F105 -> -1106.8842 | G106: =F106+G105 -> -1667.7595 | H106: =G106+H105 -> -1990.8865 | I106: =H106+I105 -> -2439.9338 | J106: =I106+J105 -> -2614.1349 | K106: =J106+K105 -> -2663.7231 | L106: =K106+L105 -> -2629.6986 | M106: =L106+M105 -> -1986.2927 | ... P106: =O106+P105 -> -198.12504
E110: =E91/$Q$91 -> 0.0057562783 | F110: =F91/$Q$91 -> 0.010200375 | G110: =G91/$Q$91 -> 0.013818682 | H110: =H91/$Q$91 -> 0.05948465 | I110: =I91/$Q$91 -> 0.056891032 | J110: =J91/$Q$91 -> 0.071785642 | K110: =K91/$Q$91 -> 0.083586549 | L110: =L91/$Q$91 -> 0.095387456 | ... P110: =P91/$Q$91 -> 0.15077233

Sheet PT Recap costs
A3: Étiquettes de lignes | B3: Somme de Q1 21 | C3: Somme de Q2 21 | D3: Somme de Q3 21 | E3: Somme de Q4 21 | F3: Somme de Q1 22 | G3: Somme de Q2 22 | H3: Somme de Q3 22 | I3: Somme de Q4 22 | J3: Somme de Q1 23 | K3: Somme de Q2 23 | L3: Somme de Q3 23 | M3: Somme de Q4 23 | N3: TOTAL
A4: Costs not allocated to target | B4: 12726.883 | C4: 14060.113 | D4: 26145.604 | E4: 39845.395 | F4: 61067.31 | G4: 65535.693 | H4: 69075.965 | I4: 72616.237 | J4: 89231.7 | K4: 89231.7 | L4: 89231.7 | M4: 89231.7 | N4: =SUM(B4:M4) -> 718000
A5: Sales and bus dev | B5: 12726.883 | C5: 14060.113 | D5: 26145.604 | E5: 39845.395 | F5: 61067.31 | G5: 65535.693 | H5: 69075.965 | I5: 72616.237 | J5: 89231.7 | K5: 89231.7 | L5: 89231.7 | M5: 89231.7 | N5: =SUM(B5:M5) -> 718000
A6: G&A | B6: 103209.2 | C6: 136413.55 | D6: 71394.113 | E6: 123769.59 | F6: 124066.72 | G6: 88103.159 | H6: 101301.2 | I6: 124499.25 | J6: 132508.55 | K6: 122508.55 | L6: 112508.55 | M6: 122508.55 | N6: =SUM(B6:M6) -> 1362791
A7: Facilities | B7: 11850 | C7: 11850 | D7: 11850 | E7: 11850 | F7: 13850 | G7: 13850 | H7: 13850 | I7: 13850 | J7: 16350 | K7: 16350 | L7: 16350 | M7: 16350 | N7: =SUM(B7:M7) -> 168200
A8: Finance | B8: 16000 | C8: 16000 | D8: 16000 | E8: 16000 | F8: 16000 | G8: 16000 | H8: 16000 | I8: 16000 | J8: 16000 | K8: 16000 | L8: 16000 | M8: 16000 | N8: =SUM(B8:M8) -> 192000
A9: HR/Admin | B9: 66951.791 | C9: 99069.56 | D9: 40165.445 | E9: 81375.593 | F9: 80306.862 | G9: 40701.57 | H9: 51014.294 | I9: 71327.018 | J9: 63294.717 | K9: 53294.717 | L9: 43294.717 | M9: 53294.717 | N9: =SUM(B9:M9) -> 744091
A10: Other costs | B10: 1407.4101 | C10: 2493.9917 | D10: 3378.6677 | E10: 14543.997 | F10: 13909.857 | G10: 17551.59 | H10: 20436.911 | I10: 23322.233 | J10: 36863.836 | K10: 36863.836 | L10: 36863.836 | M10: 36863.836 | N10: =SUM(B10:M10) -> 244500
A11: Capital increase | B11: 7000 | C11: 7000 | D11: 0 | E11: 0 | F11: 0 | G11: 0 | H11: 0 | I11: 0 | J11: 0 | K11: 0 | L11: 0 | M11: 0 | N11: =SUM(B11:M11) -> 14000
A12: T5 | B12: 8055.5556 | C12: 8055.5556 | D12: 8055.5556 | E12: 8055.5556 | F12: 15555.556 | G12: 15555.556 | H12: 15555.556 | I12: 15555.556 | J12: 15555.556 | K12: 15555.556 | L12: 15555.556 | M12: 15555.556 | N12: =SUM(B12:M12) -> 156666.67
A13: Legal | B13: 555.55556 | C13: 555.55556 | D13: 555.55556 | E13: 555.55556 | F13: 555.55556 | G13: 555.55556 | H13: 555.55556 | I13: 555.55556 | J13: 555.55556 | K13: 555.55556 | L13: 555.55556 | M13: 555.55556 | N13: =SUM(B13:M13) -> 6666.6667
A14: T&E | B14: 7500 | C14: 7500 | D14: 7500 | E14: 7500 | F14: 15000 | G14: 15000 | H14: 15000 | I14: 15000 | J14: 15000 | K14: 15000 | L14: 15000 | M14: 15000 | N14: =SUM(B14:M14) -> 150000
A15: See Target allocation | B15: 411499.84 | C15: 598374.84 | D15: 624474.84 | E15: 779324.84 | F15: 873724.84 | G15: 843474.84 | H15: 870224.84 | I15: 927974.84 | J15: 955724.84 | K15: 1000824.8 | L15: 1000824.8 | M15: 1047574.8 | N15: =SUM(B15:M15) -> 9934023
... A30: T&E | B30: 5000 | C30: 5000 | D30: 5000 | E30: 5000 | F30: 5000 | G30: 5000 | H30: 5000 | I30: 5000 | J30: 5000 | K30: 5000 | L30: 5000 | M30: 5000 | N30: =SUM(B30:M30) -> 60000
A31: (vide) | N31: =SUM(B31:M31) -> 0
A32: (vide) | N32: =SUM(B32:M32) -> 0
A33: T1 | B33: 3888.8889 | C33: 3888.8889 | D33: 3888.8889 | E33: 3888.8889 | F33: 3888.8889 | G33: 3888.8889 | H33: 3888.8889 | I33: 3888.8889 | J33: 3888.8889 | K33: 3888.8889 | L33: 3888.8889 | M33: 3888.8889 | N33: =SUM(B33:M33) -> 46666.667
A34: Legal | B34: 555.55556 | C34: 555.55556 | D34: 555.55556 | E34: 555.55556 | F34: 555.55556 | G34: 555.55556 | H34: 555.55556 | I34: 555.55556 | J34: 555.55556 | K34: 555.55556 | L34: 555.55556 | M34: 555.55556 | N34: =SUM(B34:M34) -> 6666.6667
A35: T&E | B35: 3333.3333 | C35: 3333.3333 | D35: 3333.3333 | E35: 3333.3333 | F35: 3333.3333 | G35: 3333.3333 | H35: 3333.3333 | I35: 3333.3333 | J35: 3333.3333 | K35: 3333.3333 | L35: 3333.3333 | M35: 3333.3333 | N35: =SUM(B35:M35) -> 40000
A36: T2 | B36: 3888.8889 | C36: 3888.8889 | D36: 3888.8889 | E36: 3888.8889 | F36: 3888.8889 | G36: 3888.8889 | H36: 3888.8889 | I36: 3888.8889 | J36: 3888.8889 | K36: 3888.8889 | L36: 3888.8889 | M36: 3888.8889 | N36: =SUM(B36:M36) -> 46666.667
A37: Legal | B37: 555.55556 | C37: 555.55556 | D37: 555.55556 | E37: 555.55556 | F37: 555.55556 | G37: 555.55556 | H37: 555.55556 | I37: 555.55556 | J37: 555.55556 | K37: 555.55556 | L37: 555.55556 | M37: 555.55556 | N37: =SUM(B37:M37) -> 6666.6667
A38: T&E | B38: 3333.3333 | C38: 3333.3333 | D38: 3333.3333 | E38: 3333.3333 | F38: 3333.3333 | G38: 3333.3333 | H38: 3333.3333 | I38: 3333.3333 | J38: 3333.3333 | K38: 3333.3333 | L38: 3333.3333 | M38: 3333.3333 | N38: =SUM(B38:M38) -> 40000
A39: T4 | B39: 555.55556 | C39: 555.55556 | D39: 555.55556 | E39: 555.55556 | F39: 555.55556 | G39: 555.55556 | H39: 555.55556 | I39: 555.55556 | J39: 555.55556 | K39: 555.55556 | L39: 555.55556 | M39: 555.55556 | N39: =SUM(B39:M39) -> 6666.6667
A40: Legal | B40: 555.55556 | C40: 555.55556 | D40: 555.55556 | E40: 555.55556 | F40: 555.55556 | G40: 555.55556 | H40: 555.55556 | I40: 555.55556 | J40: 555.55556 | K40: 555.55556 | L40: 555.55556 | M40: 555.55556 | N40: =SUM(B40:M40) -> 6666.6667
A41: T&E | B41: 0 | C41: 0 | D41: 0 | E41: 0 | F41: 0 | G41: 0 | H41: 0 | I41: 0 | J41: 0 | K41: 0 | L41: 0 | M41: 0 | N41: =SUM(B41:M41) -> 0
A42: Total général | B42: 555617.52 | C42: 783367.02 | D42: 761877.35 | E42: 1188371.5 | F42: 1276565.9 | G42: 1218371.8 | H42: 1265411.2 | I42: 1353450.6 | J42: 1549679.7 | K42: 1584779.7 | L42: 1574779.7 | M42: 1631529.7 | N42: =SUM(B42:M42) -> 14743801
A45: Étiquettes de lignes | B45: Somme de Q1 212 | C45: Somme de Q2 212 | D45: Somme de Q3 212 | E45: Somme de Q4 212 | F45: Somme de Q1 222 | G45: Somme de Q2 222 | H45: Somme de Q3 222 | I45: Somme de Q4 22 | J45: Somme de Q1 232 | K45: Somme de Q2 232 | L45: Somme de Q3 232 | M45: Somme de Q4 232 | N45: TOTAL
A46: T1 | B46: 20979.09 | C46: 90416.59 | D46: 90416.59 | E46: 112966.59 | F46: 116541.59 | G46: 116541.59 | H46: 116541.59 | I46: 116541.59 | J46: 116541.59 | K46: 127816.59 | L46: 127816.59 | M46: 127816.59 | N46: =SUM(B46:M46) -> 1280936.6
A47: Consultancies | B47: 7506 | C47: 7506 | D47: 7506 | E47: 7506 | F47: 7506 | G47: 7506 | H47: 7506 | I47: 7506 | J47: 7506 | K47: 7506 | L47: 7506 | M47: 7506 | N47: =SUM(B47:M47) -> 90072
A48: Dev & Op | B48: 0 | C48: 0 | D48: 0 | E48: 0 | F48: 0 | G48: 0 | H48: 0 | I48: 0 | J48: 0 | K48: 0 | L48: 0 | M48: 0 | N48: =SUM(B48:M48) -> 0
A49: E&F | B49: 13473.09 | C49: 82910.59 | D49: 82910.59 | E49: 105460.59 | F49: 109035.59 | G49: 109035.59 | H49: 109035.59 | I49: 109035.59 | J49: 109035.59 | K49: 120310.59 | L49: 120310.59 | M49: 120310.59 | N49: =SUM(B49:M49) -> 1190864.6
A50: T2 | B50: 17973.09 | C50: 87410.59 | D50: 87410.59 | E50: 109960.59 | F50: 113535.59 | G50: 113535.59 | H50: 113535.59 | I50: 113535.59 | J50: 113535.59 | K50: 124810.59 | L50: 124810.59 | M50: 124810.59 | N50: =SUM(B50:M50) -> 1244864.6
A51: Consultancies | B51: 4500 | C51: 4500 | D51: 4500 | E51: 4500 | F51: 4500 | G51: 4500 | H51: 4500 | I51: 4500 | J51: 4500 | K51: 4500 | L51: 4500 | M51: 4500 | N51: =SUM(B51:M51) -> 54000
A52: Dev & Op | B52: 0 | C52: 0 | D52: 0 | E52: 0 | F52: 0 | G52: 0 | H52: 0 | I52: 0 | J52: 0 | K52: 0 | L52: 0 | M52: 0 | N52: =SUM(B52:M52) -> 0
A53: E&F | B53: 13473.09 | C53: 82910.59 | D53: 82910.59 | E53: 105460.59 | F53: 109035.59 | G53: 109035.59 | H53: 109035.59 | I53: 109035.59 | J53: 109035.59 | K53: 120310.59 | L53: 120310.59 | M53: 120310.59 | N53: =SUM(B53:M53) -> 1190864.6
A54: T3 | B54: 175678.91 | C54: 178428.91 | D54: 173715.61 | E54: 253465.61 | F54: 243428.91 | G54: 213178.91 | H54: 136178.91 | I54: 174678.91 | J54: 218678.91 | K54: 218678.91 | L54: 218678.91 | M54: 265428.91 | N54: =SUM(B54:M54) -> 2470220.3
A55: Consultancies | B55: 75000 | C55: 75000 | D55: 75000 | E55: 75000 | F55: 30000 | G55: 30000 | H55: 30000 | I55: 30000 | J55: 30000 | K55: 30000 | L55: 30000 | M55: 30000 | N55: =SUM(B55:M55) -> 540000
A56: Dev & Op | B56: 100678.91 | C56: 100678.91 | D56: 95965.611 | E56: 172965.61 | F56: 207928.91 | G56: 177678.91 | H56: 100678.91 | I56: 139178.91 | J56: 183178.91 | K56: 183178.91 | L56: 183178.91 | M56: 229928.91 | N56: =SUM(B56:M56) -> 1875220.3
A57: E&F | B57: 0 | C57: 2750 | D57: 2750 | E57: 5500 | F57: 5500 | G57: 5500 | H57: 5500 | I57: 5500 | J57: 5500 | K57: 5500 | L57: 5500 | M57: 5500 | N57: =SUM(B57:M57) -> 55000
... A74: Total général | B74: 411499.84 | C74: 598374.84 | D74: 624474.84 | E74: 779324.84 | F74: 873724.84 | G74: 843474.84 | H74: 870224.84 | I74: 927974.84 | J74: 955724.84 | K74: 1000824.8 | L74: 1000824.8 | M74: 1047574.8 | N74: =SUM(B74:M74) -> 9934023
N75: =SUM(B75:M75) -> 0
N76: =SUM(B76:M76) -> 0
N77: =SUM(B77:M77) -> 0
N78: =SUM(B78:M78) -> 0
N79: =SUM(B79:M79) -> 0
N80: =SUM(B80:M80) -> 0
N81: =SUM(B81:M81) -> 0

Sheet Recap costs
A1: Allocation | B1: Target | C1: Fonction | D1: Détails | E1: E&F + Consultancies | F1: Moyenne EFT | G1: Total | H1: Q1 21 | I1: Q2 21 | J1: Q3 21 | K1: Q4 21 | L1: Q1 22 | M1: Q2 22 | N1: Q3 22 | O1: Q4 22 | P1: Q1 23 | Q1: Q2 23 | R1: Q3 23 | S1: Q4 23 | T1: Total
A2: Capital increase | B2: G&A | E2: Consultancies | G2: =SUM(H2:S2) -> 14000 | H2: =14000/2 -> 7000 | I2: =14000/2 -> 7000 | J2: 0 | K2: 0 | L2: 0 | M2: 0 | N2: 0 | O2: 0 | P2: 0 | Q2: 0 | R2: 0 | S2: 0 | T2: =SUM(H2:S2) -> 14000
A3: Clinical affairs | B3: See Target allocation | C3: KOL Mngt (6) | D3: KOL Mngt (6) | E3: Consultancies | G3: =SUM(H3:S3) -> 240000 | H3: =VLOOKUP(C3,'Target allocation'!$B$2:$AF$51,19,FALSE) -> 20000 | I3: =VLOOKUP(C3,'Target allocation'!$B$2:$AF$51,20,FALSE) -> 20000 | J3: =VLOOKUP(C3,'Target allocation'!$B$2:$AF$51,21,FALSE) -> 20000 | K3: =VLOOKUP(C3,'Target allocation'!$B$2:$AF$51,22,FALSE) -> 20000 | L3: =VLOOKUP(C3,'Target allocation'!$B$2:$AF$51,23,FALSE) -> 20000 | M3: =VLOOKUP(C3,'Target allocation'!$B$2:$AF$51,24,FALSE) -> 20000 | N3: =VLOOKUP(C3,'Target allocation'!$B$2:$AF$51,25,FALSE) -> 20000 | O3: =VLOOKUP(C3,'Target allocation'!$B$2:$AF$51,26,FALSE) -> 20000 | P3: =VLOOKUP(C3,'Target allocation'!$B$2:$AF$51,27,FALSE) -> 20000 | Q3: =VLOOKUP(C3,'Target allocation'!$B$2:$AF$51,28,FALSE) -> 20000 | R3: =VLOOKUP(C3,'Target allocation'!$B$2:$AF$51,29,FALSE) -> 20000 | S3: =VLOOKUP(C3,'Target allocation'!$B$2:$AF$51,30,FALSE) -> 20000 | T3: =SUM(H3:S3) -> 240000
A4: Clinical affairs | B4: See Target allocation | C4: Italian KOL | D4: Fabiocchi | E4: Consultancies | G4: =SUM(H4:S4) -> 36072 | H4: =VLOOKUP(C4,'Target allocation'!$B$2:$AF$51,19,FALSE) -> 3006 | I4: =VLOOKUP(C4,'Target allocation'!$B$2:$AF$51,20,FALSE) -> 3006 | J4: =VLOOKUP(C4,'Target allocation'!$B$2:$AF$51,21,FALSE) -> 3006 | K4: =VLOOKUP(C4,'Target allocation'!$B$2:$AF$51,22,FALSE) -> 3006 | L4: =VLOOKUP(C4,'Target allocation'!$B$2:$AF$51,23,FALSE) -> 3006 | M4: =VLOOKUP(C4,'Target allocation'!$B$2:$AF$51,24,FALSE) -> 3006 | N4: =VLOOKUP(C4,'Target allocation'!$B$2:$AF$51,25,FALSE) -> 3006 | O4: =VLOOKUP(C4,'Target allocation'!$B$2:$AF$51,26,FALSE) -> 3006 | P4: =VLOOKUP(C4,'Target allocation'!$B$2:$AF$51,27,FALSE) -> 3006 | Q4: =VLOOKUP(C4,'Target allocation'!$B$2:$AF$51,28,FALSE) -> 3006 | R4: =VLOOKUP(C4,'Target allocation'!$B$2:$AF$51,29,FALSE) -> 3006 | S4: =VLOOKUP(C4,'Target allocation'!$B$2:$AF$51,30,FALSE) -> 3006 | T4: =SUM(H4:S4) -> 36072
A5: Clinical affairs | B5: See Target allocation | C5: Clinical Affairs watch | D5: DDG | E5: E&F | F5: =VLOOKUP(C5,'Target allocation'!$B$2:$G$51,6,FALSE) -> 0.05 | G5: =SUM(H5:S5) -> 17325 | H5: =VLOOKUP(C5,'Target allocation'!$B$2:$AF$51,19,FALSE) -> 1443.75 | I5: =VLOOKUP(C5,'Target allocation'!$B$2:$AF$51,20,FALSE) -> 1443.75 | J5: =VLOOKUP(C5,'Target allocation'!$B$2:$AF$51,21,FALSE) -> 1443.75 | K5: =VLOOKUP(C5,'Target allocation'!$B$2:$AF$51,22,FALSE) -> 1443.75 | L5: =VLOOKUP(C5,'Target allocation'!$B$2:$AF$51,23,FALSE) -> 1443.75 | M5: =VLOOKUP(C5,'Target allocation'!$B$2:$AF$51,24,FALSE) -> 1443.75 | N5: =VLOOKUP(C5,'Target allocation'!$B$2:$AF$51,25,FALSE) -> 1443.75 | O5: =VLOOKUP(C5,'Target allocation'!$B$2:$AF$51,26,FALSE) -> 1443.75 | P5: =VLOOKUP(C5,'Target allocation'!$B$2:$AF$51,27,FALSE) -> 1443.75 | Q5: =VLOOKUP(C5,'Target allocation'!$B$2:$AF$51,28,FALSE) -> 1443.75 | R5: =VLOOKUP(C5,'Target allocation'!$B$2:$AF$51,29,FALSE) -> 1443.75 | S5: =VLOOKUP(C5,'Target allocation'!$B$2:$AF$51,30,FALSE) -> 1443.75 | T5: =SUM(H5:S5) -> 17325
A6: Clinical affairs | B6: See Target allocation | C6: Clinical Affairs Onco | D6: TBH | E6: E&F | F6: =VLOOKUP(C6,'Target allocation'!$B$2:$G$51,6,FALSE) -> 0.083333333 | G6: =SUM(H6:S6) -> 45000 | H6: =VLOOKUP(C6,'Target allocation'!$B$2:$AF$51,19,FALSE) -> 11250 | I6: =VLOOKUP(C6,'Target allocation'!$B$2:$AF$51,20,FALSE) -> 11250 | J6: =VLOOKUP(C6,'Target allocation'!$B$2:$AF$51,21,FALSE) -> 11250 | K6: =VLOOKUP(C6,'Target allocation'!$B$2:$AF$51,22,FALSE) -> 11250 | L6: =VLOOKUP(C6,'Target allocation'!$B$2:$AF$51,23,FALSE) -> 0 | M6: =VLOOKUP(C6,'Target allocation'!$B$2:$AF$51,24,FALSE) -> 0 | N6: =VLOOKUP(C6,'Target allocation'!$B$2:$AF$51,25,FALSE) -> 0 | O6: =VLOOKUP(C6,'Target allocation'!$B$2:$AF$51,26,FALSE) -> 0 | P6: =VLOOKUP(C6,'Target allocation'!$B$2:$AF$51,27,FALSE) -> 0 | Q6: =VLOOKUP(C6,'Target allocation'!$B$2:$AF$51,28,FALSE) -> 0 | R6: =VLOOKUP(C6,'Target allocation'!$B$2:$AF$51,29,FALSE) -> 0 | S6: =VLOOKUP(C6,'Target allocation'!$B$2:$AF$51,30,FALSE) -> 0 | T6: =SUM(H6:S6) -> 45000
A7: Clinical affairs | B7: See Target allocation | C7: Medical director | D7: TBH | E7: E&F | F7: =VLOOKUP(C7,'Target allocation'!$B$2:$G$51,6,FALSE) -> 0.16666667 | G7: =SUM(H7:S7) -> 120000 | H7: =VLOOKUP(C7,'Target allocation'!$B$2:$AF$51,19,FALSE) -> 6000 | I7: =VLOOKUP(C7,'Target allocation'!$B$2:$AF$51,20,FALSE) -> 6000 | J7: =VLOOKUP(C7,'Target allocation'!$B$2:$AF$51,21,FALSE) -> 6000 | K7: =VLOOKUP(C7,'Target allocation'!$B$2:$AF$51,22,FALSE) -> 6000 | L7: =VLOOKUP(C7,'Target allocation'!$B$2:$AF$51,23,FALSE) -> 12000 | M7: =VLOOKUP(C7,'Target allocation'!$B$2:$AF$51,24,FALSE) -> 12000 | N7: =VLOOKUP(C7,'Target allocation'!$B$2:$AF$51,25,FALSE) -> 12000 | O7: =VLOOKUP(C7,'Target allocation'!$B$2:$AF$51,26,FALSE) -> 12000 | P7: =VLOOKUP(C7,'Target allocation'!$B$2:$AF$51,27,FALSE) -> 12000 | Q7: =VLOOKUP(C7,'Target allocation'!$B$2:$AF$51,28,FALSE) -> 12000 | R7: =VLOOKUP(C7,'Target allocation'!$B$2:$AF$51,29,FALSE) -> 12000 | S7: =VLOOKUP(C7,'Target allocation'!$B$2:$AF$51,30,FALSE) -> 12000 | T7: =SUM(H7:S7) -> 120000
A8: COGS | B8: T3 | D8: Wifi et 4G | G8: =SUM(H8:S8) -> 2358987.4 | H8: =COGS!C20 -> 2348.2652 | I8: =COGS!D20 -> 8685.1811 | J8: =COGS!E20 -> 14029.459 | K8: =COGS!F20 -> 219598.33 | L8: =COGS!G20 -> 184373.66 | M8: =COGS!H20 -> 187924.74 | N8: =COGS!I20 -> 191475.82 | O8: =COGS!J20 -> 195026.91 | ... S8: =COGS!N20 -> 338881.25 | T8: =SUM(H8:S8) -> 2358987.4
A9: Development | B9: See Target allocation | C9: Senior Engineer 3 | D9: GGO | E9: E&F | F9: =VLOOKUP(C9,'Target allocation'!$B$2:$G$51,6,FALSE) -> 1 | G9: =SUM(H9:S9) -> 396000 | H9: =VLOOKUP(C9,'Target allocation'!$B$2:$AF$51,19,FALSE) -> 33000 | I9: =VLOOKUP(C9,'Target allocation'!$B$2:$AF$51,20,FALSE) -> 33000 | J9: =VLOOKUP(C9,'Target allocation'!$B$2:$AF$51,21,FALSE) -> 33000 | K9: =VLOOKUP(C9,'Target allocation'!$B$2:$AF$51,22,FALSE) -> 33000 | L9: =VLOOKUP(C9,'Target allocation'!$B$2:$AF$51,23,FALSE) -> 33000 | M9: =VLOOKUP(C9,'Target allocation'!$B$2:$AF$51,24,FALSE) -> 33000 | N9: =VLOOKUP(C9,'Target allocation'!$B$2:$AF$51,25,FALSE) -> 33000 | O9: =VLOOKUP(C9,'Target allocation'!$B$2:$AF$51,26,FALSE) -> 33000 | P9: =VLOOKUP(C9,'Target allocation'!$B$2:$AF$51,27,FALSE) -> 33000 | Q9: =VLOOKUP(C9,'Target allocation'!$B$2:$AF$51,28,FALSE) -> 33000 | R9: =VLOOKUP(C9,'Target allocation'!$B$2:$AF$51,29,FALSE) -> 33000 | S9: =VLOOKUP(C9,'Target allocation'!$B$2:$AF$51,30,FALSE) -> 33000 | T9: =SUM(H9:S9) -> 396000
A10: Development | B10: See Target allocation | C10: Engineer 4 | D10: KSC | E10: E&F | F10: =VLOOKUP(C10,'Target allocation'!$B$2:$G$51,6,FALSE) -> 1 | G10: =SUM(H10:S10) -> 231000 | H10: =VLOOKUP(C10,'Target allocation'!$B$2:$AF$51,19,FALSE) -> 19250 | I10: =VLOOKUP(C10,'Target allocation'!$B$2:$AF$51,20,FALSE) -> 19250 | J10: =VLOOKUP(C10,'Target allocation'!$B$2:$AF$51,21,FALSE) -> 19250 | K10: =VLOOKUP(C10,'Target allocation'!$B$2:$AF$51,22,FALSE) -> 19250 | L10: =VLOOKUP(C10,'Target allocation'!$B$2:$AF$51,23,FALSE) -> 19250 | M10: =VLOOKUP(C10,'Target allocation'!$B$2:$AF$51,24,FALSE) -> 19250 | N10: =VLOOKUP(C10,'Target allocation'!$B$2:$AF$51,25,FALSE) -> 19250 | O10: =VLOOKUP(C10,'Target allocation'!$B$2:$AF$51,26,FALSE) -> 19250 | P10: =VLOOKUP(C10,'Target allocation'!$B$2:$AF$51,27,FALSE) -> 19250 | Q10: =VLOOKUP(C10,'Target allocation'!$B$2:$AF$51,28,FALSE) -> 19250 | R10: =VLOOKUP(C10,'Target allocation'!$B$2:$AF$51,29,FALSE) -> 19250 | S10: =VLOOKUP(C10,'Target allocation'!$B$2:$AF$51,30,FALSE) -> 19250 | T10: =SUM(H10:S10) -> 231000
A11: Development | B11: See Target allocation | C11: Engineer 5 | D11: RNU | E11: E&F | F11: =VLOOKUP(C11,'Target allocation'!$B$2:$G$51,6,FALSE) -> 1 | G11: =SUM(H11:S11) -> 165391.29 | H11: =VLOOKUP(C11,'Target allocation'!$B$2:$AF$51,19,FALSE) -> 13782.607 | I11: =VLOOKUP(C11,'Target allocation'!$B$2:$AF$51,20,FALSE) -> 13782.607 | J11: =VLOOKUP(C11,'Target allocation'!$B$2:$AF$51,21,FALSE) -> 13782.607 | K11: =VLOOKUP(C11,'Target allocation'!$B$2:$AF$51,22,FALSE) -> 13782.607 | L11: =VLOOKUP(C11,'Target allocation'!$B$2:$AF$51,23,FALSE) -> 13782.607 | M11: =VLOOKUP(C11,'Target allocation'!$B$2:$AF$51,24,FALSE) -> 13782.607 | N11: =VLOOKUP(C11,'Target allocation'!$B$2:$AF$51,25,FALSE) -> 13782.607 | O11: =VLOOKUP(C11,'Target allocation'!$B$2:$AF$51,26,FALSE) -> 13782.607 | P11: =VLOOKUP(C11,'Target allocation'!$B$2:$AF$51,27,FALSE) -> 13782.607 | Q11: =VLOOKUP(C11,'Target allocation'!$B$2:$AF$51,28,FALSE) -> 13782.607 | R11: =VLOOKUP(C11,'Target allocation'!$B$2:$AF$51,29,FALSE) -> 13782.607 | S11: =VLOOKUP(C11,'Target allocation'!$B$2:$AF$51,30,FALSE) -> 13782.607 | T11: =SUM(H11:S11) -> 165391.29
A12: Development | B12: See Target allocation | C12: Product Development Mgr | D12: USA | E12: E&F | F12: =VLOOKUP(C12,'Target allocation'!$B$2:$G$51,6,FALSE) -> 1 | G12: =SUM(H12:S12) -> 226238.16 | H12: =VLOOKUP(C12,'Target allocation'!$B$2:$AF$51,19,FALSE) -> 18853.18 | I12: =VLOOKUP(C12,'Target allocation'!$B$2:$AF$51,20,FALSE) -> 18853.18 | J12: =VLOOKUP(C12,'Target allocation'!$B$2:$AF$51,21,FALSE) -> 18853.18 | K12: =VLOOKUP(C12,'Target allocation'!$B$2:$AF$51,22,FALSE) -> 18853.18 | L12: =VLOOKUP(C12,'Target allocation'!$B$2:$AF$51,23,FALSE) -> 18853.18 | M12: =VLOOKUP(C12,'Target allocation'!$B$2:$AF$51,24,FALSE) -> 18853.18 | N12: =VLOOKUP(C12,'Target allocation'!$B$2:$AF$51,25,FALSE) -> 18853.18 | O12: =VLOOKUP(C12,'Target allocation'!$B$2:$AF$51,26,FALSE) -> 18853.18 | P12: =VLOOKUP(C12,'Target allocation'!$B$2:$AF$51,27,FALSE) -> 18853.18 | Q12: =VLOOKUP(C12,'Target allocation'!$B$2:$AF$51,28,FALSE) -> 18853.18 | R12: =VLOOKUP(C12,'Target allocation'!$B$2:$AF$51,29,FALSE) -> 18853.18 | S12: =VLOOKUP(C12,'Target allocation'!$B$2:$AF$51,30,FALSE) -> 18853.18 | T12: =SUM(H12:S12) -> 226238.16
A13: Development | B13: See Target allocation | C13: Product Manager 3 | D13: TBH | E13: E&F | F13: =VLOOKUP(C13,'Target allocation'!$B$2:$G$51,6,FALSE) -> 0.41666667 | G13: =SUM(H13:S13) -> 150000 | H13: =VLOOKUP(C13,'Target allocation'!$B$2:$AF$51,19,FALSE) -> 0 | I13: =VLOOKUP(C13,'Target allocation'!$B$2:$AF$51,20,FALSE) -> 0 | J13: =VLOOKUP(C13,'Target allocation'!$B$2:$AF$51,21,FALSE) -> 0 | K13: =VLOOKUP(C13,'Target allocation'!$B$2:$AF$51,22,FALSE) -> 30000 | L13: =VLOOKUP(C13,'Target allocation'!$B$2:$AF$51,23,FALSE) -> 30000 | M13: =VLOOKUP(C13,'Target allocation'!$B$2:$AF$51,24,FALSE) -> 30000 | N13: =VLOOKUP(C13,'Target allocation'!$B$2:$AF$51,25,FALSE) -> 30000 | O13: =VLOOKUP(C13,'Target allocation'!$B$2:$AF$51,26,FALSE) -> 30000 | P13: =VLOOKUP(C13,'Target allocation'!$B$2:$AF$51,27,FALSE) -> 0 | Q13: =VLOOKUP(C13,'Target allocation'!$B$2:$AF$51,28,FALSE) -> 0 | R13: =VLOOKUP(C13,'Target allocation'!$B$2:$AF$51,29,FALSE) -> 0 | S13: =VLOOKUP(C13,'Target allocation'!$B$2:$AF$51,30,FALSE) -> 0 | T13: =SUM(H13:S13) -> 150000
A14: Development | B14: See Target allocation | C14: Product Manager 2 | D14: MMO | E14: E&F | F14: =VLOOKUP(C14,'Target allocation'!$B$2:$G$51,6,FALSE) -> 1 | G14: =SUM(H14:S14) -> 189517.43 | H14: =VLOOKUP(C14,'Target allocation'!$B$2:$AF$51,19,FALSE) -> 15793.119 | I14: =VLOOKUP(C14,'Target allocation'!$B$2:$AF$51,20,FALSE) -> 15793.119 | J14: =VLOOKUP(C14,'Target allocation'!$B$2:$AF$51,21,FALSE) -> 15793.119 | K14: =VLOOKUP(C14,'Target allocation'!$B$2:$AF$51,22,FALSE) -> 15793.119 | L14: =VLOOKUP(C14,'Target allocation'!$B$2:$AF$51,23,FALSE) -> 15793.119 | M14: =VLOOKUP(C14,'Target allocation'!$B$2:$AF$51,24,FALSE) -> 15793.119 | N14: =VLOOKUP(C14,'Target allocation'!$B$2:$AF$51,25,FALSE) -> 15793.119 | O14: =VLOOKUP(C14,'Target allocation'!$B$2:$AF$51,26,FALSE) -> 15793.119 | P14: =VLOOKUP(C14,'Target allocation'!$B$2:$AF$51,27,FALSE) -> 15793.119 | Q14: =VLOOKUP(C14,'Target allocation'!$B$2:$AF$51,28,FALSE) -> 15793.119 | R14: =VLOOKUP(C14,'Target allocation'!$B$2:$AF$51,29,FALSE) -> 15793.119 | S14: =VLOOKUP(C14,'Target allocation'!$B$2:$AF$51,30,FALSE) -> 15793.119 | T14: =SUM(H14:S14) -> 189517.43
A15: Development | B15: See Target allocation | C15: Senior Engineer 4 | D15: JBE | E15: E&F | F15: =VLOOKUP(C15,'Target allocation'!$B$2:$G$51,6,FALSE) -> 0.33333333 | G15: =SUM(H15:S15) -> 121000 | H15: =VLOOKUP(C15,'Target allocation'!$B$2:$AF$51,19,FALSE) -> 0 | I15: =VLOOKUP(C15,'Target allocation'!$B$2:$AF$51,20,FALSE) -> 0 | J15: =VLOOKUP(C15,'Target allocation'!$B$2:$AF$51,21,FALSE) -> 0 | K15: =VLOOKUP(C15,'Target allocation'!$B$2:$AF$51,22,FALSE) -> 30250 | L15: =VLOOKUP(C15,'Target allocation'!$B$2:$AF$51,23,FALSE) -> 30250 | M15: =VLOOKUP(C15,'Target allocation'!$B$2:$AF$51,24,FALSE) -> 30250 | N15: =VLOOKUP(C15,'Target allocation'!$B$2:$AF$51,25,FALSE) -> 0 | O15: =VLOOKUP(C15,'Target allocation'!$B$2:$AF$51,26,FALSE) -> 0 | P15: =VLOOKUP(C15,'Target allocation'!$B$2:$AF$51,27,FALSE) -> 0 | Q15: =VLOOKUP(C15,'Target allocation'!$B$2:$AF$51,28,FALSE) -> 0 | R15: =VLOOKUP(C15,'Target allocation'!$B$2:$AF$51,29,FALSE) -> 0 | S15: =VLOOKUP(C15,'Target allocation'!$B$2:$AF$51,30,FALSE) -> 30250 | T15: =SUM(H15:S15) -> 121000 | U15: Senior Developper - début mars
A16: Development | B16: See Target allocation | C16: Senior Engineer 5 | D16: TBH | E16: E&F | F16: =VLOOKUP(C16,'Target allocation'!$B$2:$G$51,6,FALSE) -> 0.75 | G16: =SUM(H16:S16) -> 272250 | H16: =VLOOKUP(C16,'Target allocation'!$B$2:$AF$51,19,FALSE) -> 0 | I16: =VLOOKUP(C16,'Target allocation'!$B$2:$AF$51,20,FALSE) -> 0 | J16: =VLOOKUP(C16,'Target allocation'!$B$2:$AF$51,21,FALSE) -> 0 | K16: =VLOOKUP(C16,'Target allocation'!$B$2:$AF$51,22,FALSE) -> 0 | L16: =VLOOKUP(C16,'Target allocation'!$B$2:$AF$51,23,FALSE) -> 60500 | M16: =VLOOKUP(C16,'Target allocation'!$B$2:$AF$51,24,FALSE) -> 30250 | N16: =VLOOKUP(C16,'Target allocation'!$B$2:$AF$51,25,FALSE) -> 30250 | O16: =VLOOKUP(C16,'Target allocation'!$B$2:$AF$51,26,FALSE) -> 30250 | P16: =VLOOKUP(C16,'Target allocation'!$B$2:$AF$51,27,FALSE) -> 30250 | Q16: =VLOOKUP(C16,'Target allocation'!$B$2:$AF$51,28,FALSE) -> 30250 | R16: =VLOOKUP(C16,'Target allocation'!$B$2:$AF$51,29,FALSE) -> 30250 | S16: =VLOOKUP(C16,'Target allocation'!$B$2:$AF$51,30,FALSE) -> 30250 | T16: =SUM(H16:S16) -> 272250
A17: Development | B17: See Target allocation | C17: Senior Engineer 6 | D17: TBH | E17: E&F | F17: =VLOOKUP(C17,'Target allocation'!$B$2:$G$51,6,FALSE) -> 0.16666667 | G17: =SUM(H17:S17) -> 60500 | H17: =VLOOKUP(C17,'Target allocation'!$B$2:$AF$51,19,FALSE) -> 0 | I17: =VLOOKUP(C17,'Target allocation'!$B$2:$AF$51,20,FALSE) -> 0 | J17: =VLOOKUP(C17,'Target allocation'!$B$2:$AF$51,21,FALSE) -> 0 | K17: =VLOOKUP(C17,'Target allocation'!$B$2:$AF$51,22,FALSE) -> 0 | L17: =VLOOKUP(C17,'Target allocation'!$B$2:$AF$51,23,FALSE) -> 30250 | M17: =VLOOKUP(C17,'Target allocation'!$B$2:$AF$51,24,FALSE) -> 30250 | N17: =VLOOKUP(C17,'Target allocation'!$B$2:$AF$51,25,FALSE) -> 0 | O17: =VLOOKUP(C17,'Target allocation'!$B$2:$AF$51,26,FALSE) -> 0 | P17: =VLOOKUP(C17,'Target allocation'!$B$2:$AF$51,27,FALSE) -> 0 | Q17: =VLOOKUP(C17,'Target allocation'!$B$2:$AF$51,28,FALSE) -> 0 | R17: =VLOOKUP(C17,'Target allocation'!$B$2:$AF$51,29,FALSE) -> 0 | S17: =VLOOKUP(C17,'Target allocation'!$B$2:$AF$51,30,FALSE) -> 0 | T17: =SUM(H17:S17) -> 60500
A18: Development | B18: See Target allocation | C18: Engineer 6 | D18: TBH | E18: E&F | F18: =VLOOKUP(C18,'Target allocation'!$B$2:$G$51,6,FALSE) -> 0.33333333 | G18: =SUM(H18:S18) -> 66000 | H18: =VLOOKUP(C18,'Target allocation'!$B$2:$AF$51,19,FALSE) -> 0 | I18: =VLOOKUP(C18,'Target allocation'!$B$2:$AF$51,20,FALSE) -> 0 | J18: =VLOOKUP(C18,'Target allocation'!$B$2:$AF$51,21,FALSE) -> 0 | K18: =VLOOKUP(C18,'Target allocation'!$B$2:$AF$51,22,FALSE) -> 16500 | L18: =VLOOKUP(C18,'Target allocation'!$B$2:$AF$51,23,FALSE) -> 16500 | M18: =VLOOKUP(C18,'Target allocation'!$B$2:$AF$51,24,FALSE) -> 16500 | N18: =VLOOKUP(C18,'Target allocation'!$B$2:$AF$51,25,FALSE) -> 0 | O18: =VLOOKUP(C18,'Target allocation'!$B$2:$AF$51,26,FALSE) -> 0 | P18: =VLOOKUP(C18,'Target allocation'!$B$2:$AF$51,27,FALSE) -> 0 | Q18: =VLOOKUP(C18,'Target allocation'!$B$2:$AF$51,28,FALSE) -> 0 | R18: =VLOOKUP(C18,'Target allocation'!$B$2:$AF$51,29,FALSE) -> 0 | S18: =VLOOKUP(C18,'Target allocation'!$B$2:$AF$51,30,FALSE) -> 16500 | T18: =SUM(H18:S18) -> 66000
A19: Development | B19: See Target allocation | C19: Engineer 7 | D19: TBH | E19: E&F | F19: =VLOOKUP(C19,'Target allocation'!$B$2:$G$51,6,FALSE) -> 0.16666667 | G19: =SUM(H19:S19) -> 33000 | H19: =VLOOKUP(C19,'Target allocation'!$B$2:$AF$51,19,FALSE) -> 0 | I19: =VLOOKUP(C19,'Target allocation'!$B$2:$AF$51,20,FALSE) -> 0 | J19: =VLOOKUP(C19,'Target allocation'!$B$2:$AF$51,21,FALSE) -> 0 | K19: =VLOOKUP(C19,'Target allocation'!$B$2:$AF$51,22,FALSE) -> 0 | L19: =VLOOKUP(C19,'Target allocation'!$B$2:$AF$51,23,FALSE) -> 16500 | M19: =VLOOKUP(C19,'Target allocation'!$B$2:$AF$51,24,FALSE) -> 16500 | N19: =VLOOKUP(C19,'Target allocation'!$B$2:$AF$51,25,FALSE) -> 0 | O19: =VLOOKUP(C19,'Target allocation'!$B$2:$AF$51,26,FALSE) -> 0 | P19: =VLOOKUP(C19,'Target allocation'!$B$2:$AF$51,27,FALSE) -> 0 | Q19: =VLOOKUP(C19,'Target allocation'!$B$2:$AF$51,28,FALSE) -> 0 | R19: =VLOOKUP(C19,'Target allocation'!$B$2:$AF$51,29,FALSE) -> 0 | S19: =VLOOKUP(C19,'Target allocation'!$B$2:$AF$51,30,FALSE) -> 0 | T19: =SUM(H19:S19) -> 33000
A20: Development | B20: See Target allocation | C20: Engineer 8 | D20: TBH | E20: E&F | F20: =VLOOKUP(C20,'Target allocation'!$B$2:$G$51,6,FALSE) -> 0 | G20: =SUM(H20:S20) -> 0 | H20: =VLOOKUP(C20,'Target allocation'!$B$2:$AF$51,19,FALSE) -> 0 | I20: =VLOOKUP(C20,'Target allocation'!$B$2:$AF$51,20,FALSE) -> 0 | J20: =VLOOKUP(C20,'Target allocation'!$B$2:$AF$51,21,FALSE) -> 0 | K20: =VLOOKUP(C20,'Target allocation'!$B$2:$AF$51,22,FALSE) -> 0 | L20: =VLOOKUP(C20,'Target allocation'!$B$2:$AF$51,23,FALSE) -> 0 | M20: =VLOOKUP(C20,'Target allocation'!$B$2:$AF$51,24,FALSE) -> 0 | N20: =VLOOKUP(C20,'Target allocation'!$B$2:$AF$51,25,FALSE) -> 0 | O20: =VLOOKUP(C20,'Target allocation'!$B$2:$AF$51,26,FALSE) -> 0 | P20: =VLOOKUP(C20,'Target allocation'!$B$2:$AF$51,27,FALSE) -> 0 | Q20: =VLOOKUP(C20,'Target allocation'!$B$2:$AF$51,28,FALSE) -> 0 | R20: =VLOOKUP(C20,'Target allocation'!$B$2:$AF$51,29,FALSE) -> 0 | S20: =VLOOKUP(C20,'Target allocation'!$B$2:$AF$51,30,FALSE) -> 0 | T20: =SUM(H20:S20) -> 0
A21: Development | B21: See Target allocation | C21: Senior Engineer 7 | D21: TBH | E21: E&F | F21: =VLOOKUP(C21,'Target allocation'!$B$2:$G$51,6,FALSE) -> 0.66666667 | G21: =SUM(H21:S21) -> 242000 | H21: =VLOOKUP(C21,'Target allocation'!$B$2:$AF$51,19,FALSE) -> 0 | I21: =VLOOKUP(C21,'Target allocation'!$B$2:$AF$51,20,FALSE) -> 0 | J21: =VLOOKUP(C21,'Target allocation'!$B$2:$AF$51,21,FALSE) -> 0 | K21: =VLOOKUP(C21,'Target allocation'!$B$2:$AF$51,22,FALSE) -> 0 | L21: =VLOOKUP(C21,'Target allocation'!$B$2:$AF$51,23,FALSE) -> 30250 | M21: =VLOOKUP(C21,'Target allocation'!$B$2:$AF$51,24,FALSE) -> 30250 | N21: =VLOOKUP(C21,'Target allocation'!$B$2:$AF$51,25,FALSE) -> 30250 | O21: =VLOOKUP(C21,'Target allocation'!$B$2:$AF$51,26,FALSE) -> 30250 | P21: =VLOOKUP(C21,'Target allocation'!$B$2:$AF$51,27,FALSE) -> 30250 | Q21: =VLOOKUP(C21,'Target allocation'!$B$2:$AF$51,28,FALSE) -> 30250 | R21: =VLOOKUP(C21,'Target allocation'!$B$2:$AF$51,29,FALSE) -> 30250 | S21: =VLOOKUP(C21,'Target allocation'!$B$2:$AF$51,30,FALSE) -> 30250 | T21: =SUM(H21:S21) -> 242000
A22: Development | B22: See Target allocation | C22: Senior Engineer 8 | D22: TBH | E22: E&F | F22: =VLOOKUP(C22,'Target allocation'!$B$2:$G$51,6,FALSE) -> 0.5 | G22: =SUM(H22:S22) -> 181500 | H22: =VLOOKUP(C22,'Target allocation'!$B$2:$AF$51,19,FALSE) -> 0 | I22: =VLOOKUP(C22,'Target allocation'!$B$2:$AF$51,20,FALSE) -> 0 | J22: =VLOOKUP(C22,'Target allocation'!$B$2:$AF$51,21,FALSE) -> 0 | K22: =VLOOKUP(C22,'Target allocation'!$B$2:$AF$51,22,FALSE) -> 0 | L22: =VLOOKUP(C22,'Target allocation'!$B$2:$AF$51,23,FALSE) -> 0 | M22: =VLOOKUP(C22,'Target allocation'!$B$2:$AF$51,24,FALSE) -> 0 | N22: =VLOOKUP(C22,'Target allocation'!$B$2:$AF$51,25,FALSE) -> 30250 | O22: =VLOOKUP(C22,'Target allocation'!$B$2:$AF$51,26,FALSE) -> 30250 | P22: =VLOOKUP(C22,'Target allocation'!$B$2:$AF$51,27,FALSE) -> 30250 | Q22: =VLOOKUP(C22,'Target allocation'!$B$2:$AF$51,28,FALSE) -> 30250 | R22: =VLOOKUP(C22,'Target allocation'!$B$2:$AF$51,29,FALSE) -> 30250 | S22: =VLOOKUP(C22,'Target allocation'!$B$2:$AF$51,30,FALSE) -> 30250 | T22: =SUM(H22:S22) -> 181500
A23: Development | B23: See Target allocation | C23: Other costs 2 | E23: Consultancies | G23: =SUM(H23:S23) -> 540000 | H23: =VLOOKUP(C23,'Target allocation'!$B$2:$AF$51,19,FALSE) -> 75000 | I23: =VLOOKUP(C23,'Target allocation'!$B$2:$AF$51,20,FALSE) -> 75000 | J23: =VLOOKUP(C23,'Target allocation'!$B$2:$AF$51,21,FALSE) -> 75000 | K23: =VLOOKUP(C23,'Target allocation'!$B$2:$AF$51,22,FALSE) -> 75000 | L23: =VLOOKUP(C23,'Target allocation'!$B$2:$AF$51,23,FALSE) -> 30000 | M23: =VLOOKUP(C23,'Target allocation'!$B$2:$AF$51,24,FALSE) -> 30000 | N23: =VLOOKUP(C23,'Target allocation'!$B$2:$AF$51,25,FALSE) -> 30000 | O23: =VLOOKUP(C23,'Target allocation'!$B$2:$AF$51,26,FALSE) -> 30000 | P23: =VLOOKUP(C23,'Target allocation'!$B$2:$AF$51,27,FALSE) -> 30000 | Q23: =VLOOKUP(C23,'Target allocation'!$B$2:$AF$51,28,FALSE) -> 30000 | R23: =VLOOKUP(C23,'Target allocation'!$B$2:$AF$51,29,FALSE) -> 30000 | S23: =VLOOKUP(C23,'Target allocation'!$B$2:$AF$51,30,FALSE) -> 30000 | T23: =SUM(H23:S23) -> 540000
A24: Facilities | B24: G&A | C24: IT and Facilities | D24: P & P company | E24: Consultancies | G24: =SUM(H24:S24) -> 16200 | H24: =450*3 -> 1350 | I24: =450*3 -> 1350 | J24: =450*3 -> 1350 | K24: =450*3 -> 1350 | L24: =450*3 -> 1350 | M24: =450*3 -> 1350 | N24: =450*3 -> 1350 | O24: =450*3 -> 1350 | ... S24: =450*3 -> 1350 | T24: =SUM(H24:S24) -> 16200
A25: Facilities | B25: G&A | C25: Facilities | G25: =SUM(H25:S25) -> 152000 | H25: 10500 | I25: 10500 | J25: 10500 | K25: 10500 | L25: 12500 | M25: 12500 | N25: 12500 | O25: 12500 | P25: 15000 | Q25: 15000 | R25: 15000 | S25: 15000 | T25: =SUM(H25:S25) -> 152000
A26: Finance | B26: G&A | C26: CFO | D26: Argafin | E26: Consultancies | G26: =SUM(H26:S26) -> 132000 | H26: =3666.66666666667*3 -> 11000 | I26: =3666.66666666667*3 -> 11000 | J26: =3666.66666666667*3 -> 11000 | K26: =3666.66666666667*3 -> 11000 | L26: =3666.66666666667*3 -> 11000 | M26: =3666.66666666667*3 -> 11000 | N26: =3666.66666666667*3 -> 11000 | O26: =3666.66666666667*3 -> 11000 | ... S26: =3666.66666666667*3 -> 11000 | T26: =SUM(H26:S26) -> 132000
A27: Finance | B27: G&A | C27: Accountancy | D27: Trigone | E27: Consultancies | G27: =SUM(H27:S27) -> 36000 | H27: =1000*3 -> 3000 | I27: =1000*3 -> 3000 | J27: =1000*3 -> 3000 | K27: =1000*3 -> 3000 | L27: =1000*3 -> 3000 | M27: =1000*3 -> 3000 | N27: =1000*3 -> 3000 | O27: =1000*3 -> 3000 | ... S27: =1000*3 -> 3000 | T27: =SUM(H27:S27) -> 36000
A28: Finance | B28: G&A | C28: Financial costs | G28: =SUM(H28:S28) -> 24000 | H28: =8000/4 -> 2000 | I28: =8000/4 -> 2000 | J28: =8000/4 -> 2000 | K28: =8000/4 -> 2000 | L28: =8000/4 -> 2000 | M28: =8000/4 -> 2000 | N28: =8000/4 -> 2000 | O28: =8000/4 -> 2000 | ... S28: =8000/4 -> 2000 | T28: =SUM(H28:S28) -> 24000
A29: General Management | B29: See Target allocation | C29: CEO | D29: JCH | E29: E&F | F29: =VLOOKUP(C29,'Target allocation'!$B$2:$G$51,6,FALSE) -> 0.9 | G29: =SUM(H29:S29) -> 742500 | H29: =VLOOKUP(C29,'Target allocation'!$B$2:$AF$51,19,FALSE) -> 61875 | I29: =VLOOKUP(C29,'Target allocation'!$B$2:$AF$51,20,FALSE) -> 61875 | J29: =VLOOKUP(C29,'Target allocation'!$B$2:$AF$51,21,FALSE) -> 61875 | K29: =VLOOKUP(C29,'Target allocation'!$B$2:$AF$51,22,FALSE) -> 61875 | L29: =VLOOKUP(C29,'Target allocation'!$B$2:$AF$51,23,FALSE) -> 61875 | M29: =VLOOKUP(C29,'Target allocation'!$B$2:$AF$51,24,FALSE) -> 61875 | N29: =VLOOKUP(C29,'Target allocation'!$B$2:$AF$51,25,FALSE) -> 61875 | O29: =VLOOKUP(C29,'Target allocation'!$B$2:$AF$51,26,FALSE) -> 61875 | P29: =VLOOKUP(C29,'Target allocation'!$B$2:$AF$51,27,FALSE) -> 61875 | Q29: =VLOOKUP(C29,'Target allocation'!$B$2:$AF$51,28,FALSE) -> 61875 | R29: =VLOOKUP(C29,'Target allocation'!$B$2:$AF$51,29,FALSE) -> 61875 | S29: =VLOOKUP(C29,'Target allocation'!$B$2:$AF$51,30,FALSE) -> 61875 | T29: =SUM(H29:S29) -> 742500
A30: General Management | B30: See Target allocation | C30: COO | D30: TKE | E30: E&F | F30: =VLOOKUP(C30,'Target allocation'!$B$2:$G$51,6,FALSE) -> 0.8 | G30: =SUM(H30:S30) -> 660000 | H30: =VLOOKUP(C30,'Target allocation'!$B$2:$AF$51,19,FALSE) -> 55000 | I30: =VLOOKUP(C30,'Target allocation'!$B$2:$AF$51,20,FALSE) -> 55000 | J30: =VLOOKUP(C30,'Target allocation'!$B$2:$AF$51,21,FALSE) -> 55000 | K30: =VLOOKUP(C30,'Target allocation'!$B$2:$AF$51,22,FALSE) -> 55000 | L30: =VLOOKUP(C30,'Target allocation'!$B$2:$AF$51,23,FALSE) -> 55000 | M30: =VLOOKUP(C30,'Target allocation'!$B$2:$AF$51,24,FALSE) -> 55000 | N30: =VLOOKUP(C30,'Target allocation'!$B$2:$AF$51,25,FALSE) -> 55000 | O30: =VLOOKUP(C30,'Target allocation'!$B$2:$AF$51,26,FALSE) -> 55000 | P30: =VLOOKUP(C30,'Target allocation'!$B$2:$AF$51,27,FALSE) -> 55000 | Q30: =VLOOKUP(C30,'Target allocation'!$B$2:$AF$51,28,FALSE) -> 55000 | R30: =VLOOKUP(C30,'Target allocation'!$B$2:$AF$51,29,FALSE) -> 55000 | S30: =VLOOKUP(C30,'Target allocation'!$B$2:$AF$51,30,FALSE) -> 55000 | T30: =SUM(H30:S30) -> 660000
A31: HR/Admin | B31: G&A | C31: Secretary | D31: CDE | E31: E&F | F31: 1 | G31: =SUM(H31:S31) -> 183891 | H31: =4086.46666666667/80*100*3 -> 15324.25 | I31: =4086.46666666667/80*100*3 -> 15324.25 | J31: =4086.46666666667/80*100*3 -> 15324.25 | K31: =4086.46666666667/80*100*3 -> 15324.25 | L31: =4086.46666666667/80*100*3 -> 15324.25 | M31: =4086.46666666667/80*100*3 -> 15324.25 | N31: =4086.46666666667/80*100*3 -> 15324.25 | O31: =4086.46666666667/80*100*3 -> 15324.25 | ... S31: =4086.46666666667/80*100*3 -> 15324.25 | T31: =SUM(H31:S31) -> 183891
A32: HR/Admin | B32: G&A | C32: HR | D32: JCHyTECH or other | E32: Consultancies | G32: =SUM(H32:S32) -> 23700 | H32: =658.333333333333*3 -> 1975 | I32: =658.333333333333*3 -> 1975 | J32: =658.333333333333*3 -> 1975 | K32: =658.333333333333*3 -> 1975 | L32: =658.333333333333*3 -> 1975 | M32: =658.333333333333*3 -> 1975 | N32: =658.333333333333*3 -> 1975 | O32: =658.333333333333*3 -> 1975 | ... S32: =658.333333333333*3 -> 1975 | T32: =SUM(H32:S32) -> 23700
A33: HR/Admin | B33: G&A | C33: Directors | G33: =SUM(H33:S33) -> 108000 | H33: =3000*3 -> 9000 | I33: =3000*3 -> 9000 | J33: =3000*3 -> 9000 | K33: =3000*3 -> 9000 | L33: =3000*3 -> 9000 | M33: =3000*3 -> 9000 | N33: =3000*3 -> 9000 | O33: =3000*3 -> 9000 | ... S33: =3000*3 -> 9000 | T33: =SUM(H33:S33) -> 108000
A34: HR/Admin | B34: G&A | C34: Recruitment | G34: =SUM(H34:S34) -> 250000 | H34: =10000*H88 -> 30000 | I34: =10000*I88 -> 60000 | J34: =10000*J88 -> 0 | K34: =10000*K88 -> 40000 | L34: =10000*L88 -> 40000 | M34: =10000*M88 -> 0 | N34: =10000*N88 -> 10000 | O34: =10000*O88 -> 30000 | ... S34: =10000*S88 -> 10000 | T34: =SUM(H34:S34) -> 250000
A35: HR/Admin | B35: G&A | C35: Training | G35: =SUM(H35:S35) -> 152000 | H35: 10500 | I35: 12500 | J35: 13500 | K35: 13500 | L35: 12500 | M35: 12500 | N35: 12500 | O35: 12500 | P35: 13000 | Q35: 13000 | R35: 13000 | S35: 13000 | T35: =SUM(H35:S35) -> 152000
A36: HR/Admin | B36: G&A | C36: Admin costs | G36: =SUM(H36:S36) -> 26500 | H36: =26500*'Tableau recap'!E110 -> 152.54138 | I36: =26500*'Tableau recap'!F110 -> 270.30994 | J36: =26500*'Tableau recap'!G110 -> 366.19506 | K36: =26500*'Tableau recap'!H110 -> 1576.3432 | L36: =26500*'Tableau recap'!I110 -> 1507.6124 | M36: =26500*'Tableau recap'!J110 -> 1902.3195 | N36: =26500*'Tableau recap'!K110 -> 2215.0436 | O36: =26500*'Tableau recap'!L110 -> 2527.7676 | ... S36: =26500*'Tableau recap'!P110 -> 3995.4668 | T36: =SUM(H36:S36) -> 26500
A37: Legal | B37: T1 | C37: Legal | D37: Legal | E37: Consultancies | G37: =SUM(H37:S37) -> 6666.6667 | H37: =40000/12/6 -> 555.55556 | I37: =40000/12/6 -> 555.55556 | J37: =40000/12/6 -> 555.55556 | K37: =40000/12/6 -> 555.55556 | L37: =40000/12/6 -> 555.55556 | M37: =40000/12/6 -> 555.55556 | N37: =40000/12/6 -> 555.55556 | O37: =40000/12/6 -> 555.55556 | ... S37: =40000/12/6 -> 555.55556 | T37: =SUM(H37:S37) -> 6666.6667
A38: Legal | B38: T2 | C38: Legal | D38: Legal | E38: Consultancies | G38: =SUM(H38:S38) -> 6666.6667 | H38: =40000/12/6 -> 555.55556 | I38: =40000/12/6 -> 555.55556 | J38: =40000/12/6 -> 555.55556 | K38: =40000/12/6 -> 555.55556 | L38: =40000/12/6 -> 555.55556 | M38: =40000/12/6 -> 555.55556 | N38: =40000/12/6 -> 555.55556 | O38: =40000/12/6 -> 555.55556 | ... S38: =40000/12/6 -> 555.55556 | T38: =SUM(H38:S38) -> 6666.6667
A39: Legal | B39: T3 | C39: Legal | D39: Legal | E39: Consultancies | G39: =SUM(H39:S39) -> 6666.6667 | H39: =40000/12/6 -> 555.55556 | I39: =40000/12/6 -> 555.55556 | J39: =40000/12/6 -> 555.55556 | K39: =40000/12/6 -> 555.55556 | L39: =40000/12/6 -> 555.55556 | M39: =40000/12/6 -> 555.55556 | N39: =40000/12/6 -> 555.55556 | O39: =40000/12/6 -> 555.55556 | ... S39: =40000/12/6 -> 555.55556 | T39: =SUM(H39:S39) -> 6666.6667
A40: Legal | B40: T4 | C40: Legal | D40: Legal | E40: Consultancies | G40: =SUM(H40:S40) -> 6666.6667 | H40: =40000/12/6 -> 555.55556 | I40: =40000/12/6 -> 555.55556 | J40: =40000/12/6 -> 555.55556 | K40: =40000/12/6 -> 555.55556 | L40: =40000/12/6 -> 555.55556 | M40: =40000/12/6 -> 555.55556 | N40: =40000/12/6 -> 555.55556 | O40: =40000/12/6 -> 555.55556 | ... S40: =40000/12/6 -> 555.55556 | T40: =SUM(H40:S40) -> 6666.6667
A41: Legal | B41: T5 | C41: Legal | D41: Legal | E41: Consultancies | G41: =SUM(H41:S41) -> 6666.6667 | H41: =40000/12/6 -> 555.55556 | I41: =40000/12/6 -> 555.55556 | J41: =40000/12/6 -> 555.55556 | K41: =40000/12/6 -> 555.55556 | L41: =40000/12/6 -> 555.55556 | M41: =40000/12/6 -> 555.55556 | N41: =40000/12/6 -> 555.55556 | O41: =40000/12/6 -> 555.55556 | ... S41: =40000/12/6 -> 555.55556 | T41: =SUM(H41:S41) -> 6666.6667
A42: Legal | B42: T6 | C42: Legal | D42: Legal | E42: Consultancies | G42: =SUM(H42:S42) -> 6666.6667 | H42: =40000/12/6 -> 555.55556 | I42: =40000/12/6 -> 555.55556 | J42: =40000/12/6 -> 555.55556 | K42: =40000/12/6 -> 555.55556 | L42: =40000/12/6 -> 555.55556 | M42: =40000/12/6 -> 555.55556 | N42: =40000/12/6 -> 555.55556 | O42: =40000/12/6 -> 555.55556 | ... S42: =40000/12/6 -> 555.55556 | T42: =SUM(H42:S42) -> 6666.6667
A43: Manufacturing | B43: See Target allocation | C43: Manufacturing assistant 1 | D43: TBH | E43: E&F | F43: =VLOOKUP(C43,'Target allocation'!$B$2:$G$51,6,FALSE) -> 0.41666667 | G43: =SUM(H43:S43) -> 55000 | H43: =VLOOKUP(C43,'Target allocation'!$B$2:$AF$51,19,FALSE) -> 0 | I43: =VLOOKUP(C43,'Target allocation'!$B$2:$AF$51,20,FALSE) -> 2750 | J43: =VLOOKUP(C43,'Target allocation'!$B$2:$AF$51,21,FALSE) -> 2750 | K43: =VLOOKUP(C43,'Target allocation'!$B$2:$AF$51,22,FALSE) -> 5500 | L43: =VLOOKUP(C43,'Target allocation'!$B$2:$AF$51,23,FALSE) -> 5500 | M43: =VLOOKUP(C43,'Target allocation'!$B$2:$AF$51,24,FALSE) -> 5500 | N43: =VLOOKUP(C43,'Target allocation'!$B$2:$AF$51,25,FALSE) -> 5500 | O43: =VLOOKUP(C43,'Target allocation'!$B$2:$AF$51,26,FALSE) -> 5500 | P43: =VLOOKUP(C43,'Target allocation'!$B$2:$AF$51,27,FALSE) -> 5500 | Q43: =VLOOKUP(C43,'Target allocation'!$B$2:$AF$51,28,FALSE) -> 5500 | R43: =VLOOKUP(C43,'Target allocation'!$B$2:$AF$51,29,FALSE) -> 5500 | S43: =VLOOKUP(C43,'Target allocation'!$B$2:$AF$51,30,FALSE) -> 5500 | T43: =SUM(H43:S43) -> 55000
A44: Operations | B44: See Target allocation | C44: Project Manager | D44: CFR | E44: E&F | F44: =VLOOKUP(C44,'Target allocation'!$B$2:$G$51,6,FALSE) -> 1 | G44: =SUM(H44:S44) -> 324000 | H44: =VLOOKUP(C44,'Target allocation'!$B$2:$AF$51,19,FALSE) -> 27000 | I44: =VLOOKUP(C44,'Target allocation'!$B$2:$AF$51,20,FALSE) -> 27000 | J44: =VLOOKUP(C44,'Target allocation'!$B$2:$AF$51,21,FALSE) -> 27000 | K44: =VLOOKUP(C44,'Target allocation'!$B$2:$AF$51,22,FALSE) -> 27000 | L44: =VLOOKUP(C44,'Target allocation'!$B$2:$AF$51,23,FALSE) -> 27000 | M44: =VLOOKUP(C44,'Target allocation'!$B$2:$AF$51,24,FALSE) -> 27000 | N44: =VLOOKUP(C44,'Target allocation'!$B$2:$AF$51,25,FALSE) -> 27000 | O44: =VLOOKUP(C44,'Target allocation'!$B$2:$AF$51,26,FALSE) -> 27000 | P44: =VLOOKUP(C44,'Target allocation'!$B$2:$AF$51,27,FALSE) -> 27000 | Q44: =VLOOKUP(C44,'Target allocation'!$B$2:$AF$51,28,FALSE) -> 27000 | R44: =VLOOKUP(C44,'Target allocation'!$B$2:$AF$51,29,FALSE) -> 27000 | S44: =VLOOKUP(C44,'Target allocation'!$B$2:$AF$51,30,FALSE) -> 27000 | T44: =SUM(H44:S44) -> 324000
A45: Operations | B45: See Target allocation | C45: Senior Engineer 1 | D45: TBH | E45: E&F | F45: =VLOOKUP(C45,'Target allocation'!$B$2:$G$51,6,FALSE) -> 0.91666667 | G45: =SUM(H45:S45) -> 332750 | H45: =VLOOKUP(C45,'Target allocation'!$B$2:$AF$51,19,FALSE) -> 0 | I45: =VLOOKUP(C45,'Target allocation'!$B$2:$AF$51,20,FALSE) -> 30250 | J45: =VLOOKUP(C45,'Target allocation'!$B$2:$AF$51,21,FALSE) -> 30250 | K45: =VLOOKUP(C45,'Target allocation'!$B$2:$AF$51,22,FALSE) -> 30250 | L45: =VLOOKUP(C45,'Target allocation'!$B$2:$AF$51,23,FALSE) -> 30250 | M45: =VLOOKUP(C45,'Target allocation'!$B$2:$AF$51,24,FALSE) -> 30250 | N45: =VLOOKUP(C45,'Target allocation'!$B$2:$AF$51,25,FALSE) -> 30250 | O45: =VLOOKUP(C45,'Target allocation'!$B$2:$AF$51,26,FALSE) -> 30250 | P45: =VLOOKUP(C45,'Target allocation'!$B$2:$AF$51,27,FALSE) -> 30250 | Q45: =VLOOKUP(C45,'Target allocation'!$B$2:$AF$51,28,FALSE) -> 30250 | R45: =VLOOKUP(C45,'Target allocation'!$B$2:$AF$51,29,FALSE) -> 30250 | S45: =VLOOKUP(C45,'Target allocation'!$B$2:$AF$51,30,FALSE) -> 30250 | T45: =SUM(H45:S45) -> 332750
A46: Operations | B46: See Target allocation | C46: Senior Engineer 2 | D46: TBH | E46: E&F | F46: =VLOOKUP(C46,'Target allocation'!$B$2:$G$51,6,FALSE) -> 0.75 | G46: =SUM(H46:S46) -> 272250 | H46: =VLOOKUP(C46,'Target allocation'!$B$2:$AF$51,19,FALSE) -> 0 | I46: =VLOOKUP(C46,'Target allocation'!$B$2:$AF$51,20,FALSE) -> 0 | J46: =VLOOKUP(C46,'Target allocation'!$B$2:$AF$51,21,FALSE) -> 0 | K46: =VLOOKUP(C46,'Target allocation'!$B$2:$AF$51,22,FALSE) -> 30250 | L46: =VLOOKUP(C46,'Target allocation'!$B$2:$AF$51,23,FALSE) -> 30250 | M46: =VLOOKUP(C46,'Target allocation'!$B$2:$AF$51,24,FALSE) -> 30250 | N46: =VLOOKUP(C46,'Target allocation'!$B$2:$AF$51,25,FALSE) -> 30250 | O46: =VLOOKUP(C46,'Target allocation'!$B$2:$AF$51,26,FALSE) -> 30250 | P46: =VLOOKUP(C46,'Target allocation'!$B$2:$AF$51,27,FALSE) -> 30250 | Q46: =VLOOKUP(C46,'Target allocation'!$B$2:$AF$51,28,FALSE) -> 30250 | R46: =VLOOKUP(C46,'Target allocation'!$B$2:$AF$51,29,FALSE) -> 30250 | S46: =VLOOKUP(C46,'Target allocation'!$B$2:$AF$51,30,FALSE) -> 30250 | T46: =SUM(H46:S46) -> 272250
A47: Operations | B47: See Target allocation | C47: Engineer 1 | D47: TBH | E47: E&F | F47: =VLOOKUP(C47,'Target allocation'!$B$2:$G$51,6,FALSE) -> 0.41666667 | G47: =SUM(H47:S47) -> 96250 | H47: =VLOOKUP(C47,'Target allocation'!$B$2:$AF$51,19,FALSE) -> 0 | I47: =VLOOKUP(C47,'Target allocation'!$B$2:$AF$51,20,FALSE) -> 0 | J47: =VLOOKUP(C47,'Target allocation'!$B$2:$AF$51,21,FALSE) -> 0 | K47: =VLOOKUP(C47,'Target allocation'!$B$2:$AF$51,22,FALSE) -> 0 | L47: =VLOOKUP(C47,'Target allocation'!$B$2:$AF$51,23,FALSE) -> 0 | M47: =VLOOKUP(C47,'Target allocation'!$B$2:$AF$51,24,FALSE) -> 0 | N47: =VLOOKUP(C47,'Target allocation'!$B$2:$AF$51,25,FALSE) -> 0 | O47: =VLOOKUP(C47,'Target allocation'!$B$2:$AF$51,26,FALSE) -> 19250 | P47: =VLOOKUP(C47,'Target allocation'!$B$2:$AF$51,27,FALSE) -> 19250 | Q47: =VLOOKUP(C47,'Target allocation'!$B$2:$AF$51,28,FALSE) -> 19250 | R47: =VLOOKUP(C47,'Target allocation'!$B$2:$AF$51,29,FALSE) -> 19250 | S47: =VLOOKUP(C47,'Target allocation'!$B$2:$AF$51,30,FALSE) -> 19250 | T47: =SUM(H47:S47) -> 96250
A48: Operations | B48: See Target allocation | C48: Engineer 2 | D48: TBH | E48: E&F | F48: =VLOOKUP(C48,'Target allocation'!$B$2:$G$51,6,FALSE) -> 0.41666667 | G48: =SUM(H48:S48) -> 96250 | H48: =VLOOKUP(C48,'Target allocation'!$B$2:$AF$51,19,FALSE) -> 0 | I48: =VLOOKUP(C48,'Target allocation'!$B$2:$AF$51,20,FALSE) -> 0 | J48: =VLOOKUP(C48,'Target allocation'!$B$2:$AF$51,21,FALSE) -> 0 | K48: =VLOOKUP(C48,'Target allocation'!$B$2:$AF$51,22,FALSE) -> 0 | L48: =VLOOKUP(C48,'Target allocation'!$B$2:$AF$51,23,FALSE) -> 0 | M48: =VLOOKUP(C48,'Target allocation'!$B$2:$AF$51,24,FALSE) -> 0 | N48: =VLOOKUP(C48,'Target allocation'!$B$2:$AF$51,25,FALSE) -> 0 | O48: =VLOOKUP(C48,'Target allocation'!$B$2:$AF$51,26,FALSE) -> 19250 | P48: =VLOOKUP(C48,'Target allocation'!$B$2:$AF$51,27,FALSE) -> 19250 | Q48: =VLOOKUP(C48,'Target allocation'!$B$2:$AF$51,28,FALSE) -> 19250 | R48: =VLOOKUP(C48,'Target allocation'!$B$2:$AF$51,29,FALSE) -> 19250 | S48: =VLOOKUP(C48,'Target allocation'!$B$2:$AF$51,30,FALSE) -> 19250 | T48: =SUM(H48:S48) -> 96250
A49: Operations | B49: See Target allocation | C49: Engineer 3 | D49: TBH | E49: E&F | F49: =VLOOKUP(C49,'Target allocation'!$B$2:$G$51,6,FALSE) -> 0.41666667 | G49: =SUM(H49:S49) -> 96250 | H49: =VLOOKUP(C49,'Target allocation'!$B$2:$AF$51,19,FALSE) -> 0 | I49: =VLOOKUP(C49,'Target allocation'!$B$2:$AF$51,20,FALSE) -> 0 | J49: =VLOOKUP(C49,'Target allocation'!$B$2:$AF$51,21,FALSE) -> 0 | K49: =VLOOKUP(C49,'Target allocation'!$B$2:$AF$51,22,FALSE) -> 0 | L49: =VLOOKUP(C49,'Target allocation'!$B$2:$AF$51,23,FALSE) -> 0 | M49: =VLOOKUP(C49,'Target allocation'!$B$2:$AF$51,24,FALSE) -> 0 | N49: =VLOOKUP(C49,'Target allocation'!$B$2:$AF$51,25,FALSE) -> 0 | O49: =VLOOKUP(C49,'Target allocation'!$B$2:$AF$51,26,FALSE) -> 19250 | P49: =VLOOKUP(C49,'Target allocation'!$B$2:$AF$51,27,FALSE) -> 19250 | Q49: =VLOOKUP(C49,'Target allocation'!$B$2:$AF$51,28,FALSE) -> 19250 | R49: =VLOOKUP(C49,'Target allocation'!$B$2:$AF$51,29,FALSE) -> 19250 | S49: =VLOOKUP(C49,'Target allocation'!$B$2:$AF$51,30,FALSE) -> 19250 | T49: =SUM(H49:S49) -> 96250
A50: Operations | B50: See Target allocation | C50: Other costs 1 | E50: Consultancies | G50: =SUM(H50:S50) -> 12000 | H50: =VLOOKUP(C50,'Target allocation'!$B$2:$AF$51,19,FALSE) -> 1000 | I50: =VLOOKUP(C50,'Target allocation'!$B$2:$AF$51,20,FALSE) -> 1000 | J50: =VLOOKUP(C50,'Target allocation'!$B$2:$AF$51,21,FALSE) -> 1000 | K50: =VLOOKUP(C50,'Target allocation'!$B$2:$AF$51,22,FALSE) -> 1000 | L50: =VLOOKUP(C50,'Target allocation'!$B$2:$AF$51,23,FALSE) -> 1000 | M50: =VLOOKUP(C50,'Target allocation'!$B$2:$AF$51,24,FALSE) -> 1000 | N50: =VLOOKUP(C50,'Target allocation'!$B$2:$AF$51,25,FALSE) -> 1000 | O50: =VLOOKUP(C50,'Target allocation'!$B$2:$AF$51,26,FALSE) -> 1000 | P50: =VLOOKUP(C50,'Target allocation'!$B$2:$AF$51,27,FALSE) -> 1000 | Q50: =VLOOKUP(C50,'Target allocation'!$B$2:$AF$51,28,FALSE) -> 1000 | R50: =VLOOKUP(C50,'Target allocation'!$B$2:$AF$51,29,FALSE) -> 1000 | S50: =VLOOKUP(C50,'Target allocation'!$B$2:$AF$51,30,FALSE) -> 1000 | T50: =SUM(H50:S50) -> 12000
A51: Operations | B51: See Target allocation | C51: Engineer 10 | D51: TBH | E51: E&F | F51: =VLOOKUP(C51,'Target allocation'!$B$2:$G$51,6,FALSE) -> 0.33333333 | G51: =SUM(H51:S51) -> 77000 | H51: =VLOOKUP(C51,'Target allocation'!$B$2:$AF$51,19,FALSE) -> 0 | I51: =VLOOKUP(C51,'Target allocation'!$B$2:$AF$51,20,FALSE) -> 0 | J51: =VLOOKUP(C51,'Target allocation'!$B$2:$AF$51,21,FALSE) -> 0 | K51: =VLOOKUP(C51,'Target allocation'!$B$2:$AF$51,22,FALSE) -> 0 | L51: =VLOOKUP(C51,'Target allocation'!$B$2:$AF$51,23,FALSE) -> 0 | M51: =VLOOKUP(C51,'Target allocation'!$B$2:$AF$51,24,FALSE) -> 0 | N51: =VLOOKUP(C51,'Target allocation'!$B$2:$AF$51,25,FALSE) -> 0 | O51: =VLOOKUP(C51,'Target allocation'!$B$2:$AF$51,26,FALSE) -> 0 | P51: =VLOOKUP(C51,'Target allocation'!$B$2:$AF$51,27,FALSE) -> 19250 | Q51: =VLOOKUP(C51,'Target allocation'!$B$2:$AF$51,28,FALSE) -> 19250 | R51: =VLOOKUP(C51,'Target allocation'!$B$2:$AF$51,29,FALSE) -> 19250 | S51: =VLOOKUP(C51,'Target allocation'!$B$2:$AF$51,30,FALSE) -> 19250 | T51: =SUM(H51:S51) -> 77000
A52: Operations | B52: See Target allocation | C52: Engineer 11 | D52: TBH | E52: E&F | F52: =VLOOKUP(C52,'Target allocation'!$B$2:$G$51,6,FALSE) -> 0.33333333 | G52: =SUM(H52:S52) -> 77000 | H52: =VLOOKUP(C52,'Target allocation'!$B$2:$AF$51,19,FALSE) -> 0 | I52: =VLOOKUP(C52,'Target allocation'!$B$2:$AF$51,20,FALSE) -> 0 | J52: =VLOOKUP(C52,'Target allocation'!$B$2:$AF$51,21,FALSE) -> 0 | K52: =VLOOKUP(C52,'Target allocation'!$B$2:$AF$51,22,FALSE) -> 0 | L52: =VLOOKUP(C52,'Target allocation'!$B$2:$AF$51,23,FALSE) -> 0 | M52: =VLOOKUP(C52,'Target allocation'!$B$2:$AF$51,24,FALSE) -> 0 | N52: =VLOOKUP(C52,'Target allocation'!$B$2:$AF$51,25,FALSE) -> 0 | O52: =VLOOKUP(C52,'Target allocation'!$B$2:$AF$51,26,FALSE) -> 0 | P52: =VLOOKUP(C52,'Target allocation'!$B$2:$AF$51,27,FALSE) -> 19250 | Q52: =VLOOKUP(C52,'Target allocation'!$B$2:$AF$51,28,FALSE) -> 19250 | R52: =VLOOKUP(C52,'Target allocation'!$B$2:$AF$51,29,FALSE) -> 19250 | S52: =VLOOKUP(C52,'Target allocation'!$B$2:$AF$51,30,FALSE) -> 19250 | T52: =SUM(H52:S52) -> 77000
A53: Operations | B53: See Target allocation | C53: Engineer 12 | D53: TBH | E53: E&F | F53: =VLOOKUP(C53,'Target allocation'!$B$2:$G$51,6,FALSE) -> 0.33333333 | G53: =SUM(H53:S53) -> 77000 | H53: =VLOOKUP(C53,'Target allocation'!$B$2:$AF$51,19,FALSE) -> 0 | I53: =VLOOKUP(C53,'Target allocation'!$B$2:$AF$51,20,FALSE) -> 0 | J53: =VLOOKUP(C53,'Target allocation'!$B$2:$AF$51,21,FALSE) -> 0 | K53: =VLOOKUP(C53,'Target allocation'!$B$2:$AF$51,22,FALSE) -> 0 | L53: =VLOOKUP(C53,'Target allocation'!$B$2:$AF$51,23,FALSE) -> 0 | M53: =VLOOKUP(C53,'Target allocation'!$B$2:$AF$51,24,FALSE) -> 0 | N53: =VLOOKUP(C53,'Target allocation'!$B$2:$AF$51,25,FALSE) -> 0 | O53: =VLOOKUP(C53,'Target allocation'!$B$2:$AF$51,26,FALSE) -> 0 | P53: =VLOOKUP(C53,'Target allocation'!$B$2:$AF$51,27,FALSE) -> 19250 | Q53: =VLOOKUP(C53,'Target allocation'!$B$2:$AF$51,28,FALSE) -> 19250 | R53: =VLOOKUP(C53,'Target allocation'!$B$2:$AF$51,29,FALSE) -> 19250 | S53: =VLOOKUP(C53,'Target allocation'!$B$2:$AF$51,30,FALSE) -> 19250 | T53: =SUM(H53:S53) -> 77000
A54: Other costs | B54: G&A | C54: IP & patents costs | G54: =SUM(H54:S54) -> 60000 | H54: =60000*'Tableau recap'!E110 -> 345.3767 | I54: =60000*'Tableau recap'!F110 -> 612.02251 | J54: =60000*'Tableau recap'!G110 -> 829.1209 | K54: =60000*'Tableau recap'!H110 -> 3569.079 | L54: =60000*'Tableau recap'!I110 -> 3413.4619 | M54: =60000*'Tableau recap'!J110 -> 4307.1385 | N54: =60000*'Tableau recap'!K110 -> 5015.193 | O54: =60000*'Tableau recap'!L110 -> 5723.2474 | ... S54: =60000*'Tableau recap'!P110 -> 9046.34 | T54: =SUM(H54:S54) -> 60000
A55: Other costs | B55: G&A | C55: Shipment in & out | G55: =SUM(H55:S55) -> 12000 | H55: =12000*'Tableau recap'!E110 -> 69.07534 | I55: =12000*'Tableau recap'!F110 -> 122.4045 | J55: =12000*'Tableau recap'!G110 -> 165.82418 | K55: =12000*'Tableau recap'!H110 -> 713.8158 | L55: =12000*'Tableau recap'!I110 -> 682.69239 | M55: =12000*'Tableau recap'!J110 -> 861.42771 | N55: =12000*'Tableau recap'!K110 -> 1003.0386 | O55: =12000*'Tableau recap'!L110 -> 1144.6495 | ... S55: =12000*'Tableau recap'!P110 -> 1809.268 | T55: =SUM(H55:S55) -> 12000
A56: Other costs | B56: G&A | C56: Small equipment | G56: =SUM(H56:S56) -> 22500 | H56: =22500*'Tableau recap'!E110 -> 129.51626 | I56: =22500*'Tableau recap'!F110 -> 229.50844 | J56: =22500*'Tableau recap'!G110 -> 310.92034 | K56: =22500*'Tableau recap'!H110 -> 1338.4046 | L56: =22500*'Tableau recap'!I110 -> 1280.0482 | M56: =22500*'Tableau recap'!J110 -> 1615.1769 | N56: =22500*'Tableau recap'!K110 -> 1880.6974 | O56: =22500*'Tableau recap'!L110 -> 2146.2178 | ... S56: =22500*'Tableau recap'!P110 -> 3392.3775 | T56: =SUM(H56:S56) -> 22500
A57: Other costs | B57: G&A | C57: Software & licences | G57: =SUM(H57:S57) -> 150000 | H57: =150000*'Tableau recap'!E110 -> 863.44175 | I57: =150000*'Tableau recap'!F110 -> 1530.0563 | J57: =150000*'Tableau recap'!G110 -> 2072.8022 | K57: =150000*'Tableau recap'!H110 -> 8922.6975 | L57: =150000*'Tableau recap'!I110 -> 8533.6548 | M57: =150000*'Tableau recap'!J110 -> 10767.846 | N57: =150000*'Tableau recap'!K110 -> 12537.982 | O57: =150000*'Tableau recap'!L110 -> 14308.118 | ... S57: =150000*'Tableau recap'!P110 -> 22615.85 | T57: =SUM(H57:S57) -> 150000
A58: QA-RA | B58: See Target allocation | C58: QA Manager | D58: VCA | E58: E&F | F58: =VLOOKUP(C58,'Target allocation'!$B$2:$G$51,6,FALSE) -> 0.91666667 | G58: =SUM(H58:S58) -> 244200 | H58: =VLOOKUP(C58,'Target allocation'!$B$2:$AF$51,19,FALSE) -> 11100 | I58: =VLOOKUP(C58,'Target allocation'!$B$2:$AF$51,20,FALSE) -> 11100 | J58: =VLOOKUP(C58,'Target allocation'!$B$2:$AF$51,21,FALSE) -> 22200 | K58: =VLOOKUP(C58,'Target allocation'!$B$2:$AF$51,22,FALSE) -> 22200 | L58: =VLOOKUP(C58,'Target allocation'!$B$2:$AF$51,23,FALSE) -> 22200 | M58: =VLOOKUP(C58,'Target allocation'!$B$2:$AF$51,24,FALSE) -> 22200 | N58: =VLOOKUP(C58,'Target allocation'!$B$2:$AF$51,25,FALSE) -> 22200 | O58: =VLOOKUP(C58,'Target allocation'!$B$2:$AF$51,26,FALSE) -> 22200 | P58: =VLOOKUP(C58,'Target allocation'!$B$2:$AF$51,27,FALSE) -> 22200 | Q58: =VLOOKUP(C58,'Target allocation'!$B$2:$AF$51,28,FALSE) -> 22200 | R58: =VLOOKUP(C58,'Target allocation'!$B$2:$AF$51,29,FALSE) -> 22200 | S58: =VLOOKUP(C58,'Target allocation'!$B$2:$AF$51,30,FALSE) -> 22200 | T58: =SUM(H58:S58) -> 244200
A59: QA-RA | B59: See Target allocation | C59: Regulatory Affairs consultant | D59: Salma Michor | E59: Consultancies | G59: =SUM(H59:S59) -> 26400 | H59: =VLOOKUP(C59,'Target allocation'!$B$2:$AF$51,19,FALSE) -> 2200 | I59: =VLOOKUP(C59,'Target allocation'!$B$2:$AF$51,20,FALSE) -> 2200 | J59: =VLOOKUP(C59,'Target allocation'!$B$2:$AF$51,21,FALSE) -> 2200 | K59: =VLOOKUP(C59,'Target allocation'!$B$2:$AF$51,22,FALSE) -> 2200 | L59: =VLOOKUP(C59,'Target allocation'!$B$2:$AF$51,23,FALSE) -> 2200 | M59: =VLOOKUP(C59,'Target allocation'!$B$2:$AF$51,24,FALSE) -> 2200 | N59: =VLOOKUP(C59,'Target allocation'!$B$2:$AF$51,25,FALSE) -> 2200 | O59: =VLOOKUP(C59,'Target allocation'!$B$2:$AF$51,26,FALSE) -> 2200 | P59: =VLOOKUP(C59,'Target allocation'!$B$2:$AF$51,27,FALSE) -> 2200 | Q59: =VLOOKUP(C59,'Target allocation'!$B$2:$AF$51,28,FALSE) -> 2200 | R59: =VLOOKUP(C59,'Target allocation'!$B$2:$AF$51,29,FALSE) -> 2200 | S59: =VLOOKUP(C59,'Target allocation'!$B$2:$AF$51,30,FALSE) -> 2200 | T59: =SUM(H59:S59) -> 26400
A60: Sales and bus dev | B60: Costs not allocated to target | C60: Marketing 1 | D60: TBH | E60: E&F | F60: =(0.5*2+1*10)/12 -> 0.91666667 | G60: =SUM(H60:S60) -> 242000 | H60: =(400*220/4)*0.5 -> 11000 | I60: =(400*220/4)*0.5 -> 11000 | J60: =400*220/4 -> 22000 | K60: =400*220/4 -> 22000 | L60: =400*220/4 -> 22000 | M60: =400*220/4 -> 22000 | N60: =400*220/4 -> 22000 | O60: =400*220/4 -> 22000 | P60: =400*220/4 -> 22000 | Q60: =400*220/4 -> 22000 | ... S60: =400*220/4 -> 22000 | T60: =SUM(H60:S60) -> 242000
A61: Sales and bus dev | B61: Costs not allocated to target | C61: Marketing 2 | D61: TBH | E61: E&F | F61: =(1*8)/12 -> 0.66666667 | G61: =SUM(H61:S61) -> 176000 | H61: =(400*220/4)*0 -> 0 | I61: =(400*220/4)*0 -> 0 | J61: =(400*220/4)*0 -> 0 | K61: =(400*220/4)*0 -> 0 | L61: =400*220/4 -> 22000 | M61: =400*220/4 -> 22000 | N61: =400*220/4 -> 22000 | O61: =400*220/4 -> 22000 | P61: =400*220/4 -> 22000 | Q61: =400*220/4 -> 22000 | R61: =400*220/4 -> 22000 | S61: =400*220/4 -> 22000 | T61: =SUM(H61:S61) -> 176000
A62: Sales and bus dev | B62: Costs not allocated to target | C62: Marketing & communication | G62: =SUM(H62:S62) -> 300000 | H62: =300000*'Tableau recap'!E110 -> 1726.8835 | I62: =300000*'Tableau recap'!F110 -> 3060.1125 | J62: =300000*'Tableau recap'!G110 -> 4145.6045 | K62: =300000*'Tableau recap'!H110 -> 17845.395 | L62: =300000*'Tableau recap'!I110 -> 17067.31 | M62: =300000*'Tableau recap'!J110 -> 21535.693 | N62: =300000*'Tableau recap'!K110 -> 25075.965 | O62: =300000*'Tableau recap'!L110 -> 28616.237 | ... S62: =300000*'Tableau recap'!P110 -> 45231.7 | T62: =SUM(H62:S62) -> 300000
A63: Sales and bus dev | B63: See Target allocation | C63: Business Development Manager HQ | D63: BPI | E63: E&F | F63: =VLOOKUP(C63,'Target allocation'!$B$2:$G$51,6,FALSE) -> 1 | G63: =SUM(H63:S63) -> 237554.16 | H63: =VLOOKUP(C63,'Target allocation'!$B$2:$AF$51,19,FALSE) -> 19796.18 | I63: =VLOOKUP(C63,'Target allocation'!$B$2:$AF$51,20,FALSE) -> 19796.18 | J63: =VLOOKUP(C63,'Target allocation'!$B$2:$AF$51,21,FALSE) -> 19796.18 | K63: =VLOOKUP(C63,'Target allocation'!$B$2:$AF$51,22,FALSE) -> 19796.18 | L63: =VLOOKUP(C63,'Target allocation'!$B$2:$AF$51,23,FALSE) -> 19796.18 | M63: =VLOOKUP(C63,'Target allocation'!$B$2:$AF$51,24,FALSE) -> 19796.18 | N63: =VLOOKUP(C63,'Target allocation'!$B$2:$AF$51,25,FALSE) -> 19796.18 | O63: =VLOOKUP(C63,'Target allocation'!$B$2:$AF$51,26,FALSE) -> 19796.18 | P63: =VLOOKUP(C63,'Target allocation'!$B$2:$AF$51,27,FALSE) -> 19796.18 | Q63: =VLOOKUP(C63,'Target allocation'!$B$2:$AF$51,28,FALSE) -> 19796.18 | R63: =VLOOKUP(C63,'Target allocation'!$B$2:$AF$51,29,FALSE) -> 19796.18 | S63: =VLOOKUP(C63,'Target allocation'!$B$2:$AF$51,30,FALSE) -> 19796.18 | T63: =SUM(H63:S63) -> 237554.16
A64: Sales and bus dev | B64: See Target allocation | C64: Business Development Manager Italy | D64: GTA | E64: Consultancies | G64: =SUM(H64:S64) -> 108000 | H64: =VLOOKUP(C64,'Target allocation'!$B$2:$AF$51,19,FALSE) -> 9000 | I64: =VLOOKUP(C64,'Target allocation'!$B$2:$AF$51,20,FALSE) -> 9000 | J64: =VLOOKUP(C64,'Target allocation'!$B$2:$AF$51,21,FALSE) -> 9000 | K64: =VLOOKUP(C64,'Target allocation'!$B$2:$AF$51,22,FALSE) -> 9000 | L64: =VLOOKUP(C64,'Target allocation'!$B$2:$AF$51,23,FALSE) -> 9000 | M64: =VLOOKUP(C64,'Target allocation'!$B$2:$AF$51,24,FALSE) -> 9000 | N64: =VLOOKUP(C64,'Target allocation'!$B$2:$AF$51,25,FALSE) -> 9000 | O64: =VLOOKUP(C64,'Target allocation'!$B$2:$AF$51,26,FALSE) -> 9000 | P64: =VLOOKUP(C64,'Target allocation'!$B$2:$AF$51,27,FALSE) -> 9000 | Q64: =VLOOKUP(C64,'Target allocation'!$B$2:$AF$51,28,FALSE) -> 9000 | R64: =VLOOKUP(C64,'Target allocation'!$B$2:$AF$51,29,FALSE) -> 9000 | S64: =VLOOKUP(C64,'Target allocation'!$B$2:$AF$51,30,FALSE) -> 9000 | T64: =SUM(H64:S64) -> 108000
A65: Sales and bus dev | B65: See Target allocation | C65: Senior Sales Manager France | D65: TBH | E65: E&F | F65: =VLOOKUP(C65,'Target allocation'!$B$2:$G$51,6,FALSE) -> 0.91666667 | G65: =SUM(H65:S65) -> 496100 | H65: =VLOOKUP(C65,'Target allocation'!$B$2:$AF$51,19,FALSE) -> 0 | I65: =VLOOKUP(C65,'Target allocation'!$B$2:$AF$51,20,FALSE) -> 45100 | J65: =VLOOKUP(C65,'Target allocation'!$B$2:$AF$51,21,FALSE) -> 45100 | K65: =VLOOKUP(C65,'Target allocation'!$B$2:$AF$51,22,FALSE) -> 45100 | L65: =VLOOKUP(C65,'Target allocation'!$B$2:$AF$51,23,FALSE) -> 45100 | M65: =VLOOKUP(C65,'Target allocation'!$B$2:$AF$51,24,FALSE) -> 45100 | N65: =VLOOKUP(C65,'Target allocation'!$B$2:$AF$51,25,FALSE) -> 45100 | O65: =VLOOKUP(C65,'Target allocation'!$B$2:$AF$51,26,FALSE) -> 45100 | P65: =VLOOKUP(C65,'Target allocation'!$B$2:$AF$51,27,FALSE) -> 45100 | Q65: =VLOOKUP(C65,'Target allocation'!$B$2:$AF$51,28,FALSE) -> 45100 | R65: =VLOOKUP(C65,'Target allocation'!$B$2:$AF$51,29,FALSE) -> 45100 | S65: =VLOOKUP(C65,'Target allocation'!$B$2:$AF$51,30,FALSE) -> 45100 | T65: =SUM(H65:S65) -> 496100
A66: Sales and bus dev | B66: See Target allocation | C66: Senior Sales Manager Germany | D66: TBH | E66: E&F | F66: =VLOOKUP(C66,'Target allocation'!$B$2:$G$51,6,FALSE) -> 0.91666667 | G66: =SUM(H66:S66) -> 496100 | H66: =VLOOKUP(C66,'Target allocation'!$B$2:$AF$51,19,FALSE) -> 0 | I66: =VLOOKUP(C66,'Target allocation'!$B$2:$AF$51,20,FALSE) -> 45100 | J66: =VLOOKUP(C66,'Target allocation'!$B$2:$AF$51,21,FALSE) -> 45100 | K66: =VLOOKUP(C66,'Target allocation'!$B$2:$AF$51,22,FALSE) -> 45100 | L66: =VLOOKUP(C66,'Target allocation'!$B$2:$AF$51,23,FALSE) -> 45100 | M66: =VLOOKUP(C66,'Target allocation'!$B$2:$AF$51,24,FALSE) -> 45100 | N66: =VLOOKUP(C66,'Target allocation'!$B$2:$AF$51,25,FALSE) -> 45100 | O66: =VLOOKUP(C66,'Target allocation'!$B$2:$AF$51,26,FALSE) -> 45100 | P66: =VLOOKUP(C66,'Target allocation'!$B$2:$AF$51,27,FALSE) -> 45100 | Q66: =VLOOKUP(C66,'Target allocation'!$B$2:$AF$51,28,FALSE) -> 45100 | R66: =VLOOKUP(C66,'Target allocation'!$B$2:$AF$51,29,FALSE) -> 45100 | S66: =VLOOKUP(C66,'Target allocation'!$B$2:$AF$51,30,FALSE) -> 45100 | T66: =SUM(H66:S66) -> 496100
A67: Sales and bus dev | B67: See Target allocation | C67: Senior Business Dev Belgium | D67: Ghislain | E67: E&F | F67: =VLOOKUP(C67,'Target allocation'!$B$2:$G$51,6,FALSE) -> 0.425 | G67: =SUM(H67:S67) -> 182325 | H67: =VLOOKUP(C67,'Target allocation'!$B$2:$AF$51,19,FALSE) -> 7150 | I67: =VLOOKUP(C67,'Target allocation'!$B$2:$AF$51,20,FALSE) -> 10725 | J67: =VLOOKUP(C67,'Target allocation'!$B$2:$AF$51,21,FALSE) -> 10725 | K67: =VLOOKUP(C67,'Target allocation'!$B$2:$AF$51,22,FALSE) -> 10725 | L67: =VLOOKUP(C67,'Target allocation'!$B$2:$AF$51,23,FALSE) -> 17875 | M67: =VLOOKUP(C67,'Target allocation'!$B$2:$AF$51,24,FALSE) -> 17875 | N67: =VLOOKUP(C67,'Target allocation'!$B$2:$AF$51,25,FALSE) -> 17875 | O67: =VLOOKUP(C67,'Target allocation'!$B$2:$AF$51,26,FALSE) -> 17875 | P67: =VLOOKUP(C67,'Target allocation'!$B$2:$AF$51,27,FALSE) -> 17875 | Q67: =VLOOKUP(C67,'Target allocation'!$B$2:$AF$51,28,FALSE) -> 17875 | R67: =VLOOKUP(C67,'Target allocation'!$B$2:$AF$51,29,FALSE) -> 17875 | S67: =VLOOKUP(C67,'Target allocation'!$B$2:$AF$51,30,FALSE) -> 17875 | T67: =SUM(H67:S67) -> 182325
A68: Sales and bus dev | B68: See Target allocation | C68: Sales Manager France | D68: TBH | E68: E&F | F68: =VLOOKUP(C68,'Target allocation'!$B$2:$G$51,6,FALSE) -> 0.5 | G68: =SUM(H68:S68) -> 180000 | H68: =VLOOKUP(C68,'Target allocation'!$B$2:$AF$51,19,FALSE) -> 0 | I68: =VLOOKUP(C68,'Target allocation'!$B$2:$AF$51,20,FALSE) -> 0 | J68: =VLOOKUP(C68,'Target allocation'!$B$2:$AF$51,21,FALSE) -> 0 | K68: =VLOOKUP(C68,'Target allocation'!$B$2:$AF$51,22,FALSE) -> 0 | L68: =VLOOKUP(C68,'Target allocation'!$B$2:$AF$51,23,FALSE) -> 0 | M68: =VLOOKUP(C68,'Target allocation'!$B$2:$AF$51,24,FALSE) -> 0 | N68: =VLOOKUP(C68,'Target allocation'!$B$2:$AF$51,25,FALSE) -> 30000 | O68: =VLOOKUP(C68,'Target allocation'!$B$2:$AF$51,26,FALSE) -> 30000 | P68: =VLOOKUP(C68,'Target allocation'!$B$2:$AF$51,27,FALSE) -> 30000 | Q68: =VLOOKUP(C68,'Target allocation'!$B$2:$AF$51,28,FALSE) -> 30000 | R68: =VLOOKUP(C68,'Target allocation'!$B$2:$AF$51,29,FALSE) -> 30000 | S68: =VLOOKUP(C68,'Target allocation'!$B$2:$AF$51,30,FALSE) -> 30000 | T68: =SUM(H68:S68) -> 180000
A69: Sales and bus dev | B69: See Target allocation | C69: Sales Manager Germany | D69: TBH | E69: E&F | F69: =VLOOKUP(C69,'Target allocation'!$B$2:$G$51,6,FALSE) -> 0.5 | G69: =SUM(H69:S69) -> 180000 | H69: =VLOOKUP(C69,'Target allocation'!$B$2:$AF$51,19,FALSE) -> 0 | I69: =VLOOKUP(C69,'Target allocation'!$B$2:$AF$51,20,FALSE) -> 0 | J69: =VLOOKUP(C69,'Target allocation'!$B$2:$AF$51,21,FALSE) -> 0 | K69: =VLOOKUP(C69,'Target allocation'!$B$2:$AF$51,22,FALSE) -> 0 | L69: =VLOOKUP(C69,'Target allocation'!$B$2:$AF$51,23,FALSE) -> 0 | M69: =VLOOKUP(C69,'Target allocation'!$B$2:$AF$51,24,FALSE) -> 0 | N69: =VLOOKUP(C69,'Target allocation'!$B$2:$AF$51,25,FALSE) -> 30000 | O69: =VLOOKUP(C69,'Target allocation'!$B$2:$AF$51,26,FALSE) -> 30000 | P69: =VLOOKUP(C69,'Target allocation'!$B$2:$AF$51,27,FALSE) -> 30000 | Q69: =VLOOKUP(C69,'Target allocation'!$B$2:$AF$51,28,FALSE) -> 30000 | R69: =VLOOKUP(C69,'Target allocation'!$B$2:$AF$51,29,FALSE) -> 30000 | S69: =VLOOKUP(C69,'Target allocation'!$B$2:$AF$51,30,FALSE) -> 30000 | T69: =SUM(H69:S69) -> 180000
A70: Sales and bus dev | B70: See Target allocation | C70: VP Sales | D70: TBH | E70: E&F | F70: =VLOOKUP(C70,'Target allocation'!$B$2:$G$51,6,FALSE) -> 0.25 | G70: =SUM(H70:S70) -> 135300 | H70: =VLOOKUP(C70,'Target allocation'!$B$2:$AF$51,19,FALSE) -> 0 | I70: =VLOOKUP(C70,'Target allocation'!$B$2:$AF$51,20,FALSE) -> 0 | J70: =VLOOKUP(C70,'Target allocation'!$B$2:$AF$51,21,FALSE) -> 0 | K70: =VLOOKUP(C70,'Target allocation'!$B$2:$AF$51,22,FALSE) -> 0 | L70: =VLOOKUP(C70,'Target allocation'!$B$2:$AF$51,23,FALSE) -> 0 | M70: =VLOOKUP(C70,'Target allocation'!$B$2:$AF$51,24,FALSE) -> 0 | N70: =VLOOKUP(C70,'Target allocation'!$B$2:$AF$51,25,FALSE) -> 0 | O70: =VLOOKUP(C70,'Target allocation'!$B$2:$AF$51,26,FALSE) -> 0 | P70: =VLOOKUP(C70,'Target allocation'!$B$2:$AF$51,27,FALSE) -> 0 | Q70: =VLOOKUP(C70,'Target allocation'!$B$2:$AF$51,28,FALSE) -> 45100 | R70: =VLOOKUP(C70,'Target allocation'!$B$2:$AF$51,29,FALSE) -> 45100 | S70: =VLOOKUP(C70,'Target allocation'!$B$2:$AF$51,30,FALSE) -> 45100 | T70: =SUM(H70:S70) -> 135300
A71: Sales and bus dev | B71: See Target allocation | C71: Senior Sales Manager BeNeLux | D71: TBH | E71: E&F | F71: =VLOOKUP(C71,'Target allocation'!$B$2:$G$51,6,FALSE) -> 0.75 | G71: =SUM(H71:S71) -> 405900 | H71: =VLOOKUP(C71,'Target allocation'!$B$2:$AF$51,19,FALSE) -> 0 | I71: =VLOOKUP(C71,'Target allocation'!$B$2:$AF$51,20,FALSE) -> 0 | J71: =VLOOKUP(C71,'Target allocation'!$B$2:$AF$51,21,FALSE) -> 0 | K71: =VLOOKUP(C71,'Target allocation'!$B$2:$AF$51,22,FALSE) -> 45100 | L71: =VLOOKUP(C71,'Target allocation'!$B$2:$AF$51,23,FALSE) -> 45100 | M71: =VLOOKUP(C71,'Target allocation'!$B$2:$AF$51,24,FALSE) -> 45100 | N71: =VLOOKUP(C71,'Target allocation'!$B$2:$AF$51,25,FALSE) -> 45100 | O71: =VLOOKUP(C71,'Target allocation'!$B$2:$AF$51,26,FALSE) -> 45100 | P71: =VLOOKUP(C71,'Target allocation'!$B$2:$AF$51,27,FALSE) -> 45100 | Q71: =VLOOKUP(C71,'Target allocation'!$B$2:$AF$51,28,FALSE) -> 45100 | R71: =VLOOKUP(C71,'Target allocation'!$B$2:$AF$51,29,FALSE) -> 45100 | S71: =VLOOKUP(C71,'Target allocation'!$B$2:$AF$51,30,FALSE) -> 45100 | T71: =SUM(H71:S71) -> 405900
A72: Sales and bus dev | B72: See Target allocation | C72: Sales Manager OEM | D72: TBH | E72: E&F | F72: =VLOOKUP(C72,'Target allocation'!$B$2:$G$51,6,FALSE) -> 0.875 | G72: =SUM(H72:S72) -> 315000 | H72: =VLOOKUP(C72,'Target allocation'!$B$2:$AF$51,19,FALSE) -> 0 | I72: =VLOOKUP(C72,'Target allocation'!$B$2:$AF$51,20,FALSE) -> 15000 | J72: =VLOOKUP(C72,'Target allocation'!$B$2:$AF$51,21,FALSE) -> 30000 | K72: =VLOOKUP(C72,'Target allocation'!$B$2:$AF$51,22,FALSE) -> 30000 | L72: =VLOOKUP(C72,'Target allocation'!$B$2:$AF$51,23,FALSE) -> 30000 | M72: =VLOOKUP(C72,'Target allocation'!$B$2:$AF$51,24,FALSE) -> 30000 | N72: =VLOOKUP(C72,'Target allocation'!$B$2:$AF$51,25,FALSE) -> 30000 | O72: =VLOOKUP(C72,'Target allocation'!$B$2:$AF$51,26,FALSE) -> 30000 | P72: =VLOOKUP(C72,'Target allocation'!$B$2:$AF$51,27,FALSE) -> 30000 | Q72: =VLOOKUP(C72,'Target allocation'!$B$2:$AF$51,28,FALSE) -> 30000 | R72: =VLOOKUP(C72,'Target allocation'!$B$2:$AF$51,29,FALSE) -> 30000 | S72: =VLOOKUP(C72,'Target allocation'!$B$2:$AF$51,30,FALSE) -> 30000 | T72: =SUM(H72:S72) -> 315000
A73: Sales and bus dev | B73: See Target allocation | C73: Senior Sales Manager Country 1 | D73: TBH | E73: E&F | F73: =VLOOKUP(C73,'Target allocation'!$B$2:$G$51,6,FALSE) -> 0.91666667 | G73: =SUM(H73:S73) -> 496100 | H73: =VLOOKUP(C73,'Target allocation'!$B$2:$AF$51,19,FALSE) -> 0 | I73: =VLOOKUP(C73,'Target allocation'!$B$2:$AF$51,20,FALSE) -> 45100 | J73: =VLOOKUP(C73,'Target allocation'!$B$2:$AF$51,21,FALSE) -> 45100 | K73: =VLOOKUP(C73,'Target allocation'!$B$2:$AF$51,22,FALSE) -> 45100 | L73: =VLOOKUP(C73,'Target allocation'!$B$2:$AF$51,23,FALSE) -> 45100 | M73: =VLOOKUP(C73,'Target allocation'!$B$2:$AF$51,24,FALSE) -> 45100 | N73: =VLOOKUP(C73,'Target allocation'!$B$2:$AF$51,25,FALSE) -> 45100 | O73: =VLOOKUP(C73,'Target allocation'!$B$2:$AF$51,26,FALSE) -> 45100 | P73: =VLOOKUP(C73,'Target allocation'!$B$2:$AF$51,27,FALSE) -> 45100 | Q73: =VLOOKUP(C73,'Target allocation'!$B$2:$AF$51,28,FALSE) -> 45100 | R73: =VLOOKUP(C73,'Target allocation'!$B$2:$AF$51,29,FALSE) -> 45100 | S73: =VLOOKUP(C73,'Target allocation'!$B$2:$AF$51,30,FALSE) -> 45100 | T73: =SUM(H73:S73) -> 496100
A74: Sales and bus dev | B74: See Target allocation | C74: Sales Manager Country 1 | D74: TBH | E74: E&F | F74: =VLOOKUP(C74,'Target allocation'!$B$2:$G$51,6,FALSE) -> 0.5 | G74: =SUM(H74:S74) -> 180000 | H74: =VLOOKUP(C74,'Target allocation'!$B$2:$AF$51,19,FALSE) -> 0 | I74: =VLOOKUP(C74,'Target allocation'!$B$2:$AF$51,20,FALSE) -> 0 | J74: =VLOOKUP(C74,'Target allocation'!$B$2:$AF$51,21,FALSE) -> 0 | K74: =VLOOKUP(C74,'Target allocation'!$B$2:$AF$51,22,FALSE) -> 0 | L74: =VLOOKUP(C74,'Target allocation'!$B$2:$AF$51,23,FALSE) -> 0 | M74: =VLOOKUP(C74,'Target allocation'!$B$2:$AF$51,24,FALSE) -> 0 | N74: =VLOOKUP(C74,'Target allocation'!$B$2:$AF$51,25,FALSE) -> 30000 | O74: =VLOOKUP(C74,'Target allocation'!$B$2:$AF$51,26,FALSE) -> 30000 | P74: =VLOOKUP(C74,'Target allocation'!$B$2:$AF$51,27,FALSE) -> 30000 | Q74: =VLOOKUP(C74,'Target allocation'!$B$2:$AF$51,28,FALSE) -> 30000 | R74: =VLOOKUP(C74,'Target allocation'!$B$2:$AF$51,29,FALSE) -> 30000 | S74: =VLOOKUP(C74,'Target allocation'!$B$2:$AF$51,30,FALSE) -> 30000 | T74: =SUM(H74:S74) -> 180000
A75: T&E | B75: T1 | C75: T&E | D75: T&E | G75: =SUM(H75:S75) -> 40000 | H75: =40000/12 -> 3333.3333 | I75: =40000/12 -> 3333.3333 | J75: =40000/12 -> 3333.3333 | K75: =40000/12 -> 3333.3333 | L75: =40000/12 -> 3333.3333 | M75: =40000/12 -> 3333.3333 | N75: =40000/12 -> 3333.3333 | O75: =40000/12 -> 3333.3333 | ... S75: =40000/12 -> 3333.3333 | T75: =SUM(H75:S75) -> 40000
A76: T&E | B76: T2 | C76: T&E | D76: T&E | G76: =SUM(H76:S76) -> 40000 | H76: =40000/12 -> 3333.3333 | I76: =40000/12 -> 3333.3333 | J76: =40000/12 -> 3333.3333 | K76: =40000/12 -> 3333.3333 | L76: =40000/12 -> 3333.3333 | M76: =40000/12 -> 3333.3333 | N76: =40000/12 -> 3333.3333 | O76: =40000/12 -> 3333.3333 | ... S76: =40000/12 -> 3333.3333 | T76: =SUM(H76:S76) -> 40000
A77: T&E | B77: T3 | C77: T&E | D77: T&E | G77: =SUM(H77:S77) -> 60000 | H77: 5000 | I77: 5000 | J77: 5000 | K77: 5000 | L77: 5000 | M77: 5000 | N77: 5000 | O77: 5000 | P77: 5000 | Q77: 5000 | R77: 5000 | S77: 5000 | T77: =SUM(H77:S77) -> 60000
A78: T&E | B78: T4 | C78: T&E | D78: T&E | G78: =SUM(H78:S78) -> 0 | H78: 0 | I78: 0 | J78: 0 | K78: 0 | L78: 0 | M78: 0 | N78: 0 | O78: 0 | P78: 0 | Q78: 0 | R78: 0 | S78: 0 | T78: =SUM(H78:S78) -> 0
A79: T&E | B79: T5 | C79: T&E | D79: T&E | G79: =SUM(H79:S79) -> 150000 | H79: 7500 | I79: 7500 | J79: 7500 | K79: 7500 | L79: 15000 | M79: 15000 | N79: 15000 | O79: 15000 | P79: 15000 | Q79: 15000 | R79: 15000 | S79: 15000 | T79: =SUM(H79:S79) -> 150000
A80: T&E | B80: T6 | C80: T&E | D80: T&E | G80: =SUM(H80:S80) -> 40000 | H80: =40000/12 -> 3333.3333 | I80: =40000/12 -> 3333.3333 | J80: =40000/12 -> 3333.3333 | K80: =40000/12 -> 3333.3333 | L80: =40000/12 -> 3333.3333 | M80: =40000/12 -> 3333.3333 | N80: =40000/12 -> 3333.3333 | O80: =40000/12 -> 3333.3333 | ... S80: =40000/12 -> 3333.3333 | T80: =SUM(H80:S80) -> 40000
A82: TOTAL | F82: =SUM(F3:F79) -> 26.716667 | G82: =SUM(G2:G80) -> 14743801 | H82: =SUM(H2:H80) -> 555617.52 | I82: =SUM(I2:I80) -> 783367.02 | J82: =SUM(J2:J80) -> 761877.35 | K82: =SUM(K2:K80) -> 1188371.5 | L82: =SUM(L2:L80) -> 1276565.9 | M82: =SUM(M2:M80) -> 1218371.8 | N82: =SUM(N2:N80) -> 1265411.2 | ... T82: =SUM(T2:T80) -> 14743801
E85: E&F | G85: =SUMIF($E$2:$E$80,"E&F",G2:G80) -> 9573442 | H85: =SUMIF($E$2:$E$80,"E&F",H2:H80) -> 327618.09 | I85: =SUMIF($E$2:$E$80,"E&F",I2:I80) -> 514493.09 | J85: =SUMIF($E$2:$E$80,"E&F",J2:J80) -> 551593.09 | K85: =SUMIF($E$2:$E$80,"E&F",K2:K80) -> 706443.09 | L85: =SUMIF($E$2:$E$80,"E&F",L2:L80) -> 867843.09 | M85: =SUMIF($E$2:$E$80,"E&F",M2:M80) -> 837593.09 | N85: =SUMIF($E$2:$E$80,"E&F",N2:N80) -> 864343.09 | ... T85: =SUMIF($E$2:$E$80,"E&F",T2:T80) -> 9573442
E86: Consultancies | G86: =SUMIF($E$2:$E$80,"Consultancies",G2:G80) -> 1224372 | H86: =SUMIF($E$2:$E$80,"Consultancies",H2:H80) -> 137864.33 | I86: =SUMIF($E$2:$E$80,"Consultancies",I2:I80) -> 137864.33 | J86: =SUMIF($E$2:$E$80,"Consultancies",J2:J80) -> 130864.33 | K86: =SUMIF($E$2:$E$80,"Consultancies",K2:K80) -> 130864.33 | L86: =SUMIF($E$2:$E$80,"Consultancies",L2:L80) -> 85864.333 | M86: =SUMIF($E$2:$E$80,"Consultancies",M2:M80) -> 85864.333 | N86: =SUMIF($E$2:$E$80,"Consultancies",N2:N80) -> 85864.333 | ... T86: =SUMIF($E$2:$E$80,"Consultancies",T2:T80) -> 1224372
E87: NB TBH | H87: =COUNTIFS($D$2:$D$81,"TBH",H2:H81,">0") -> 3 | I87: =COUNTIFS($D$2:$D$81,"TBH",I2:I81,">0") -> 9 | J87: =COUNTIFS($D$2:$D$81,"TBH",J2:J81,">0") -> 9 | K87: =COUNTIFS($D$2:$D$81,"TBH",K2:K81,">0") -> 13 | L87: =COUNTIFS($D$2:$D$81,"TBH",L2:L81,">0") -> 17 | M87: =COUNTIFS($D$2:$D$81,"TBH",M2:M81,">0") -> 17 | N87: =COUNTIFS($D$2:$D$81,"TBH",N2:N81,">0") -> 18 | O87: =COUNTIFS($D$2:$D$81,"TBH",O2:O81,">0") -> 21 | ... S87: =COUNTIFS($D$2:$D$81,"TBH",S2:S81,">0") -> 25 | T87: =COUNTIF(Q1:Q80,"TBH") -> 0
E88: TBH per Q | G88: =SUM(H88:S88) -> 25 | H88: =H87 -> 3 | I88: =IF(I87>H87,I87-H87,0) -> 6 | J88: =IF(J87>I87,J87-I87,0) -> 0 | K88: =IF(K87>J87,K87-J87,0) -> 4 | L88: =IF(L87>K87,L87-K87,0) -> 4 | M88: =IF(M87>L87,M87-L87,0) -> 0 | N88: =IF(N87>M87,N87-M87,0) -> 1 | O88: =IF(O87>N87,O87-N87,0) -> 3 | P88: =IF(P87>O87,P87-O87,0) -> 2 | ... S88: =IF(S87>R87,S87-R87,0) -> 1

Sheet Target allocation
H1: FTE | I1: FTE | J1: FTE | K1: FTE | L1: FTE | M1: FTE | N1: FTE | O1: FTE | P1: FTE | Q1: FTE | R1: FTE | S1: FTE | T1: Montant | U1: Montant | V1: Montant | W1: Montant | X1: Montant | Y1: Montant | Z1: Montant | AA1: Montant | AB1: Montant | AC1: Montant | AD1: Montant | AE1: Montant | AF1: Montant
A2: Allocation | B2: Fonction | C2: Détails | D2: E&F + Consultancies | E2: Montly full costs - 1 FTE | F2: Full costs/Q - 1FTE | G2: Moyenne EFT | H2: Q1 21 | I2: Q2 21 | J2: Q3 21 | K2: Q4 21 | L2: Q1 22 | M2: Q2 22 | N2: Q3 22 | O2: Q4 22 | P2: Q1 23 | Q2: Q2 23 | R2: Q3 23 | S2: Q4 23 | T2: Q1 21 | U2: Q2 21 | V2: Q3 21 | W2: Q4 21 | X2: Q1 22 | Y2: Q2 22 | Z2: Q3 22 | AA2: Q4 22 | AB2: Q1 23 | AC2: Q2 23 | AD2: Q3 23 | AE2: Q4 23 | AF2: Total
A3: General management | B3: CEO | C3: JCH | D3: E&F | E3: =1250*220/12 -> 22916.667 | F3: =E3*3 -> 68750 | G3: =AVERAGE(H3:S3) -> 0.9 | H3: =SUMIFS(H54:H974,$C$54:$C$974,$B$3) -> 0.9 | I3: =SUMIFS(I54:I974,$C$54:$C$974,$B$3) -> 0.9 | J3: =SUMIFS(J54:J974,$C$54:$C$974,$B$3) -> 0.9 | K3: =SUMIFS(K54:K974,$C$54:$C$974,$B$3) -> 0.9 | L3: =SUMIFS(L54:L974,$C$54:$C$974,$B$3) -> 0.9 | M3: =SUMIFS(M54:M974,$C$54:$C$974,$B$3) -> 0.9 | N3: =SUMIFS(N54:N974,$C$54:$C$974,$B$3) -> 0.9 | O3: =SUMIFS(O54:O974,$C$54:$C$974,$B$3) -> 0.9 | ... AE3: =SUMIFS(AE54:AE974,$C$54:$C$974,$B$3) -> 61875 | AF3: =SUM(T3:AE3) -> 742500
A4: General management | B4: COO | C4: TKE | D4: E&F | E4: =1250*220/12 -> 22916.667 | F4: =E4*3 -> 68750 | G4: =AVERAGE(H4:S4) -> 0.8 | H4: =SUMIFS(H54:H974,$C$54:$C$974,$B$4) -> 0.8 | I4: =SUMIFS(I54:I974,$C$54:$C$974,$B$4) -> 0.8 | J4: =SUMIFS(J54:J974,$C$54:$C$974,$B$4) -> 0.8 | K4: =SUMIFS(K54:K974,$C$54:$C$974,$B$4) -> 0.8 | L4: =SUMIFS(L54:L974,$C$54:$C$974,$B$4) -> 0.8 | M4: =SUMIFS(M54:M974,$C$54:$C$974,$B$4) -> 0.8 | N4: =SUMIFS(N54:N974,$C$54:$C$974,$B$4) -> 0.8 | O4: =SUMIFS(O54:O974,$C$54:$C$974,$B$4) -> 0.8 | ... AE4: =SUMIFS(AE54:AE974,$C$54:$C$974,$B$4) -> 55000 | AF4: =SUM(T4:AE4) -> 660000
A5: Operations | B5: Project Manager | C5: CFR | D5: Dev & Op | E5: =4500*2 -> 9000 | F5: =E5*3 -> 27000 | G5: =AVERAGE(H5:S5) -> 1 | H5: =SUMIFS(H54:H974,$C$54:$C$974,$B$5) -> 1 | I5: =SUMIFS(I54:I974,$C$54:$C$974,$B$5) -> 1 | J5: =SUMIFS(J54:J974,$C$54:$C$974,$B$5) -> 1 | K5: =SUMIFS(K54:K974,$C$54:$C$974,$B$5) -> 1 | L5: =SUMIFS(L54:L974,$C$54:$C$974,$B$5) -> 1 | M5: =SUMIFS(M54:M974,$C$54:$C$974,$B$5) -> 1 | N5: =SUMIFS(N54:N974,$C$54:$C$974,$B$5) -> 1 | O5: =SUMIFS(O54:O974,$C$54:$C$974,$B$5) -> 1 | ... AE5: =SUMIFS(AE54:AE974,$C$54:$C$974,$B$5) -> 27000 | AF5: =SUM(T5:AE5) -> 324000
A6: Operations | B6: Senior Engineer 1 | C6: TBH | D6: Dev & Op | E6: =550*220/12 -> 10083.333 | F6: =E6*3 -> 30250 | G6: =AVERAGE(H6:S6) -> 0.91666667 | H6: =SUMIFS(H54:H974,$C$54:$C$974,$B$6) -> 0 | I6: =SUMIFS(I54:I974,$C$54:$C$974,$B$6) -> 1 | J6: =SUMIFS(J54:J974,$C$54:$C$974,$B$6) -> 1 | K6: =SUMIFS(K54:K974,$C$54:$C$974,$B$6) -> 1 | L6: =SUMIFS(L54:L974,$C$54:$C$974,$B$6) -> 1 | M6: =SUMIFS(M54:M974,$C$54:$C$974,$B$6) -> 1 | N6: =SUMIFS(N54:N974,$C$54:$C$974,$B$6) -> 1 | O6: =SUMIFS(O54:O974,$C$54:$C$974,$B$6) -> 1 | ... AE6: =SUMIFS(AE54:AE974,$C$54:$C$974,$B$6) -> 30250 | AF6: =SUM(T6:AE6) -> 332750
A7: Operations | B7: Senior Engineer 2 | C7: TBH | D7: Dev & Op | E7: =550*220/12 -> 10083.333 | F7: =E7*3 -> 30250 | G7: =AVERAGE(H7:S7) -> 0.75 | H7: =SUMIFS(H54:H974,$C$54:$C$974,$B$7) -> 0 | I7: =SUMIFS(I54:I974,$C$54:$C$974,$B$7) -> 0 | J7: =SUMIFS(J54:J974,$C$54:$C$974,$B$7) -> 0 | K7: =SUMIFS(K54:K974,$C$54:$C$974,$B$7) -> 1 | L7: =SUMIFS(L54:L974,$C$54:$C$974,$B$7) -> 1 | M7: =SUMIFS(M54:M974,$C$54:$C$974,$B$7) -> 1 | N7: =SUMIFS(N54:N974,$C$54:$C$974,$B$7) -> 1 | O7: =SUMIFS(O54:O974,$C$54:$C$974,$B$7) -> 1 | ... AE7: =SUMIFS(AE54:AE974,$C$54:$C$974,$B$7) -> 30250 | AF7: =SUM(T7:AE7) -> 272250
A8: Operations | B8: Engineer 1 | C8: TBH | D8: Dev & Op | E8: =350*220/12 -> 6416.6667 | F8: =E8*3 -> 19250 | G8: =AVERAGE(H8:S8) -> 0.41666667 | H8: =SUMIFS(H54:H974,$C$54:$C$974,$B$8) -> 0 | I8: =SUMIFS(I54:I974,$C$54:$C$974,$B$8) -> 0 | J8: =SUMIFS(J54:J974,$C$54:$C$974,$B$8) -> 0 | K8: =SUMIFS(K54:K974,$C$54:$C$974,$B$8) -> 0 | L8: =SUMIFS(L54:L974,$C$54:$C$974,$B$8) -> 0 | M8: =SUMIFS(M54:M974,$C$54:$C$974,$B$8) -> 0 | N8: =SUMIFS(N54:N974,$C$54:$C$974,$B$8) -> 0 | O8: =SUMIFS(O54:O974,$C$54:$C$974,$B$8) -> 1 | ... AE8: =SUMIFS(AE54:AE974,$C$54:$C$974,$B$8) -> 19250 | AF8: =SUM(T8:AE8) -> 96250
A9: Operations | B9: Engineer 2 | C9: TBH | D9: Dev & Op | E9: =350*220/12 -> 6416.6667 | F9: =E9*3 -> 19250 | G9: =AVERAGE(H9:S9) -> 0.41666667 | H9: =SUMIFS(H54:H974,$C$54:$C$974,$B$9) -> 0 | I9: =SUMIFS(I54:I974,$C$54:$C$974,$B$9) -> 0 | J9: =SUMIFS(J54:J974,$C$54:$C$974,$B$9) -> 0 | K9: =SUMIFS(K54:K974,$C$54:$C$974,$B$9) -> 0 | L9: =SUMIFS(L54:L974,$C$54:$C$974,$B$9) -> 0 | M9: =SUMIFS(M54:M974,$C$54:$C$974,$B$9) -> 0 | N9: =SUMIFS(N54:N974,$C$54:$C$974,$B$9) -> 0 | O9: =SUMIFS(O54:O974,$C$54:$C$974,$B$9) -> 1 | ... AE9: =SUMIFS(AE54:AE974,$C$54:$C$974,$B$9) -> 19250 | AF9: =SUM(T9:AE9) -> 96250
A10: Operations | B10: Engineer 3 | C10: TBH | D10: Dev & Op | E10: =350*220/12 -> 6416.6667 | F10: =E10*3 -> 19250 | G10: =AVERAGE(H10:S10) -> 0.41666667 | H10: =SUMIFS(H54:H974,$C$54:$C$974,$B$10) -> 0 | I10: =SUMIFS(I54:I974,$C$54:$C$974,$B$10) -> 0 | J10: =SUMIFS(J54:J974,$C$54:$C$974,$B$10) -> 0 | K10: =SUMIFS(K54:K974,$C$54:$C$974,$B$10) -> 0 | L10: =SUMIFS(L54:L974,$C$54:$C$974,$B$10) -> 0 | M10: =SUMIFS(M54:M974,$C$54:$C$974,$B$10) -> 0 | N10: =SUMIFS(N54:N974,$C$54:$C$974,$B$10) -> 0 | O10: =SUMIFS(O54:O974,$C$54:$C$974,$B$10) -> 1 | ... AE10: =SUMIFS(AE54:AE974,$C$54:$C$974,$B$10) -> 19250 | AF10: =SUM(T10:AE10) -> 96250
A11: Operations | B11: Engineer 10 | C11: TBH | D11: Dev & Op | E11: =350*220/12 -> 6416.6667 | F11: =E11*3 -> 19250 | G11: =AVERAGE(H11:S11) -> 0.33333333 | H11: =SUMIFS(H54:H974,$C$54:$C$974,$B$11) -> 0 | I11: =SUMIFS(I54:I974,$C$54:$C$974,$B$11) -> 0 | J11: =SUMIFS(J54:J974,$C$54:$C$974,$B$11) -> 0 | K11: =SUMIFS(K54:K974,$C$54:$C$974,$B$11) -> 0 | L11: =SUMIFS(L54:L974,$C$54:$C$974,$B$11) -> 0 | M11: =SUMIFS(M54:M974,$C$54:$C$974,$B$11) -> 0 | N11: =SUMIFS(N54:N974,$C$54:$C$974,$B$11) -> 0 | O11: =SUMIFS(O54:O974,$C$54:$C$974,$B$11) -> 0 | ... AE11: =SUMIFS(AE54:AE974,$C$54:$C$974,$B$11) -> 19250 | AF11: =SUM(T11:AE11) -> 77000
A12: Operations | B12: Engineer 11 | C12: TBH | D12: Dev & Op | E12: =350*220/12 -> 6416.6667 | F12: =E12*3 -> 19250 | G12: =AVERAGE(H12:S12) -> 0.33333333 | H12: =SUMIFS(H54:H974,$C$54:$C$974,$B$12) -> 0 | I12: =SUMIFS(I54:I974,$C$54:$C$974,$B$12) -> 0 | J12: =SUMIFS(J54:J974,$C$54:$C$974,$B$12) -> 0 | K12: =SUMIFS(K54:K974,$C$54:$C$974,$B$12) -> 0 | L12: =SUMIFS(L54:L974,$C$54:$C$974,$B$12) -> 0 | M12: =SUMIFS(M54:M974,$C$54:$C$974,$B$12) -> 0 | N12: =SUMIFS(N54:N974,$C$54:$C$974,$B$12) -> 0 | O12: =SUMIFS(O54:O974,$C$54:$C$974,$B$12) -> 0 | ... AE12: =SUMIFS(AE54:AE974,$C$54:$C$974,$B$12) -> 19250 | AF12: =SUM(T12:AE12) -> 77000
A13: Operations | B13: Engineer 12 | C13: TBH | D13: Dev & Op | E13: =350*220/12 -> 6416.6667 | F13: =E13*3 -> 19250 | G13: =AVERAGE(H13:S13) -> 0.33333333 | H13: =SUMIFS(H54:H974,$C$54:$C$974,$B$13) -> 0 | I13: =SUMIFS(I54:I974,$C$54:$C$974,$B$13) -> 0 | J13: =SUMIFS(J54:J974,$C$54:$C$974,$B$13) -> 0 | K13: =SUMIFS(K54:K974,$C$54:$C$974,$B$13) -> 0 | L13: =SUMIFS(L54:L974,$C$54:$C$974,$B$13) -> 0 | M13: =SUMIFS(M54:M974,$C$54:$C$974,$B$13) -> 0 | N13: =SUMIFS(N54:N974,$C$54:$C$974,$B$13) -> 0 | O13: =SUMIFS(O54:O974,$C$54:$C$974,$B$13) -> 0 | ... AE13: =SUMIFS(AE54:AE974,$C$54:$C$974,$B$13) -> 19250 | AF13: =SUM(T13:AE13) -> 77000
A14: Operations | B14: Other costs 1 | D14: Consultancies | E14: =1000/3 -> 333.33333 | F14: =E14*3 -> 1000 | G14: =AVERAGE(H14:S14) -> 1 | H14: =SUMIFS(H54:H974,$C$54:$C$974,$B$14) -> 1 | I14: =SUMIFS(I54:I974,$C$54:$C$974,$B$14) -> 1 | J14: =SUMIFS(J54:J974,$C$54:$C$974,$B$14) -> 1 | K14: =SUMIFS(K54:K974,$C$54:$C$974,$B$14) -> 1 | L14: =SUMIFS(L54:L974,$C$54:$C$974,$B$14) -> 1 | M14: =SUMIFS(M54:M974,$C$54:$C$974,$B$14) -> 1 | N14: =SUMIFS(N54:N974,$C$54:$C$974,$B$14) -> 1 | O14: =SUMIFS(O54:O974,$C$54:$C$974,$B$14) -> 1 | ... AE14: =SUMIFS(AE54:AE974,$C$54:$C$974,$B$14) -> 1000 | AF14: =SUM(T14:AE14) -> 12000
A15: Clinical affairs | B15: KOL Mngt (6) | C15: KOL Mngt (6) | D15: Consultancies | E15: =80000/12 -> 6666.6667 | F15: =E15*3 -> 20000 | G15: =AVERAGE(H15:S15) -> 1 | H15: =SUMIFS(H54:H974,$C$54:$C$974,$B$15) -> 1 | I15: =SUMIFS(I54:I974,$C$54:$C$974,$B$15) -> 1 | J15: =SUMIFS(J54:J974,$C$54:$C$974,$B$15) -> 1 | K15: =SUMIFS(K54:K974,$C$54:$C$974,$B$15) -> 1 | L15: =SUMIFS(L54:L974,$C$54:$C$974,$B$15) -> 1 | M15: =SUMIFS(M54:M974,$C$54:$C$974,$B$15) -> 1 | N15: =SUMIFS(N54:N974,$C$54:$C$974,$B$15) -> 1 | O15: =SUMIFS(O54:O974,$C$54:$C$974,$B$15) -> 1 | ... AE15: =SUMIFS(AE54:AE974,$C$54:$C$974,$B$15) -> 20000 | AF15: =SUM(T15:AE15) -> 240000
A16: Clinical affairs | B16: Italian KOL | C16: Fabiocchi | D16: Consultancies | E16: 1002 | F16: =E16*3 -> 3006 | G16: =AVERAGE(H16:S16) -> 1 | H16: =SUMIFS(H54:H974,$C$54:$C$974,$B$16) -> 1 | I16: =SUMIFS(I54:I974,$C$54:$C$974,$B$16) -> 1 | J16: =SUMIFS(J54:J974,$C$54:$C$974,$B$16) -> 1 | K16: =SUMIFS(K54:K974,$C$54:$C$974,$B$16) -> 1 | L16: =SUMIFS(L54:L974,$C$54:$C$974,$B$16) -> 1 | M16: =SUMIFS(M54:M974,$C$54:$C$974,$B$16) -> 1 | N16: =SUMIFS(N54:N974,$C$54:$C$974,$B$16) -> 1 | O16: =SUMIFS(O54:O974,$C$54:$C$974,$B$16) -> 1 | ... AE16: =SUMIFS(AE54:AE974,$C$54:$C$974,$B$16) -> 3006 | AF16: =SUM(T16:AE16) -> 36072
A17: Clinical affairs | B17: Clinical Affairs watch | C17: DDG | D17: E&F | E17: =525*220/12 -> 9625 | F17: =E17*3 -> 28875 | G17: =AVERAGE(H17:S17) -> 0.05 | H17: =SUMIFS(H54:H974,$C$54:$C$974,$B$17) -> 0.05 | I17: =SUMIFS(I54:I974,$C$54:$C$974,$B$17) -> 0.05 | J17: =SUMIFS(J54:J974,$C$54:$C$974,$B$17) -> 0.05 | K17: =SUMIFS(K54:K974,$C$54:$C$974,$B$17) -> 0.05 | L17: =SUMIFS(L54:L974,$C$54:$C$974,$B$17) -> 0.05 | M17: =SUMIFS(M54:M974,$C$54:$C$974,$B$17) -> 0.05 | N17: =SUMIFS(N54:N974,$C$54:$C$974,$B$17) -> 0.05 | O17: =SUMIFS(O54:O974,$C$54:$C$974,$B$17) -> 0.05 | ... AE17: =SUMIFS(AE54:AE974,$C$54:$C$974,$B$17) -> 1443.75 | AF17: =SUM(T17:AE17) -> 17325
A18: Clinical affairs | B18: Clinical Affairs Onco | C18: TBH | D18: E&F | E18: =180000/12 -> 15000 | F18: =E18*3 -> 45000 | G18: =AVERAGE(H18:S18) -> 0.083333333 | H18: =SUMIFS(H54:H974,$C$54:$C$974,$B$18) -> 0.25 | I18: =SUMIFS(I54:I974,$C$54:$C$974,$B$18) -> 0.25 | J18: =SUMIFS(J54:J974,$C$54:$C$974,$B$18) -> 0.25 | K18: =SUMIFS(K54:K974,$C$54:$C$974,$B$18) -> 0.25 | L18: =SUMIFS(L54:L974,$C$54:$C$974,$B$18) -> 0 | M18: =SUMIFS(M54:M974,$C$54:$C$974,$B$18) -> 0 | N18: =SUMIFS(N54:N974,$C$54:$C$974,$B$18) -> 0 | O18: =SUMIFS(O54:O974,$C$54:$C$974,$B$18) -> 0 | ... AE18: =SUMIFS(AE54:AE974,$C$54:$C$974,$B$18) -> 0 | AF18: =SUM(T18:AE18) -> 45000
A19: Clinical affairs | B19: Medical director | C19: TBH | D19: E&F | E19: 20000 | F19: =E19*3 -> 60000 | G19: =AVERAGE(H19:S19) -> 0.16666667 | H19: =SUMIFS(H54:H974,$C$54:$C$974,$B$19) -> 0.1 | I19: =SUMIFS(I54:I974,$C$54:$C$974,$B$19) -> 0.1 | J19: =SUMIFS(J54:J974,$C$54:$C$974,$B$19) -> 0.1 | K19: =SUMIFS(K54:K974,$C$54:$C$974,$B$19) -> 0.1 | L19: =SUMIFS(L54:L974,$C$54:$C$974,$B$19) -> 0.2 | M19: =SUMIFS(M54:M974,$C$54:$C$974,$B$19) -> 0.2 | N19: =SUMIFS(N54:N974,$C$54:$C$974,$B$19) -> 0.2 | O19: =SUMIFS(O54:O974,$C$54:$C$974,$B$19) -> 0.2 | ... AE19: =SUMIFS(AE54:AE974,$C$54:$C$974,$B$19) -> 12000 | AF19: =SUM(T19:AE19) -> 120000
A20: QA-RA | B20: QA Manager | C20: VCA | D20: E&F | E20: =3700*2 -> 7400 | F20: =E20*3 -> 22200 | G20: =AVERAGE(H20:S20) -> 0.91666667 | H20: =SUMIFS(H54:H974,$C$54:$C$974,$B$20) -> 0.5 | I20: =SUMIFS(I54:I974,$C$54:$C$974,$B$20) -> 0.5 | J20: =SUMIFS(J54:J974,$C$54:$C$974,$B$20) -> 1 | K20: =SUMIFS(K54:K974,$C$54:$C$974,$B$20) -> 1 | L20: =SUMIFS(L54:L974,$C$54:$C$974,$B$20) -> 1 | M20: =SUMIFS(M54:M974,$C$54:$C$974,$B$20) -> 1 | N20: =SUMIFS(N54:N974,$C$54:$C$974,$B$20) -> 1 | O20: =SUMIFS(O54:O974,$C$54:$C$974,$B$20) -> 1 | ... AE20: =SUMIFS(AE54:AE974,$C$54:$C$974,$B$20) -> 22200 | AF20: =SUM(T20:AE20) -> 244200
A21: QA-RA | B21: Regulatory Affairs consultant | C21: Salma Michor | D21: Consultancies | E21: =800*220/12 -> 14666.667 | F21: =E21*3 -> 44000 | G21: =AVERAGE(H21:S21) -> 0.05 | H21: =SUMIFS(H54:H974,$C$54:$C$974,$B$21) -> 0.05 | I21: =SUMIFS(I54:I974,$C$54:$C$974,$B$21) -> 0.05 | J21: =SUMIFS(J54:J974,$C$54:$C$974,$B$21) -> 0.05 | K21: =SUMIFS(K54:K974,$C$54:$C$974,$B$21) -> 0.05 | L21: =SUMIFS(L54:L974,$C$54:$C$974,$B$21) -> 0.05 | M21: =SUMIFS(M54:M974,$C$54:$C$974,$B$21) -> 0.05 | N21: =SUMIFS(N54:N974,$C$54:$C$974,$B$21) -> 0.05 | O21: =SUMIFS(O54:O974,$C$54:$C$974,$B$21) -> 0.05 | ... AE21: =SUMIFS(AE54:AE974,$C$54:$C$974,$B$21) -> 2200 | AF21: =SUM(T21:AE21) -> 26400
A22: Sales and bus dev | B22: Business Development Manager HQ | C22: BPI | D22: E&F | E22: =6469.34*1.02 -> 6598.7268 | F22: =E22*3 -> 19796.18 | G22: =AVERAGE(H22:S22) -> 1 | H22: =SUMIFS(H54:H974,$C$54:$C$974,$B$22) -> 1 | I22: =SUMIFS(I54:I974,$C$54:$C$974,$B$22) -> 1 | J22: =SUMIFS(J54:J974,$C$54:$C$974,$B$22) -> 1 | K22: =SUMIFS(K54:K974,$C$54:$C$974,$B$22) -> 1 | L22: =SUMIFS(L54:L974,$C$54:$C$974,$B$22) -> 1 | M22: =SUMIFS(M54:M974,$C$54:$C$974,$B$22) -> 1 | N22: =SUMIFS(N54:N974,$C$54:$C$974,$B$22) -> 1 | O22: =SUMIFS(O54:O974,$C$54:$C$974,$B$22) -> 1 | ... AE22: =SUMIFS(AE54:AE974,$C$54:$C$974,$B$22) -> 19796.18 | AF22: =SUM(T22:AE22) -> 237554.16
A23: Sales and bus dev | B23: Business Development Manager Italy | C23: GTA | D23: Consultancies | E23: 3000 | F23: =E23*3 -> 9000 | G23: =AVERAGE(H23:S23) -> 1 | H23: =SUMIFS(H54:H974,$C$54:$C$974,$B$23) -> 1 | I23: =SUMIFS(I54:I974,$C$54:$C$974,$B$23) -> 1 | J23: =SUMIFS(J54:J974,$C$54:$C$974,$B$23) -> 1 | K23: =SUMIFS(K54:K974,$C$54:$C$974,$B$23) -> 1 | L23: =SUMIFS(L54:L974,$C$54:$C$974,$B$23) -> 1 | M23: =SUMIFS(M54:M974,$C$54:$C$974,$B$23) -> 1 | N23: =SUMIFS(N54:N974,$C$54:$C$974,$B$23) -> 1 | O23: =SUMIFS(O54:O974,$C$54:$C$974,$B$23) -> 1 | ... AE23: =SUMIFS(AE54:AE974,$C$54:$C$974,$B$23) -> 9000 | AF23: =SUM(T23:AE23) -> 108000
A24: Sales and bus dev | B24: Senior Sales Manager France | C24: TBH | D24: E&F | E24: =820*220/12 -> 15033.333 | F24: =E24*3 -> 45100 | G24: =AVERAGE(H24:S24) -> 0.91666667 | H24: =SUMIFS(H54:H974,$C$54:$C$974,$B$24) -> 0 | I24: =SUMIFS(I54:I974,$C$54:$C$974,$B$24) -> 1 | J24: =SUMIFS(J54:J974,$C$54:$C$974,$B$24) -> 1 | K24: =SUMIFS(K54:K974,$C$54:$C$974,$B$24) -> 1 | L24: =SUMIFS(L54:L974,$C$54:$C$974,$B$24) -> 1 | M24: =SUMIFS(M54:M974,$C$54:$C$974,$B$24) -> 1 | N24: =SUMIFS(N54:N974,$C$54:$C$974,$B$24) -> 1 | O24: =SUMIFS(O54:O974,$C$54:$C$974,$B$24) -> 1 | ... AE24: =SUMIFS(AE54:AE974,$C$54:$C$974,$B$24) -> 45100 | AF24: =SUM(T24:AE24) -> 496100
A25: Sales and bus dev | B25: Senior Sales Manager Germany | C25: TBH | D25: E&F | E25: =820*220/12 -> 15033.333 | F25: =E25*3 -> 45100 | G25: =AVERAGE(H25:S25) -> 0.91666667 | H25: =SUMIFS(H54:H974,$C$54:$C$974,$B$25) -> 0 | I25: =SUMIFS(I54:I974,$C$54:$C$974,$B$25) -> 1 | J25: =SUMIFS(J54:J974,$C$54:$C$974,$B$25) -> 1 | K25: =SUMIFS(K54:K974,$C$54:$C$974,$B$25) -> 1 | L25: =SUMIFS(L54:L974,$C$54:$C$974,$B$25) -> 1 | M25: =SUMIFS(M54:M974,$C$54:$C$974,$B$25) -> 1 | N25: =SUMIFS(N54:N974,$C$54:$C$974,$B$25) -> 1 | O25: =SUMIFS(O54:O974,$C$54:$C$974,$B$25) -> 1 | ... AE25: =SUMIFS(AE54:AE974,$C$54:$C$974,$B$25) -> 45100 | AF25: =SUM(T25:AE25) -> 496100
A26: Sales and bus dev | B26: Senior Business Dev Belgium | C26: Ghislain | D26: E&F | E26: =650*220/12 -> 11916.667 | F26: =E26*3 -> 35750 | G26: =AVERAGE(H26:S26) -> 0.425 | H26: =SUMIFS(H54:H974,$C$54:$C$974,$B$26) -> 0.2 | I26: =SUMIFS(I54:I974,$C$54:$C$974,$B$26) -> 0.3 | J26: =SUMIFS(J54:J974,$C$54:$C$974,$B$26) -> 0.3 | K26: =SUMIFS(K54:K974,$C$54:$C$974,$B$26) -> 0.3 | L26: =SUMIFS(L54:L974,$C$54:$C$974,$B$26) -> 0.5 | M26: =SUMIFS(M54:M974,$C$54:$C$974,$B$26) -> 0.5 | N26: =SUMIFS(N54:N974,$C$54:$C$974,$B$26) -> 0.5 | O26: =SUMIFS(O54:O974,$C$54:$C$974,$B$26) -> 0.5 | ... AE26: =SUMIFS(AE54:AE974,$C$54:$C$974,$B$26) -> 17875 | AF26: =SUM(T26:AE26) -> 182325
A27: Sales and bus dev | B27: Sales Manager France | C27: TBH | D27: E&F | E27: 10000 | F27: =E27*3 -> 30000 | G27: =AVERAGE(H27:S27) -> 0.5 | H27: =SUMIFS(H54:H974,$C$54:$C$974,$B$27) -> 0 | I27: =SUMIFS(I54:I974,$C$54:$C$974,$B$27) -> 0 | J27: =SUMIFS(J54:J974,$C$54:$C$974,$B$27) -> 0 | K27: =SUMIFS(K54:K974,$C$54:$C$974,$B$27) -> 0 | L27: =SUMIFS(L54:L974,$C$54:$C$974,$B$27) -> 0 | M27: =SUMIFS(M54:M974,$C$54:$C$974,$B$27) -> 0 | N27: =SUMIFS(N54:N974,$C$54:$C$974,$B$27) -> 1 | O27: =SUMIFS(O54:O974,$C$54:$C$974,$B$27) -> 1 | ... AE27: =SUMIFS(AE54:AE974,$C$54:$C$974,$B$27) -> 30000 | AF27: =SUM(T27:AE27) -> 180000
A28: Sales and bus dev | B28: Sales Manager Germany | C28: TBH | D28: E&F | E28: 10000 | F28: =E28*3 -> 30000 | G28: =AVERAGE(H28:S28) -> 0.5 | H28: =SUMIFS(H54:H974,$C$54:$C$974,$B$28) -> 0 | I28: =SUMIFS(I54:I974,$C$54:$C$974,$B$28) -> 0 | J28: =SUMIFS(J54:J974,$C$54:$C$974,$B$28) -> 0 | K28: =SUMIFS(K54:K974,$C$54:$C$974,$B$28) -> 0 | L28: =SUMIFS(L54:L974,$C$54:$C$974,$B$28) -> 0 | M28: =SUMIFS(M54:M974,$C$54:$C$974,$B$28) -> 0 | N28: =SUMIFS(N54:N974,$C$54:$C$974,$B$28) -> 1 | O28: =SUMIFS(O54:O974,$C$54:$C$974,$B$28) -> 1 | ... AE28: =SUMIFS(AE54:AE974,$C$54:$C$974,$B$28) -> 30000 | AF28: =SUM(T28:AE28) -> 180000
A29: Sales and bus dev | B29: VP Sales | C29: TBH | D29: E&F | E29: =820*220/12 -> 15033.333 | F29: =E29*3 -> 45100 | G29: =AVERAGE(H29:S29) -> 0.25 | H29: =SUMIFS(H54:H974,$C$54:$C$974,$B$29) -> 0 | I29: =SUMIFS(I54:I974,$C$54:$C$974,$B$29) -> 0 | J29: =SUMIFS(J54:J974,$C$54:$C$974,$B$29) -> 0 | K29: =SUMIFS(K54:K974,$C$54:$C$974,$B$29) -> 0 | L29: =SUMIFS(L54:L974,$C$54:$C$974,$B$29) -> 0 | M29: =SUMIFS(M54:M974,$C$54:$C$974,$B$29) -> 0 | N29: =SUMIFS(N54:N974,$C$54:$C$974,$B$29) -> 0 | O29: =SUMIFS(O54:O974,$C$54:$C$974,$B$29) -> 0 | ... AE29: =SUMIFS(AE54:AE974,$C$54:$C$974,$B$29) -> 45100 | AF29: =SUM(T29:AE29) -> 135300
A30: Sales and bus dev | B30: Senior Sales Manager BeNeLux | C30: TBH | D30: E&F | E30: =820*220/12 -> 15033.333 | F30: =E30*3 -> 45100 | G30: =AVERAGE(H30:S30) -> 0.75 | H30: =SUMIFS(H54:H974,$C$54:$C$974,$B$30) -> 0 | I30: =SUMIFS(I54:I974,$C$54:$C$974,$B$30) -> 0 | J30: =SUMIFS(J54:J974,$C$54:$C$974,$B$30) -> 0 | K30: =SUMIFS(K54:K974,$C$54:$C$974,$B$30) -> 1 | L30: =SUMIFS(L54:L974,$C$54:$C$974,$B$30) -> 1 | M30: =SUMIFS(M54:M974,$C$54:$C$974,$B$30) -> 1 | N30: =SUMIFS(N54:N974,$C$54:$C$974,$B$30) -> 1 | O30: =SUMIFS(O54:O974,$C$54:$C$974,$B$30) -> 1 | ... AE30: =SUMIFS(AE54:AE974,$C$54:$C$974,$B$30) -> 45100 | AF30: =SUM(T30:AE30) -> 405900
A31: Sales and bus dev | B31: Sales Manager OEM | C31: TBH | D31: E&F | E31: 10000 | F31: =E31*3 -> 30000 | G31: =AVERAGE(H31:S31) -> 0.875 | H31: =SUMIFS(H54:H974,$C$54:$C$974,$B$31) -> 0 | I31: =SUMIFS(I54:I974,$C$54:$C$974,$B$31) -> 0.5 | J31: =SUMIFS(J54:J974,$C$54:$C$974,$B$31) -> 1 | K31: =SUMIFS(K54:K974,$C$54:$C$974,$B$31) -> 1 | L31: =SUMIFS(L54:L974,$C$54:$C$974,$B$31) -> 1 | M31: =SUMIFS(M54:M974,$C$54:$C$974,$B$31) -> 1 | N31: =SUMIFS(N54:N974,$C$54:$C$974,$B$31) -> 1 | O31: =SUMIFS(O54:O974,$C$54:$C$974,$B$31) -> 1 | ... AE31: =SUMIFS(AE54:AE974,$C$54:$C$974,$B$31) -> 30000 | AF31: =SUM(T31:AE31) -> 315000
A32: Sales and bus dev | B32: Senior Sales Manager Country 1 | C32: TBH | D32: E&F | E32: =820*220/12 -> 15033.333 | F32: =E32*3 -> 45100 | G32: =AVERAGE(H32:S32) -> 0.91666667 | H32: =SUMIFS(H54:H974,$C$54:$C$974,$B$32) -> 0 | I32: =SUMIFS(I54:I974,$C$54:$C$974,$B$32) -> 1 | J32: =SUMIFS(J54:J974,$C$54:$C$974,$B$32) -> 1 | K32: =SUMIFS(K54:K974,$C$54:$C$974,$B$32) -> 1 | L32: =SUMIFS(L54:L974,$C$54:$C$974,$B$32) -> 1 | M32: =SUMIFS(M54:M974,$C$54:$C$974,$B$32) -> 1 | N32: =SUMIFS(N54:N974,$C$54:$C$974,$B$32) -> 1 | O32: =SUMIFS(O54:O974,$C$54:$C$974,$B$32) -> 1 | ... AE32: =SUMIFS(AE54:AE974,$C$54:$C$974,$B$32) -> 45100 | AF32: =SUM(T32:AE32) -> 496100
A33: Sales and bus dev | B33: Sales Manager Country 1 | C33: TBH | D33: E&F | E33: 10000 | F33: =E33*3 -> 30000 | G33: =AVERAGE(H33:S33) -> 0.5 | H33: =SUMIFS(H54:H974,$C$54:$C$974,$B$33) -> 0 | I33: =SUMIFS(I54:I974,$C$54:$C$974,$B$33) -> 0 | J33: =SUMIFS(J54:J974,$C$54:$C$974,$B$33) -> 0 | K33: =SUMIFS(K54:K974,$C$54:$C$974,$B$33) -> 0 | L33: =SUMIFS(L54:L974,$C$54:$C$974,$B$33) -> 0 | M33: =SUMIFS(M54:M974,$C$54:$C$974,$B$33) -> 0 | N33: =SUMIFS(N54:N974,$C$54:$C$974,$B$33) -> 1 | O33: =SUMIFS(O54:O974,$C$54:$C$974,$B$33) -> 1 | ... AE33: =SUMIFS(AE54:AE974,$C$54:$C$974,$B$33) -> 30000 | AF33: =SUM(T33:AE33) -> 180000
A34: Development | B34: Senior Engineer 3 | C34: GGO | D34: Dev & Op | E34: =600*220/12 -> 11000 | F34: =E34*3 -> 33000 | G34: =AVERAGE(H34:S34) -> 1 | H34: =SUMIFS(H54:H974,$C$54:$C$974,$B$34) -> 1 | I34: =SUMIFS(I54:I974,$C$54:$C$974,$B$34) -> 1 | J34: =SUMIFS(J54:J974,$C$54:$C$974,$B$34) -> 1 | K34: =SUMIFS(K54:K974,$C$54:$C$974,$B$34) -> 1 | L34: =SUMIFS(L54:L974,$C$54:$C$974,$B$34) -> 1 | M34: =SUMIFS(M54:M974,$C$54:$C$974,$B$34) -> 1 | N34: =SUMIFS(N54:N974,$C$54:$C$974,$B$34) -> 1 | O34: =SUMIFS(O54:O974,$C$54:$C$974,$B$34) -> 1 | ... AE34: =SUMIFS(AE54:AE974,$C$54:$C$974,$B$34) -> 33000 | AF34: =SUM(T34:AE34) -> 396000
A35: Development | B35: Engineer 4 | C35: KSC | D35: Dev & Op | E35: =350*220/12 -> 6416.6667 | F35: =E35*3 -> 19250 | G35: =AVERAGE(H35:S35) -> 1 | H35: =SUMIFS(H54:H974,$C$54:$C$974,$B$35) -> 1 | I35: =SUMIFS(I54:I974,$C$54:$C$974,$B$35) -> 1 | J35: =SUMIFS(J54:J974,$C$54:$C$974,$B$35) -> 1 | K35: =SUMIFS(K54:K974,$C$54:$C$974,$B$35) -> 1 | L35: =SUMIFS(L54:L974,$C$54:$C$974,$B$35) -> 1 | M35: =SUMIFS(M54:M974,$C$54:$C$974,$B$35) -> 1 | N35: =SUMIFS(N54:N974,$C$54:$C$974,$B$35) -> 1 | O35: =SUMIFS(O54:O974,$C$54:$C$974,$B$35) -> 1 | ... AE35: =SUMIFS(AE54:AE974,$C$54:$C$974,$B$35) -> 19250 | AF35: =SUM(T35:AE35) -> 231000
A36: Development | B36: Engineer 5 | C36: RNU | D36: Dev & Op | E36: =4504.12*1.02 -> 4594.2024 | F36: =E36*3 -> 13782.607 | G36: =AVERAGE(H36:S36) -> 1 | H36: =SUMIFS(H54:H974,$C$54:$C$974,$B$36) -> 1 | I36: =SUMIFS(I54:I974,$C$54:$C$974,$B$36) -> 1 | J36: =SUMIFS(J54:J974,$C$54:$C$974,$B$36) -> 1 | K36: =SUMIFS(K54:K974,$C$54:$C$974,$B$36) -> 1 | L36: =SUMIFS(L54:L974,$C$54:$C$974,$B$36) -> 1 | M36: =SUMIFS(M54:M974,$C$54:$C$974,$B$36) -> 1 | N36: =SUMIFS(N54:N974,$C$54:$C$974,$B$36) -> 1 | O36: =SUMIFS(O54:O974,$C$54:$C$974,$B$36) -> 1 | ... AE36: =SUMIFS(AE54:AE974,$C$54:$C$974,$B$36) -> 13782.607 | AF36: =SUM(T36:AE36) -> 165391.29
A37: Development | B37: Product Development Mgr | C37: USA | D37: Dev & Op | E37: =6161.17*1.02 -> 6284.3934 | F37: =E37*3 -> 18853.18 | G37: =AVERAGE(H37:S37) -> 1 | H37: =SUMIFS(H54:H974,$C$54:$C$974,$B$37) -> 1 | I37: =SUMIFS(I54:I974,$C$54:$C$974,$B$37) -> 1 | J37: =SUMIFS(J54:J974,$C$54:$C$974,$B$37) -> 1 | K37: =SUMIFS(K54:K974,$C$54:$C$974,$B$37) -> 1 | L37: =SUMIFS(L54:L974,$C$54:$C$974,$B$37) -> 1 | M37: =SUMIFS(M54:M974,$C$54:$C$974,$B$37) -> 1 | N37: =SUMIFS(N54:N974,$C$54:$C$974,$B$37) -> 1 | O37: =SUMIFS(O54:O974,$C$54:$C$974,$B$37) -> 1 | ... AE37: =SUMIFS(AE54:AE974,$C$54:$C$974,$B$37) -> 18853.18 | AF37: =SUM(T37:AE37) -> 226238.16
A38: Development | B38: Product Manager 3 | C38: TBH | D38: Dev & Op | E38: 10000 | F38: =E38*3 -> 30000 | G38: =AVERAGE(H38:S38) -> 0.41666667 | H38: =SUMIFS(H54:H974,$C$54:$C$974,$B$38) -> 0 | I38: =SUMIFS(I54:I974,$C$54:$C$974,$B$38) -> 0 | J38: =SUMIFS(J54:J974,$C$54:$C$974,$B$38) -> 0 | K38: =SUMIFS(K54:K974,$C$54:$C$974,$B$38) -> 1 | L38: =SUMIFS(L54:L974,$C$54:$C$974,$B$38) -> 1 | M38: =SUMIFS(M54:M974,$C$54:$C$974,$B$38) -> 1 | N38: =SUMIFS(N54:N974,$C$54:$C$974,$B$38) -> 1 | O38: =SUMIFS(O54:O974,$C$54:$C$974,$B$38) -> 1 | ... AE38: =SUMIFS(AE54:AE974,$C$54:$C$974,$B$38) -> 0 | AF38: =SUM(T38:AE38) -> 150000
A39: Development | B39: Product Manager 2 | C39: MMO | D39: Dev & Op | E39: =5161.15*1.02 -> 5264.373 | F39: =E39*3 -> 15793.119 | G39: =AVERAGE(H39:S39) -> 1 | H39: =SUMIFS(H54:H974,$C$54:$C$974,$B$39) -> 1 | I39: =SUMIFS(I54:I974,$C$54:$C$974,$B$39) -> 1 | J39: =SUMIFS(J54:J974,$C$54:$C$974,$B$39) -> 1 | K39: =SUMIFS(K54:K974,$C$54:$C$974,$B$39) -> 1 | L39: =SUMIFS(L54:L974,$C$54:$C$974,$B$39) -> 1 | M39: =SUMIFS(M54:M974,$C$54:$C$974,$B$39) -> 1 | N39: =SUMIFS(N54:N974,$C$54:$C$974,$B$39) -> 1 | O39: =SUMIFS(O54:O974,$C$54:$C$974,$B$39) -> 1 | ... AE39: =SUMIFS(AE54:AE974,$C$54:$C$974,$B$39) -> 15793.119 | AF39: =SUM(T39:AE39) -> 189517.43
A40: Development | B40: Senior Engineer 4 | C40: TBH | D40: Dev & Op | E40: =550*220/12 -> 10083.333 | F40: =E40*3 -> 30250 | G40: =AVERAGE(H40:S40) -> 0.33333333 | H40: =SUMIFS(H54:H974,$C$54:$C$974,$B$40) -> 0 | I40: =SUMIFS(I54:I974,$C$54:$C$974,$B$40) -> 0 | J40: =SUMIFS(J54:J974,$C$54:$C$974,$B$40) -> 0 | K40: =SUMIFS(K54:K974,$C$54:$C$974,$B$40) -> 1 | L40: =SUMIFS(L54:L974,$C$54:$C$974,$B$40) -> 1 | M40: =SUMIFS(M54:M974,$C$54:$C$974,$B$40) -> 1 | N40: =SUMIFS(N54:N974,$C$54:$C$974,$B$40) -> 0 | O40: =SUMIFS(O54:O974,$C$54:$C$974,$B$40) -> 0 | ... AE40: =SUMIFS(AE54:AE974,$C$54:$C$974,$B$40) -> 30250 | AF40: =SUM(T40:AE40) -> 121000
A41: Development | B41: Senior Engineer 5 | C41: TBH | D41: Dev & Op | E41: =550*220/12 -> 10083.333 | F41: =E41*3 -> 30250 | G41: =AVERAGE(H41:S41) -> 0.75 | H41: =SUMIFS(H54:H974,$C$54:$C$974,$B$41) -> 0 | I41: =SUMIFS(I54:I974,$C$54:$C$974,$B$41) -> 0 | J41: =SUMIFS(J54:J974,$C$54:$C$974,$B$41) -> 0 | K41: =SUMIFS(K54:K974,$C$54:$C$974,$B$41) -> 0 | L41: =SUMIFS(L54:L974,$C$54:$C$974,$B$41) -> 2 | M41: =SUMIFS(M54:M974,$C$54:$C$974,$B$41) -> 1 | N41: =SUMIFS(N54:N974,$C$54:$C$974,$B$41) -> 1 | O41: =SUMIFS(O54:O974,$C$54:$C$974,$B$41) -> 1 | ... AE41: =SUMIFS(AE54:AE974,$C$54:$C$974,$B$41) -> 30250 | AF41: =SUM(T41:AE41) -> 272250
A42: Development | B42: Senior Engineer 6 | C42: TBH | D42: Dev & Op | E42: =550*220/12 -> 10083.333 | F42: =E42*3 -> 30250 | G42: =AVERAGE(H42:S42) -> 0.16666667 | H42: =SUMIFS(H54:H974,$C$54:$C$974,$B$42) -> 0 | I42: =SUMIFS(I54:I974,$C$54:$C$974,$B$42) -> 0 | J42: =SUMIFS(J54:J974,$C$54:$C$974,$B$42) -> 0 | K42: =SUMIFS(K54:K974,$C$54:$C$974,$B$42) -> 0 | L42: =SUMIFS(L54:L974,$C$54:$C$974,$B$42) -> 1 | M42: =SUMIFS(M54:M974,$C$54:$C$974,$B$42) -> 1 | N42: =SUMIFS(N54:N974,$C$54:$C$974,$B$42) -> 0 | O42: =SUMIFS(O54:O974,$C$54:$C$974,$B$42) -> 0 | ... AE42: =SUMIFS(AE54:AE974,$C$54:$C$974,$B$42) -> 0 | AF42: =SUM(T42:AE42) -> 60500
A43: Development | B43: Engineer 6 | C43: TBH | D43: Dev & Op | E43: 5500 | F43: =E43*3 -> 16500 | G43: =AVERAGE(H43:S43) -> 0.33333333 | H43: =SUMIFS(H54:H974,$C$54:$C$974,$B$43) -> 0 | I43: =SUMIFS(I54:I974,$C$54:$C$974,$B$43) -> 0 | J43: =SUMIFS(J54:J974,$C$54:$C$974,$B$43) -> 0 | K43: =SUMIFS(K54:K974,$C$54:$C$974,$B$43) -> 1 | L43: =SUMIFS(L54:L974,$C$54:$C$974,$B$43) -> 1 | M43: =SUMIFS(M54:M974,$C$54:$C$974,$B$43) -> 1 | N43: =SUMIFS(N54:N974,$C$54:$C$974,$B$43) -> 0 | O43: =SUMIFS(O54:O974,$C$54:$C$974,$B$43) -> 0 | ... AE43: =SUMIFS(AE54:AE974,$C$54:$C$974,$B$43) -> 16500 | AF43: =SUM(T43:AE43) -> 66000
A44: Development | B44: Engineer 7 | C44: TBH | D44: Dev & Op | E44: 5500 | F44: =E44*3 -> 16500 | G44: =AVERAGE(H44:S44) -> 0.16666667 | H44: =SUMIFS(H54:H974,$C$54:$C$974,$B$44) -> 0 | I44: =SUMIFS(I54:I974,$C$54:$C$974,$B$44) -> 0 | J44: =SUMIFS(J54:J974,$C$54:$C$974,$B$44) -> 0 | K44: =SUMIFS(K54:K974,$C$54:$C$974,$B$44) -> 0 | L44: =SUMIFS(L54:L974,$C$54:$C$974,$B$44) -> 1 | M44: =SUMIFS(M54:M974,$C$54:$C$974,$B$44) -> 1 | N44: =SUMIFS(N54:N974,$C$54:$C$974,$B$44) -> 0 | O44: =SUMIFS(O54:O974,$C$54:$C$974,$B$44) -> 0 | ... AE44: =SUMIFS(AE54:AE974,$C$54:$C$974,$B$44) -> 0 | AF44: =SUM(T44:AE44) -> 33000
A45: Development | B45: Engineer 8 | C45: TBH | D45: Dev & Op | E45: 5500 | F45: =E45*3 -> 16500 | G45: =AVERAGE(H45:S45) -> 0 | H45: =SUMIFS(H54:H974,$C$54:$C$974,$B$45) -> 0 | I45: =SUMIFS(I54:I974,$C$54:$C$974,$B$45) -> 0 | J45: =SUMIFS(J54:J974,$C$54:$C$974,$B$45) -> 0 | K45: =SUMIFS(K54:K974,$C$54:$C$974,$B$45) -> 0 | L45: =SUMIFS(L54:L974,$C$54:$C$974,$B$45) -> 0 | M45: =SUMIFS(M54:M974,$C$54:$C$974,$B$45) -> 0 | N45: =SUMIFS(N54:N974,$C$54:$C$974,$B$45) -> 0 | O45: =SUMIFS(O54:O974,$C$54:$C$974,$B$45) -> 0 | ... AE45: =SUMIFS(AE54:AE974,$C$54:$C$974,$B$45) -> 0 | AF45: =SUM(T45:AE45) -> 0
A46: Development | B46: Senior Engineer 7 | C46: TBH | D46: Dev & Op | E46: =550*220/12 -> 10083.333 | F46: =E46*3 -> 30250 | G46: =AVERAGE(H46:S46) -> 0.66666667 | H46: =SUMIFS(H54:H974,$C$54:$C$974,$B$46) -> 0 | I46: =SUMIFS(I54:I974,$C$54:$C$974,$B$46) -> 0 | J46: =SUMIFS(J54:J974,$C$54:$C$974,$B$46) -> 0 | K46: =SUMIFS(K54:K974,$C$54:$C$974,$B$46) -> 0 | L46: =SUMIFS(L54:L974,$C$54:$C$974,$B$46) -> 1 | M46: =SUMIFS(M54:M974,$C$54:$C$974,$B$46) -> 1 | N46: =SUMIFS(N54:N974,$C$54:$C$974,$B$46) -> 1 | O46: =SUMIFS(O54:O974,$C$54:$C$974,$B$46) -> 1 | ... AE46: =SUMIFS(AE54:AE974,$C$54:$C$974,$B$46) -> 30250 | AF46: =SUM(T46:AE46) -> 242000
A47: Development | B47: Senior Engineer 8 | C47: TBH | D47: Dev & Op | E47: =550*220/12 -> 10083.333 | F47: =E47*3 -> 30250 | G47: =AVERAGE(H47:S47) -> 0.5 | H47: =SUMIFS(H54:H974,$C$54:$C$974,$B$47) -> 0 | I47: =SUMIFS(I54:I974,$C$54:$C$974,$B$47) -> 0 | J47: =SUMIFS(J54:J974,$C$54:$C$974,$B$47) -> 0 | K47: =SUMIFS(K54:K974,$C$54:$C$974,$B$47) -> 0 | L47: =SUMIFS(L54:L974,$C$54:$C$974,$B$47) -> 0 | M47: =SUMIFS(M54:M974,$C$54:$C$974,$B$47) -> 0 | N47: =SUMIFS(N54:N974,$C$54:$C$974,$B$47) -> 1 | O47: =SUMIFS(O54:O974,$C$54:$C$974,$B$47) -> 1 | ... AE47: =SUMIFS(AE54:AE974,$C$54:$C$974,$B$47) -> 30250 | AF47: =SUM(T47:AE47) -> 181500
A48: Development | B48: Other costs 2 | D48: Consultancies | E48: =75000/3 -> 25000 | F48: =E48*3 -> 75000 | G48: =AVERAGE(H48:S48) -> 0.6 | H48: =SUMIFS(H54:H974,$C$54:$C$974,$B$48) -> 1 | I48: =SUMIFS(I54:I974,$C$54:$C$974,$B$48) -> 1 | J48: =SUMIFS(J54:J974,$C$54:$C$974,$B$48) -> 1 | K48: =SUMIFS(K54:K974,$C$54:$C$974,$B$48) -> 1 | L48: =SUMIFS(L54:L974,$C$54:$C$974,$B$48) -> 0.4 | M48: =SUMIFS(M54:M974,$C$54:$C$974,$B$48) -> 0.4 | N48: =SUMIFS(N54:N974,$C$54:$C$974,$B$48) -> 0.4 | O48: =SUMIFS(O54:O974,$C$54:$C$974,$B$48) -> 0.4 | ... AE48: =SUMIFS(AE54:AE974,$C$54:$C$974,$B$48) -> 30000 | AF48: =SUM(T48:AE48) -> 540000
A49: Manufacturing | B49: Manufacturing assistant 1 | C49: TBH | D49: E&F | E49: =44000/12 -> 3666.6667 | F49: =E49*3 -> 11000 | G49: =AVERAGE(H49:S49) -> 0.41666667 | H49: =SUMIFS(H54:H974,$C$54:$C$974,$B$49) -> 0 | I49: =SUMIFS(I54:I974,$C$54:$C$974,$B$49) -> 0.25 | J49: =SUMIFS(J54:J974,$C$54:$C$974,$B$49) -> 0.25 | K49: =SUMIFS(K54:K974,$C$54:$C$974,$B$49) -> 0.5 | L49: =SUMIFS(L54:L974,$C$54:$C$974,$B$49) -> 0.5 | M49: =SUMIFS(M54:M974,$C$54:$C$974,$B$49) -> 0.5 | N49: =SUMIFS(N54:N974,$C$54:$C$974,$B$49) -> 0.5 | O49: =SUMIFS(O54:O974,$C$54:$C$974,$B$49) -> 0.5 | ... AE49: =SUMIFS(AE54:AE974,$C$54:$C$974,$B$49) -> 5500 | AF49: =SUM(T49:AE49) -> 55000
A51: TOTAL | H51: =SUM(H3:H50) -> 14.85 | I51: =SUM(I3:I50) -> 19.7 | J51: =SUM(J3:J50) -> 20.7 | K51: =SUM(K3:K50) -> 25.95 | L51: =SUM(L3:L50) -> 30.4 | M51: =SUM(M3:M50) -> 29.4 | N51: =SUM(N3:N50) -> 29.4 | O51: =SUM(O3:O50) -> 32.4 | ... AF51: =SUM(AF3:AF50) -> 9934023
AE52: CHECK | AF52: =AF51-SUM(AF54:AF1048576) -> 0
A53: Allocation | B53: Target | C53: Fonction | D53: Détails | E53: E&F + Consultancies | F53: # | G53: Moyenne EFT | H53: Q1 21 | I53: Q2 21 | J53: Q3 21 | K53: Q4 21 | L53: Q1 22 | M53: Q2 22 | N53: Q3 22 | O53: Q4 22 | P53: Q1 23 | Q53: Q2 23 | R53: Q3 23 | S53: Q4 23 | T53: Q1 21 | U53: Q2 21 | V53: Q3 21 | W53: Q4 21 | X53: Q1 22 | Y53: Q2 22 | Z53: Q3 22 | AA53: Q4 22 | AB53: Q1 23 | AC53: Q2 23 | AD53: Q3 23 | AE53: Q4 23 | AF53: Total
A54: Operations | B54: Other | C54: Engineer 1 | D54: TBH | E54: Dev & Op | G54: =AVERAGE(H54:S54) -> 0 | H54: 0 | I54: 0 | J54: 0 | K54: 0 | L54: 0 | M54: 0 | N54: 0 | O54: 0 | P54: 0 | Q54: 0 | R54: 0 | S54: 0 | T54: =$F$8*H54 -> 0 | U54: =$F$8*I54 -> 0 | V54: =$F$8*J54 -> 0 | W54: =$F$8*K54 -> 0 | X54: =$F$8*L54 -> 0 | Y54: =$F$8*M54 -> 0 | Z54: =$F$8*N54 -> 0 | AA54: =$F$8*O54 -> 0 | ... AE54: =$F$8*S54 -> 0 | AF54: =SUM(T54:AE54) -> 0
A55: Operations | B55: Other | C55: Engineer 2 | D55: TBH | E55: Dev & Op | G55: =AVERAGE(H55:S55) -> 0 | H55: 0 | I55: 0 | J55: 0 | K55: 0 | L55: 0 | M55: 0 | N55: 0 | O55: 0 | P55: 0 | Q55: 0 | R55: 0 | S55: 0 | T55: =$F$9*H55 -> 0 | U55: =$F$9*I55 -> 0 | V55: =$F$9*J55 -> 0 | W55: =$F$9*K55 -> 0 | X55: =$F$9*L55 -> 0 | Y55: =$F$9*M55 -> 0 | Z55: =$F$9*N55 -> 0 | AA55: =$F$9*O55 -> 0 | ... AE55: =$F$9*S55 -> 0 | AF55: =SUM(T55:AE55) -> 0
A56: Operations | B56: Other | C56: Engineer 3 | D56: TBH | E56: Dev & Op | G56: =AVERAGE(H56:S56) -> 0 | H56: 0 | I56: 0 | J56: 0 | K56: 0 | L56: 0 | M56: 0 | N56: 0 | O56: 0 | P56: 0 | Q56: 0 | R56: 0 | S56: 0 | T56: =$F$10*H56 -> 0 | U56: =$F$10*I56 -> 0 | V56: =$F$10*J56 -> 0 | W56: =$F$10*K56 -> 0 | X56: =$F$10*L56 -> 0 | Y56: =$F$10*M56 -> 0 | Z56: =$F$10*N56 -> 0 | AA56: =$F$10*O56 -> 0 | ... AE56: =$F$10*S56 -> 0 | AF56: =SUM(T56:AE56) -> 0
A57: Manufacturing | B57: Other | C57: Manufacturing assistant 1 | D57: TBH | E57: E&F | G57: =AVERAGE(H57:S57) -> 0 | H57: 0 | I57: 0 | J57: 0 | K57: 0 | L57: 0 | M57: 0 | N57: 0 | O57: 0 | P57: 0 | Q57: 0 | R57: 0 | S57: 0 | T57: =H57*$F$49 -> 0 | U57: =I57*$F$49 -> 0 | V57: =J57*$F$49 -> 0 | W57: =K57*$F$49 -> 0 | X57: =L57*$F$49 -> 0 | Y57: =M57*$F$49 -> 0 | Z57: =N57*$F$49 -> 0 | AA57: =O57*$F$49 -> 0 | ... AE57: =S57*$F$49 -> 0 | AF57: =SUM(T57:AE57) -> 0
A58: Operations | B58: Other | C58: Senior Engineer 1 | D58: TBH | E58: Dev & Op | G58: =AVERAGE(H58:S58) -> 0 | H58: 0 | I58: 0 | J58: 0 | K58: 0 | L58: 0 | M58: 0 | N58: 0 | O58: 0 | P58: 0 | Q58: 0 | R58: 0 | S58: 0 | T58: =H58*$F$6 -> 0 | U58: =I58*$F$6 -> 0 | V58: =J58*$F$6 -> 0 | W58: =K58*$F$6 -> 0 | X58: =L58*$F$6 -> 0 | Y58: =M58*$F$6 -> 0 | Z58: =N58*$F$6 -> 0 | AA58: =O58*$F$6 -> 0 | ... AE58: =S58*$F$6 -> 0 | AF58: =SUM(T58:AE58) -> 0
A59: Operations | B59: Other | C59: Senior Engineer 2 | D59: TBH | E59: Dev & Op | G59: =AVERAGE(H59:S59) -> 0 | H59: 0 | I59: 0 | J59: 0 | K59: 0 | L59: 0 | M59: 0 | N59: 0 | O59: 0 | P59: 0 | Q59: 0 | R59: 0 | S59: 0 | T59: =H59*$F$7 -> 0 | U59: =I59*$F$7 -> 0 | V59: =J59*$F$7 -> 0 | W59: =K59*$F$7 -> 0 | X59: =L59*$F$7 -> 0 | Y59: =M59*$F$7 -> 0 | Z59: =N59*$F$7 -> 0 | AA59: =O59*$F$7 -> 0 | ... AE59: =S59*$F$7 -> 0 | AF59: =SUM(T59:AE59) -> 0
A60: Sales and bus dev | B60: Other | C60: Business Development Manager HQ | D60: BPI | E60: E&F | G60: =AVERAGE(H60:S60) -> 0 | H60: 0 | I60: 0 | J60: 0 | K60: 0 | L60: 0 | M60: 0 | N60: 0 | O60: 0 | P60: 0 | Q60: 0 | R60: 0 | S60: 0 | T60: =H60*$F$22 -> 0 | U60: =I60*$F$22 -> 0 | V60: =J60*$F$22 -> 0 | W60: =K60*$F$22 -> 0 | X60: =L60*$F$22 -> 0 | Y60: =M60*$F$22 -> 0 | Z60: =N60*$F$22 -> 0 | AA60: =O60*$F$22 -> 0 | ... AE60: =S60*$F$22 -> 0 | AF60: =SUM(T60:AE60) -> 0
A61: Sales and bus dev | B61: Other | C61: Business Development Manager Italy | D61: GTA | E61: Consultancies | G61: =AVERAGE(H61:S61) -> 0 | H61: 0 | I61: 0 | J61: 0 | K61: 0 | L61: 0 | M61: 0 | N61: 0 | O61: 0 | P61: 0 | Q61: 0 | R61: 0 | S61: 0 | T61: =$F$23*H61 -> 0 | U61: =$F$23*I61 -> 0 | V61: =$F$23*J61 -> 0 | W61: =$F$23*K61 -> 0 | X61: =$F$23*L61 -> 0 | Y61: =$F$23*M61 -> 0 | Z61: =$F$23*N61 -> 0 | AA61: =$F$23*O61 -> 0 | ... AE61: =$F$23*S61 -> 0 | AF61: =SUM(T61:AE61) -> 0
A62: General management | B62: Other | C62: CEO | D62: JCH | E62: E&F | G62: =AVERAGE(H62:S62) -> 0.9 | H62: 0.9 | I62: 0.9 | J62: 0.9 | K62: 0.9 | L62: 0.9 | M62: 0.9 | N62: 0.9 | O62: 0.9 | P62: 0.9 | Q62: 0.9 | R62: 0.9 | S62: 0.9 | T62: =H62*$F$3 -> 61875 | U62: =I62*$F$3 -> 61875 | V62: =J62*$F$3 -> 61875 | W62: =K62*$F$3 -> 61875 | X62: =L62*$F$3 -> 61875 | Y62: =M62*$F$3 -> 61875 | Z62: =N62*$F$3 -> 61875 | AA62: =O62*$F$3 -> 61875 | ... AE62: =S62*$F$3 -> 61875 | AF62: =SUM(T62:AE62) -> 742500
A63: Clinical affairs | B63: Other | C63: Clinical Affairs Onco | D63: TBH | E63: E&F | G63: =AVERAGE(H63:S63) -> 0 | H63: 0 | I63: 0 | J63: 0 | K63: 0 | L63: 0 | M63: 0 | N63: 0 | O63: 0 | P63: 0 | Q63: 0 | R63: 0 | S63: 0 | T63: =H63*$F$18 -> 0 | U63: =I63*$F$18 -> 0 | V63: =J63*$F$18 -> 0 | W63: =K63*$F$18 -> 0 | X63: =L63*$F$18 -> 0 | Y63: =M63*$F$18 -> 0 | Z63: =N63*$F$18 -> 0 | AA63: =O63*$F$18 -> 0 | ... AE63: =S63*$F$18 -> 0 | AF63: =SUM(T63:AE63) -> 0
A64: Clinical affairs | B64: Other | C64: Clinical Affairs watch | D64: DDG | E64: E&F | G64: =AVERAGE(H64:S64) -> 0.05 | H64: 0.05 | I64: 0.05 | J64: 0.05 | K64: 0.05 | L64: 0.05 | M64: 0.05 | N64: 0.05 | O64: 0.05 | P64: 0.05 | Q64: 0.05 | R64: 0.05 | S64: 0.05 | T64: =$F$17*H64 -> 1443.75 | U64: =$F$17*I64 -> 1443.75 | V64: =$F$17*J64 -> 1443.75 | W64: =$F$17*K64 -> 1443.75 | X64: =$F$17*L64 -> 1443.75 | Y64: =$F$17*M64 -> 1443.75 | Z64: =$F$17*N64 -> 1443.75 | AA64: =$F$17*O64 -> 1443.75 | ... AE64: =$F$17*S64 -> 1443.75 | AF64: =SUM(T64:AE64) -> 17325
A65: General management | B65: Other | C65: COO | D65: TKE | E65: E&F | G65: =AVERAGE(H65:S65) -> 0.8 | H65: 0.8 | I65: 0.8 | J65: 0.8 | K65: 0.8 | L65: 0.8 | M65: 0.8 | N65: 0.8 | O65: 0.8 | P65: 0.8 | Q65: 0.8 | R65: 0.8 | S65: 0.8 | T65: =$F$4*H65 -> 55000 | U65: =$F$4*I65 -> 55000 | V65: =$F$4*J65 -> 55000 | W65: =$F$4*K65 -> 55000 | X65: =$F$4*L65 -> 55000 | Y65: =$F$4*M65 -> 55000 | Z65: =$F$4*N65 -> 55000 | AA65: =$F$4*O65 -> 55000 | ... AE65: =$F$4*S65 -> 55000 | AF65: =SUM(T65:AE65) -> 660000
A66: Development | B66: Other | C66: Engineer 4 | D66: KSC | E66: Dev & Op | G66: =AVERAGE(H66:S66) -> 0 | H66: 0 | I66: 0 | J66: 0 | K66: 0 | L66: 0 | M66: 0 | N66: 0 | O66: 0 | P66: 0 | Q66: 0 | R66: 0 | S66: 0 | T66: =H66*$F$35 -> 0 | U66: =I66*$F$35 -> 0 | V66: =J66*$F$35 -> 0 | W66: =K66*$F$35 -> 0 | X66: =L66*$F$35 -> 0 | Y66: =M66*$F$35 -> 0 | Z66: =N66*$F$35 -> 0 | AA66: =O66*$F$35 -> 0 | ... AE66: =S66*$F$35 -> 0 | AF66: =SUM(T66:AE66) -> 0
A67: Development | B67: Other | C67: Engineer 5 | D67: RNU | E67: Dev & Op | G67: =AVERAGE(H67:S67) -> 0 | H67: 0 | I67: 0 | J67: 0 | K67: 0 | L67: 0 | M67: 0 | N67: 0 | O67: 0 | P67: 0 | Q67: 0 | R67: 0 | S67: 0 | T67: =H67*$F$36 -> 0 | U67: =I67*$F$36 -> 0 | V67: =J67*$F$36 -> 0 | W67: =K67*$F$36 -> 0 | X67: =L67*$F$36 -> 0 | Y67: =M67*$F$36 -> 0 | Z67: =N67*$F$36 -> 0 | AA67: =O67*$F$36 -> 0 | ... AE67: =S67*$F$36 -> 0 | AF67: =SUM(T67:AE67) -> 0
A68: Development | B68: Other | C68: Engineer 6 | D68: TBH | E68: Dev & Op | G68: =AVERAGE(H68:S68) -> 0 | H68: 0 | I68: 0 | J68: 0 | K68: 0 | L68: 0 | M68: 0 | N68: 0 | O68: 0 | P68: 0 | Q68: 0 | R68: 0 | S68: 0 | T68: =H68*$F$43 -> 0 | U68: =I68*$F$43 -> 0 | V68: =J68*$F$43 -> 0 | W68: =K68*$F$43 -> 0 | X68: =L68*$F$43 -> 0 | Y68: =M68*$F$43 -> 0 | Z68: =N68*$F$43 -> 0 | AA68: =O68*$F$43 -> 0 | ... AE68: =S68*$F$43 -> 0 | AF68: =SUM(T68:AE68) -> 0
A69: Development | B69: Other | C69: Engineer 7 | D69: TBH | E69: Dev & Op | G69: =AVERAGE(H69:S69) -> 0 | H69: 0 | I69: 0 | J69: 0 | K69: 0 | L69: 0 | M69: 0 | N69: 0 | O69: 0 | P69: 0 | Q69: 0 | R69: 0 | S69: 0 | T69: =H69*$F$44 -> 0 | U69: =I69*$F$44 -> 0 | V69: =J69*$F$44 -> 0 | W69: =K69*$F$44 -> 0 | X69: =L69*$F$44 -> 0 | Y69: =M69*$F$44 -> 0 | Z69: =N69*$F$44 -> 0 | AA69: =O69*$F$44 -> 0 | ... AE69: =S69*$F$44 -> 0 | AF69: =SUM(T69:AE69) -> 0
A70: Development | B70: Other | C70: Engineer 8 | D70: TBH | E70: Dev & Op | G70: =AVERAGE(H70:S70) -> 0 | H70: 0 | I70: 0 | J70: 0 | K70: 0 | L70: 0 | M70: 0 | N70: 0 | O70: 0 | P70: 0 | Q70: 0 | R70: 0 | S70: 0 | T70: =H70*$F$45 -> 0 | U70: =I70*$F$45 -> 0 | V70: =J70*$F$45 -> 0 | W70: =K70*$F$45 -> 0 | X70: =L70*$F$45 -> 0 | Y70: =M70*$F$45 -> 0 | Z70: =N70*$F$45 -> 0 | AA70: =O70*$F$45 -> 0 | ... AE70: =S70*$F$45 -> 0 | AF70: =SUM(T70:AE70) -> 0
A71: Development | B71: Other | C71: Senior Engineer 7 | D71: TBH | E71: Dev & Op | G71: =AVERAGE(H71:S71) -> 0 | H71: 0 | I71: 0 | J71: 0 | K71: 0 | L71: 0 | M71: 0 | N71: 0 | O71: 0 | P71: 0 | Q71: 0 | R71: 0 | S71: 0 | T71: =H71*$F$46 -> 0 | U71: =I71*$F$46 -> 0 | V71: =J71*$F$46 -> 0 | W71: =K71*$F$46 -> 0 | X71: =L71*$F$46 -> 0 | Y71: =M71*$F$46 -> 0 | Z71: =N71*$F$46 -> 0 | AA71: =O71*$F$46 -> 0 | ... AE71: =S71*$F$46 -> 0 | AF71: =SUM(T71:AE71) -> 0
A72: Clinical affairs | B72: Other | C72: Italian KOL | D72: Fabiocchi | E72: Consultancies | G72: =AVERAGE(H72:S72) -> 0 | H72: 0 | I72: 0 | J72: 0 | K72: 0 | L72: 0 | M72: 0 | N72: 0 | O72: 0 | P72: 0 | Q72: 0 | R72: 0 | S72: 0 | T72: =H72*$F$16 -> 0 | U72: =I72*$F$16 -> 0 | V72: =J72*$F$16 -> 0 | W72: =K72*$F$16 -> 0 | X72: =L72*$F$16 -> 0 | Y72: =M72*$F$16 -> 0 | Z72: =N72*$F$16 -> 0 | AA72: =O72*$F$16 -> 0 | ... AE72: =S72*$F$16 -> 0 | AF72: =SUM(T72:AE72) -> 0
A73: Clinical affairs | B73: Other | C73: KOL Mngt (6) | D73: KOL Mngt (6) | E73: Consultancies | G73: =AVERAGE(H73:S73) -> 1 | H73: 1 | I73: 1 | J73: 1 | K73: 1 | L73: 1 | M73: 1 | N73: 1 | O73: 1 | P73: 1 | Q73: 1 | R73: 1 | S73: 1 | T73: =H73*$F$15 -> 20000 | U73: =I73*$F$15 -> 20000 | V73: =J73*$F$15 -> 20000 | W73: =K73*$F$15 -> 20000 | X73: =L73*$F$15 -> 20000 | Y73: =M73*$F$15 -> 20000 | Z73: =N73*$F$15 -> 20000 | AA73: =O73*$F$15 -> 20000 | ... AE73: =S73*$F$15 -> 20000 | AF73: =SUM(T73:AE73) -> 240000
A74: Development | B74: Other | C74: Product Development Mgr | D74: USA | E74: Dev & Op | G74: =AVERAGE(H74:S74) -> 0 | H74: 0 | I74: 0 | J74: 0 | K74: 0 | L74: 0 | M74: 0 | N74: 0 | O74: 0 | P74: 0 | Q74: 0 | R74: 0 | S74: 0 | T74: =H74*$F$37 -> 0 | U74: =I74*$F$37 -> 0 | V74: =J74*$F$37 -> 0 | W74: =K74*$F$37 -> 0 | X74: =L74*$F$37 -> 0 | Y74: =M74*$F$37 -> 0 | Z74: =N74*$F$37 -> 0 | AA74: =O74*$F$37 -> 0 | ... AE74: =S74*$F$37 -> 0 | AF74: =SUM(T74:AE74) -> 0
A75: Development | B75: Other | C75: Product Manager 2 | D75: MMO | E75: Dev & Op | G75: =AVERAGE(H75:S75) -> 0 | H75: 0 | I75: 0 | J75: 0 | K75: 0 | L75: 0 | M75: 0 | N75: 0 | O75: 0 | P75: 0 | Q75: 0 | R75: 0 | S75: 0 | T75: =H75*$F$39 -> 0 | U75: =I75*$F$39 -> 0 | V75: =J75*$F$39 -> 0 | W75: =K75*$F$39 -> 0 | X75: =L75*$F$39 -> 0 | Y75: =M75*$F$39 -> 0 | Z75: =N75*$F$39 -> 0 | AA75: =O75*$F$39 -> 0 | ... AE75: =S75*$F$39 -> 0 | AF75: =SUM(T75:AE75) -> 0
A76: Development | B76: Other | C76: Product Manager 3 | D76: TBH | E76: Dev & Op | G76: =AVERAGE(H76:S76) -> 0 | H76: 0 | I76: 0 | J76: 0 | K76: 0 | L76: 0 | M76: 0 | N76: 0 | O76: 0 | P76: 0 | Q76: 0 | R76: 0 | S76: 0 | T76: =H76*$F$38 -> 0 | U76: =I76*$F$38 -> 0 | V76: =J76*$F$38 -> 0 | W76: =K76*$F$38 -> 0 | X76: =L76*$F$38 -> 0 | Y76: =M76*$F$38 -> 0 | Z76: =N76*$F$38 -> 0 | AA76: =O76*$F$38 -> 0 | ... AE76: =S76*$F$38 -> 0 | AF76: =SUM(T76:AE76) -> 0
A77: Operations | B77: Other | C77: Project Manager | D77: CFR | E77: Dev & Op | G77: =AVERAGE(H77:S77) -> 0 | H77: 0 | I77: 0 | J77: 0 | K77: 0 | L77: 0 | M77: 0 | N77: 0 | O77: 0 | P77: 0 | Q77: 0 | R77: 0 | S77: 0 | T77: =$F$5*H77 -> 0 | U77: =$F$5*I77 -> 0 | V77: =$F$5*J77 -> 0 | W77: =$F$5*K77 -> 0 | X77: =$F$5*L77 -> 0 | Y77: =$F$5*M77 -> 0 | Z77: =$F$5*N77 -> 0 | AA77: =$F$5*O77 -> 0 | ... AE77: =$F$5*S77 -> 0 | AF77: =SUM(T77:AE77) -> 0
A78: QA-RA | B78: Other | C78: QA Manager | D78: VCA | E78: E&F | G78: =AVERAGE(H78:S78) -> 0.91666667 | H78: 0.5 | I78: 0.5 | J78: 1 | K78: 1 | L78: 1 | M78: 1 | N78: 1 | O78: 1 | P78: 1 | Q78: 1 | R78: 1 | S78: 1 | T78: =$F$20*H78 -> 11100 | U78: =$F$20*I78 -> 11100 | V78: =$F$20*J78 -> 22200 | W78: =$F$20*K78 -> 22200 | X78: =$F$20*L78 -> 22200 | Y78: =$F$20*M78 -> 22200 | Z78: =$F$20*N78 -> 22200 | AA78: =$F$20*O78 -> 22200 | ... AE78: =$F$20*S78 -> 22200 | AF78: =SUM(T78:AE78) -> 244200
A79: QA-RA | B79: Other | C79: Regulatory Affairs consultant | D79: Salma Michor | E79: Consultancies | G79: =AVERAGE(H79:S79) -> 0.05 | H79: 0.05 | I79: 0.05 | J79: 0.05 | K79: 0.05 | L79: 0.05 | M79: 0.05 | N79: 0.05 | O79: 0.05 | P79: 0.05 | Q79: 0.05 | R79: 0.05 | S79: 0.05 | T79: =H79*$F$21 -> 2200 | U79: =I79*$F$21 -> 2200 | V79: =J79*$F$21 -> 2200 | W79: =K79*$F$21 -> 2200 | X79: =L79*$F$21 -> 2200 | Y79: =M79*$F$21 -> 2200 | Z79: =N79*$F$21 -> 2200 | AA79: =O79*$F$21 -> 2200 | ... AE79: =S79*$F$21 -> 2200 | AF79: =SUM(T79:AE79) -> 26400
A80: Development | B80: Other | C80: Senior Engineer 3 | D80: GGO | E80: Dev & Op | G80: =AVERAGE(H80:S80) -> 0 | H80: 0 | I80: 0 | J80: 0 | K80: 0 | L80: 0 | M80: 0 | N80: 0 | O80: 0 | P80: 0 | Q80: 0 | R80: 0 | S80: 0 | T80: =H80*$F$34 -> 0 | U80: =I80*$F$34 -> 0 | V80: =J80*$F$34 -> 0 | W80: =K80*$F$34 -> 0 | X80: =L80*$F$34 -> 0 | Y80: =M80*$F$34 -> 0 | Z80: =N80*$F$34 -> 0 | AA80: =O80*$F$34 -> 0 | ... AE80: =S80*$F$34 -> 0 | AF80: =SUM(T80:AE80) -> 0
A81: Development | B81: Other | C81: Senior Engineer 4 | D81: TBH | E81: Dev & Op | G81: =AVERAGE(H81:S81) -> 0 | H81: 0 | I81: 0 | J81: 0 | K81: 0 | L81: 0 | M81: 0 | N81: 0 | O81: 0 | P81: 0 | Q81: 0 | R81: 0 | S81: 0 | T81: =H81*$F$40 -> 0 | U81: =I81*$F$40 -> 0 | V81: =J81*$F$40 -> 0 | W81: =K81*$F$40 -> 0 | X81: =L81*$F$40 -> 0 | Y81: =M81*$F$40 -> 0 | Z81: =N81*$F$40 -> 0 | AA81: =O81*$F$40 -> 0 | ... AE81: =S81*$F$40 -> 0 | AF81: =SUM(T81:AE81) -> 0
A82: Development | B82: Other | C82: Senior Engineer 5 | D82: TBH | E82: Dev & Op | G82: =AVERAGE(H82:S82) -> 0 | H82: 0 | I82: 0 | J82: 0 | K82: 0 | L82: 0 | M82: 0 | N82: 0 | O82: 0 | P82: 0 | Q82: 0 | R82: 0 | S82: 0 | T82: =H82*$F$41 -> 0 | U82: =I82*$F$41 -> 0 | V82: =J82*$F$41 -> 0 | W82: =K82*$F$41 -> 0 | X82: =L82*$F$41 -> 0 | Y82: =M82*$F$41 -> 0 | Z82: =N82*$F$41 -> 0 | AA82: =O82*$F$41 -> 0 | ... AE82: =S82*$F$41 -> 0 | AF82: =SUM(T82:AE82) -> 0
A83: Development | B83: Other | C83: Senior Engineer 6 | D83: TBH | E83: Dev & Op | G83: =AVERAGE(H83:S83) -> 0 | H83: 0 | I83: 0 | J83: 0 | K83: 0 | L83: 0 | M83: 0 | N83: 0 | O83: 0 | P83: 0 | Q83: 0 | R83: 0 | S83: 0 | T83: =H83*$F$42 -> 0 | U83: =I83*$F$42 -> 0 | V83: =J83*$F$42 -> 0 | W83: =K83*$F$42 -> 0 | X83: =L83*$F$42 -> 0 | Y83: =M83*$F$42 -> 0 | Z83: =N83*$F$42 -> 0 | AA83: =O83*$F$42 -> 0 | ... AE83: =S83*$F$42 -> 0 | AF83: =SUM(T83:AE83) -> 0
A84: Sales and bus dev | B84: Other | C84: Senior Sales Manager France | D84: TBH | E84: E&F | G84: =AVERAGE(H84:S84) -> 0 | H84: 0 | I84: 0 | J84: 0 | K84: 0 | L84: 0 | M84: 0 | N84: 0 | O84: 0 | P84: 0 | Q84: 0 | R84: 0 | S84: 0 | T84: =H84*$F$24 -> 0 | U84: =I84*$F$24 -> 0 | V84: =J84*$F$24 -> 0 | W84: =K84*$F$24 -> 0 | X84: =L84*$F$24 -> 0 | Y84: =M84*$F$24 -> 0 | Z84: =N84*$F$24 -> 0 | AA84: =O84*$F$24 -> 0 | ... AE84: =S84*$F$24 -> 0 | AF84: =SUM(T84:AE84) -> 0
A85: Clinical affairs | B85: Other | C85: Medical director | D85: TBH | E85: E&F | G85: =AVERAGE(H85:S85) -> 0.16666667 | H85: 0.1 | I85: 0.1 | J85: 0.1 | K85: 0.1 | L85: 0.2 | M85: 0.2 | N85: 0.2 | O85: 0.2 | P85: 0.2 | Q85: 0.2 | R85: 0.2 | S85: 0.2 | T85: =H85*$F$19 -> 6000 | U85: =I85*$F$19 -> 6000 | V85: =J85*$F$19 -> 6000 | W85: =K85*$F$19 -> 6000 | X85: =L85*$F$19 -> 12000 | Y85: =M85*$F$19 -> 12000 | Z85: =N85*$F$19 -> 12000 | AA85: =O85*$F$19 -> 12000 | ... AE85: =S85*$F$19 -> 12000 | AF85: =SUM(T85:AE85) -> 120000
A86: Sales and bus dev | B86: T1 | C86: Business Development Manager HQ | D86: BPI | E86: E&F | G86: =AVERAGE(H86:S86) -> 0.5 | H86: 0.5 | I86: 0.5 | J86: 0.5 | K86: 0.5 | L86: 0.5 | M86: 0.5 | N86: 0.5 | O86: 0.5 | P86: 0.5 | Q86: 0.5 | R86: 0.5 | S86: 0.5 | T86: =H86*$F$22 -> 9898.0902 | U86: =I86*$F$22 -> 9898.0902 | V86: =J86*$F$22 -> 9898.0902 | W86: =K86*$F$22 -> 9898.0902 | X86: =L86*$F$22 -> 9898.0902 | Y86: =M86*$F$22 -> 9898.0902 | Z86: =N86*$F$22 -> 9898.0902 | AA86: =O86*$F$22 -> 9898.0902 | ... AE86: =S86*$F$22 -> 9898.0902 | AF86: =SUM(T86:AE86) -> 118777.08
