Workbook

Sheet Hospital 
S1: Ramp-up | T1: 0.1 | U1: 0.2 | V1: 0.3 | W1: 0.4
P3: Market Penetration - Hospital | BF3: Total - Y1 | BG3: Total - Y2 | BH3: Total - Y3
C4: Total Adressable Market - Hospital | AI4: Hospital projection | BF4: Beds - Y1 | BG4: Beds - Y2 | BH4: Beds - Y3
C5: Unmet clinical needs: | P5: General beds pricing (B) | T5: Y1 | X5: Total - Y1 | Y5: Y2 | AC5: Total - Y2 | AD5: Y3 | AH5: Total - Y3 | AJ5: Based on average size without targeting | AM5: Based on hospital size = 750 beds | BE5: Belgium | BF5: 558.99856 | BG5: 1117.9971 | BH5: 2794.9928
C6: All patients at-risk of malnutrition that need nutritionnal support during their stay | Q6: Y1 | R6: Y2 | S6: Y3 | T6: Q1 | U6: Q2 | V6: Q3 | W6: Q4 | X6: Beds - Y1 | Y6: Q1 | Z6: Q2 | AA6: Q3 | AB6: Q4 | AC6: Beds - Y2 | AD6: Q1 | AE6: Q2 | AF6: Q3 | AG6: Q4 | AH6: Beds - Y3 | AI6: Hospitals - Y1 | AJ6: Hospitals - Y2 | AK6: Hospitals - Y3 | AL6: Hospitals - Y1 | AM6: Hospitals - Y2 | AN6: Hospitals - Y3 | BE6: France | BF6: 0 | BG6: 1749.7695 | BH6: 5249.3085
C7: All -ICU patients | P7: Belgium | Q7: 0.02 | R7: =4% -> 0.04 | S7: =8% -> 0.08 | T7: =$X$7*10% -> 43.8676 | U7: =X$7*20% -> 87.7352 | V7: =$X$7*30% -> 131.6028 | W7: =$X$7*40% -> 175.4704 | X7: =$F$32*Q7 -> 438.676 | Y7: =$AC$7*25% -> 219.338 | Z7: =$AC$7*25% -> 219.338 | AA7: =$AC$7*25% -> 219.338 | AB7: =$AC$7*25% -> 219.338 | AC7: =$F$32*R7 -> 877.352 | AD7: =$AH$7*25% -> 438.676 | AE7: =$AH$7*25% -> 438.676 | AF7: =$AH$7*25% -> 438.676 | AG7: =$AH$7*25% -> 438.676 | AH7: =$F$32*S7 -> 1754.704 | AI7: =ROUND(X7/$K$32,0) -> 2 | AJ7: =ROUND(AC7/$K$32,0) -> 5 | AK7: =ROUND(AH7/$K$32,0) -> 9 | AL7: =ROUND(X7/$M$42,0) -> 2 | AM7: =ROUND(AC7/$M$42,0) -> 4 | AN7: =ROUND(AH7/$M$42,0) -> 8 | BE7: Italy | BF7: 577.56376 | BG7: 1237.6366 | BH7: 4125.4554
P8: France | Q8: 0 | R8: 0.005 | S8: 0.018 | T8: =X8*10% -> 0 | U8: =X$8*20% -> 0 | V8: =$X$8*30% -> 0 | W8: =$X$8*40% -> 0 | X8: =$F$33*Q8 -> 0 | Y8: =$AC$8*10% -> 68.656875 | Z8: =$AC$8*20% -> 137.31375 | AA8: =$AC$8*30% -> 205.97063 | AB8: =$AC$8*40% -> 274.6275 | AC8: =$F$33*R8 -> 686.56875 | AD8: =$AH$8*25% -> 617.91188 | AE8: =$AH$8*25% -> 617.91188 | AF8: =$AH$8*25% -> 617.91188 | AG8: =$AH$8*25% -> 617.91188 | AH8: =$F$33*S8 -> 2471.6475 | AI8: =ROUND(X8/$K$33,0) -> 0 | AJ8: =ROUND(AC8/$K$33,0) -> 5 | AK8: =ROUND(AH8/$K$33,0) -> 17 | AL8: =ROUND(X8/$M$42,0) -> 0 | AM8: =ROUND(AC8/$M$42,0) -> 3 | AN8: =ROUND(AH8/$M$42,0) -> 11 | BE8: Germany | BF8: 0 | BG8: 2843.5087 | BH8: 8530.526
P9: Italy | Q9: 0.009 | R9: 0.025 | S9: 0.05 | T9: =X9*10% -> 58.27437 | U9: =X$9*20% -> 116.54874 | V9: =$X$7*30% -> 131.6028 | W9: =$X$9*40% -> 233.09748 | X9: =$F$34*Q9 -> 582.7437 | Y9: =$AC$9*25% -> 404.68313 | Z9: =$AC$9*25% -> 404.68313 | AA9: =$AC$9*25% -> 404.68313 | AB9: =$AC$9*25% -> 404.68313 | AC9: =$F$34*R9 -> 1618.7325 | AD9: =$AH$9*25% -> 809.36625 | AE9: =$AH$9*25% -> 809.36625 | AF9: =$AH$9*25% -> 809.36625 | AG9: =$AH$9*25% -> 809.36625 | AH9: =$F$34*S9 -> 3237.465 | AI9: =ROUND(X9/$K$34,0) -> 11 | AJ9: =ROUND(AC9/$K$34,0) -> 30 | AK9: =ROUND(AH9/$K$34,0) -> 59 | AL9: =ROUND(X9/$M$42,0) -> 3 | AM9: =ROUND(AC9/$M$42,0) -> 7 | AN9: =ROUND(AH9/$M$42,0) -> 14
C10: Prevalence in general hospital patient population: | P10: Germany | Q10: 0 | R10: 0.005 | S10: 0.018 | T10: =X10*10% -> 0 | U10: =X$10*20% -> 0 | V10: =$X$10*30% -> 0 | W10: =$X$10*40% -> 0 | X10: =$F$35*Q10 -> 0 | Y10: =$AC$10*10% -> 111.57265 | Z10: =$AC$10*20% -> 223.1453 | AA10: =$AC$10*30% -> 334.71795 | AB10: =$AC$10*40% -> 446.2906 | AC10: =$F$35*R10 -> 1115.7265 | AD10: =$AH$10*25% -> 1004.1538 | AE10: =$AC$10*25% -> 278.93162 | AF10: =$AC$10*25% -> 278.93162 | AG10: =$AC$10*25% -> 278.93162 | AH10: =$F$35*S10 -> 4016.6154 | AI10: =ROUND(X10/$K$35,0) -> 0 | AJ10: =ROUND(AC10/$K$35,0) -> 11 | AK10: =ROUND(AH10/$K$35,0) -> 39 | AL10: =ROUND(X10/$M$42,0) -> 0 | AM10: =ROUND(AC10/$M$42,0) -> 5 | AN10: =ROUND(AH10/$M$42,0) -> 18
C11: "At-risk" | E11: Min | F11: 0.2 | P11: Netherlands | Q11: 0 | R11: 0.02 | S11: 0.04 | T11: 0 | U11: =X11*10% -> 0 | V11: =X11*10% -> 0 | W11: =X11*10% -> 0 | X11: =$F$36*Q11 -> 0 | Y11: =$AC$11*10% -> 39.0747 | Z11: =$AC$10*20% -> 223.1453 | AA11: =$AC$10*30% -> 334.71795 | AB11: =$AC$10*40% -> 446.2906 | AC11: =$F36*R11 -> 390.747 | AD11: =$AH$11*25% -> 195.3735 | AE11: =$AH$11*25% -> 195.3735 | AF11: =$AH$11*25% -> 195.3735 | AG11: =$AH$11*25% -> 195.3735 | AH11: =$F36*S11 -> 781.494 | AI11: =ROUND(X11/$K$35,0) -> 0 | AJ11: =ROUND(AC11/$K$35,0) -> 4 | AK11: =ROUND(AH11/$K$35,0) -> 8 | AL11: =X11/$M$42 -> 0 | AM11: =ROUNDUP(AC11/$M$42,0) -> 2 | AN11: =ROUNDUP(AH11/$M$42,0) -> 4
E12: Max | F12: 0.5 | P12: =C37 -> Country 1 | Q12: 0 | R12: 0.003 | S12: 0.012 | X12: =$F$36*Q12 -> 0 | AC12: =$F37*R12 -> 203.7 | AH12: =$F37*S12 -> 814.8 | AI12: =ROUND(X12/$K$35,0) -> 0 | AJ12: =ROUND(AC12/$K$35,0) -> 2 | AK12: =ROUND(AH12/$K$35,0) -> 8 | AL12: =X12/$M$42 -> 0 | AM12: =ROUNDUP(AC12/$M$42,0) -> 1 | AN12: =ROUNDUP(AH12/$M$42,0) -> 4
E13: Median | F13: 0.35 | G13: 1 | P13: =C38 -> Country 2 | Q13: 0 | X13: =$F$36*Q13 -> 0 | AC13: =$F38*R13 -> 0 | AH13: =$F38*S13 -> 0 | AI13: =ROUND(X13/$K$35,0) -> 0 | AJ13: =ROUND(AC13/$K$35,0) -> 0 | AK13: =ROUND(AH13/$K$35,0) -> 0 | AL13: =X13/$M$42 -> 0 | AM13: =ROUNDUP(AC13/$M$42,0) -> 0 | AN13: =ROUNDUP(AH13/$M$42,0) -> 0
C14: ICU Beds | F14: 0.05 | P14: =C39 -> Country 3 | Q14: 0 | X14: =$F$36*Q14 -> 0 | AC14: =$F39*R14 -> 0 | AH14: =$F39*S14 -> 0 | AI14: =ROUND(X14/$K$35,0) -> 0 | AJ14: =ROUND(AC14/$K$35,0) -> 0 | AK14: =ROUND(AH14/$K$35,0) -> 0 | AL14: =X14/$M$42 -> 0 | AM14: =ROUNDUP(AC14/$M$42,0) -> 0 | AN14: =ROUNDUP(AH14/$M$42,0) -> 0
P15: =C40 -> Country 4 | Q15: 0 | X15: =$F$36*Q15 -> 0 | AC15: =$F40*R15 -> 0 | AH15: =$F40*S15 -> 0 | AI15: =ROUND(X15/$K$35,0) -> 0 | AJ15: =ROUND(AC15/$K$35,0) -> 0 | AK15: =ROUND(AH15/$K$35,0) -> 0 | AL15: =X15/$M$42 -> 0 | AM15: =ROUNDUP(AC15/$M$42,0) -> 0 | AN15: =ROUNDUP(AH15/$M$42,0) -> 0
C16: Metric: | P16: Total | AK16: Total | AL16: =SUM(AL7:AL15) -> 5 | AM16: =SUM(AM7:AM15) -> 22 | AN16: =SUM(AN7:AN15) -> 59
C17: Hospital Beds | BF17: Total - Y1 | BG17: Total - Y2 | BH17: Total - Y3
C18: ICU Beds | P18: Feedim EN devices | T18: Y1 | X18: Total - Y1 | Y18: Y2 | AC18: Total - Y2 | AD18: Y3 | AH18: Total - Y3 | BE18: Belgium | BF18: 55.899856 | BG18: 111.79971 | BH18: 279.49928
T19: Q1 | U19: Q2 | V19: Q3 | W19: Q4 | X19: Devices - Y1 | Y19: Q1 | Z19: Q2 | AA19: Q3 | AB19: Q4 | AC19: Devices - Y2 | AD19: Q1 | AE19: Q2 | AF19: Q3 | AG19: Q4 | AH19: Devices - Y3 | BE19: France | BF19: 0 | BG19: 174.97695 | BH19: 524.93085
C20: Geographic criteria | P20: Belgium | T20: =$X$20*10% -> 4.38676 | U20: =$X$20*20% -> 8.77352 | V20: =$X$20*30% -> 13.16028 | W20: =$X$20*40% -> 17.54704 | X20: =X7*$J$27 -> 43.8676 | Y20: =$AC$20*25% -> 21.9338 | Z20: =$AC$20*25% -> 21.9338 | AA20: =$AC$20*25% -> 21.9338 | AB20: =$AC$20*25% -> 21.9338 | AC20: =AC7*$J$27 -> 87.7352 | AD20: =$AH$20*25% -> 43.8676 | AE20: =$AH$20*25% -> 43.8676 | AF20: =$AH$20*25% -> 43.8676 | AG20: =$AH$20*25% -> 43.8676 | AH20: =AH7*$J$27 -> 175.4704 | BE20: Italy | BF20: 57.756376 | BG20: 123.76366 | BH20: 412.54554
P21: France | T21: =$X$21*10% -> 0 | U21: =$X$21*20% -> 0 | V21: =$X$21*30% -> 0 | W21: =$X$21*40% -> 0 | X21: =X8*$J$27 -> 0 | Y21: =$AC21*10% -> 6.8656875 | Z21: =$AC21*20% -> 13.731375 | AA21: =$AC21*30% -> 20.597062 | AB21: =$AC21*40% -> 27.46275 | AC21: =AC8*$J$27 -> 68.656875 | AD21: =$AH$21*25% -> 61.791188 | AE21: =$AH$21*25% -> 61.791188 | AF21: =$AH$21*25% -> 61.791188 | AG21: =$AH$21*25% -> 61.791188 | AH21: =AH8*$J$27 -> 247.16475 | BE21: Germany | BF21: 0 | BG21: 284.35087 | BH21: 853.0526
C22: Belgium + top European western countries | P22: Italy | T22: =$X$22*10% -> 5.827437 | U22: =$X$22*20% -> 11.654874 | V22: =$X$22*30% -> 17.482311 | W22: =$X$22*40% -> 23.309748 | X22: =X9*$J$27 -> 58.27437 | Y22: =$AC22*25% -> 40.468313 | Z22: =$AC22*25% -> 40.468313 | AA22: =$AC22*25% -> 40.468313 | AB22: =$AC22*25% -> 40.468313 | AC22: =AC9*$J$27 -> 161.87325 | AD22: =$AH$22*25% -> 80.936625 | AE22: =$AH$22*25% -> 80.936625 | AF22: =$AH$22*25% -> 80.936625 | AG22: =$AH$22*25% -> 80.936625 | AH22: =AH9*$J$27 -> 323.7465
P23: Germany | T23: =$X$23*10% -> 0 | U23: =$X$23*20% -> 0 | V23: =$X$23*30% -> 0 | W23: =$X$23*40% -> 0 | X23: =X10*$J$27 -> 0 | Y23: =$AC23*10% -> 11.157265 | Z23: =$AC23*20% -> 22.31453 | AA23: =$AC23*30% -> 33.471795 | AB23: =$AC23*40% -> 44.62906 | AC23: =AC10*$J$27 -> 111.57265 | AD23: =$AH$23*25% -> 100.41539 | AE23: =$AH$23*25% -> 100.41539 | AF23: =$AH$23*25% -> 100.41539 | AG23: =$AH$23*25% -> 100.41539 | AH23: =AH10*$J$27 -> 401.66154
C24: Feedim | P24: Netherlands | T24: =$X$24*10% -> 0 | U24: =X24*20% -> 0 | V24: =X24*30% -> 0 | W24: =$X$24*40% -> 0 | X24: =X11*$J$27 -> 0 | Y24: =$AC24*10% -> 3.90747 | Z24: =$AC24*20% -> 7.81494 | AA24: =$AC24*30% -> 11.72241 | AB24: =$AC24*40% -> 15.62988 | AC24: =AC11*$J$27 -> 39.0747 | AD24: =$AH24*25% -> 19.53735 | AE24: =$AH24*25% -> 19.53735 | AF24: =$AH24*25% -> 19.53735 | AG24: =$AH24*25% -> 19.53735 | AH24: =AH11*$J$27 -> 78.1494
C25: EN prevalence in hospital | F25: =2% -> 0.02 | G25: of all stays | H25: 8 | P25: =C37 -> Country 1 | T25: =X25*10% -> 0 | U25: =X25*20% -> 0 | V25: =X25*30% -> 0 | W25: =$X$24*40% -> 0 | X25: =X12*$J$27 -> 0 | Y25: =$AC25*10% -> 2.037 | Z25: =$AC25*20% -> 4.074 | AA25: =$AC25*30% -> 6.111 | AB25: =$AC25*40% -> 8.148 | AC25: =AC12*$J$27 -> 20.37 | AD25: =$AH25*25% -> 20.37 | AE25: =$AH25*25% -> 20.37 | AF25: =$AH25*25% -> 20.37 | AG25: =$AH25*25% -> 20.37 | AH25: =AH12*$J$27 -> 81.48
C26: EN prevalence in at-risk patient | F26: =6% -> 0.06 | P26: =C38 -> Country 2 | T26: =X26*10% -> 0 | U26: =X26*20% -> 0 | V26: =X26*30% -> 0 | W26: =$X$24*40% -> 0 | X26: =X13*$J$27 -> 0 | Y26: =$AC26*10% -> 0 | Z26: =$AC26*20% -> 0 | AA26: =$AC26*30% -> 0 | AB26: =$AC26*40% -> 0 | AC26: =AC13*$J$27 -> 0 | AD26: =$AH26*25% -> 0 | AE26: =$AH26*25% -> 0 | AF26: =$AH26*25% -> 0 | AG26: =$AH26*25% -> 0 | AH26: =AH13*$J$27 -> 0
C27: EN prevalence in ICU | F27: =50% -> 0.5 | H27: EN pumps per hospital beds | J27: 0.1 | P27: =C39 -> Country 3 | T27: =X27*10% -> 0 | U27: =X27*20% -> 0 | V27: =X27*30% -> 0 | W27: =$X$24*40% -> 0 | X27: =X14*$J$27 -> 0 | Y27: =$AC27*10% -> 0 | Z27: =$AC27*20% -> 0 | AA27: =$AC27*30% -> 0 | AB27: =$AC27*40% -> 0 | AC27: =AC14*$J$27 -> 0 | AD27: =$AH27*25% -> 0 | AE27: =$AH27*25% -> 0 | AF27: =$AH27*25% -> 0 | AG27: =$AH27*25% -> 0 | AH27: =AH14*$J$27 -> 0
C28: PN prevalence in at-risk patients | F28: 0.045 | P28: =C40 -> Country 4 | T28: =X28*10% -> 0 | U28: =X28*20% -> 0 | V28: =X28*30% -> 0 | W28: =$X$24*40% -> 0 | X28: =X15*$J$27 -> 0 | Y28: =$AC28*10% -> 0 | Z28: =$AC28*20% -> 0 | AA28: =$AC28*30% -> 0 | AB28: =$AC28*40% -> 0 | AC28: =AC15*$J$27 -> 0 | AD28: =$AH28*25% -> 0 | AE28: =$AH28*25% -> 0 | AF28: =$AH28*25% -> 0 | AG28: =$AH28*25% -> 0 | AH28: =AH15*$J$27 -> 0
C29: PN prevalence in ICU | F29: 0.5 | P29: Total | T29: =SUM(T20:T29) -> 0 | U29: =SUM(U20:U24) -> 20.428394 | V29: =SUM(V20:V24) -> 30.642591 | W29: =SUM(W20:W24) -> 40.856788 | X29: =SUM(X20:X28) -> 102.14197 | Y29: =SUM(Y20:Y28) -> 86.369535 | Z29: =SUM(Z20:Z28) -> 110.33696 | AA29: =SUM(AA20:AA28) -> 134.30438 | AB29: =SUM(AB20:AB28) -> 158.2718 | AC29: =SUM(AC20:AC28) -> 489.28268 | AD29: =SUM(AD20:AD28) -> 326.91815 | AE29: =SUM(AE20:AE28) -> 326.91815 | ... AH29: =SUM(AH20:AH28) -> 1307.6726 | BF29: Total - Y1 | BG29: Total - Y2 | BH29: Total - Y3
E31: All Beds2 | F31: At-risk beds w/o ICU (A) | G31: ICU beds (B)7 | H31: TAM (A+B) | I31: Hospitals 4,5,6,7 | J31: Average hospital size | K31: Average At-risk beds w/o ICU per hospital | L31: Average ICU Beds per hospital | M31: Scenario A - hospital size = 750 beds | N31: Scenario B - ICu size = 20 beds
C32: Belgium | E32: 64423 | F32: =(E32-G32)*$F$13 -> 21933.8 | G32: 1755 | H32: =G32+F32 -> 23688.8 | I32: 103 | J32: =E32/I32 -> 625.46602 | K32: =J32*($F$13-5%) -> 187.63981 | L32: =G32/I32 -> 17.038835 | P32: Feedim PN devices | T32: Y1 | X32: Total - Y1 | Y32: Y2 | AC32: Total - Y2 | AD32: Y3 | AH32: Total - Y3 | BE32: Belgium | BF32: 0 | BG32: 50.30987 | BH32: 125.77468
C33: France | E33: 399865 | F33: =(E33-G33)*$F$13 -> 137313.75 | G33: 7540 | H33: =G33+F33 -> 144853.75 | I33: 822 | J33: =E33/I33 -> 486.45377 | K33: =J33*($F$13-5%) -> 145.93613 | L33: =G33/I33 -> 9.1727494 | T33: Q1 | U33: Q2 | V33: Q3 | W33: Q4 | X33: Devices - Y1 | Y33: Q1 | Z33: Q2 | AA33: Q3 | AB33: Q4 | AC33: Devices - Y2 | AD33: Q1 | AE33: Q2 | AF33: Q3 | AG33: Q4 | AH33: Devices - Y3 | BE33: France | BF33: 0 | BG33: 78.739627 | BH33: 236.21888
C34: Italy | E34: 192548 | F34: =(E34-G34)*$F$13 -> 64749.3 | G34: 7550 | H34: =G34+F34 -> 72299.3 | I34: 1055 | J34: =E34/I34 -> 182.50995 | K34: =J34*($F$13-5%) -> 54.752986 | L34: =G34/I34 -> 7.1563981 | P34: Belgium | T34: 0 | U34: 0 | V34: 0 | W34: 0 | X34: 0 | Y34: =$AC$34*10% -> 3.948084 | Z34: =$AC34*20% -> 7.896168 | AA34: =$AC34*30% -> 11.844252 | AB34: =$AC34*40% -> 15.792336 | AC34: =AC7*$F$28 -> 39.48084 | AD34: =$AH$34*25% -> 19.74042 | AE34: =$AH$34*25% -> 19.74042 | AF34: =$AH$34*25% -> 19.74042 | AG34: =$AH$34*25% -> 19.74042 | AH34: =AH7*$F$28 -> 78.96168 | BE34: Italy | BF34: 0 | BG34: 55.693648 | BH34: 185.64549
C35: Germany | E35: 661448 | F35: =(E35-G35)*$F$13 -> 223145.3 | G35: 23890 | H35: =G35+F35 -> 247035.3 | I35: 1925 | J35: =E35/I35 -> 343.60935 | K35: =J35*($F$13-5%) -> 103.08281 | L35: =G35/I35 -> 12.41039 | P35: France | T35: 0 | U35: 0 | V35: 0 | W35: 0 | X35: =X8*$F$28 -> 0 | Y35: =AC35*10% -> 3.0895594 | Z35: =$AC35*20% -> 6.1791188 | AA35: =$AC35*30% -> 9.2686781 | AB35: =$AC35*40% -> 12.358238 | AC35: =AC8*$F$28 -> 30.895594 | AD35: =$AH$35*25% -> 27.806034 | AE35: =$AH$35*25% -> 27.806034 | AF35: =$AH$35*25% -> 27.806034 | AG35: =$AH$35*25% -> 27.806034 | AH35: =AH8*$F$28 -> 111.22414 | BE35: Germany | BF35: 0 | BG35: 127.95789 | BH35: 383.87367
C36: Netherlands | E36: 56886 | F36: =(E36-G36)*$F$13 -> 19537.35 | G36: 1065 | H36: =G36+F36 -> 20602.35 | I36: 545 | J36: =E36/I36 -> 104.37798 | K36: =J36*($F$13-5%) -> 31.313394 | L36: =G36/I36 -> 1.9541284 | P36: Italy | T36: 0 | U36: 0 | V36: 0 | W36: 0 | X36: 0 | Y36: =AC36*10% -> 7.2842963 | Z36: =$AC36*20% -> 14.568593 | AA36: =$AC36*30% -> 21.852889 | AB36: =$AC36*40% -> 29.137185 | AC36: =AC9*$F$28 -> 72.842962 | AD36: =$AH$36*25% -> 36.421481 | AE36: =$AH$36*25% -> 36.421481 | AF36: =$AH$36*25% -> 36.421481 | AG36: =$AH$36*25% -> 36.421481 | AH36: =AH9*$F$28 -> 145.68592
C37: Country 1 | E37: =200000 -> 200000 | F37: =(E37-G37)*$F$13 -> 67900 | G37: =E37*3% -> 6000 | H37: =G37+F37 -> 73900 | P37: Germany | T37: 0 | U37: 0 | V37: 0 | W37: 0 | X37: 0 | Y37: =AC37*10% -> 5.0207693 | Z37: =$AC37*20% -> 10.041539 | AA37: =$AC37*30% -> 15.062308 | AB37: =$AC37*40% -> 20.083077 | AC37: =AC10*$F$28 -> 50.207693 | AD37: =$AH$37*25% -> 45.186923 | AE37: =$AH$37*25% -> 45.186923 | AF37: =$AH$37*25% -> 45.186923 | AG37: =$AH$37*25% -> 45.186923 | AH37: =AH10*$F$28 -> 180.74769
C38: Country 2 | P38: Netherlands | T38: 0 | U38: 0 | V38: 0 | W38: 0 | X38: 0 | Y38: =AC38*10% -> 1.7583615 | Z38: =$AC38*20% -> 3.516723 | AA38: =$AC38*30% -> 5.2750845 | AB38: =$AC38*40% -> 7.033446 | AC38: =AC11*$F$28 -> 17.583615 | AD38: =$AH38*25% -> 8.7918075 | AE38: =$AH38*25% -> 8.7918075 | AF38: =$AH38*25% -> 8.7918075 | AG38: =$AH38*25% -> 8.7918075 | AH38: =AH11*$F$28 -> 35.16723
C39: Country 3 | P39: =C37 -> Country 1 | T39: 0 | U39: 0 | V39: 0 | W39: 0 | X39: 0 | Y39: =AC39*10% -> 0.91665 | Z39: =$AC39*20% -> 1.8333 | AA39: =$AC39*30% -> 2.74995 | AB39: =$AC39*40% -> 3.6666 | AC39: =AC12*$F$28 -> 9.1665 | AD39: =$AH39*25% -> 9.1665 | AE39: =$AH39*25% -> 9.1665 | AF39: =$AH39*25% -> 9.1665 | AG39: =$AH39*25% -> 9.1665 | AH39: =AH12*$F$28 -> 36.666
C40: Country 4 | P40: =C38 -> Country 2 | T40: 0 | U40: 0 | V40: 0 | W40: 0 | X40: 0 | Y40: =AC40*10% -> 0 | Z40: =$AC40*20% -> 0 | AA40: =$AC40*30% -> 0 | AB40: =$AC40*40% -> 0 | AC40: =AC13*$F$28 -> 0 | AD40: =$AH40*25% -> 0 | AE40: =$AH40*25% -> 0 | AF40: =$AH40*25% -> 0 | AG40: =$AH40*25% -> 0 | AH40: =AH13*$F$28 -> 0
P41: =C39 -> Country 3 | T41: 0 | U41: 0 | V41: 0 | W41: 0 | X41: 0 | Y41: =AC41*10% -> 0 | Z41: =$AC41*20% -> 0 | AA41: =$AC41*30% -> 0 | AB41: =$AC41*40% -> 0 | AC41: =AC14*$F$28 -> 0 | AD41: =$AH41*25% -> 0 | AE41: =$AH41*25% -> 0 | AF41: =$AH41*25% -> 0 | AG41: =$AH41*25% -> 0 | AH41: =AH14*$F$28 -> 0
C42: Total | E42: =SUM(E32:E40) -> 1575170 | F42: =SUM(F32:F40) -> 534579.5 | G42: =SUM(G32:G40) -> 47800 | H42: =SUM(H32:H40) -> 582379.5 | I42: =SUM(I32:I40) -> 4450 | J42: =SUM(J32:J40) -> 1742.4171 | K42: =SUM(K32:K40) -> 522.72512 | L42: =SUM(L32:L40) -> 47.7325 | M42: =750*(F13-F14) -> 225 | N42: 20 | P42: =C40 -> Country 4 | T42: 0 | U42: 0 | V42: 0 | W42: 0 | X42: 0 | Y42: =AC42*10% -> 0 | Z42: =$AC42*20% -> 0 | AA42: =$AC42*30% -> 0 | AB42: =$AC42*40% -> 0 | AC42: =AC15*$F$28 -> 0 | AD42: =$AH42*25% -> 0 | AE42: =$AH42*25% -> 0 | AF42: =$AH42*25% -> 0 | AG42: =$AH42*25% -> 0 | AH42: =AH15*$F$28 -> 0
P43: Total | T43: =SUM(T34:T42) -> 0 | U43: =SUM(U34:U42) -> 0 | V43: =SUM(V34:V42) -> 0 | W43: =SUM(W34:W42) -> 0 | X43: =SUM(X34:X42) -> 0 | Y43: =SUM(Y34:Y42) -> 22.01772 | Z43: =SUM(Z34:Z42) -> 44.035441 | AA43: =SUM(AA34:AA42) -> 66.053161 | ... AH43: =SUM(AH34:AH42) -> 588.45267
C44: Feedim EN devices | F44: =F42*6% -> 32074.77 | G44: =G42*50% -> 23900 | H44: =SUM(F44:G44) -> 55974.77
C45: Feedim PN devices | F45: =F42*$F$28 -> 24056.077 | G45: =G42*$F$28 -> 2151 | H45: =H42*$F$28 -> 26207.077 | P45: ICU beds (A) | T45: Y1 | X45: Total - Y1 | Y45: Y2 | AC45: Total - Y2 | AD45: Y3 | AH45: Total - Y3 | AJ45: Based on average size without targeting | AM45: Based on ICU beds = 20
Q46: Y1 | R46: Y2 | S46: Y3 | T46: Q1 | U46: Q2 | V46: Q3 | W46: Q4 | X46: ICU Beds - Y1 | Y46: Q1 | Z46: Q2 | AA46: Q3 | AB46: Q4 | AC46: ICU Beds - Y2 | AD46: Q1 | AE46: Q2 | AF46: Q3 | AG46: Q4 | AH46: ICU Beds - Y3 | AI46: Hospitals - Y1 | AJ46: Hospitals - Y2 | AK46: Hospitals - Y3 | AL46: Hospitals - Y1 | AM46: Hospitals - Y2 | AN46: Hospitals - Y3 | BF46: ICU Beds - Y1 | BG46: ICU Beds - Y2 | BH46: ICU Beds - Y3
C47: References : | P47: Belgium | Q47: 0.02 | R47: =3% -> 0.03 | S47: =8% -> 0.08 | T47: =$X$47*0% -> 0 | U47: =$X$47*0% -> 0 | V47: =$X$47*50% -> 17.55 | W47: =$X$47*50% -> 17.55 | X47: =$G$32*Q47 -> 35.1 | Y47: =$AC$47*25% -> 13.1625 | Z47: =$AC$47*25% -> 13.1625 | AA47: =$AC$47*25% -> 13.1625 | AB47: =$AC$47*25% -> 13.1625 | AC47: =$G$32*R47 -> 52.65 | AD47: =$AH$47*25% -> 35.1 | AE47: =$AH$47*25% -> 35.1 | AF47: =$AH$47*25% -> 35.1 | AG47: =$AH$47*25% -> 35.1 | AH47: =$G$32*S47 -> 140.4 | AI47: =ROUND(X47/$L$32,0) -> 2 | AJ47: =ROUND(AC47/$L$32,0) -> 3 | AK47: =ROUND(AH47/$L$32,0) -> 8 | AL47: =ROUND(X47/$N$42,0) -> 2 | AM47: =ROUND(AC47/$N$42,0) -> 3 | AN47: =ROUND(AH47/$N$42,0) -> 7 | BE47: Belgium | BF47: 35.1 | BG47: 70.2 | BH47: 175.5
B48: 1. | C48: Malnutrition prevalence | E48: https://www.ncbi.nlm.nih.gov/pmc/articles/PMC4596423/#b6-medscimonit-21-2969 | P48: France | Q48: 0 | R48: 0.005 | S48: 0.03 | T48: =$X$48*10% -> 0 | U48: =$X$48*20% -> 0 | V48: =$X$48*30% -> 0 | W48: =$X$48*40% -> 0 | X48: =$G$33*Q48 -> 0 | Y48: =$AC$48*10% -> 3.77 | Z48: =$AC$48*20% -> 7.54 | AA48: =$AC$48*30% -> 11.31 | AB48: =$AC$48*40% -> 15.08 | AC48: =$G$33*R48 -> 37.7 | AD48: =$AH$48*25% -> 56.55 | AE48: =$AH$48*25% -> 56.55 | AF48: =$AH$48*25% -> 56.55 | AG48: =$AH$48*25% -> 56.55 | AH48: =$G$33*S48 -> 226.2 | AI48: =ROUND(X48/$L$33,0) -> 0 | AJ48: =ROUND(AC48/$L$33,0) -> 4 | AK48: =ROUND(AH48/$L$33,0) -> 25 | AL48: =ROUND(X48/$N$42,0) -> 0 | AM48: =ROUND(AC48/$N$42,0) -> 2 | AN48: =ROUND(AH48/$N$42,0) -> 11 | BE48: France | BF48: 0 | BG48: 75.4 | BH48: 226.2
B49: 2. | C49: Hospital Beds: | E49: https://ec.europa.eu/eurostat/statistics-explained/images/9/98/Hospital_beds_by_type_of_care%2C_2017_Health2019.png | P49: Italy | Q49: 0.005 | R49: 0.01 | S49: 0.035 | T49: =$X$49*0% -> 0 | U49: =$X$49*0% -> 0 | V49: =$X$49*50% -> 18.875 | W49: =$X$49*50% -> 18.875 | X49: =$G$34*Q49 -> 37.75 | Y49: =$AC$49*25% -> 18.875 | Z49: =$AC$49*25% -> 18.875 | AA49: =$AC$49*25% -> 18.875 | AB49: =$AC$49*25% -> 18.875 | AC49: =$G$34*R49 -> 75.5 | AD49: =$AH$49*25% -> 66.0625 | AE49: =$AH$49*25% -> 66.0625 | AF49: =$AH$49*25% -> 66.0625 | AG49: =$AH$49*25% -> 66.0625 | AH49: =$G$34*S49 -> 264.25 | AI49: =ROUND(X49/$L$34,0) -> 5 | AJ49: =ROUND(AC49/$L$34,0) -> 11 | AK49: =ROUND(AH49/$L$34,0) -> 37 | AL49: =ROUND(X49/$N$42,0) -> 2 | AM49: =ROUND(AC49/$N$42,0) -> 4 | AN49: =ROUND(AH49/$N$42,0) -> 13
B50: 3. | C50: Belgian hospitals: | E50: https://www.lespecialiste.be/fr/actualites/hopitaux-generaux-10-chiffres-a-retenir-rapport-sante-publique.html | P50: Germany | Q50: 0 | R50: 0.005 | S50: 0.018 | T50: =$X$50*10% -> 0 | U50: =$X$50*20% -> 0 | V50: =$X$50*30% -> 0 | W50: =$X$50*40% -> 0 | X50: =$G$35*Q50 -> 0 | Y50: =$AC$50*10% -> 11.945 | Z50: =$AC$50*20% -> 23.89 | AA50: =$AC$50*30% -> 35.835 | AB50: =$AC$50*40% -> 47.78 | AC50: =$G$35*R50 -> 119.45 | AD50: =$AH$50*25% -> 107.505 | AE50: =$AH$50*25% -> 107.505 | AF50: =$AH$50*25% -> 107.505 | AG50: =$AH$50*25% -> 107.505 | AH50: =$G$35*S50 -> 430.02 | AI50: =ROUND(X50/$L36,0) -> 0 | AJ50: =ROUND(AC50/$L36,0) -> 61 | AK50: =ROUND(AH50/$L36,0) -> 220 | AL50: =ROUND(X50/$N$42,0) -> 0 | AM50: =ROUND(AC50/$N$42,0) -> 6 | AN50: =ROUND(AH50/$N$42,0) -> 22 | BE50: Italy | BF50: 37.75 | BG50: 113.25 | BH50: 377.5
B51: 4. | C51: French Hospitals | E51: https://etablissements.fhf.fr/annuaire/ | P51: Netherlands | Q51: 0 | R51: 0.01 | S51: 0.02 | T51: =0 -> 0 | U51: =0 -> 0 | V51: =0 -> 0 | W51: =0 -> 0 | X51: =Q51*G36 -> 0 | Y51: =$X$50*10% -> 0 | Z51: =$X$50*10% -> 0 | AA51: =$X$50*10% -> 0 | AB51: =AC51 -> 10.65 | AC51: =$G$36*R51 -> 10.65 | AD51: =$AH$51*25% -> 5.325 | AE51: =$AH$51*25% -> 5.325 | AF51: =$AH$51*25% -> 5.325 | AG51: =$AH$51*25% -> 5.325 | AH51: =$G$36*S51 -> 21.3 | AI51: =ROUND(X51/$L36,0) -> 0 | AL51: =ROUNDUP(X51/$N$42,0) -> 0 | AM51: =ROUNDUP(AC51/$N$42,0) -> 1 | AN51: =ROUND(AH51/$N$42,0) -> 1 | BE51: Germany | BF51: 0 | BG51: 238.9 | BH51: 477.8
B52: 5. | C52: Italian Hospitals | E52: https://www.statista.com/statistics/557042/hospitals-in-italy/ | P52: =C37 -> Country 1 | Q52: 0 | R52: 0.003 | S52: 0.012 | T52: 0 | U52: 0 | V52: 0 | W52: 0 | X52: =Q52*G37 -> 0 | Y52: =$AC52*T$1 -> 1.8 | Z52: =$AC52*U$1 -> 3.6 | AA52: =$AC52*V$1 -> 5.4 | AB52: =$AC52*W$1 -> 7.2 | AC52: =G37*R52 -> 18 | AD52: =$AH$52*25% -> 18 | AE52: =$AH$52*25% -> 18 | AF52: =$AH$52*25% -> 18 | AG52: =$AH$52*25% -> 18 | AH52: =G37*S52 -> 72 | AL52: =ROUNDUP(X52/$N$42,0) -> 0 | AM52: =ROUNDUP(AC52/$N$42,0) -> 1 | AN52: =ROUND(AH52/$N$42,0) -> 4
B53: 6. | C53: German Hospitals | E53: https://www.statista.com/statistics/578444/number-of-hospitals-germany/ | P53: =C38 -> Country 2 | Q53: 0 | T53: 0 | U53: 0 | V53: 0 | W53: 0 | X53: =Q53*G38 -> 0 | Y53: =$AC53*T$1 -> 0 | Z53: =$AC53*U$1 -> 0 | AA53: =$AC53*V$1 -> 0 | AB53: =$AC53*W$1 -> 0 | AC53: =G38*R53 -> 0 | AD53: =$AH$53*25% -> 0 | AE53: =$AH$53*25% -> 0 | AF53: =$AH$53*25% -> 0 | AG53: =$AH$53*25% -> 0 | AH53: =G38*S53 -> 0 | AL53: =ROUNDUP(X53/$N$42,0) -> 0 | AM53: =ROUNDUP(AC53/$N$42,0) -> 0 | AN53: =ROUND(AH53/$N$42,0) -> 0
B54: 7. | C54: ICU Beds | E54: Rhodes 2012 : https://link.springer.com/article/10.1007/s00134-012-2627-8 | P54: =C39 -> Country 3 | Q54: 0 | T54: 0 | U54: 0 | V54: 0 | W54: 0 | X54: =Q54*G39 -> 0 | Y54: =$AC54*T$1 -> 0 | Z54: =$AC54*U$1 -> 0 | AA54: =$AC54*V$1 -> 0 | AB54: =$AC54*W$1 -> 0 | AC54: =G39*R54 -> 0 | AD54: =$AH$54*25% -> 0 | AE54: =$AH$54*25% -> 0 | AF54: =$AH$54*25% -> 0 | AG54: =$AH$54*25% -> 0 | AH54: =G39*S54 -> 0 | AL54: =ROUNDUP(X54/$N$42,0) -> 0 | AM54: =ROUNDUP(AC54/$N$42,0) -> 0 | AN54: =ROUND(AH54/$N$42,0) -> 0
B55: 8. | C55: EN/PN prevalence | E55: KCE report : https://kce.fgov.be/en/organization-and-reimbursement-of-enteral-and-parenteral-nutrition-in-and-outside-the-hospital-in | P55: =C40 -> Country 4 | Q55: 0 | T55: 0 | U55: 0 | V55: 0 | W55: 0 | X55: =Q55*G40 -> 0 | Y55: =$AC55*T$1 -> 0 | Z55: =$AC55*U$1 -> 0 | AA55: =$AC55*V$1 -> 0 | AB55: =$AC55*W$1 -> 0 | AC55: =G40*R55 -> 0 | AD55: =$AH$55*25% -> 0 | AE55: =$AH$55*25% -> 0 | AF55: =$AH$55*25% -> 0 | AG55: =$AH$55*25% -> 0 | AH55: =G40*S55 -> 0 | AL55: =ROUNDUP(X55/$N$42,0) -> 0 | AM55: =ROUNDUP(AC55/$N$42,0) -> 0 | AN55: =ROUND(AH55/$N$42,0) -> 0
P56: Total | T56: =SUM(T47:T55) -> 0 | U56: =SUM(U47:U55) -> 0 | V56: =SUM(V47:V55) -> 36.425 | W56: =SUM(W47:W55) -> 36.425 | X56: =SUM(X47:X55) -> 72.85 | Y56: =SUM(Y47:Y55) -> 49.5525 | Z56: =SUM(Z47:Z55) -> 67.0675 | AA56: =SUM(AA47:AA55) -> 84.5825 | ... AH56: =SUM(AH47:AH55) -> 1154.17 | AK56: Total | AL56: =SUM(AL47:AL51) -> 4 | AM56: =SUM(AM47:AM51) -> 16 | AN56: =SUM(AN47:AN51) -> 54
B57: 9. | C57: Wards with manutrition | E57: https://pubmed.ncbi.nlm.nih.gov/16698132/ | AK57: Total installation | AL57: =MAX(AL16,AL56) -> 5 | AM57: =MAX(AM16,AM56)-AL57 -> 17 | AN57: =MAX(AN16,AN56)-AM57-AL57 -> 37 | BF57: Devices - Y1 | BG57: Devices - Y2 | BH57: Devices - Y3
P58: Feedim EN devices | T58: Y1 | X58: Total - Y1 | Y58: Y2 | AC58: Total - Y2 | AD58: Y3 | AH58: Total - Y3 | BE58: Belgium | BF58: 17.55 | BG58: 35.1 | BH58: 87.75
T59: Q1 | U59: Q2 | V59: Q3 | W59: Q4 | X59: Devices - Y1 | Y59: Q1 | Z59: Q2 | AA59: Q3 | AB59: Q4 | AC59: Devices - Y2 | AD59: Q1 | AE59: Q2 | AF59: Q3 | AG59: Q4 | AH59: Devices - Y3 | BE59: France | BF59: 0 | BG59: 37.7 | BH59: 113.1
C60: Business Model - Hospital | P60: Belgium | T60: =$X$60*0% -> 0 | U60: =$X$60*0% -> 0 | V60: =$X$60*50% -> 8.775 | W60: =$X$60*50% -> 8.775 | X60: =X47*$F$27 -> 17.55 | Y60: =$AC$60*25% -> 6.58125 | Z60: =$AC$60*25% -> 6.58125 | AA60: =$AC$60*25% -> 6.58125 | AB60: =$AC$60*25% -> 6.58125 | AC60: =AC47*$F$27 -> 26.325 | AD60: =$AH$60*25% -> 17.55 | AE60: =$AH$60*25% -> 17.55 | AF60: =$AH$60*25% -> 17.55 | AG60: =$AH$60*25% -> 17.55 | AH60: =AH47*$F$27 -> 70.2 | BE60: Italy | BF60: 18.875 | BG60: 56.625 | BH60: 188.75
P61: France | T61: =$X$48*10% -> 0 | U61: =$X$48*20% -> 0 | V61: =$X$48*30% -> 0 | W61: =$X$48*40% -> 0 | X61: =X48*$F$27 -> 0 | Y61: =$AC$61*10% -> 1.885 | Z61: =$AC$61*20% -> 3.77 | AA61: =$AC$61*30% -> 5.655 | AB61: =$AC$61*40% -> 7.54 | AC61: =AC48*$F$27 -> 18.85 | AD61: =$AH$61*25% -> 28.275 | AE61: =$AH$61*25% -> 28.275 | AF61: =$AH$61*25% -> 28.275 | AG61: =$AH$61*25% -> 28.275 | AH61: =AH48*$F$27 -> 113.1 | BE61: Germany | BF61: 0 | BG61: 119.45 | BH61: 238.9
C62: Annual Software Licences per bed | F62: Feedim PN available EOY1 | P62: Italy | T62: =$X$49*0% -> 0 | U62: =$X$49*0% -> 0 | V62: =X62*50% -> 9.4375 | W62: =Y62*50% -> 4.71875 | X62: =X49*$F$27 -> 18.875 | Y62: =$AC$62*25% -> 9.4375 | Z62: =$AC$62*25% -> 9.4375 | AA62: =$AC$62*25% -> 9.4375 | AB62: =$AC$62*25% -> 9.4375 | AC62: =AC49*$F$27 -> 37.75 | AD62: =$AH$62*25% -> 33.03125 | AE62: =$AH$62*25% -> 33.03125 | AF62: =$AH$62*25% -> 33.03125 | AG62: =$AH$62*25% -> 33.03125 | AH62: =AH49*$F$27 -> 132.125
C63: Volume-based pricing | F63: All setups during Y1 and Y2, Y3 with distributor | P63: Germany | T63: =$X$50*10% -> 0 | U63: =$X$50*20% -> 0 | V63: =$X$50*30% -> 0 | W63: =$X$51*40% -> 0 | X63: =X50*$F$27 -> 0 | Y63: =$AC$63*10% -> 5.9725 | Z63: =$AC$63*20% -> 11.945 | AA63: =$AC$63*30% -> 17.9175 | AB63: =$AC$63*40% -> 23.89 | AC63: =AC50*$F$27 -> 59.725 | AD63: =$AH$63*25% -> 53.7525 | AE63: =$AH$63*25% -> 53.7525 | AF63: =$AH$63*25% -> 53.7525 | AG63: =$AH$63*25% -> 53.7525 | AH63: =AH50*$F$27 -> 215.01 | BF63: Devices - Y1 | BG63: Devices - Y2 | BH63: Devices - Y3
C64: Distributor channel - All beds are sold to distributor | P64: Netherlands | T64: =$X51*10% -> 0 | U64: =$X51*20% -> 0 | V64: =$X51*30% -> 0 | W64: =$X51*40% -> 0 | X64: =X51*$F$27 -> 0 | Y64: =$AC64*10% -> 0.5325 | Z64: =$AC64*20% -> 1.065 | AA64: =$AC64*30% -> 1.5975 | AB64: =$AC64*40% -> 2.13 | AC64: =AC51*$F$27 -> 5.325 | AD64: =$AH64*25% -> 2.6625 | AE64: =$AH64*25% -> 2.6625 | AF64: =$AH64*25% -> 2.6625 | AG64: =$AH64*25% -> 2.6625 | AH64: =AH51*$F$27 -> 10.65
C65: Feedim direct purchase | P65: =C37 -> Country 1 | T65: =$X52*10% -> 0 | U65: =$X52*20% -> 0 | V65: =$X$51*30% -> 0 | W65: =$X52*40% -> 0 | X65: =X52*$F$27 -> 0 | Y65: =$AC65*10% -> 0.9 | Z65: =$AC65*20% -> 1.8 | AA65: =$AC65*30% -> 2.7 | AB65: =$AC65*40% -> 3.6 | AC65: =AC52*$F$27 -> 9 | AD65: =$AH65*25% -> 9 | AE65: =$AH65*25% -> 9 | AF65: =$AH65*25% -> 9 | AG65: =$AH65*25% -> 9 | AH65: =AH52*$F$27 -> 36
P66: =C38 -> Country 2 | T66: =$X53*10% -> 0 | U66: =$X53*20% -> 0 | V66: =$X$51*30% -> 0 | W66: =$X53*40% -> 0 | X66: =X53*$F$27 -> 0 | Y66: =$AC66*10% -> 0 | Z66: =$AC66*20% -> 0 | AA66: =$AC66*30% -> 0 | AB66: =$AC66*40% -> 0 | AC66: =AC53*$F$27 -> 0 | AD66: =$AH66*25% -> 0 | AE66: =$AH66*25% -> 0 | AF66: =$AH66*25% -> 0 | AG66: =$AH66*25% -> 0 | AH66: =AH53*$F$27 -> 0
B67: Beds pricing | P67: =C39 -> Country 3 | T67: =$X54*10% -> 0 | U67: =$X54*20% -> 0 | V67: =$X$51*30% -> 0 | W67: =$X54*40% -> 0 | X67: =X54*$F$27 -> 0 | Y67: =$AC67*10% -> 0 | Z67: =$AC67*20% -> 0 | AA67: =$AC67*30% -> 0 | AB67: =$AC67*40% -> 0 | AC67: =AC54*$F$27 -> 0 | AD67: =$AH67*25% -> 0 | AE67: =$AH67*25% -> 0 | AF67: =$AH67*25% -> 0 | AG67: =$AH67*25% -> 0 | AH67: =AH54*$F$27 -> 0
C68: Minimum Beds | D68: 10 | E68: 40 | F68: 100 | G68: 200 | H68: 500 | I68: 1000 | J68: ASP | P68: =C40 -> Country 4 | T68: =$X55*10% -> 0 | U68: =$X55*20% -> 0 | V68: =$X$51*30% -> 0 | W68: =$X55*40% -> 0 | X68: =X55*$F$27 -> 0 | Y68: =$AC68*10% -> 0 | Z68: =$AC68*20% -> 0 | AA68: =$AC68*30% -> 0 | AB68: =$AC68*40% -> 0 | AC68: =AC55*$F$27 -> 0 | AD68: =$AH68*25% -> 0 | AE68: =$AH68*25% -> 0 | AF68: =$AH68*25% -> 0 | AG68: =$AH68*25% -> 0 | AH68: =AH55*$F$27 -> 0
C69: Nutrow software (EUR) | D69: 400 | E69: 250 | F69: =225 -> 225 | G69: =87%*G72 -> 196.533 | H69: =87%*H72 -> 176.8797 | I69: =87%*I72 -> 159.19173 | P69: Total | T69: =SUM(T60:T68) -> 0 | U69: =SUM(U60:U68) -> 0 | V69: =SUM(V60:V68) -> 18.2125 | W69: =SUM(W60:W68) -> 13.49375 | X69: =SUM(X60:X68) -> 36.425 | Y69: =SUM(Y60:Y68) -> 25.30875 | Z69: =SUM(Z60:Z68) -> 34.59875 | AA69: =SUM(AA60:AA68) -> 43.88875 | ... AH69: =SUM(AH60:AH68) -> 577.085 | BE69: Belgium | BF69: 0 | BG69: 35.1 | BH69: 87.75
C71: Feedim software (EUR) | D71: =70 -> 70 | E71: 35 | F71: 26 | G71: =G72*13% -> 29.367 | H71: =H72*13% -> 26.4303 | I71: =I72*13% -> 23.78727 | P71: Feedim PN devices | T71: Y1 | X71: Total - Y1 | Y71: Y2 | AC71: Total - Y2 | AD71: Y3 | AH71: Total - Y3 | BE71: France | BF71: 0 | BG71: 37.7 | BH71: 113.1
C72: Total transfer price (EUR) | D72: =SUM(D69:D71) -> 470 | E72: =SUM(E69:E71) -> 285 | F72: =SUM(F69:F71) -> 251 | G72: =F72*90% -> 225.9 | H72: =G72*90% -> 203.31 | I72: =H72*90% -> 182.979 | T72: Q1 | U72: Q2 | V72: Q3 | W72: Q4 | X72: Devices - Y1 | Y72: Q1 | Z72: Q2 | AA72: Q3 | AB72: Q4 | AC72: Devices - Y2 | AD72: Q1 | AE72: Q2 | AF72: Q3 | AG72: Q4 | AH72: Devices - Y3 | BE72: Italy | BF72: 0 | BG72: 56.625 | BH72: 188.75
C73: Total | D73: =D72*D68 -> 4700 | E73: =E72*E68 -> 11400 | F73: =F72*F68 -> 25100 | G73: =G72*G68 -> 45180 | H73: =H72*H68 -> 101655 | I73: =I72*I68 -> 182979 | P73: Belgium | T73: 0 | U73: 0 | V73: 0 | W73: 0 | X73: 0 | Y73: =$AC$73*25% -> 6.58125 | Z73: =$AC$73*25% -> 6.58125 | AA73: =$AC$73*25% -> 6.58125 | AB73: =$AC$73*25% -> 6.58125 | AC73: =AC47*$F$27 -> 26.325 | AD73: =$AH$73*25% -> 17.55 | AE73: =$AH$73*25% -> 17.55 | AF73: =$AH$73*25% -> 17.55 | AG73: =$AH$73*25% -> 17.55 | AH73: =AH47*$F$27 -> 70.2 | BE73: Germany | BF73: 0 | BG73: 119.45 | BH73: 238.9
C74: Total + 30% distributor margin | D74: =D73*1.3 -> 6110 | E74: =E73*1.3 -> 14820 | F74: =F73*1.3 -> 32630 | G74: =G73*1.3 -> 58734 | H74: =H73*1.3 -> 132151.5 | I74: =I73*1.3 -> 237872.7 | P74: France | T74: 0 | U74: 0 | V74: 0 | W74: 0 | X74: =X50*$F$28 -> 0 | Y74: =$AC$74*10% -> 1.885 | Z74: =$AC$74*20% -> 3.77 | AA74: =$AC$74*30% -> 5.655 | AB74: =$AC$74*40% -> 7.54 | AC74: =AC48*$F$27 -> 18.85 | AD74: =$AH$74*25% -> 28.275 | AE74: =$AH$74*25% -> 28.275 | AF74: =$AH$74*25% -> 28.275 | AG74: =$AH$74*25% -> 28.275 | AH74: =AH48*$F$27 -> 113.1
P75: Italy | T75: 0 | U75: 0 | V75: 0 | W75: 0 | X75: 0 | Y75: =$AC$75*25% -> 9.4375 | Z75: =$AC$75*25% -> 9.4375 | AA75: =$AC$75*25% -> 9.4375 | AB75: =$AC$75*25% -> 9.4375 | AC75: =AC49*$F$27 -> 37.75 | AD75: =$AH$75*25% -> 33.03125 | AE75: =$AH$75*25% -> 33.03125 | AF75: =$AH$75*25% -> 33.03125 | AG75: =$AH$75*25% -> 33.03125 | AH75: =AH49*$F$27 -> 132.125
P76: Germany | T76: 0 | U76: 0 | V76: 0 | W76: 0 | X76: 0 | Y76: =$AC$76*10% -> 5.9725 | Z76: =$AC$76*20% -> 11.945 | AA76: =$AC$76*30% -> 17.9175 | AB76: =$AC$76*40% -> 23.89 | AC76: =AC50*$F$27 -> 59.725 | AD76: =$AH$76*25% -> 53.7525 | AE76: =$AH$63*25% -> 53.7525 | AF76: =$AH$63*25% -> 53.7525 | AG76: =$AH$63*25% -> 53.7525 | AH76: =AH50*$F$27 -> 215.01
P77: Netherlands | T77: 0 | U77: 0 | V77: 0 | W77: 0 | X77: 0 | Y77: =$AC77*10% -> 0.5325 | Z77: =$AC77*20% -> 1.065 | AA77: =$AC77*30% -> 1.5975 | AB77: =$AC77*40% -> 2.13 | AC77: =AC51*$F$27 -> 5.325 | AD77: =$AH77*25% -> 2.6625 | AE77: =$AH77*25% -> 2.6625 | AF77: =$AH77*25% -> 2.6625 | AG77: =$AH77*25% -> 2.6625 | AH77: =AH51*$F$27 -> 10.65
P78: =C37 -> Country 1 | T78: 0 | U78: 0 | V78: 0 | W78: 0 | X78: 0 | Y78: =$AC78*10% -> 0.9 | Z78: =$AC78*20% -> 1.8 | AA78: =$AC78*30% -> 2.7 | AB78: =$AC78*40% -> 3.6 | AC78: =AC52*$F$27 -> 9 | AD78: =$AH78*25% -> 9 | AE78: =$AH78*25% -> 9 | AF78: =$AH78*25% -> 9 | AG78: =$AH78*25% -> 9 | AH78: =AH52*$F$27 -> 36
P79: =C38 -> Country 2 | T79: 0 | U79: 0 | V79: 0 | W79: 0 | X79: 0 | Y79: =$AC79*10% -> 0 | Z79: =$AC79*20% -> 0 | AA79: =$AC79*30% -> 0 | AB79: =$AC79*40% -> 0 | AC79: =AC53*$F$27 -> 0 | AD79: =$AH79*25% -> 0 | AE79: =$AH79*25% -> 0 | AF79: =$AH79*25% -> 0 | AG79: =$AH79*25% -> 0 | AH79: =AH53*$F$27 -> 0
B80: ICU pricing | P80: =C39 -> Country 3 | T80: 0 | U80: 0 | V80: 0 | W80: 0 | X80: 0 | Y80: =$AC80*10% -> 0 | Z80: =$AC80*20% -> 0 | AA80: =$AC80*30% -> 0 | AB80: =$AC80*40% -> 0 | AC80: =AC54*$F$27 -> 0 | AD80: =$AH80*25% -> 0 | AE80: =$AH80*25% -> 0 | AF80: =$AH80*25% -> 0 | AG80: =$AH80*25% -> 0 | AH80: =AH54*$F$27 -> 0
C81: Minimum Beds | D81: 10 | E81: 50 | F81: 100 | G81: ASP | P81: =C40 -> Country 4 | T81: 0 | U81: 0 | V81: 0 | W81: 0 | X81: 0 | Y81: =$AC81*10% -> 0 | Z81: =$AC81*20% -> 0 | AA81: =$AC81*30% -> 0 | AB81: =$AC81*40% -> 0 | AC81: =AC55*$F$27 -> 0 | AD81: =$AH81*25% -> 0 | AE81: =$AH81*25% -> 0 | AF81: =$AH81*25% -> 0 | AG81: =$AH81*25% -> 0 | AH81: =AH55*$F$27 -> 0
C82: Total transfer price (EUR) | D82: 700 | E82: =D82*80% -> 560 | F82: =E82*80% -> 448 | P82: Total | T82: =SUM(T73:T81) -> 0 | U82: =SUM(U73:U81) -> 0 | V82: =SUM(V73:V81) -> 0 | W82: =SUM(W73:W81) -> 0 | X82: =SUM(X73:X81) -> 0 | Y82: =SUM(Y73:Y81) -> 25.30875 | Z82: =SUM(Z73:Z81) -> 34.59875 | AA82: =SUM(AA73:AA81) -> 43.88875 | ... AH82: =SUM(AH73:AH81) -> 577.085
B84: Feedim pricing | P84: Total Feedim Hospital | T84: =T82+T69+T43+T29 -> 10.214197 | U84: =U82+U69+U43+U29 -> 20.428394 | V84: =V82+V69+V43+V29 -> 48.855091 | W84: =W82+W69+W43+W29 -> 54.350538 | X84: =X82+X69+X43+X29 -> 138.56697 | Y84: =Y82+Y69+Y43+Y29 -> 159.00476 | Z84: =Z82+Z69+Z43+Z29 -> 223.5699 | AA84: =AA82+AA69+AA43+AA29 -> 288.13504 | ... AH84: =AH82+AH69+AH43+AH29 -> 3050.2953
C85: Minimum quantities | D85: 100 | E85: 200 | F85: 500
C86: Feedim Wi-Fi device (EUR) | D86: 179 | E86: 169 | F86: 159 | P86: Expected Revenues - Hospital
Q87: General beds - Expected Revenues
T88: Y1 | X88: Total - Y1 | Y88: Y2 | AC88: Total - Y2 | AD88: Y3 | AH88: Total - Y3
B89: Services | E89: Min | F89: Max | G89: ASP | R89: General Beds | T89: Q1 | U89: Q2 | V89: Q3 | W89: Q4 | X89: Y1 | Y89: Q1 | Z89: Q2 | AA89: Q3 | AB89: Q4 | AC89: Y2 | AD89: Q1 | AE89: Q2 | AF89: Q3 | AG89: Q4 | AH89: Y3
C90: Setup | E90: 15000 | F90: 40000 | G90: =AVERAGE(E90:F90) -> 27500 | S90: Belgium | T90: =$X$90*10% -> 9909.6908 | U90: =$X$90*20% -> 19819.382 | V90: =$X$90*30% -> 29729.073 | W90: =$X$90*40% -> 39638.763 | X90: =X7*IF(X7>$I$68,$I$72,IF(X7>$H$68,$H$72,IF(X7>$G$68,$G$72,$F$72))) -> 99096.908 | Y90: =$AC90*25% -> 44593.609 | Z90: =$AC90*25% -> 44593.609 | AA90: =$AC90*25% -> 44593.609 | AB90: =$AC90*25% -> 44593.609 | AC90: =AC7*IF(AC7>$I$68,$I$72,IF(AC7>$H$68,$H$72,IF(AC7>$G$68,$G$72,$F$72))) -> 178374.44 | AD90: =$AH90*25% -> 80268.496 | AE90: =$AH90*25% -> 80268.496 | AF90: =$AH90*25% -> 80268.496 | AG90: =$AH90*25% -> 80268.496 | AH90: =AH7*IF(AH7>$I$68,$I$72,IF(AH7>$H$68,$H$72,IF(AH7>$G$68,$G$72,$F$72))) -> 321073.98
S91: France | T91: =X91*10% -> 0 | U91: =$X$91*20% -> 0 | V91: =$X$91*30% -> 0 | W91: =$X$91*40% -> 0 | X91: =X8*IF(X8>$I$68,$I$72,IF(X8>$H$68,$H$72,IF(X8>$G$68,$G$72,$F$72))) -> 0 | Y91: =$AC91*10% -> 13958.629 | Z91: =$AC91*20% -> 27917.259 | AA91: =$AC91*30% -> 41875.888 | AB91: =$AC91*40% -> 55834.517 | AC91: =AC8*IF(AC8>$I$68,$I$72,IF(AC8>$H$68,$H$72,IF(AC8>$G$68,$G$72,$F$72))) -> 139586.29 | AD91: =$AH91*25% -> 113064.9 | AE91: =$AH91*25% -> 113064.9 | AF91: =$AH91*25% -> 113064.9 | AG91: =$AH91*25% -> 113064.9 | AH91: =AH8*IF(AH8>$I$68,$I$72,IF(AH8>$H$68,$H$72,IF(AH8>$G$68,$G$72,$F$72))) -> 452259.59
S92: Italy | T92: =X92*10% -> 11847.762 | U92: =X92*20% -> 23695.524 | V92: =X92*30% -> 35543.286 | W92: =X92*40% -> 47391.049 | X92: =X9*IF(X9>$I$68,$I$72,IF(X9>$H$68,$H$72,IF(X9>$G$68,$G$72,$F$72))) -> 118477.62 | Y92: =$AC92*25% -> 74048.514 | Z92: =$AC92*25% -> 74048.514 | AA92: =$AC92*25% -> 74048.514 | AB92: =$AC92*25% -> 74048.514 | AC92: =AC9*IF(AC9>$I$68,$I$72,IF(AC9>$H$68,$H$72,IF(AC9>$G$68,$G$72,$F$72))) -> 296194.05 | AD92: =$AH92*25% -> 148097.03 | AE92: =$AH92*25% -> 148097.03 | AF92: =$AH92*25% -> 148097.03 | AG92: =$AH92*25% -> 148097.03 | AH92: =AH9*IF(AH9>$I$68,$I$72,IF(AH9>$H$68,$H$72,IF(AH9>$G$68,$G$72,$F$72))) -> 592388.11
S93: Germany | T93: =X93*10% -> 0 | U93: =X93*20% -> 0 | V93: =X93*30% -> 0 | W93: =X93*40% -> 0 | X93: =X10*IF(X10>$I$68,$I$72,IF(X10>$H$68,$H$72,IF(X10>$G$68,$G$72,$F$72))) -> 0 | Y93: =$AC93*10% -> 20415.452 | Z93: =$AC93*20% -> 40830.904 | AA93: =$AC93*30% -> 61246.356 | AB93: =$AC93*40% -> 81661.808 | AC93: =AC10*IF(AC10>$I$68,$I$72,IF(AC10>$H$68,$H$72,IF(AC10>$G$68,$G$72,$F$72))) -> 204154.52 | AD93: =$AH93*25% -> 183739.07 | AE93: =$AH93*25% -> 183739.07 | AF93: =$AH93*25% -> 183739.07 | AG93: =$AH93*25% -> 183739.07 | AH93: =AH10*IF(AH10>$I$68,$I$72,IF(AH10>$H$68,$H$72,IF(AH10>$G$68,$G$72,$F$72))) -> 734956.27 | AJ93: Expected revenues per products/services
S94: Netherlands | T94: 0 | U94: 0 | V94: 0 | W94: 0 | X94: =X11*IF(X11>$I$68,$I$72,IF(X11>$H$68,$H$72,IF(X11>$G$68,$G$72,$F$72))) -> 0 | Y94: =$AC94*10% -> 8826.9747 | Z94: =$AC94*20% -> 17653.949 | AA94: =$AC94*30% -> 26480.924 | AB94: =$AC94*40% -> 35307.899 | AC94: =AC11*IF(AC11>$I$68,$I$72,IF(AC11>$H$68,$H$72,IF(AC11>$G$68,$G$72,$F$72))) -> 88269.747 | AD94: =$AH94*25% -> 39721.386 | AE94: =$AH94*25% -> 39721.386 | AF94: =$AH94*25% -> 39721.386 | AG94: =$AH94*25% -> 39721.386 | AH94: =AH11*IF(AH11>$I$68,$I$72,IF(AH11>$H$68,$H$72,IF(AH11>$G$68,$G$72,$F$72))) -> 158885.55 | AK94: Y1 | AL94: Y2 | AM94: Y3
B95: Executive Summary | S95: Country 1 | T95: 0 | U95: 0 | V95: 0 | W95: 0 | X95: =X12*IF(X12>$I$68,$I$72,IF(X12>$H$68,$H$72,IF(X12>$G$68,$G$72,$F$72))) -> 0 | Y95: =$AC95*10% -> 4601.583 | Z95: =$AC95*20% -> 9203.166 | AA95: =$AC95*30% -> 13804.749 | AB95: =$AC95*40% -> 18406.332 | AC95: =AC12*IF(AC12>$I$68,$I$72,IF(AC12>$H$68,$H$72,IF(AC12>$G$68,$G$72,$F$72))) -> 46015.83 | AD95: =$AH95*25% -> 41414.247 | AE95: =$AH95*25% -> 41414.247 | AF95: =$AH95*25% -> 41414.247 | AG95: =$AH95*25% -> 41414.247 | AH95: =AH12*IF(AH12>$I$68,$I$72,IF(AH12>$H$68,$H$72,IF(AH12>$G$68,$G$72,$F$72))) -> 165656.99 | AJ95: Software | AK95: =X99+X125 -> 268569.53 | AL95: =SUM(AC99)+SUM(AC125) -> 1124317.5 | AM95: =SUM(AH99)+SUM(AH125) -> 2955720.2
S96: Country 2 | T96: 0 | U96: 0 | V96: 0 | W96: 0 | X96: =X13*IF(X13>$I$68,$I$72,IF(X13>$H$68,$H$72,IF(X13>$G$68,$G$72,$F$72))) -> 0 | Y96: =$AC96*10% -> 0 | Z96: =$AC96*20% -> 0 | AA96: =$AC96*30% -> 0 | AB96: =$AC96*40% -> 0 | AC96: =AC13*IF(AC13>$I$68,$I$72,IF(AC13>$H$68,$H$72,IF(AC13>$G$68,$G$72,$F$72))) -> 0 | AD96: =$AH96*25% -> 0 | AE96: =$AH96*25% -> 0 | AF96: =$AH96*25% -> 0 | AG96: =$AH96*25% -> 0 | AH96: =AH13*IF(AH13>$I$68,$I$72,IF(AH13>$H$68,$H$72,IF(AH13>$G$68,$G$72,$F$72))) -> 0 | AJ96: Devices | AK96: =X111+X137 -> 24803.488 | AL96: =AC111+AC137 -> 180843.21 | AM96: =AH111+AH137 -> 514327.43
B97: Value creation | S97: Country 3 | T97: 0 | U97: 0 | V97: 0 | W97: 0 | X97: =X14*IF(X14>$I$68,$I$72,IF(X14>$H$68,$H$72,IF(X14>$G$68,$G$72,$F$72))) -> 0 | Y97: =$AC97*10% -> 0 | Z97: =$AC97*20% -> 0 | AA97: =$AC97*30% -> 0 | AB97: =$AC97*40% -> 0 | AC97: =AC14*IF(AC14>$I$68,$I$72,IF(AC14>$H$68,$H$72,IF(AC14>$G$68,$G$72,$F$72))) -> 0 | AD97: =$AH97*25% -> 0 | AE97: =$AH97*25% -> 0 | AF97: =$AH97*25% -> 0 | AG97: =$AH97*25% -> 0 | AH97: =AH14*IF(AH14>$I$68,$I$72,IF(AH14>$H$68,$H$72,IF(AH14>$G$68,$G$72,$F$72))) -> 0 | AJ97: Operations | AK97: =X152 -> 137500 | AL97: =AC152 -> 495000 | AM97: =AH152 -> 0
B98: Improving individualized nutritionnal support to all hospital patients at risk of malnutrition | S98: Country 4 | T98: 0 | U98: 0 | V98: 0 | W98: 0 | X98: =X15*IF(X15>$I$68,$I$72,IF(X15>$H$68,$H$72,IF(X15>$G$68,$G$72,$F$72))) -> 0 | Y98: =$AC98*10% -> 0 | Z98: =$AC98*20% -> 0 | AA98: =$AC98*30% -> 0 | AB98: =$AC98*40% -> 0 | AC98: =AC15*IF(AC15>$I$68,$I$72,IF(AC15>$H$68,$H$72,IF(AC15>$G$68,$G$72,$F$72))) -> 0 | AD98: =$AH98*25% -> 0 | AE98: =$AH98*25% -> 0 | AF98: =$AH98*25% -> 0 | AG98: =$AH98*25% -> 0 | AH98: =AH15*IF(AH15>$I$68,$I$72,IF(AH15>$H$68,$H$72,IF(AH15>$G$68,$G$72,$F$72))) -> 0 | AJ98: Total Hospital Revenues | AK98: =SUM(AK95:AK97) -> 430873.02 | AL98: =SUM(AL95:AL97) -> 1800160.7 | AM98: =SUM(AM95:AM97) -> 3470047.7
B99: Complete therapy journey in the hospital and smooth transition outside of hospital | S99: Total | T99: =SUM(T90:T98) -> 21757.453 | U99: =SUM(U90:U98) -> 43514.906 | V99: =SUM(V90:V98) -> 65272.359 | W99: =SUM(W90:W98) -> 87029.812 | X99: =SUM(X90:X98) -> 217574.53 | Y99: =SUM(Y90:Y98) -> 166444.76 | Z99: =SUM(Z90:Z98) -> 214247.4 | AA99: =SUM(AA90:AA98) -> 262050.04 | ... AH99: =SUM(AH90:AH98) -> 2425220.5
B100: Positive ROI | R100: Feedim devices | T100: Y1 | X100: Total - Y1 | Y100: Y2 | AC100: Total - Y2 | AD100: Y3 | AH100: Total - Y3
T101: Q1 | U101: Q2 | V101: Q3 | W101: Q4 | X101: Y1 | Y101: Q1 | Z101: Q2 | AA101: Q3 | AB101: Q4 | AC101: Y2 | AD101: Q1 | AE101: Q2 | AF101: Q3 | AG101: Q4 | AH101: Y3
B102: Commercial strategy & Business Model | S102: Belgium | T102: =$X$102*10% -> 785.23004 | U102: =$X$102*20% -> 1570.4601 | V102: =$X$102*30% -> 2355.6901 | W102: =$X$102*40% -> 3140.9202 | X102: =IF(SUM(X20,X34)>$F$85,$F$86,IF(SUM(X20,X34)>$E$85,$E$86,$D$86))*SUM(X20,X34) -> 7852.3004 | Y102: =$AC102*25% -> 5692.9178 | Z102: =$AC102*25% -> 5692.9178 | AA102: =$AC102*25% -> 5692.9178 | AB102: =$AC102*25% -> 5692.9178 | AC102: =IF(SUM(AC20,AC34)>$F$85,$F$86,IF(SUM(AC20,AC34)>$E$85,$E$86,$D$86))*SUM(AC20,AC34) -> 22771.671 | AD102: =$AH102*25% -> 10749.755 | AE102: =$AH102*25% -> 10749.755 | AF102: =$AH102*25% -> 10749.755 | AG102: =$AH102*25% -> 10749.755 | AH102: =IF(SUM(AH20,AH34)>$F$85,$F$86,IF(SUM(AH20,AH34)>$E$85,$E$86,$D$86))*SUM(AH20,AH34) -> 42999.022
B103: Distributor channel in all countries except Belgium, prices are transfer prices | S103: France | T103: =X103*10% -> 0 | U103: =X103*20% -> 0 | V103: =X103*30% -> 0 | W103: =X103*40% -> 0 | X103: =IF(SUM(X21,X35)>$F$85,$F$86,IF(SUM(X21,X35)>$E$85,$E$86,$D$86))*SUM(X21,X35) -> 0 | Y103: =$AC103*10% -> 1781.9892 | Z103: =$AC103*20% -> 3563.9784 | AA103: =$AC103*30% -> 5345.9676 | AB103: =$AC103*40% -> 7127.9568 | AC103: =IF(SUM(AC21,AC35)>$F$85,$F$86,IF(SUM(AC21,AC35)>$E$85,$E$86,$D$86))*SUM(AC21,AC35) -> 17819.892 | AD103: =$AH103*25% -> 15141.93 | AE103: =$AH103*25% -> 15141.93 | AF103: =$AH103*25% -> 15141.93 | AG103: =$AH103*25% -> 15141.93 | AH103: =IF(SUM(AH21,AH35)>$F$85,$F$86,IF(SUM(AH21,AH35)>$E$85,$E$86,$D$86))*SUM(AH21,AH35) -> 60567.722
B104: Annual Software Licences per bed | S104: Italy | T104: =X104*10% -> 1043.1112 | U104: =X104*20% -> 2086.2224 | V104: =X104*30% -> 3129.3337 | W104: =X104*40% -> 4172.4449 | X104: =IF(SUM(X22,X36)>$F$85,$F$86,IF(SUM(X22,X36)>$E$85,$E$86,$D$86))*SUM(X22,X36) -> 10431.112 | Y104: =$AC104*25% -> 9916.76 | Z104: =$AC104*25% -> 9916.76 | AA104: =$AC104*25% -> 9916.76 | AB104: =$AC104*25% -> 9916.76 | AC104: =IF(SUM(AC22,AC36)>$F$85,$F$86,IF(SUM(AC22,AC36)>$E$85,$E$86,$D$86))*SUM(AC22,AC36) -> 39667.04 | AD104: =$AH104*25% -> 19833.52 | AE104: =$AH104*25% -> 19833.52 | AF104: =$AH104*25% -> 19833.52 | AG104: =$AH104*25% -> 19833.52 | AH104: =IF(SUM(AH22,AH36)>$F$85,$F$86,IF(SUM(AH22,AH36)>$E$85,$E$86,$D$86))*SUM(AH22,AH36) -> 79334.08
...

Sheet Homecare
BB2: Total Y1 | BC2: Total Y2 | BD2: Total Y3
Z3: Business Model 1 | BA3: Belgium | BB3: =AH23 -> 4769.9364 | BC3: =AM23 -> 23849.682 | BD3: =AR23 -> 47699.364
B4: Total Adressable Market - Homecare | O4: Business Model - Homecare | Z4: Market Penetration - Home Enteral Nutrition | BA4: France | BB4: =AH24 -> 52922.225 | BC4: =AM24 -> 264611.12 | BD4: =AR24 -> 643648.68
B5: Unmet clinical needs: | O5: Business Model 1 | BA5: Italy | BB5: =AH25 -> 120181.68 | BC5: =AM25 -> 450681.28 | BD5: =AR25 -> 609028.76
C6: Telemonitoring of HEN patients | Z6: HEN | BA6: Germany | BB6: =AH26 -> 0 | BC6: =AM26 -> 154413.33 | BD6: =AR26 -> 463240
C7: Telemonitoring of HPN patients | O7: Follow-up HEN Days Purchased | P7: 100000 | Q7: 250000 | R7: 500000 | U7: Follow-up HPN Days Purchased | V7: 25000 | W7: 100000 | X7: 200000 | AD7: Days Sold - Y1 | AI7: Days - Y2 | AN7: Days - Y3
O8: Cost per day - Nutrow (EUR) | P8: 0.22 | Q8: 0.2 | R8: 0.19 | U8: Cost per day - Nutrow | V8: =P8*5 -> 1.1 | W8: =Q8*5 -> 1 | X8: =R8*5 -> 0.95 | AA8: Y1 | AB8: Y2 | AC8: Y3 | AD8: Q1 | AE8: Q2 | AF8: Q3 | AG8: Q4 | AH8: Total Y1 | AI8: Q1 | AJ8: Q2 | AK8: Q3 | AL8: Q4 | AM8: Total Y2 | AN8: Q1 | AO8: Q2 | AP8: Q3 | AQ8: Q4 | AR8: Total Y3
C9: Geographic criteria | O9: Cost per day - Feedim | P9: 0.15 | Q9: 0.14 | R9: 0.11 | U9: Cost per day - Feedim | V9: =P9*5 -> 0.75 | W9: =Q9*5 -> 0.7 | X9: =R9*5 -> 0.55 | Z9: Belgium | AA9: 0.02 | AB9: 0.1 | AC9: 0.2 | AD9: =0%*AH9 -> 0 | AE9: =20%*AH9 -> 2578.344 | AF9: =30%*AH9 -> 3867.516 | AG9: =50%*AH9 -> 6445.86 | AH9: =AA9*H20 -> 12891.72 | AI9: =25%*$AM9 -> 16114.65 | AJ9: =25%*$AM$9 -> 16114.65 | AK9: =25%*$AM$9 -> 16114.65 | AL9: =25%*$AM$9 -> 16114.65 | AM9: =AB9*H20 -> 64458.6 | AN9: =25%*$AR$9 -> 32229.3 | AO9: =25%*$AR$9 -> 32229.3 | AP9: =25%*$AR$9 -> 32229.3 | AQ9: =25%*$AR$9 -> 32229.3 | AR9: =AC9*H20 -> 128917.2
C10: Belgium and Top European western countries | O10: Total cost per day (EUR) | P10: =SUM(P8:P9) -> 0.37 | Q10: =SUM(Q8:Q9) -> 0.34 | R10: =SUM(R8:R9) -> 0.3 | U10: Total cost per day (EUR) | V10: =SUM(V8:V9) -> 1.85 | W10: =SUM(W8:W9) -> 1.7 | X10: =SUM(X8:X9) -> 1.5 | Z10: France | AA10: 0.01 | AB10: 0.05 | AC10: 0.15 | AD10: =0%*AH10 -> 0 | AE10: =20%*AH10 -> 28606.608 | AF10: =30%*AH10 -> 42909.912 | AG10: =50%*AH10 -> 71516.52 | AH10: =AA10*H21 -> 143033.04 | AI10: =25%*$AM$10 -> 178791.3 | AJ10: =25%*$AM$10 -> 178791.3 | AK10: =25%*$AM$10 -> 178791.3 | AL10: =25%*$AM$10 -> 178791.3 | AM10: =AB10*H21 -> 715165.2 | AN10: =25%*$AR$10 -> 536373.9 | AO10: =25%*$AR$10 -> 536373.9 | AP10: =25%*$AR$10 -> 536373.9 | AQ10: =25%*$AR$10 -> 536373.9 | AR10: =AC10*H21 -> 2145495.6
C11: Countries with favorable reimbursment scheme for EN/PN therapies | Z11: Italy | AA11: 0.04 | AB11: 0.15 | AC11: 0.25 | AD11: =10%*AH11 -> 32481.534 | AE11: =20%*AH11 -> 64963.068 | AF11: =30%*AH11 -> 97444.602 | AG11: =40%*AH11 -> 129926.14 | AH11: =AA11*H22 -> 324815.34 | AI11: =25%*$AM11 -> 304514.38 | AJ11: =25%*$AM11 -> 304514.38 | AK11: =25%*$AM11 -> 304514.38 | AL11: =25%*$AM11 -> 304514.38 | AM11: =AB11*H22 -> 1218057.5 | AN11: =25%*$AR$11 -> 507523.97 | AO11: =25%*$AR$11 -> 507523.97 | AP11: =25%*$AR$11 -> 507523.97 | AQ11: =25%*$AR$11 -> 507523.97 | AR11: =AC11*H22 -> 2030095.9
Z12: Germany | AA12: 0 | AB12: 0.02 | AC12: 0.06 | AD12: =0%*AH12 -> 0 | AE12: =20%*AH12 -> 0 | AF12: =30%*AH12 -> 0 | AG12: =50%*AH12 -> 0 | AH12: =AA12*H23 -> 0 | AI12: =25%*$AM12 -> 104333.33 | AJ12: =25%*$AM12 -> 104333.33 | AK12: =25%*$AM12 -> 104333.33 | AL12: =25%*$AM12 -> 104333.33 | AM12: =AB12*H23 -> 417333.33 | AN12: =25%*$AR12 -> 313000 | AO12: =25%*$AR12 -> 313000 | AP12: =25%*$AR12 -> 313000 | AQ12: =25%*$AR12 -> 313000 | AR12: =AC12*H23 -> 1252000
Z13: =C24 -> Country 1 | AA13: 0 | AB13: 0.02 | AC13: 0.06 | AD13: =0%*AH13 -> 0 | AE13: =20%*AH13 -> 0 | AF13: =30%*AH13 -> 0 | AG13: =50%*AH13 -> 0 | AH13: =AA13*H24 -> 0 | AI13: =25%*$AM13 -> 40000 | AJ13: =25%*$AM13 -> 40000 | AK13: =25%*$AM13 -> 40000 | AL13: =25%*$AM13 -> 40000 | AM13: =AB13*H24 -> 160000 | AN13: =25%*$AR13 -> 120000 | AO13: =25%*$AR13 -> 120000 | AP13: =25%*$AR13 -> 120000 | AQ13: =25%*$AR13 -> 120000 | AR13: =AC13*H24 -> 480000
Z14: =C25 -> Country 2 | AD14: =0%*AH14 -> 0 | AE14: =20%*AH14 -> 0 | AF14: =30%*AH14 -> 0 | AG14: =50%*AH14 -> 0 | AH14: =AA14*H25 -> 0 | AI14: =25%*$AM14 -> 0 | AJ14: =25%*$AM14 -> 0 | AK14: =25%*$AM14 -> 0 | AL14: =25%*$AM14 -> 0 | AM14: =AB14*H25 -> 0 | AN14: =25%*$AR14 -> 0 | AO14: =25%*$AR14 -> 0 | AP14: =25%*$AR14 -> 0 | AQ14: =25%*$AR14 -> 0 | AR14: =AC14*H25 -> 0
Z15: =C26 -> Country 3 | AD15: =0%*AH15 -> 0 | AE15: =20%*AH15 -> 0 | AF15: =30%*AH15 -> 0 | AG15: =50%*AH15 -> 0 | AH15: =AA15*H26 -> 0 | AI15: =25%*$AM15 -> 0 | AJ15: =25%*$AM15 -> 0 | AK15: =25%*$AM15 -> 0 | AL15: =25%*$AM15 -> 0 | AM15: =AB15*H26 -> 0 | AN15: =25%*$AR15 -> 0 | AO15: =25%*$AR15 -> 0 | AP15: =25%*$AR15 -> 0 | AQ15: =25%*$AR15 -> 0 | AR15: =AC15*H26 -> 0
Z16: =C27 -> Country 4 | AD16: =0%*AH16 -> 0 | AE16: =20%*AH16 -> 0 | AF16: =30%*AH16 -> 0 | AG16: =50%*AH16 -> 0 | AH16: =AA16*H27 -> 0 | AI16: =25%*$AM16 -> 0 | AJ16: =25%*$AM16 -> 0 | AK16: =25%*$AM16 -> 0 | AL16: =25%*$AM16 -> 0 | AM16: =AB16*H27 -> 0 | AN16: =25%*$AR16 -> 0 | AO16: =25%*$AR16 -> 0 | AP16: =25%*$AR16 -> 0 | AQ16: =25%*$AR16 -> 0 | AR16: =AC16*H27 -> 0
C17: HEN | Z17: Total | AD17: =SUM(AD9:AD16) -> 32481.534 | AE17: =SUM(AE9:AE16) -> 96148.02 | AF17: =SUM(AF9:AF16) -> 144222.03 | AG17: =SUM(AG9:AG16) -> 207888.52 | AH17: =SUM(AH9:AH16) -> 480740.1 | AI17: =SUM(AI9:AI16) -> 643753.66 | AJ17: =SUM(AJ9:AJ16) -> 643753.66 | AK17: =SUM(AK9:AK16) -> 643753.66 | ... AR17: =SUM(AR9:AR16) -> 6036508.7
Z18: Total Feedim devices | AD18: =AD17/1000 -> 32.481534 | AE18: =AE17/1000 -> 96.14802 | AF18: =AF17/1000 -> 144.22203 | AG18: =AG17/1000 -> 207.88852 | AH18: =AH17/1000 -> 480.7401 | AI18: =AI17/1000 -> 643.75366 | AJ18: =AJ17/1000 -> 643.75366 | AK18: =AK17/1000 -> 643.75366 | ... AR18: =AR17/1000 -> 6036.5087
D19: Inhabitants (Millions) | E19: HEN Prevalence | F19: Annual EN Patients | G19: Therapy duration (average) | H19: Total therapy days
C20: Belgium1 | D20: 11.4 | E20: =F20/(D20*10) -> 53.342105 | F20: 6081 | G20: 106 | H20: =F20*G20 -> 644586 | Z20: Expected Revenues - Home Enteral Nutrition
C21: France2 | D21: 66.99 | E21: 65.9 | F21: 44146 | G21: 324 | H21: =F21*G21 -> 14303304 | AD21: Days Sold - Y1 | AI21: Days - Y2 | AN21: Days - Y3
C22: Italy3 | D22: 60.48 | E22: =F22/(D22*10) -> 68.502857 | F22: =16650*(1.2^5) -> 41430.528 | G22: 196 | H22: =F22*G22 -> 8120383.5 | AD22: Q1 | AE22: Q2 | AF22: Q3 | AG22: Q4 | AH22: Total Y1 | AI22: Q1 | AJ22: Q2 | AK22: Q3 | AL22: Q4 | AM22: Total Y2 | AN22: Q1 | AO22: Q2 | AP22: Q3 | AQ22: Q4 | AR22: Total Y3
C23: Germany4 | D23: 82.79 | E23: =F23/(D23*10) -> 120.78753 | F23: 100000 | G23: =AVERAGE(G20:G22) -> 208.66667 | H23: =F23*G23 -> 20866667 | Z23: Belgium | AD23: =IF(AD9<$R$7,$P$10,$R$10)*AD9 -> 0 | AE23: =IF(AE9<$R$7,$P$10,$R$10)*AE9 -> 953.98728 | AF23: =IF(AF9<$R$7,$P$10,$R$10)*AF9 -> 1430.9809 | AG23: =IF(AG9<$R$7,$P$10,$R$10)*AG9 -> 2384.9682 | AH23: =IF(AH9<$R$7,$P$10,$R$10)*AH9 -> 4769.9364 | AI23: =IF(AI9<$R$7,$P$10,$R$10)*AI9 -> 5962.4205 | AJ23: =IF(AJ9<$R$7,$P$10,$R$10)*AJ9 -> 5962.4205 | AK23: =IF(AK9<$R$7,$P$10,$R$10)*AK9 -> 5962.4205 | AL23: =IF(AL9<$R$7,$P$10,$R$10)*AL9 -> 5962.4205 | AM23: =SUM(AI23:AL23) -> 23849.682 | AN23: =IF(AN9<$R$7,$P$10,$R$10)*AN9 -> 11924.841 | AO23: =IF(AO9<$R$7,$P$10,$R$10)*AO9 -> 11924.841 | AP23: =IF(AP9<$R$7,$P$10,$R$10)*AP9 -> 11924.841 | AQ23: =IF(AQ9<$R$7,$P$10,$R$10)*AQ9 -> 11924.841 | AR23: =SUM(AN23:AQ23) -> 47699.364
C24: Country 1 | F24: 40000 | G24: 200 | H24: =F24*G24 -> 8000000 | Z24: France | AD24: =IF(AD10<$R$7,$P$10,$R$10)*AD10 -> 0 | AE24: =IF(AE10<$R$7,$P$10,$R$10)*AE10 -> 10584.445 | AF24: =IF(AF10<$R$7,$P$10,$R$10)*AF10 -> 15876.667 | AG24: =IF(AG10<$R$7,$P$10,$R$10)*AG10 -> 26461.112 | AH24: =IF(AH10<$R$7,$P$10,$R$10)*AH10 -> 52922.225 | AI24: =IF(AI10<$R$7,$P$10,$R$10)*AI10 -> 66152.781 | AJ24: =IF(AJ10<$R$7,$P$10,$R$10)*AJ10 -> 66152.781 | AK24: =IF(AK10<$R$7,$P$10,$R$10)*AK10 -> 66152.781 | AL24: =IF(AL10<$R$7,$P$10,$R$10)*AL10 -> 66152.781 | AM24: =SUM(AI24:AL24) -> 264611.12 | AN24: =IF(AN10<$R$7,$P$10,$R$10)*AN10 -> 160912.17 | AO24: =IF(AO10<$R$7,$P$10,$R$10)*AO10 -> 160912.17 | AP24: =IF(AP10<$R$7,$P$10,$R$10)*AP10 -> 160912.17 | AQ24: =IF(AQ10<$R$7,$P$10,$R$10)*AQ10 -> 160912.17 | AR24: =SUM(AN24:AQ24) -> 643648.68
C25: Country 2 | G25: 200 | H25: =F25*G25 -> 0 | Z25: Italy | AD25: =IF(AD11<$R$7,$P$10,$R$10)*AD11 -> 12018.168 | AE25: =IF(AE11<$R$7,$P$10,$R$10)*AE11 -> 24036.335 | AF25: =IF(AF11<$R$7,$P$10,$R$10)*AF11 -> 36054.503 | AG25: =IF(AG11<$R$7,$P$10,$R$10)*AG11 -> 48072.67 | AH25: =IF(AH11<$R$7,$P$10,$R$10)*AH11 -> 120181.68 | AI25: =IF(AI11<$R$7,$P$10,$R$10)*AI11 -> 112670.32 | AJ25: =IF(AJ11<$R$7,$P$10,$R$10)*AJ11 -> 112670.32 | AK25: =IF(AK11<$R$7,$P$10,$R$10)*AK11 -> 112670.32 | AL25: =IF(AL11<$R$7,$P$10,$R$10)*AL11 -> 112670.32 | AM25: =SUM(AI25:AL25) -> 450681.28 | AN25: =IF(AN11<$R$7,$P$10,$R$10)*AN11 -> 152257.19 | AO25: =IF(AO11<$R$7,$P$10,$R$10)*AO11 -> 152257.19 | AP25: =IF(AP11<$R$7,$P$10,$R$10)*AP11 -> 152257.19 | AQ25: =IF(AQ11<$R$7,$P$10,$R$10)*AQ11 -> 152257.19 | AR25: =SUM(AN25:AQ25) -> 609028.76
C26: Country 3 | G26: 200 | H26: =F26*G26 -> 0 | Z26: Germany | AD26: =IF(AD12<$R$7,$P$10,$R$10)*AD12 -> 0 | AE26: =IF(AE12<$R$7,$P$10,$R$10)*AE12 -> 0 | AF26: =IF(AF12<$R$7,$P$10,$R$10)*AF12 -> 0 | AG26: =IF(AG12<$R$7,$P$10,$R$10)*AG12 -> 0 | AH26: =IF(AH12<$R$7,$P$10,$R$10)*AH12 -> 0 | AI26: =IF(AI12<$R$7,$P$10,$R$10)*AI12 -> 38603.333 | AJ26: =IF(AJ12<$R$7,$P$10,$R$10)*AJ12 -> 38603.333 | AK26: =IF(AK12<$R$7,$P$10,$R$10)*AK12 -> 38603.333 | AL26: =IF(AL12<$R$7,$P$10,$R$10)*AL12 -> 38603.333 | AM26: =SUM(AI26:AL26) -> 154413.33 | AN26: =IF(AN12<$R$7,$P$10,$R$10)*AN12 -> 115810 | AO26: =IF(AO12<$R$7,$P$10,$R$10)*AO12 -> 115810 | AP26: =IF(AP12<$R$7,$P$10,$R$10)*AP12 -> 115810 | AQ26: =IF(AQ12<$R$7,$P$10,$R$10)*AQ12 -> 115810 | AR26: =SUM(AN26:AQ26) -> 463240
C27: Country 4 | G27: 200 | H27: =F27*G27 -> 0 | Z27: =C24 -> Country 1 | AD27: =IF(AD13<$R$7,$P$10,$R$10)*AD13 -> 0 | AE27: =IF(AE13<$R$7,$P$10,$R$10)*AE13 -> 0 | AF27: =IF(AF13<$R$7,$P$10,$R$10)*AF13 -> 0 | AG27: =IF(AG13<$R$7,$P$10,$R$10)*AG13 -> 0 | AH27: =IF(AH13<$R$7,$P$10,$R$10)*AH13 -> 0 | AI27: =IF(AI13<$R$7,$P$10,$R$10)*AI13 -> 14800 | AJ27: =IF(AJ13<$R$7,$P$10,$R$10)*AJ13 -> 14800 | AK27: =IF(AK13<$R$7,$P$10,$R$10)*AK13 -> 14800 | AL27: =IF(AL13<$R$7,$P$10,$R$10)*AL13 -> 14800 | AM27: =SUM(AI27:AL27) -> 59200 | AN27: =IF(AN13<$R$7,$P$10,$R$10)*AN13 -> 44400 | AO27: =IF(AO13<$R$7,$P$10,$R$10)*AO13 -> 44400 | AP27: =IF(AP13<$R$7,$P$10,$R$10)*AP13 -> 44400 | AQ27: =IF(AQ13<$R$7,$P$10,$R$10)*AQ13 -> 44400 | AR27: =SUM(AN27:AQ27) -> 177600
C28: Total | F28: =SUM(F20:F27) -> 231657.53 | H28: =SUM(H20:H27) -> 51934940 | Z28: =C25 -> Country 2 | AD28: =IF(AD14<$R$7,$P$10,$R$10)*AD14 -> 0 | AE28: =IF(AE14<$R$7,$P$10,$R$10)*AE14 -> 0 | AF28: =IF(AF14<$R$7,$P$10,$R$10)*AF14 -> 0 | AG28: =IF(AG14<$R$7,$P$10,$R$10)*AG14 -> 0 | AH28: =IF(AH14<$R$7,$P$10,$R$10)*AH14 -> 0 | AI28: =IF(AI14<$R$7,$P$10,$R$10)*AI14 -> 0 | AJ28: =IF(AJ14<$R$7,$P$10,$R$10)*AJ14 -> 0 | AK28: =IF(AK14<$R$7,$P$10,$R$10)*AK14 -> 0 | AL28: =IF(AL14<$R$7,$P$10,$R$10)*AL14 -> 0 | AM28: =SUM(AI28:AL28) -> 0 | AN28: =IF(AN14<$R$7,$P$10,$R$10)*AN14 -> 0 | AO28: =IF(AO14<$R$7,$P$10,$R$10)*AO14 -> 0 | AP28: =IF(AP14<$R$7,$P$10,$R$10)*AP14 -> 0 | AQ28: =IF(AQ14<$R$7,$P$10,$R$10)*AQ14 -> 0 | AR28: =SUM(AN28:AQ28) -> 0
Z29: =C26 -> Country 3 | AD29: =IF(AD15<$R$7,$P$10,$R$10)*AD15 -> 0 | AE29: =IF(AE15<$R$7,$P$10,$R$10)*AE15 -> 0 | AF29: =IF(AF15<$R$7,$P$10,$R$10)*AF15 -> 0 | AG29: =IF(AG15<$R$7,$P$10,$R$10)*AG15 -> 0 | AH29: =IF(AH15<$R$7,$P$10,$R$10)*AH15 -> 0 | AI29: =IF(AI15<$R$7,$P$10,$R$10)*AI15 -> 0 | AJ29: =IF(AJ15<$R$7,$P$10,$R$10)*AJ15 -> 0 | AK29: =IF(AK15<$R$7,$P$10,$R$10)*AK15 -> 0 | AL29: =IF(AL15<$R$7,$P$10,$R$10)*AL15 -> 0 | AM29: =SUM(AI29:AL29) -> 0 | AN29: =IF(AN15<$R$7,$P$10,$R$10)*AN15 -> 0 | AO29: =IF(AO15<$R$7,$P$10,$R$10)*AO15 -> 0 | AP29: =IF(AP15<$R$7,$P$10,$R$10)*AP15 -> 0 | AQ29: =IF(AQ15<$R$7,$P$10,$R$10)*AQ15 -> 0 | AR29: =SUM(AN29:AQ29) -> 0
Z30: =C27 -> Country 4 | AD30: =IF(AD16<$R$7,$P$10,$R$10)*AD16 -> 0 | AE30: =IF(AE16<$R$7,$P$10,$R$10)*AE16 -> 0 | AG30: =IF(AG16<$R$7,$P$10,$R$10)*AG16 -> 0 | AH30: =IF(AH16<$R$7,$P$10,$R$10)*AH16 -> 0 | AI30: =IF(AI16<$R$7,$P$10,$R$10)*AI16 -> 0 | AJ30: =IF(AJ16<$R$7,$P$10,$R$10)*AJ16 -> 0 | AK30: =IF(AK16<$R$7,$P$10,$R$10)*AK16 -> 0 | AL30: =IF(AL16<$R$7,$P$10,$R$10)*AL16 -> 0 | AM30: =SUM(AI30:AL30) -> 0 | AN30: =IF(AN16<$R$7,$P$10,$R$10)*AN16 -> 0 | AO30: =IF(AO16<$R$7,$P$10,$R$10)*AO16 -> 0 | AP30: =IF(AP16<$R$7,$P$10,$R$10)*AP16 -> 0 | AQ30: =IF(AQ16<$R$7,$P$10,$R$10)*AQ16 -> 0 | AR30: =SUM(AN30:AQ30) -> 0
O31: Business Model 2 | Z31: Total | AD31: =SUM(AD23:AD30) -> 12018.168 | AE31: =SUM(AE23:AE30) -> 35574.767 | AF31: =SUM(AF23:AF30) -> 53362.151 | AG31: =SUM(AG23:AG30) -> 76918.751 | AH31: =SUM(AH23:AH30) -> 177873.84 | AI31: =SUM(AI23:AI30) -> 238188.86 | AJ31: =SUM(AJ23:AJ30) -> 238188.86 | AK31: =SUM(AK23:AK30) -> 238188.86 | ... AR31: =SUM(AR23:AR30) -> 1941216.8
C33: HPN | O33: Reimbursment HEN per day | U33: Reimbursment HPN per day
D34: Inhabitants (Millions) | E34: HPN Prevalence | F34: Annual PN Patients | G34: Therapy duration (average) | H34: Total therapy days | P34: Reimbursed | Q34: Patient-out-of pocket | R34: Dim3 Price per day | V34: Reimbursed | W34: Patient-out-of pocket | X34: Dim3 Price per day
C35: Belgium1 | D35: 11.4 | E35: =F35/(D35*10) -> 11.473684 | F35: 1308 | G35: 33 | H35: =G35*F35 -> 43164 | O35: Belgium (with polymeric solution)1 | P35: 5.66 | Q35: 11.85 | R35: =P35*$P$40 -> 0.3396 | U35: Belgium (only materials)1 | V35: 28 | W35: 0.62 | X35: =V40*V35 -> 1.68
C36: France2 | D36: 66.99 | E36: 24.4 | F36: 16345 | G36: 33 | H36: =F36*G36 -> 539385 | O36: France (without setup budget)5 | P36: =82/7 -> 11.714286 | Q36: 0 | R36: =P36*$P$40 -> 0.70285714 | U36: France (without setup budget)6 | V36: =190/7 -> 27.142857 | W36: 0 | X36: =V40*V36 -> 1.6285714
C37: Italy3 | D37: 60.48 | E37: 5.02 | F37: =E37*10*D37*(1.2^5) -> 7554.7784 | G37: 33 | H37: =F37*G37 -> 249307.69 | O37: Italy | P37: 5 | Q37: 0 | R37: =P37*$P$40 -> 0.3 | U37: Italy
C38: Germany | D38: 82.79 | O38: Germany | P38: ? | Q38: ? | R38: ? | U38: Germany
C39: Total | F39: =SUM(F35:F38) -> 25207.778 | H39: =SUM(H35:H38) -> 831856.69
O40: Price as % of reimbursment | P40: 0.06 | U40: Price as % of reimbursment | V40: 0.06
C43: References :
B44: 1 | C44: KCE report : https://kce.fgov.be/en/organization-and-reimbursement-of-enteral-and-parenteral-nutrition-in-and-outside-the-hospital-in
B45: 2 | C45: Presentation JDPN 2018 Liege - Prof Dominique Lescut - EPIDÉMIOLOGIE DE LA NUTRITION ARTIFICIELLE À DOMICILE (NAD)
B46: 3 | C46: Italy HEN prevalence : https://bmcnutr.biomedcentral.com/articles/10.1186/s40795-016-0118-y
B47: 4 | C47: https://pubmed.ncbi.nlm.nih.gov/15818022/
B48: 5 | C48: France reimbursment : http://www.codage.ext.cnamts.fr/cgi/tips/cgi-fiche?p_code_tips=1176876&p_date_jo_arrete=%25&p_menu=FICHE&p_site=AMELI | Z48: Business Model 2
B49: 6 | C49: http://www.codage.ext.cnamts.fr/cgi/tips/cgi-fiche?p_code_tips=1185680&p_date_jo_arrete=%25&p_menu=FICHE&p_site=AMELI | Z49: Market Penetration - Homecare
B51: Executive Summary | Z51: HEN
AD52: Days Sold - Y1 | AI52: Days - Y2 | AN52: Days - Y3
B53: Commercial strategy & Business Model | AA53: Y1 | AB53: Y2 | AC53: Y3 | AD53: Q1 | AE53: Q2 | AF53: Q3 | AG53: Q4 | AH53: Total Y1 | AI53: Q1 | AJ53: Q2 | AK53: Q3 | AL53: Q4 | AM53: Total Y2 | AN53: Q1 | AO53: Q2 | AP53: Q3 | AQ53: Q4 | AR53: Total Y3
B54: We provide follow-up days, 1 Feedim device included every 1000 days (volume dependent), BM1 uses Vivisol prices - BM2 uses % of reimbursment (yellow cells) | Z54: Belgium | AA54: 0.02 | AB54: 0.1 | AC54: 0.2 | AD54: =0%*AH54 -> 0 | AE54: =20%*AH54 -> 2578.344 | AF54: =30%*AH54 -> 3867.516 | AG54: =50%*AH54 -> 6445.86 | AH54: =AA54*H20 -> 12891.72 | AI54: =25%*$AM54 -> 16114.65 | AJ54: =25%*$AM$9 -> 16114.65 | AK54: =25%*$AM$9 -> 16114.65 | AL54: =25%*$AM$9 -> 16114.65 | AM54: =AB54*H20 -> 64458.6 | AN54: =25%*$AR$9 -> 32229.3 | AO54: =25%*$AR$9 -> 32229.3 | AP54: =25%*$AR$9 -> 32229.3 | AQ54: =25%*$AR$9 -> 32229.3 | AR54: =AC54*H20 -> 128917.2
B55: We go direct in the different countries without a distributor, apart from Italy, exclusivity cannot be accepted (it would reduce too much our adressable market) | Z55: France | AA55: 0.01 | AB55: 0.05 | AC55: 0.15 | AD55: =0%*AH55 -> 0 | AE55: =20%*AH55 -> 28606.608 | AF55: =30%*AH55 -> 42909.912 | AG55: =50%*AH55 -> 71516.52 | AH55: =AA55*H21 -> 143033.04 | AI55: =25%*$AM$10 -> 178791.3 | AJ55: =25%*$AM$10 -> 178791.3 | AK55: =25%*$AM$10 -> 178791.3 | AL55: =25%*$AM$10 -> 178791.3 | AM55: =AB55*H21 -> 715165.2 | AN55: =25%*$AR$10 -> 536373.9 | AO55: =25%*$AR$10 -> 536373.9 | AP55: =25%*$AR$10 -> 536373.9 | AQ55: =25%*$AR$10 -> 536373.9 | AR55: =AC55*H21 -> 2145495.6
B56: France is more fragmented than Italy and Belgium (more companies acting as homecare providers) | Z56: Italy | AA56: 0.05 | AB56: 0.12 | AC56: 0.25 | AD56: =10%*AH56 -> 40601.917 | AE56: =20%*AH56 -> 81203.835 | AF56: =30%*AH56 -> 121805.75 | AG56: =40%*AH56 -> 162407.67 | AH56: =AA56*H22 -> 406019.17 | AI56: =25%*$AM56 -> 243611.5 | AJ56: =25%*$AM56 -> 243611.5 | AK56: =25%*$AM56 -> 243611.5 | AL56: =25%*$AM56 -> 243611.5 | AM56: =AB56*H22 -> 974446.02 | AN56: =25%*$AR$11 -> 507523.97 | AO56: =25%*$AR$11 -> 507523.97 | AP56: =25%*$AR$11 -> 507523.97 | AQ56: =25%*$AR$11 -> 507523.97 | AR56: =AC56*H22 -> 2030095.9
B57: Few documented info on Germany | Z57: Germany | AA57: 0.01 | AB57: 0.03 | AC57: 0.08 | AD57: =0%*AH57 -> 0 | AE57: =20%*AH57 -> 41733.333 | AF57: =30%*AH57 -> 62600 | AG57: =50%*AH57 -> 104333.33 | AH57: =AA57*H23 -> 208666.67 | AI57: =25%*$AM57 -> 156500 | AJ57: =25%*$AM57 -> 156500 | AK57: =25%*$AM57 -> 156500 | AL57: =25%*$AM57 -> 156500 | AM57: =AB57*H23 -> 626000 | AN57: =25%*$AR$12 -> 313000 | AO57: =25%*$AR$12 -> 313000 | AP57: =25%*$AR$12 -> 313000 | AQ57: =25%*$AR$12 -> 313000 | AR57: =AC57*H23 -> 1669333.3
Z58: Total | AH58: =SUM(AH54:AH57) -> 770610.6 | AM58: =SUM(AM54:AM57) -> 2380069.8 | AR58: =SUM(AR54:AR57) -> 5973842
B60: Product insights | Z60: Expected Revenues - Home Enteral nutrition
B61: Nutrow Onco module available in EOY1 accelerate adoption | AD61: Days Sold - Y1 | AI61: Days - Y2 | AN61: Days - Y3
B62: Feedim 4G available EOY1 boosts sales in Y2 | AD62: Q1 | AE62: Q2 | AF62: Q3 | AG62: Q4 | AH62: Total Y1 | AI62: Q1 | AJ62: Q2 | AK62: Q3 | AL62: Q4 | AM62: Total Y2 | AN62: Q1 | AO62: Q2 | AP62: Q3 | AQ62: Q4 | AR62: Total Y3
B63: HPN market is not included in the revenues but it's a market with interesting potential that could be quickly adressed. | Z63: Belgium | AD63: =AD54*$R35 -> 0 | AE63: =AE54*$R35 -> 875.60562 | AF63: =AF54*$R35 -> 1313.4084 | AG63: =AG54*$R35 -> 2189.0141 | AH63: =AH54*R35 -> 4378.0281 | AI63: =AI54*$R$35 -> 5472.5351 | AJ63: =AJ54*$R$35 -> 5472.5351 | AK63: =AK54*$R$35 -> 5472.5351 | AL63: =AL54*$R$35 -> 5472.5351 | AM63: =SUM(AI63:AL63) -> 21890.141 | AN63: =AN54*$R$35 -> 10945.07 | AO63: =AO54*$R$35 -> 10945.07 | AP63: =AP54*$R$35 -> 10945.07 | AQ63: =AQ54*$R$35 -> 10945.07 | AR63: =SUM(AN63:AQ63) -> 43780.281
Z64: France | AD64: =AD55*$R36 -> 0 | AE64: =AE55*$R36 -> 20106.359 | AF64: =AF55*$R36 -> 30159.538 | AG64: =AG55*$R36 -> 50265.897 | AH64: =AH55*R36 -> 100531.79 | AI64: =AI55*$R$36 -> 125664.74 | AJ64: =AJ55*$R$36 -> 125664.74 | AK64: =AK55*$R$36 -> 125664.74 | AL64: =AL55*$R$36 -> 125664.74 | AM64: =SUM(AI64:AL64) -> 502658.97 | AN64: =AN55*$R$36 -> 376994.23 | AO64: =AO55*$R$36 -> 376994.23 | AP64: =AP55*$R$36 -> 376994.23 | AQ64: =AQ55*$R$36 -> 376994.23 | AR64: =SUM(AN64:AQ64) -> 1507976.9
Z65: Italy | AD65: =AD56*$R37 -> 12180.575 | AE65: =AE56*$R37 -> 24361.15 | AF65: =AF56*$R37 -> 36541.726 | AG65: =AG56*$R37 -> 48722.301 | AH65: =AH56*R37 -> 121805.75 | AI65: =AI56*$R$37 -> 73083.451 | AJ65: =AJ56*$R$37 -> 73083.451 | AK65: =AK56*$R$37 -> 73083.451 | AL65: =AL56*$R$37 -> 73083.451 | AM65: =SUM(AI65:AL65) -> 292333.81 | AN65: =AN56*$R$37 -> 152257.19 | AO65: =AO56*$R$37 -> 152257.19 | AP65: =AP56*$R$37 -> 152257.19 | AQ65: =AQ56*$R$37 -> 152257.19 | AR65: =SUM(AN65:AQ65) -> 609028.76
Z66: Germany | AM66: =SUM(AI66:AL66) -> 0 | AR66: =SUM(AN66:AQ66) -> 0
Z67: Total | AH67: =SUM(AH63:AH66) -> 226715.57 | AM67: =SUM(AM63:AM66) -> 816882.92 | AR67: =SUM(AR63:AR66) -> 2160786
Z86: Market Penetration - Home Parenteral Nutrition
Z88: Market Penetration - Other Medical devices and pathologies

Sheet OEM-B2B 
B3: Total Adressable Market - Homecare | N3: Business Model - OEM | V3: Market Penetration - OEM Feedim
B4: Unmet clinical needs: | N4: Sell OEM Feedim devices w/o UI
W5: Y1 | AA5: Total - Y1 | AB5: Y2 | AF5: Total - Y2 | AG5: Y3 | AK5: Total - Y3
B6: Expert tool to follow clinical nutrition in ICU | N6: OEM Feedim Integration with device | W6: Q1 | X6: Q2 | Y6: Q3 | Z6: Q4 | AA6: Y1 | AB6: Q1 | AC6: Q2 | AD6: Q3 | AE6: Q4 | AF6: Y2 | AG6: Q1 | AH6: Q2 | AI6: Q3 | AJ6: Q4 | AK6: Y3 | AL6: Total
B7: Pumps connectivity | O7: ASP2 | V7: Integration projects | W7: 0 | X7: 1 | Y7: 0 | Z7: 1 | AA7: 2 | AC7: 1 | AD7: 1 | AE7: 1 | AF7: 3 | AG7: 1 | AH7: 1 | AI7: 1 | AJ7: 1 | AK7: 4 | AL7: =AA7+AF7+AK7 -> 9
B8: Medical device connectivity - Hospital and Homecare | N8: Integration service | O8: 45000 | V8: Feedim OEM sold | W8: 0 | X8: 0 | Y8: 0 | Z8: =AA8*100% -> 2000 | AA8: =2000 -> 2000 | AB8: =$AF$8*25% -> 1250 | AC8: =$AF$8*25% -> 1250 | AD8: =$AF$8*25% -> 1250 | AE8: =$AF$8*25% -> 1250 | AF8: 5000 | AG8: =$AK$8*25% -> 2000 | AH8: =$AK$8*25% -> 2000 | AI8: =$AK$8*25% -> 2000 | AJ8: =$AK$8*25% -> 2000 | AK8: 8000 | AL8: =AA8+AF8+AK8 -> 15000
V9: Nutrow OEM (20% of devices) | W9: 0 | X9: 0 | Y9: 0 | Z9: =Z8*20% -> 400 | AA9: =AA8*20% -> 400 | AB9: =AB8*20% -> 250 | AC9: =AC8*20% -> 250 | AD9: =AD8*20% -> 250 | AE9: =AE8*20% -> 250 | AF9: =AF8*20% -> 1000 | AG9: =AG8*20% -> 400 | ... AK9: =AK8*20% -> 1600 | AL9: =AA9+AF9+AK9 -> 3000
N10: OEM Feedim Transfer price w/o UI
C11: 17B$1 | D11: General infusion pumps and devices market | N11: MOQ | O11: 1000 | P11: 5000 | Q11: 10000 | V11: Expected Revenues - OEM Feedim
B12: BD1 | C12: 0.068 | D12: market share general infusion pumps | N12: Feedim device (EUR) | O12: =149 -> 149 | P12: =MEDIAN(O12,Q12) -> 134 | Q12: 119
B13: Baxter1 | C13: 0.117 | D13: market share general infusion pumps
N14: OEM Nutrow - one per Feedim - Pricing
O15: 500 | P15: 5000 | Q15: 10000
B16: References | O16: 159 | P16: 139 | Q16: 129 | W16: Y1 | AA16: Total - Y1 | AB16: Y2 | AF16: Total - Y2 | AG16: Y3 | AK16: Total - Y3
B17: 1 | C17: BCC Research - HLC071C - Infusion Pumps and Devices: Technologies and Global Markets - November 2016 | N17: Maintenance Fee | O17: =O16*$R$17 -> 23.85 | P17: =P16*$R$17 -> 20.85 | Q17: =Q16*$R$17 -> 19.35 | R17: =15% -> 0.15 | W17: Q1 | X17: Q2 | Y17: Q3 | Z17: Q4 | AA17: Y1 | AB17: Q1 | AC17: Q2 | AD17: Q3 | AE17: Q4 | AF17: Y2 | AG17: Q1 | AH17: Q2 | AI17: Q3 | AJ17: Q4 | AK17: Y3
B18: 2 | C18: SOW-BD2 (internal file) | V18: Integration projects | W18: =W7*$O$8 -> 0 | X18: =X7*$O$8 -> 45000 | Y18: =Y7*$O$8 -> 0 | Z18: =Z7*$O$8 -> 45000 | AA18: =AA7*$O$8 -> 90000 | AB18: =AB7*$O$8 -> 0 | AC18: =AC7*$O$8 -> 45000 | AD18: =AD7*$O$8 -> 45000 | ... AJ18: =AJ7*$O$8 -> 45000 | AK18: =AK7*O8 -> 180000
V19: Feedim OEM sold | W19: =W8*$O$12 -> 0 | X19: =X8*$O$12 -> 0 | Y19: =Y8*$O$12 -> 0 | Z19: =Z8*$O$12 -> 298000 | AA19: =AA8*$O$12 -> 298000 | AB19: =AB8*$O$12 -> 186250 | AC19: =AC8*$O$12 -> 186250 | AD19: =AD8*$O$12 -> 186250 | ... AK19: =AK8*$O$12 -> 1192000
V20: Nutrow OEM (20% of devices) | W20: =W9*$Q$16 -> 0 | X20: =X9*$Q$16 -> 0 | Y20: =Y9*$Q$16 -> 0 | Z20: =Z9*$Q$16 -> 51600 | AA20: =AA9*$Q$16 -> 51600 | AB20: =AB9*$Q$16 -> 32250 | AC20: =AC9*$Q$16 -> 32250 | AD20: =AD9*$Q$16 -> 32250 | ... AK20: =AK9*$Q$16 -> 206400
V21: Total | W21: =SUM(W18:W20) -> 0 | X21: =SUM(X18:X20) -> 45000 | Y21: =SUM(Y18:Y20) -> 0 | Z21: =SUM(Z18:Z20) -> 394600 | AA21: =SUM(AA18:AA20) -> 439600 | AB21: =SUM(AB18:AB20) -> 218500 | AC21: =SUM(AC18:AC20) -> 263500 | AD21: =SUM(AD18:AD20) -> 263500 | ... AK21: =SUM(AK18:AK20) -> 1578400
W23: Y1 | X23: Y2 | Y23: Y3
V24: Integration projects | W24: =AA18 -> 90000 | X24: =AF18 -> 135000 | Y24: =AK18 -> 180000
V25: Feedim OEM sold | W25: =AA19 -> 298000 | X25: =AF19 -> 745000 | Y25: =AK19 -> 1192000
V26: Nutrow OEM (20% of devices) | W26: =AA20 -> 51600 | X26: =AF20 -> 129000 | Y26: =AK20 -> 206400
W27: =SUM(W24:W26) -> 439600 | X27: =SUM(X24:X26) -> 1009000 | Y27: =SUM(Y24:Y26) -> 1578400
C29: All Beds2 | D29: At-risk beds w/o ICU (A) | E29: ICU beds (B)7 | F29: TAM (A+B) | G29: Hospitals 4,5,6,7 | H29: Average hospital size | I29: Average At-risk beds w/o ICU per hospital | J29: Average ICU Beds per hospital | L29: If target size is 750 beds, beds at risk =
B30: US | C30: 924107 | D30: =(C30-E30)*'Hospital '!F13 -> 295633.45 | E30: 79440 | F30: =D30+E30 -> 375073.45 | G30: 6146 | H30: =C30/G30 -> 150.3591 | I30: =H30*('Hospital '!F13-'Hospital '!F14) -> 45.107729 | J30: =E30/G30 -> 12.92548 | L30: =750*'Hospital '!F13 -> 262.5 | V30: Baxter Partnership
V31: No sales in Y1 because Study ongoing,commercial effort to start in Y1Q3, first sales in Y2 = Y1 Dim3
B32: Executive Summary
V33: Achievements | W33: Y1 | X33: Y2 | Y33: Y3 | Z33: Y1 | AD33: Total - Y1 | AE33: Y2 | AI33: Total - Y2 | AJ33: Y3 | AN33: Total - Y3
B34: Commercial strategy & Business Model | Z34: Q1 | AA34: Q2 | AB34: Q3 | AC34: Q4 | AD34: Y1 | AE34: Q1 | AF34: Q2 | AG34: Q3 | AH34: Q4 | AI34: Y2 | AJ34: Q1 | AK34: Q2 | AL34: Q3 | AM34: Q4 | AN34: Y3
B35: OEM | V35: General Beds | W35: 0 | X35: 0.004 | Y35: 0.01 | Z35: 0 | AA35: 0 | AB35: 0 | AC35: 0 | AD35: =W35*D30 -> 0 | AI35: =X35*D30 -> 1182.5338 | AN35: =D30*Y35 -> 2956.3345
B36: Assumption = 1 FTE for OEM Sales only | V36: ICU Beds | W36: 0 | X36: 0.004 | Y36: 0.01 | Z36: 0 | AA36: 0 | AB36: 0 | AC36: 0 | AD36: =W36*E30 -> 0 | AI36: =X36*E30 -> 317.76 | AN36: =E30*Y36 -> 794.4
B37: Targeting medical devices companies that benefits from connectivity | V37: Feedim devices | AD37: 0 | AI37: =AI36+(AI35*'Hospital '!J27) -> 436.01338 | AN37: =AN36+(AN35*'Hospital '!J27) -> 1090.0334 | AW37: Y1 | AX37: Y2 | AY37: Y3
B38: Each OEM project comes with a MOQ of 1000 Feedim devices | V38: Total Beds | AD38: =SUM(AD35:AD36) -> 0 | AI38: =AI36+AI35 -> 1500.2938 | AN38: =AN36+AN35 -> 3750.7345 | AV38: Lump Sum | AW38: 250000 | AX38: =AI44 -> 0 | AY38: =AN44 -> 0
B39: Baxter | AV39: Hospital Revenues | AW39: =AD48*'Hospital '!E94 -> 0 | AX39: =AI45 -> 305024.73 | AY39: =AN45 -> 762561.83
B40: No sales in Y1 because Study ongoing,commercial effort to start in Y1Q3, first sales in Y2 = Y1 Dim3 | V40: Total projects | AD40: =AD38/L30 -> 0 | AI40: =ROUNDUP(AI38/L30,0) -> 6 | AN40: =ROUNDUP(AN38/L30,0) -> 15 | AV40: Feedim devices | AW40: =AD46 -> 0 | AX40: =AI46 -> 78046.395 | AY40: =AN46 -> 195115.99
B41: Assumption Baxter sales = US sales | AV41: Operations | AW41: =0 -> 0 | AX41: =AI47 -> 165000 | AY41: =AN47 -> 412500
B42: We also assume that Baxter will target entire hospital and not only ICU (not verified yet) | V42: Expected Revenues | Z42: Y1 | AD42: Total - Y1 | AE42: Y2 | AI42: Total - Y2 | AJ42: Y3 | AN42: Total - Y3
B43: Prices = same as distributor, see hospital tab | Z43: Q1 | AA43: Q2 | AB43: Q3 | AC43: Q4 | AD43: Y1 | AE43: Q1 | AF43: Q2 | AG43: Q3 | AH43: Q4 | AI43: Y2 | AJ43: Q1 | AK43: Q2 | AL43: Q3 | AM43: Q4 | AN43: Y3
B44: As for distributors in hospital, we assume we would have to manage operations for the 2 first years | V44: Lump Sum | Z44: 0 | AA44: 0 | AB44: 0 | AC44: =250000 -> 250000 | AD44: 250000 | AE44: 0 | AF44: 0 | AG44: 0 | AH44: 0 | AI44: 0 | AJ44: 0 | AK44: 0 | AL44: 0 | AM44: 0 | AN44: 0
V45: Hospital Revenues | Z45: 0 | AA45: 0 | AB45: 0 | AC45: 0 | AD45: 0 | AE45: =AI45*10% -> 30502.473 | AF45: =AI45*20% -> 61004.946 | AG45: =AI45*30% -> 91507.42 | AH45: =AI45*40% -> 122009.89 | AI45: =IF(AI38>'Hospital '!I72,IF(AI38>'Hospital '!H68,'Hospital '!H72,IF(AI38>'Hospital '!G68,'Hospital '!G72,IF(AI38>'Hospital '!F68,'Hospital '!F72,IF(AI38>'Hospital '!E68,'Hospital '!E72,0)))))*AI38 -> 305024.73 | AJ45: =AN45*25% -> 190640.46 | AK45: =AN45*25% -> 190640.46 | AL45: =AN45*25% -> 190640.46 | AM45: =AN45*25% -> 190640.46 | AN45: =IF(AN38>'Hospital '!I72,IF(AN38>'Hospital '!H68,'Hospital '!H72,IF(AN38>'Hospital '!G68,'Hospital '!G72,IF(AN38>'Hospital '!F68,'Hospital '!F72,IF(AN38>'Hospital '!E68,'Hospital '!E72,0)))))*AN38 -> 762561.83
V46: Feedim devices | Z46: 0 | AA46: 0 | AB46: 0 | AC46: 0 | AD46: =AD37*'Hospital '!D86 -> 0 | AE46: =$AI$46*10% -> 7804.6395 | AF46: =$AI$46*20% -> 15609.279 | AG46: =$AI$46*30% -> 23413.919 | AH46: =$AI$46*40% -> 31218.558 | AI46: =AI37*'Hospital '!D86 -> 78046.395 | AJ46: =$AN$46*25% -> 48778.997 | AK46: =$AN$46*25% -> 48778.997 | AL46: =$AN$46*25% -> 48778.997 | AM46: =$AN$46*25% -> 48778.997 | AN46: =AN37*'Hospital '!D86 -> 195115.99
V47: Operations | Z47: 0 | AA47: 0 | AB47: 0 | AC47: 0 | AD47: =AD40*'Hospital '!G90 -> 0 | AE47: =AI47*10% -> 16500 | AF47: =AI47*20% -> 33000 | AG47: =AI47*30% -> 49500 | AH47: =AI47*40% -> 66000 | AI47: =AI40*'Hospital '!G90 -> 165000 | AJ47: =$AN$47*25% -> 103125 | AK47: =$AN$47*25% -> 103125 | AL47: =$AN$47*25% -> 103125 | AM47: =$AN$47*25% -> 103125 | AN47: =AN40*'Hospital '!G90 -> 412500
V48: Total | Z48: =SUM(Z44:Z47) -> 0 | AA48: =SUM(AA44:AA47) -> 0 | AB48: =SUM(AB44:AB47) -> 0 | AC48: =SUM(AC44:AC47) -> 250000 | AD48: =SUM(AD44:AD47) -> 250000 | AE48: =SUM(AE44:AE47) -> 54807.113 | AF48: =SUM(AF44:AF47) -> 109614.23 | AG48: =SUM(AG44:AG47) -> 164421.34 | ... AN48: =SUM(AN44:AN47) -> 1370177.8

Sheet Summary
C3: Y1 | G3: Total - Y1 | H3: Y2 | L3: Total - Y2 | M3: Y3 | Q3: Total - Y3
C4: Q1 | D4: Q2 | E4: Q3 | F4: Q4 | G4: Y1 | H4: Q1 | I4: Q2 | J4: Q3 | K4: Q4 | L4: Y2 | M4: Q1 | N4: Q2 | O4: Q3 | P4: Q4 | Q4: Y3
B5: Total Hospital Revenues | C5: ='Hospital '!T112+'Hospital '!T138 -> 23585.794 | D5: ='Hospital '!U112+'Hospital '!U138 -> 47171.589 | E5: ='Hospital '!V112+'Hospital '!V138 -> 99514.92 | F5: ='Hospital '!W112+'Hospital '!W138 -> 123100.71 | G5: =SUM('Hospital '!AK95:AK96) -> 293373.02 | H5: ='Hospital '!Y112+'Hospital '!Y138 -> 225272.58 | I5: ='Hospital '!Z112+'Hospital '!Z138 -> 292617.64 | J5: ='Hospital '!AA112+'Hospital '!AA138 -> 359962.7 | K5: ='Hospital '!AB112+'Hospital '!AB138 -> 427307.77 | L5: =SUM('Hospital '!AL95:AL96) -> 1305160.7 | M5: ='Hospital '!AD112+'Hospital '!AD138 -> 867511.92 | N5: ='Hospital '!AE112+'Hospital '!AE138 -> 867511.92 | O5: ='Hospital '!AF112+'Hospital '!AF138 -> 867511.92 | P5: ='Hospital '!AG112+'Hospital '!AG138 -> 867511.92 | Q5: =SUM('Hospital '!AM95:AM96) -> 3470047.7 | AN5: Y1 | AO5: Y2 | AP5: Y3
B6: Baxter Partnership | C6: ='OEM-B2B '!Z48 -> 0 | D6: ='OEM-B2B '!AA48 -> 0 | E6: ='OEM-B2B '!AB48 -> 0 | F6: ='OEM-B2B '!AC48 -> 250000 | G6: ='OEM-B2B '!AD48 -> 250000 | H6: ='OEM-B2B '!AE48 -> 54807.113 | I6: ='OEM-B2B '!AF48 -> 109614.23 | J6: ='OEM-B2B '!AG48 -> 164421.34 | ... Q6: ='OEM-B2B '!AN48 -> 1370177.8 | AL6: Total OEM Feedim | AN6: =G8 -> 439600 | AO6: =L8 -> 1009000 | AP6: =Q8 -> 1578400
B7: Total Homecare Revenues | C7: =Homecare!AD31 -> 12018.168 | D7: =Homecare!AE31 -> 35574.767 | E7: =Homecare!AF31 -> 53362.151 | F7: =Homecare!AG31 -> 76918.751 | G7: =Homecare!AH31 -> 177873.84 | H7: =Homecare!AI31 -> 238188.86 | I7: =Homecare!AJ31 -> 238188.86 | J7: =Homecare!AK31 -> 238188.86 | ... Q7: =Homecare!AR31 -> 1941216.8 | AL7: Total Hospital Revenues | AN7: =G5 -> 293373.02 | AO7: =L5 -> 1305160.7 | AP7: =Q5 -> 3470047.7
B8: Total OEM Feedim | C8: ='OEM-B2B '!W21 -> 0 | D8: ='OEM-B2B '!X21 -> 45000 | E8: ='OEM-B2B '!Y21 -> 0 | F8: ='OEM-B2B '!Z21 -> 394600 | G8: ='OEM-B2B '!AA21 -> 439600 | H8: ='OEM-B2B '!AB21 -> 218500 | I8: ='OEM-B2B '!AC21 -> 263500 | J8: ='OEM-B2B '!AD21 -> 263500 | ... Q8: ='OEM-B2B '!AK21 -> 1578400 | AL8: Total Homecare Revenues | AN8: =G7 -> 177873.84 | AO8: =L7 -> 952755.42 | AP8: =Q7 -> 1941216.8
B9: Operations | C9: ='Hospital '!T152+'OEM-B2B '!Z47 -> 48125 | D9: ='Hospital '!U152+'OEM-B2B '!AA47 -> 20625 | E9: ='Hospital '!V152+'OEM-B2B '!AB47 -> 48125 | F9: ='Hospital '!W152+'OEM-B2B '!AC47 -> 20625 | G9: ='Hospital '!X152+'OEM-B2B '!AD47 -> 137500 | H9: ='Hospital '!Y152+'OEM-B2B '!AE47 -> 90750 | I9: ='Hospital '!Z152+'OEM-B2B '!AF47 -> 140250 | J9: ='Hospital '!AA152+'OEM-B2B '!AG47 -> 189750 | ... Q9: ='Hospital '!AH152+'OEM-B2B '!AN47 -> 412500 | AL9: Baxter Partnership | AN9: =G6 -> 250000 | AO9: =L6 -> 548071.13 | AP9: =Q6 -> 1370177.8
B10: Grand Total | C10: =SUM(C5:C9) -> 83728.962 | D10: =SUM(D5:D9) -> 148371.36 | E10: =SUM(E5:E9) -> 201002.07 | F10: =SUM(F5:F9) -> 865244.47 | G10: =SUM(G5:G9) -> 1298346.9 | H10: =SUM(H5:H9) -> 827518.54 | I10: =SUM(I5:I9) -> 1044170.7 | J10: =SUM(J5:J9) -> 1215822.9 | ... Q10: =SUM(Q5:Q9) -> 8772342.3 | AL10: Operations | AN10: =G9 -> 137500 | AO10: =L9 -> 660000 | AP10: =Q9 -> 412500
AN11: =SUM(AN7:AN10) -> 858746.85 | AO11: =SUM(AO7:AO10) -> 3465987.2 | AP11: =SUM(AP7:AP10) -> 7193942.3
B12: Total operations projects | G12: ='Hospital '!AL57 -> 5 | L12: ='Hospital '!AM57+'OEM-B2B '!AI40 -> 23 | Q12: ='OEM-B2B '!AN40 -> 15
B14: Feedim devices Wi-Fi | C14: ='Hospital '!T84 -> 10.214197 | D14: ='Hospital '!U84 -> 20.428394 | E14: ='Hospital '!V84 -> 48.855091 | F14: ='Hospital '!W84 -> 54.350538 | G14: ='Hospital '!X84 -> 138.56697 | H14: ='Hospital '!Y84 -> 159.00476 | I14: ='Hospital '!Z84 -> 223.5699 | J14: ='Hospital '!AA84 -> 288.13504 | ... Q14: ='Hospital '!AH84 -> 3050.2953
B15: Feedim 4G Wi-Fi | C15: =Homecare!AD18 -> 32.481534 | D15: =Homecare!AE18 -> 96.14802 | E15: =Homecare!AF18 -> 144.22203 | F15: =Homecare!AG18 -> 207.88852 | G15: =Homecare!AH18 -> 480.7401 | H15: =Homecare!AI18 -> 643.75366 | I15: =Homecare!AJ18 -> 643.75366 | J15: =Homecare!AK18 -> 643.75366 | ... Q15: =Homecare!AR18 -> 6036.5087
B16: Feedim OEM | C16: ='OEM-B2B '!W8 -> 0 | D16: ='OEM-B2B '!X8 -> 0 | E16: ='OEM-B2B '!Y8 -> 0 | F16: ='OEM-B2B '!Z8 -> 2000 | G16: ='OEM-B2B '!AA8 -> 2000 | H16: ='OEM-B2B '!AB8 -> 1250 | I16: ='OEM-B2B '!AC8 -> 1250 | J16: ='OEM-B2B '!AD8 -> 1250 | ... Q16: ='OEM-B2B '!AK8 -> 8000
B18: Total Feedim devices | C18: =SUM(C14:C16) -> 42.695731 | D18: =SUM(D14:D16) -> 116.57641 | E18: =SUM(E14:E16) -> 193.07712 | F18: =SUM(F14:F16) -> 2262.2391 | G18: =SUM(G14:G16) -> 2619.3071 | H18: =SUM(H14:H16) -> 2052.7584 | I18: =SUM(I14:I16) -> 2117.3236 | J18: =SUM(J14:J16) -> 2181.8887 | ... Q18: =SUM(Q14:Q16) -> 17086.804

Sheet Changes 8.2 -> 8.3
B3: Changes | C3: Y1 | D3: Y2 | E3: Y3 | F3: Total over 3 years | G3: Change impact | H3: Delta with previous base
B4: Baseline V8.2 | C4: 1046734.2 | D4: 3074489.2 | E4: 6285371.1 | F4: =SUM(C4:E4) -> 10406594
B5: +Oem boost (devices X2) | C5: 1221534.2 | D5: 3424089.2 | E5: 6809771.1 | F5: =SUM(C5:E5) -> 11455394 | G5: =F5-F4 -> 1048800 | H5: =F5-$F$4 -> 1048800
B6: +Baxter boost | C6: 1221534.2 | D6: 3559573.7 | E6: 7135740 | F6: =SUM(C6:E6) -> 11916848 | G6: =F6-F5 -> 461453.43 | H6: =F6-$F$4 -> 1510253.4
B7: +Boost total hospital (5-14-30) | C7: 1259401.4 | D7: 3894464.3 | E7: 7303529.3 | F7: =SUM(C7:E7) -> 12457395 | G7: =F7-F6 -> 540547.09 | H7: =F7-$F$4 -> 2050800.5
B8: +Boost Pricing hospital | C8: 1280043 | D8: 3999083.1 | E8: 7550600 | F8: =SUM(C8:E8) -> 12829726 | G8: =F8-F7 -> 372331.16 | H8: =F8-$F$4 -> 2423131.7
B9: +Mini Boost HC pricing (+1 cents over 500,000 | C9: 1280043 | D9: 3999083.1 | E9: 7592355.9 | F9: =SUM(C9:E9) -> 12871482 | G9: =F9-F8 -> 41755.915 | H9: =F9-$F$4 -> 2464887.6
C10: 1280043 | D10: 4086759.3 | E10: 7794998.8 | F10: =SUM(C10:E10) -> 13161801 | G10: =F10-F9 -> 290319.09 | H10: =F10-$F$4 -> 2755206.7
C11: 1280043 | D11: 4145959.3 | E11: 7972598.8 | F11: =SUM(C11:E11) -> 13398601 | G11: =F11-F10 -> 236800 | H11: =F11-$F$4 -> 2992006.7
C12: 1280043 | D12: 4321384.7 | E12: 8323885.7 | F12: =SUM(C12:E12) -> 13925313 | G12: =F12-F11 -> 526712.3 | H12: =F12-$F$4 -> 3518719

Sheet For BP 
B1: Y1 | F1: Total - Y1 | G1: Y2 | K1: Total - Y2 | L1: Y3 | P1: Total - Y3
B2: Q1 | C2: Q2 | D2: Q3 | E2: Q4 | F2: Y1 | G2: Q1 | H2: Q2 | I2: Q3 | J2: Q4 | K2: Y2 | L2: Q1 | M2: Q2 | N2: Q3 | O2: Q4 | P2: Y3
A3: Total Hospital Revenues | B3: 18654.53 | C3: 37309.06 | D3: 84721.127 | E3: 103375.66 | F3: 244060.37 | G3: 134152.43 | H3: 167843.45 | I3: 201534.47 | J3: 235225.49 | K3: 694796.8 | L3: 539323.65 | M3: 539323.65 | N3: 539323.65 | O3: 539323.65 | P3: 2082564.3
A4: Total Homecare Revenues | B4: 12018.168 | C4: 35574.767 | D4: 53362.151 | E4: 76918.751 | F4: 177873.84 | G4: 223388.86 | H4: 223388.86 | I4: 223388.86 | J4: 223388.86 | K4: 893555.42 | L4: 430465.22 | M4: 430465.22 | N4: 430465.22 | O4: 430465.22 | P4: 1721860.9
A5: Total OEM Feedim | B5: 0 | C5: 45000 | D5: 0 | E5: 219800 | F5: 264800 | G5: 87400 | H5: 132400 | I5: 219800 | J5: 219800 | K5: 659400 | L5: 219800 | M5: 219800 | N5: 219800 | O5: 394600 | P5: 1054000
A6: Baxter Partnership | B6: 0 | C6: 0 | D6: 0 | E6: 250000 | F6: 250000 | G6: 37895.343 | H6: 75790.686 | I6: 113686.03 | J6: 151581.37 | K6: 378953.43 | L6: 243468.95 | M6: 243468.95 | N6: 243468.95 | O6: 243468.95 | P6: 973875.81
A7: Operations | B7: 55000 | C7: 0 | D7: 55000 | E7: 0 | F7: 110000 | G7: 42625 | H7: 75625 | I7: 103125 | J7: 130625 | K7: 357500 | L7: 82500 | M7: 82500 | N7: 82500 | O7: 82500 | P7: 330000
A8: Grand Total | B8: 85672.697 | C8: 117883.83 | D8: 193083.28 | E8: 650094.41 | F8: 1046734.2 | G8: 525461.63 | H8: 675047.99 | I8: 861534.35 | J8: 960620.72 | K8: 2984205.7 | L8: 1515557.8 | M8: 1515557.8 | N8: 1515557.8 | O8: 1690357.8 | P8: 6162301
A10: Total Hospital Revenues | B10: =B3/1000 -> 18.65453 | C10: =C3/1000 -> 37.30906 | D10: =D3/1000 -> 84.721127 | E10: =E3/1000 -> 103.37566 | F10: =F3/1000 -> 244.06037 | G10: =G3/1000 -> 134.15243 | H10: =H3/1000 -> 167.84345 | I10: =I3/1000 -> 201.53447 | ... P10: =P3/1000 -> 2082.5643
A11: Total Homecare Revenues | B11: =B4/1000 -> 12.018168 | C11: =C4/1000 -> 35.574767 | D11: =D4/1000 -> 53.362151 | E11: =E4/1000 -> 76.918751 | F11: =F4/1000 -> 177.87384 | G11: =G4/1000 -> 223.38886 | H11: =H4/1000 -> 223.38886 | I11: =I4/1000 -> 223.38886 | ... P11: =P4/1000 -> 1721.8609
A12: Total OEM Feedim | B12: =B5/1000 -> 0 | C12: =C5/1000 -> 45 | D12: =D5/1000 -> 0 | E12: =E5/1000 -> 219.8 | F12: =F5/1000 -> 264.8 | G12: =G5/1000 -> 87.4 | H12: =H5/1000 -> 132.4 | I12: =I5/1000 -> 219.8 | ... P12: =P5/1000 -> 1054
A13: Baxter Partnership | B13: =B6/1000 -> 0 | C13: =C6/1000 -> 0 | D13: =D6/1000 -> 0 | E13: =E6/1000 -> 250 | F13: =F6/1000 -> 250 | G13: =G6/1000 -> 37.895343 | H13: =H6/1000 -> 75.790686 | I13: =I6/1000 -> 113.68603 | ... P13: =P6/1000 -> 973.87581
A14: Operations | B14: =B7/1000 -> 55 | C14: =C7/1000 -> 0 | D14: =D7/1000 -> 55 | E14: =E7/1000 -> 0 | F14: =F7/1000 -> 110 | G14: =G7/1000 -> 42.625 | H14: =H7/1000 -> 75.625 | I14: =I7/1000 -> 103.125 | ... P14: =P7/1000 -> 330
A15: Grand Total | B15: =B8/1000 -> 85.672697 | C15: =C8/1000 -> 117.88383 | D15: =D8/1000 -> 193.08328 | E15: =E8/1000 -> 650.09441 | F15: =F8/1000 -> 1046.7342 | G15: =G8/1000 -> 525.46163 | H15: =H8/1000 -> 675.04799 | I15: =I8/1000 -> 861.53435 | ... P15: =P8/1000 -> 6162.301
