Workbook

Sheet DATA Raw
A1: DATA RAW FOR MARKET POTENTIAL CALCULATION
B2: Min | C2: Max
A3: Market Growth % | B3: 8 | C3: 12
A5: Epidemiology – Allergies
A6: Dogs: 12–18% prevalence | B6: 12 | C6: 18
A7: Cats: 10–14% prevalence | B7: 10 | C7: 14
A8: Symptomatic cases tested | C8: 25 | G8: Distribution Strategy EU5
G9: • FR: Centravet, Alcyon, Coveto
A10: Pet Allergy Diagnostics Market | G10: • IT: Agrisan, Virbac Italy
A11: Global: $370M (2025) → $714M (2035) | G11: • ES: Distrivet, Covetrus
A12: KIT SALES PRICES € | B12: Min € | C12: Max € | G12: • DE: Alvetra & Werfft
A13: Lab IgE panels ELISA | B13: 85 | C13: 150 | G13: • BE: Ecuphar, Cenvet
A14: Rapid tests: | B14: 28 | C14: 45
A15: Dot arrays: | B15: 120 | C15: 180
A16: DIATECH Rapid Test | B16: 35 | C16: 39
A17: DIATECH Array | B17: 120 | C17: 150
A18: READER SALES PRICES €
A19: Unknown | B19: 1000
A21: CLINICS & MARKET POTENTIAL TESTS | B21: Clinics | C21: Tests Max
A22: France | B22: 7200 | C22: 270000
A23: Germany | B23: 10000 | C23: =+C22/B22*B23 -> 375000
A24: Italy | B24: 8500 | C24: =+C23/B23*B24 -> 318750
A25: Spain | B25: 7100 | C25: =+C24/B24*B25 -> 266250
A26: Belgium | B26: 750 | C26: =+C25/B25*B26 -> 28125
C27: =SUM(C22:C26) -> 1258125 | D27: TEST/Y
A32: Metric France | B32: Value | C32: Notes
A33: Number of veterinary clinics | B33: 7500 | C33: Ordre National des Vétérinaires (France)
A34: Dogs population (million) | B34: 7.6 | C34: FACCO / Kantar
A35: Cats population (million) | B35: 15.1 | C35: FACCO / Kantar
A36: Dermatology-related consultations (%) | B36: 15–20% | C36: Veterinary dermatology benchmarks
A37: Average test price (€) | B37: 35 | C37: JCHYTECH internal pricing
A38: Target gross margin (%) | B38: 60 | C38: Manufacturing & distribution model

Sheet SALES
A1: DIATECH
A2: Controls Sheet
A3: Amounts in €
B4: Year 1 | C4: Year 2 | D4: Year 3 | E4: Year 4 | F4: Year 5
A5: Assumptions for the Annual Period | B5: 2026 | C5: =+B5+1 -> 2027 | D5: =+C5+1 -> 2028 | E5: =+D5+1 -> 2029 | F5: =+E5+1 -> 2030
A6: Start Date of the Model | B6: 46174
A7: REVENUE ASSUMPTIONS
A9: Quarterly Sales Targets
A11: Thermic Units
A12: La 12T Belgium | B12: =SUM(#REF!) -> #REF! | C12: =SUM(#REF!) -> #REF! | D12: =SUM(#REF!) -> #REF! | E12: =SUM(#REF!) -> #REF! | F12: =SUM(#REF!) -> #REF!
A13: La 12T France | B13: =SUM(#REF!) -> #REF! | C13: =SUM(#REF!) -> #REF! | D13: =SUM(#REF!) -> #REF! | E13: =SUM(#REF!) -> #REF! | F13: =SUM(#REF!) -> #REF!
A14: La 12T Europe | B14: =SUM(#REF!) -> #REF! | C14: =SUM(#REF!) -> #REF! | D14: =SUM(#REF!) -> #REF! | E14: =SUM(#REF!) -> #REF! | F14: =SUM(#REF!) -> #REF!
A15: La 12T USA | B15: =SUM(#REF!) -> #REF! | C15: =SUM(#REF!) -> #REF! | D15: =SUM(#REF!) -> #REF! | E15: =SUM(#REF!) -> #REF! | F15: =SUM(#REF!) -> #REF!
A16: La 12T SE ASIA | B16: =SUM(#REF!) -> #REF! | C16: =SUM(#REF!) -> #REF! | D16: =SUM(#REF!) -> #REF! | E16: =SUM(#REF!) -> #REF! | F16: =SUM(#REF!) -> #REF!
B17: =SUM(B12:B16) -> #REF! | C17: =SUM(C12:C16) -> #REF! | D17: =SUM(D12:D16) -> #REF! | E17: =SUM(E12:E16) -> #REF! | F17: =SUM(F12:F16) -> #REF!
A18: Electric Units
A19: La 12E Belgium | B19: =SUM(#REF!) -> #REF! | C19: =SUM(#REF!) -> #REF! | D19: =SUM(#REF!) -> #REF! | E19: =SUM(#REF!) -> #REF! | F19: =SUM(#REF!) -> #REF!
A20: La 12E France | B20: =SUM(#REF!) -> #REF! | C20: =SUM(#REF!) -> #REF! | D20: =SUM(#REF!) -> #REF! | E20: =SUM(#REF!) -> #REF! | F20: =SUM(#REF!) -> #REF!
A21: La 12E Europe | B21: =SUM(#REF!) -> #REF! | C21: =SUM(#REF!) -> #REF! | D21: =SUM(#REF!) -> #REF! | E21: =SUM(#REF!) -> #REF! | F21: =SUM(#REF!) -> #REF!
A22: La 12E USA | B22: =SUM(#REF!) -> #REF! | C22: =SUM(#REF!) -> #REF! | D22: =SUM(#REF!) -> #REF! | E22: =SUM(#REF!) -> #REF! | F22: =SUM(#REF!) -> #REF!
A23: La 12E SE ASIA | B23: =SUM(#REF!) -> #REF! | C23: =SUM(#REF!) -> #REF! | D23: =SUM(#REF!) -> #REF! | E23: =SUM(#REF!) -> #REF! | F23: =SUM(#REF!) -> #REF!
B24: =SUM(B19:B23) -> #REF! | C24: =SUM(C19:C23) -> #REF! | D24: =SUM(D19:D23) -> #REF! | E24: =SUM(E19:E23) -> #REF! | F24: =SUM(F19:F23) -> #REF!
A25: KITS RAPID TEST
A26: Total Units Sold | B26: =SUM(B27:B29) -> 8100 | C26: =SUM(C27:C29) -> 23137.5 | D26: =SUM(D27:D29) -> 46275 | E26: =SUM(E27:E29) -> 76350 | F26: =SUM(F27:F29) -> 104805
A27: FRANCE | B27: =+'DATA Raw'!C22*0.03 -> 8100 | C27: =+B27*2 -> 16200 | D27: =+C27*2 -> 32400 | E27: =+D27*1.5 -> 48600 | F27: =+E27*1.3 -> 63180
A28: COUNTRIES 2 | C28: =+'DATA Raw'!C24*0.01 -> 3187.5 | D28: =+C28*2 -> 6375 | E28: =+D28*2 -> 12750 | F28: =+E28*1.5 -> 19125
A29: COUNTRIES 3 | B29: 0 | C29: =+'DATA Raw'!C23*0.01 -> 3750 | D29: =+C29*2 -> 7500 | E29: =+D29*2 -> 15000 | F29: =+E29*1.5 -> 22500
A30: Revenue generated | B30: =+B26*'DATA Raw'!$B$16 -> 283500 | C30: =+C26*'DATA Raw'!$B$16 -> 809812.5 | D30: =+D26*'DATA Raw'!$B$16 -> 1619625 | E30: =+E26*'DATA Raw'!$B$16 -> 2672250 | F30: =+F26*'DATA Raw'!$B$16 -> 3668175
A31: KITS ARRAY | B31: =SUM(B33:B35) -> 0 | C31: =SUM(C33:C35) -> 0 | D31: =SUM(D33:D35) -> 4860 | E31: =SUM(E32:E35) -> 27765 | F31: =SUM(F32:F35) -> 55530
A32: Total Units Sold | B32: =SUM(B33:B35) -> 0 | C32: =SUM(C33:C35) -> 0 | D32: =SUM(D33:D35) -> 4860 | E32: =SUM(E33:E35) -> 13882.5 | F32: =SUM(F33:F35) -> 27765
A33: FRANCE | D33: =+B27*0.6 -> 4860 | E33: =+C27*0.6 -> 9720 | F33: =+D27*0.6 -> 19440
A34: COUNTRIES 2 | D34: =+B28*0.6 -> 0 | E34: =+C28*0.6 -> 1912.5 | F34: =+D28*0.6 -> 3825
A35: COUNTRIES 3 | D35: =+B29*0.6 -> 0 | E35: =+C29*0.6 -> 2250 | F35: =+D29*0.6 -> 4500
A36: Revenue generated | F36: =SUM(F33:F35) -> 27765
A37: READERS | B37: 0 | C37: =B37*(1+C38) -> 0 | D37: =C37*(1+D38) -> 0 | E37: =D37*(1+E38) -> 0 | F37: =E37*(1+F38) -> 0
A38: Total Units Sold | C38: 0.05 | D38: 0.05 | E38: 0.05 | F38: 0.05
A39: FRANCE | B39: 0 | C39: =B39*(1+C40) -> 0 | D39: =C39*(1+D40) -> 0 | E39: =D39*(1+E40) -> 0 | F39: =E39*(1+F40) -> 0
A40: COUNTRIES 2 | C40: 0.05 | D40: 0.05 | E40: 0.05 | F40: 0.05
A41: COUNTRIES 3 | B41: 0.25 | C41: 0.25 | D41: 0.25 | E41: 0.25 | F41: 0.25
A42: Revenue generated | C42: NA | D42: NA | E42: NA | F42: NA
A43: Revenue generated | D43: =+D32*'DATA Raw'!$B$17 -> 583200 | E43: =+E32*'DATA Raw'!$B$17 -> 1665900 | F43: =+F32*'DATA Raw'!$B$17 -> 3331800 | G43: =+G32*'DATA Raw'!$B$17 -> 0
A44: READERS
A45: Total Units Sold | B45: =+B26/500 -> 16.2 | C45: =+C26/500 -> 46.275 | D45: =+D26/500 -> 92.55 | E45: =+E26/500 -> 152.7 | F45: =+F26/500 -> 209.61
A46: Revenue generated | B46: =+B45*'DATA Raw'!$B$19 -> 16200 | C46: =+C45*'DATA Raw'!$B$19 -> 46275 | D46: =+D45*'DATA Raw'!$B$19 -> 92550 | E46: =+E45*'DATA Raw'!$B$19 -> 152700 | F46: =+F45*'DATA Raw'!$B$19 -> 209610
A47: SERVICES
A48: Network and software customization | B48: NOT CONSIDERED
A49: Revenue generated | B49: NOT CONSIDERED
A51: TOTAL REVENUES | B51: =+B46+B43+B30 -> 299700 | C51: =+C46+C43+C30 -> 856087.5 | D51: =+D46+D43+D30 -> 2295375 | E51: =+E46+E43+E30 -> 4490850 | F51: =+F46+F43+F30 -> 7209585
A53: Distributor Margin | B53: 0.21
A55: Operating Expenses (OPEX) MONTHLY COST
A56: Cost of Sales Services as a % of sales
A62: Car rental | B62: 0 | C62: 300 | D62: =C62*(1+D63) -> 330 | E62: =D62*(1+E63) -> 379.5 | F62: =E62*(1+F63) -> 417.45
A63: Annual Increase % | C63: 0.1 | D63: 0.1 | E63: 0.15 | F63: 0.1
B64: =+B62*12 -> 0 | C64: =+C62*12 -> 3600 | D64: =+D62*12 -> 3960 | E64: =+E62*12 -> 4554 | F64: =+F62*12 -> 5009.4
A66: Commercial vehicle rentals | B66: 0 | C66: =B66*(1+C67) -> 0 | D66: 300 | E66: =D66*(1+E67) -> 345 | F66: =E66*(1+F67) -> 379.5
A67: Annual Increase % | C67: 0.1 | D67: 0.1 | E67: 0.15 | F67: 0.1
B68: =+B66*12 -> 0 | C68: =+C66*12 -> 0 | D68: =+D66*12 -> 3600 | E68: =+E66*12 -> 4140 | F68: =+F66*12 -> 4554
A70: Fuel | B70: 0 | C70: 300 | D70: =C70*(1+D71) -> 450 | E70: =D70*(1+E71) -> 517.5 | F70: =E70*(1+F71) -> 569.25
A71: Annual Increase % | C71: 0.1 | D71: 0.5 | E71: 0.15 | F71: 0.1
B72: =+B70*12 -> 0 | C72: =+C70*12 -> 3600 | D72: =+D70*12 -> 5400 | E72: =+E70*12 -> 6210 | F72: =+F70*12 -> 6831
A74: Travel costs (parking, etc.) | B74: 400 | C74: =B74*(1+C75) -> 500 | D74: =C74*(1+D75) -> 625 | E74: =D74*(1+E75) -> 687.5 | F74: =E74*(1+F75) -> 756.25
A75: Annual Increase % | C75: 0.25 | D75: 0.25 | E75: 0.1 | F75: 0.1
B76: =+B74*12 -> 4800 | C76: =+C74*12 -> 6000 | D76: =+D74*12 -> 7500 | E76: =+E74*12 -> 8250 | F76: =+F74*12 -> 9075
A78: Car insurance (omnium) | B78: 0 | C78: 120 | D78: =C78*(1+D79) -> 180 | E78: =D78*(1+E79) -> 207 | F78: =E78*(1+F79) -> 227.7
A79: Annual Increase % | C79: 0.1 | D79: 0.5 | E79: 0.15 | F79: 0.1
B80: =+B78*12 -> 0 | C80: =+C78*12 -> 1440 | D80: =+D78*12 -> 2160 | E80: =+E78*12 -> 2484 | F80: =+F78*12 -> 2732.4
A82: Events , Fairs , Missions | B82: 150 | C82: =B82*(1+C83) -> 300 | D82: =C82*(1+D83) -> 330 | E82: =D82*(1+E83) -> 379.5 | F82: 250
A83: Annual Increase % | C83: 1 | D83: 0.1 | E83: 0.15 | F83: 0.1
B84: =+B82*12 -> 1800 | C84: =+C82*12 -> 3600 | D84: =+D82*12 -> 3960 | E84: =+E82*12 -> 4554 | F84: =+F82*12 -> 3000
A86: Website | B86: 200 | C86: =B86*(1+C87) -> 250 | D86: =C86*(1+D87) -> 312.5 | E86: =D86*(1+E87) -> 359.375 | F86: =E86*(1+F87) -> 395.3125
A87: Annual Increase % | C87: 0.25 | D87: 0.25 | E87: 0.15 | F87: 0.1
B88: =+B86*12 -> 2400 | C88: =+C86*12 -> 3000 | D88: =+D86*12 -> 3750 | E88: =+E86*12 -> 4312.5 | F88: =+F86*12 -> 4743.75
A90: Advertising / SPONSORSHIP | B90: 100 | C90: =B90*(1+C91) -> 110 | D90: =C90*(1+D91) -> 121 | E90: =D90*(1+E91) -> 139.15 | F90: =E90*(1+F91) -> 153.065
A91: Annual Increase % | C91: 0.1 | D91: 0.1 | E91: 0.15 | F91: 0.1
B92: =+B90*12 -> 1200 | C92: =+C90*12 -> 1320 | D92: =+D90*12 -> 1452 | E92: =+E90*12 -> 1669.8 | F92: =+F90*12 -> 1836.78
A94: Building rent | B94: 200 | C94: 500 | D94: 1000 | E94: 2000 | F94: =E94*(1+F95) -> 2200
A95: Annual Increase % | C95: 0.1 | D95: 0.1 | E95: 0.15 | F95: 0.1
B96: =+B94*12 -> 2400 | C96: =+C94*12 -> 6000 | D96: =+D94*12 -> 12000 | E96: =+E94*12 -> 24000 | F96: =+F94*12 -> 26400
A98: Office General & Admin | B98: 250 | C98: =B98*(1+C99) -> 375 | D98: =C98*(1+D99) -> 562.5 | E98: =D98*(1+E99) -> 843.75 | F98: =E98*(1+F99) -> 1265.625
A99: Annual Increase % | C99: 0.5 | D99: 0.5 | E99: 0.5 | F99: 0.5
B100: =+B98*12 -> 3000 | C100: =+C98*12 -> 4500 | D100: =+D98*12 -> 6750 | E100: =+E98*12 -> 10125 | F100: =+F98*12 -> 15187.5
A102: Consulting fees STRATEGY / B2B / SALES ORGANIZATION | B102: 3000 | C102: =B102*(1+C103) -> 3600 | D102: =C102*(1+D103) -> 4140 | E102: =D102*(1+E103) -> 4761 | F102: =E102*(1+F103) -> 5475.15
A103: Annual Increase % | C103: 0.2 | D103: 0.15 | E103: 0.15 | F103: 0.15
B104: =+B102*12 -> 36000 | C104: =+C102*12 -> 43200 | D104: =+D102*12 -> 49680 | E104: =+E102*12 -> 57132 | F104: =+F102*12 -> 65701.8
A106: Consulting fees REGULATORY AFFAIRS / R&D | B106: 3000 | C106: =B106*(1+C107) -> 4050 | D106: =C106*(1+D107) -> 5467.5 | E106: =D106*(1+E107) -> 6287.625 | F106: =E106*(1+F107) -> 7230.7688
A107: Annual Increase % | C107: 0.35 | D107: 0.35 | E107: 0.15 | F107: 0.15
B108: =+B106*12 -> 36000 | C108: =+C106*12 -> 48600 | D108: =+D106*12 -> 65610 | E108: =+E106*12 -> 75451.5 | F108: =+F106*12 -> 86769.225
A110: Accounting fees | B110: 150 | C110: =B110*(1+C111) -> 300 | D110: =C110*(1+D111) -> 330 | E110: =D110*(1+E111) -> 363 | F110: =E110*(1+F111) -> 381.15
A111: Annual Increase % | C111: 1 | D111: 0.1 | E111: 0.1 | F111: 0.05
B112: =+B110*12 -> 1800 | C112: =+C110*12 -> 3600 | D112: =+D110*12 -> 3960 | E112: =+E110*12 -> 4356 | F112: =+F110*12 -> 4573.8
A114: Lawyer fees | B114: 100 | C114: =B114*(1+C115) -> 200 | D114: =C114*(1+D115) -> 210 | E114: =D114*(1+E115) -> 231 | F114: =E114*(1+F115) -> 242.55
A115: Annual Increase % | C115: 1 | D115: 0.05 | E115: 0.1 | F115: 0.05
B116: =+B114*12 -> 1200 | C116: =+C114*12 -> 2400 | D116: =+D114*12 -> 2520 | E116: =+E114*12 -> 2772 | F116: =+F114*12 -> 2910.6
A118: Coordination chinese partners | B118: 750 | C118: =B118*(1+C119) -> 787.5 | D118: =C118*(1+D119) -> 826.875 | E118: =D118*(1+E119) -> 909.5625 | F118: =E118*(1+F119) -> 955.04063
A119: Annual Increase % | C119: 0.05 | D119: 0.05 | E119: 0.1 | F119: 0.05
B120: =+B118*12 -> 9000 | C120: =+C118*12 -> 9450 | D120: =+D118*12 -> 9922.5 | E120: =+E118*12 -> 10914.75 | F120: =+F118*12 -> 11460.488
A122: Professional contribution | B122: 30 | C122: =B122*(1+C123) -> 31.5 | D122: =C122*(1+D123) -> 33.075 | E122: =D122*(1+E123) -> 36.3825 | F122: =E122*(1+F123) -> 38.201625
A123: Annual Increase % | C123: 0.05 | D123: 0.05 | E123: 0.1 | F123: 0.05
B124: =+B122*12 -> 360 | C124: =+C122*12 -> 378 | D124: =+D122*12 -> 396.9 | E124: =+E122*12 -> 436.59 | F124: =+F122*12 -> 458.4195
A126: Monthly TOTAL | B126: =+B122+B118+B114+B110+B106+B102+B98+B94+B90+B86+B82+B78+B74+B70+B66+B62 -> 8330 | C126: =+C122+C118+C114+C110+C106+C102+C98+C94+C90+C86+C82+C78+C74+C70+C66+C62 -> 11724 | D126: =+D122+D118+D114+D110+D106+D102+D98+D94+D90+D86+D82+D78+D74+D70+D66+D62 -> 15218.45 | E126: =+E122+E118+E114+E110+E106+E102+E98+E94+E90+E86+E82+E78+E74+E70+E66+E62 -> 18446.845 | F126: =+F122+F118+F114+F110+F106+F102+F98+F94+F90+F86+F82+F78+F74+F70+F66+F62 -> 20937.014
...

Sheet Expense Assumptions
A1: DIATECH
A2: Expense Assumptions Sheet
A3: Amounts in €
A5: Assumptions for the Monthly Period
A7: Cost Of Goods Sold (COGS)
B8: Year 1 | C8: Year 2 | D8: Year 3 | E8: Year 4 | F8: Year 5
A9: Thermic Units Sold | B9: 2026 | C9: =+B9+1 -> 2027 | D9: =+C9+1 -> 2028 | E9: =+D9+1 -> 2029 | F9: =+E9+1 -> 2030
A10: Thermic Unit Average Cost
A11: Distrib Costs
A12: Cost of sales for Thermic Units
A14: Electric Units Sold
A15: Electric Unit Average Cost
A16: Distrib Costs
A17: Cost of sales for Electric Units
A19: Cost of Sales for Spare Parts and Aftermarket Services as a % of sales
A20: Distrib Costs or royalties
A21: Cost of Sales for Spare Parts and Aftermarket Services
A23: PRODUCTS
A24: Cost Of Rapid TEST | B24: =+SALES!B30*0.5 -> 141750 | C24: =+SALES!C30*0.5 -> 404906.25 | D24: =+SALES!D30*0.5 -> 809812.5 | E24: =+SALES!E30*0.5 -> 1336125 | F24: =+SALES!F30*0.5 -> 1834087.5
A25: cost of Array TEST | B25: =+SALES!B43*0.55 -> 0 | C25: =+SALES!C43*0.55 -> 0 | D25: =+SALES!D43*0.55 -> 320760 | E25: =+SALES!E43*0.55 -> 916245 | F25: =+SALES!F43*0.55 -> 1832490
A26: Cost of Readers | B26: =+SALES!B46*0.5 -> 8100 | C26: =+SALES!C46*0.5 -> 23137.5 | D26: =+SALES!D46*0.5 -> 46275 | E26: =+SALES!E46*0.5 -> 76350 | F26: =+SALES!F46*0.5 -> 104805
A27: Cost of Sales | B27: =SUM(B24:B26) -> 149850 | C27: =SUM(C24:C26) -> 428043.75 | D27: =SUM(D24:D26) -> 1176847.5 | E27: =SUM(E24:E26) -> 2328720 | F27: =SUM(F24:F26) -> 3771382.5
A30: Operating Expenses (OPEX)
A32: Car rental | B32: =+SALES!B64 -> 0 | C32: =+SALES!C64 -> 3600 | D32: =+SALES!D64 -> 3960 | E32: =+SALES!E64 -> 4554 | F32: =+SALES!F64 -> 5009.4
A33: Commercial vehicle rentals | B33: =+SALES!B68 -> 0 | C33: =+SALES!C68 -> 0 | D33: =+SALES!D68 -> 3600 | E33: =+SALES!E68 -> 4140 | F33: =+SALES!F68 -> 4554
A34: Fuel | B34: =+SALES!B70 -> 0 | C34: =+SALES!C72 -> 3600 | D34: =+SALES!D72 -> 5400 | E34: =+SALES!E72 -> 6210 | F34: =+SALES!F72 -> 6831
A35: Travel costs (parking, etc.) | B35: =+SALES!B76 -> 4800 | C35: =+SALES!C76 -> 6000 | D35: =+SALES!D76 -> 7500 | E35: =+SALES!E76 -> 8250 | F35: =+SALES!F76 -> 9075
A36: Car insurance (omnium) | B36: =+SALES!B80 -> 0 | C36: =+SALES!C80 -> 1440 | D36: =+SALES!D80 -> 2160 | E36: =+SALES!E80 -> 2484 | F36: =+SALES!F80 -> 2732.4
A37: Events , Fairs , Missions | B37: =+SALES!B84 -> 1800 | C37: =+SALES!C84 -> 3600 | D37: =+SALES!D84 -> 3960 | E37: =+SALES!E84 -> 4554 | F37: =+SALES!F84 -> 3000
A38: Website | B38: =+SALES!B88 -> 2400 | C38: =+SALES!C88 -> 3000 | D38: =+SALES!D88 -> 3750 | E38: =+SALES!E88 -> 4312.5 | F38: =+SALES!F88 -> 4743.75
A39: Advertising / SPONSORSHIP | B39: =+SALES!B92 -> 1200 | C39: =+SALES!C92 -> 1320 | D39: =+SALES!D92 -> 1452 | E39: =+SALES!E92 -> 1669.8 | F39: =+SALES!F92 -> 1836.78
A40: Building rent | B40: =+SALES!B96 -> 2400 | C40: =+SALES!C96 -> 6000 | D40: =+SALES!D96 -> 12000 | E40: =+SALES!E96 -> 24000 | F40: =+SALES!F96 -> 26400
A41: Office General & Admin | B41: =+SALES!B100 -> 3000 | C41: =+SALES!C100 -> 4500 | D41: =+SALES!D100 -> 6750 | E41: =+SALES!E100 -> 10125 | F41: =+SALES!F100 -> 15187.5
A42: Consulting fees 1 (JCH) | B42: =+SALES!B104 -> 36000 | C42: =+SALES!C104 -> 43200 | D42: =+SALES!D104 -> 49680 | E42: =+SALES!E104 -> 57132 | F42: =+SALES!F104 -> 65701.8
A43: Consulting fees 2 (AB) | B43: =+SALES!B108 -> 36000 | C43: =+SALES!C108 -> 48600 | D43: =+SALES!D108 -> 65610 | E43: =+SALES!E108 -> 75451.5 | F43: =+SALES!F108 -> 86769.225
A44: Accounting fees | B44: =+SALES!B112 -> 1800 | C44: =+SALES!C112 -> 3600 | D44: =+SALES!D112 -> 3960 | E44: =+SALES!E112 -> 4356 | F44: =+SALES!F112 -> 4573.8
A45: Lawyer fees | B45: =+SALES!B116 -> 1200 | C45: =+SALES!C116 -> 2400 | D45: =+SALES!D116 -> 2520 | E45: =+SALES!E116 -> 2772 | F45: =+SALES!F116 -> 2910.6
A46: Coordination chinese partners | B46: =+SALES!B120 -> 9000 | C46: =+SALES!C120 -> 9450 | D46: =+SALES!D120 -> 9922.5 | E46: =+SALES!E120 -> 10914.75 | F46: =+SALES!F120 -> 11460.488
A47: Professional contribution | B47: =+SALES!B124 -> 360 | C47: =+SALES!C124 -> 378 | D47: =+SALES!D124 -> 396.9 | E47: =+SALES!E124 -> 436.59 | F47: =+SALES!F124 -> 458.4195
A48: Regulatory including 9001
A49: Overheads | B49: 0 | C49: 0 | D49: 0 | E49: 0 | F49: 0
A50: Total Operating Expenses | B50: =SUM(B32:B49) -> 99960 | C50: =SUM(C32:C49) -> 140688 | D50: =SUM(D32:D49) -> 182621.4 | E50: =SUM(E32:E49) -> 221362.14 | F50: =SUM(F32:F49) -> 251244.16
A53: PAYROLL ASSUMPTIONS
A55: Management Team
A56: Chief Technical Officer - CXO | B56: 0 | C56: =+SALES!B137*13*1.5 -> 0 | D56: =+SALES!C137*13*1.5 -> 58500 | E56: =+SALES!D137*13*1.5 -> 117000 | F56: =+SALES!E137*13*1.5 -> 120510
A57: Board of Directors | B57: 0 | C57: 7000 | D57: =+C57*1.1 -> 7700 | E57: =+D57*1.1 -> 8470 | F57: =+E57*1.1 -> 9317
A58: Production Team
A59: Production and QC Technician | B59: 0 | C59: =+SALES!B141*13*1.5 -> 0 | D59: =+SALES!C141*13*1.5 -> 0 | E59: =+SALES!D141*13*1.5 -> 87750 | F59: =+SALES!E141*13*1.5 -> 90382.5
A60: QC Technician | B60: 0 | C60: =+SALES!B142*13*1.5 -> 0 | D60: =+SALES!C142*13*1.5 -> 0 | E60: =+SALES!D142*13*1.5 -> 0 | F60: =+SALES!E142*13*1.5 -> 90382.5
A61: Quality Insurance | B61: 0 | C61: =+SALES!B143*13*1.5 -> 0 | D61: =+SALES!C143*13*1.5 -> 0 | E61: =+SALES!D143*13*1.5 -> 0 | F61: =+SALES!E143*13*1.5 -> 58500
A62: Secretary Logistics/ordering etc | C62: =+SALES!C144*12*1.5 -> 72000 | D62: =+SALES!D144*12*1.5 -> 74160 | E62: =+SALES!E144*12*1.5 -> 76384.8 | F62: =+SALES!F144*12*1.5 -> 78676.344
A63: Sales Team
A64: Sales Director (consultant partially paid by % on sales (50% of Revenu) | B64: 0 | C64: =+SALES!C147*12 -> 60000 | D64: =+SALES!D147*12 -> 75000 | E64: =+SALES!E147*12 -> 93750 | F64: =+SALES!F147*12 -> 117187.5
A65: Sales Director (consultant partially paid by % on sales (25% of Revenu) | B65: 0 | C65: =+SALES!C148*12 -> 0 | D65: =+SALES!D148*12 -> 60000 | E65: =+SALES!E148*12 -> 66000 | F65: =+SALES!F148*12 -> 72600
A66: Marketing Team
A67: Marketing Manager | B67: =+SALES!B151*13*1.05 -> 0 | C67: =+SALES!C151*13*1.05 -> 0 | D67: =+SALES!D151*13*1.05 -> 0 | E67: =+SALES!E151*13*1.05 -> 0 | F67: =+SALES!F151*13*1.05 -> 81900
A68: Product Development Team
A69: IT Project Manager (consultant) | B69: =+SALES!B154*12 -> 0 | C69: =+SALES!C154*12 -> 24000 | D69: =+SALES!D154*12 -> 36000 | E69: =+SALES!E154*12 -> 48000 | F69: =+SALES!F154*12 -> 60000
B71: =+B69+B67+B65+B64+B61+B60+B59+B57+B56 -> 0 | C71: =+C69+C67+C65+C64+C61+C60+C59+C57+C56 -> 91000 | D71: =+D69+D67+D65+D64+D61+D60+D59+D57+D56 -> 237200 | E71: =+E69+E67+E65+E64+E61+E60+E59+E57+E56 -> 420970 | F71: =+F69+F67+F65+F64+F61+F60+F59+F57+F56 -> 700779.5

Sheet Annual P&L
A1: DIATECH
A2: Compte de résultat annuel Montants en € | B2: Annual Profit & Loss Statement
B3: Amounts in €
A4: Hypothèses pour la période annuelle | B4: Assumptions for the Annual Period | C4: Y1 | D4: Y2 | E4: Y3 | F4: Y4 | G4: Y5
A5: SIM
A6: Services | B6: Thermic Unit Sales | C6: =SUMIF(#REF!,C$4,#REF!) -> #REF! | D6: =SUMIF(#REF!,D$4,#REF!) -> #REF! | E6: =SUMIF(#REF!,E$4,#REF!) -> #REF! | F6: =SUMIF(#REF!,F$4,#REF!) -> #REF! | G6: =SUMIF(#REF!,G$4,#REF!) -> #REF!
A7: Subventions à la R&D | B7: Electric Unit Sales | C7: =SUMIF(#REF!,C$4,#REF!) -> #REF! | D7: =SUMIF(#REF!,D$4,#REF!) -> #REF! | E7: =SUMIF(#REF!,E$4,#REF!) -> #REF! | F7: =SUMIF(#REF!,F$4,#REF!) -> #REF! | G7: =SUMIF(#REF!,G$4,#REF!) -> #REF!
A8: Chiffre d'affaires total | B8: Spare Parts and Aftermarket Services | C8: =SUMIF(#REF!,C$4,#REF!) -> #REF! | D8: =SUMIF(#REF!,D$4,#REF!) -> #REF! | E8: =SUMIF(#REF!,E$4,#REF!) -> #REF! | F8: =SUMIF(#REF!,F$4,#REF!) -> #REF! | G8: =SUMIF(#REF!,G$4,#REF!) -> #REF!
A10: Chiffre d'affaires total | B10: Total Revenue | C10: =+SALES!B51 -> 299700 | D10: =+SALES!C51 -> 856087.5 | E10: =+SALES!D51 -> 2295375 | F10: =+SALES!E51 -> 4490850 | G10: =+SALES!F51 -> 7209585
A12: SIM | B12: Thermic Units | C12: =SUMIF(#REF!,C$4,#REF!) -> #REF! | D12: =SUMIF(#REF!,D$4,#REF!) -> #REF! | E12: =SUMIF(#REF!,E$4,#REF!) -> #REF! | F12: =SUMIF(#REF!,F$4,#REF!) -> #REF! | G12: =SUMIF(#REF!,G$4,#REF!) -> #REF!
A13: Services | B13: Electric Units | C13: =SUMIF(#REF!,C$4,#REF!) -> #REF! | D13: =SUMIF(#REF!,D$4,#REF!) -> #REF! | E13: =SUMIF(#REF!,E$4,#REF!) -> #REF! | F13: =SUMIF(#REF!,F$4,#REF!) -> #REF! | G13: =SUMIF(#REF!,G$4,#REF!) -> #REF!
A14: Subventions à la R&D | B14: Spare Parts and Aftermarket Services | C14: =SUMIF(#REF!,C$4,#REF!) -> #REF! | D14: =SUMIF(#REF!,D$4,#REF!) -> #REF! | E14: =SUMIF(#REF!,E$4,#REF!) -> #REF! | F14: =SUMIF(#REF!,F$4,#REF!) -> #REF! | G14: =SUMIF(#REF!,G$4,#REF!) -> #REF!
A15: Coût total des marchandises vendues | B15: Total COGS | C15: =+'Expense Assumptions'!B27 -> 149850 | D15: =+'Expense Assumptions'!C27 -> 428043.75 | E15: =+'Expense Assumptions'!D27 -> 1176847.5 | F15: =+'Expense Assumptions'!E27 -> 2328720 | G15: =+'Expense Assumptions'!F27 -> 3771382.5
A17: Bénéfice brut | B17: Gross Profit | C17: =C10-C15 -> 149850 | D17: =D10-D15 -> 428043.75 | E17: =E10-E15 -> 1118527.5 | F17: =F10-F15 -> 2162130 | G17: =G10-G15 -> 3438202.5
A20: Total des dépenses d'exploitation | B20: Total Operating Expenses | C20: =+SALES!B127 -> 99960 | D20: =+SALES!C127 -> 140688 | E20: =+SALES!D127 -> 182621.4 | F20: =+SALES!E127 -> 221362.14 | G20: =+SALES!F127 -> 251244.16
A21: dépenses salariales | B21: Payroll Expenses | C21: =+'Expense Assumptions'!B71 -> 0 | D21: =+'Expense Assumptions'!C71 -> 91000 | E21: =+'Expense Assumptions'!D71 -> 237200 | F21: =+'Expense Assumptions'!E71 -> 420970 | G21: =+'Expense Assumptions'!F71 -> 700779.5
A23: Total des dépenses d'exploitation, y compris la masse salariale | B23: Total Operating Expenses including Payroll | C23: =+C21+C20 -> 99960 | D23: =+D21+D20 -> 231688 | E23: =+E21+E20 -> 419821.4 | F23: =+F21+F20 -> 642332.14 | G23: =+G21+G20 -> 952023.66
A25: EBITDA | B25: EBITDA | C25: =+C17-C23 -> 49890 | D25: =+D17-D23 -> 196355.75 | E25: =+E17-E23 -> 698706.1 | F25: =+F17-F23 -> 1519797.9 | G25: =+G17-G23 -> 2486178.8
A27: Amortissement et dépréciation | B27: Depreciation & Amortization
A28: Intérêt | B28: Interest
A30: Bénéfice avant impôt (BAI) | B30: Profit Before Tax (PBT) | C30: =+C25-C27-C28 -> 49890 | D30: =+D25-D27-D28 -> 196355.75 | E30: =+E25-E27-E28 -> 698706.1 | F30: =+F25-F27-F28 -> 1519797.9 | G30: =+G25-G27-G28 -> 2486178.8
