Workbook

Sheet Suivi
A1: Phase | B1: Tâches principales | C1: Livrable | D1: Responsable(s) | E1: Calendar Duration | F1: Work Day ex-Dim3's | G1: Work Day Lisam | H1: Commentaires / Dépendances | I1: État d'avancement | J1: Date début (plan) | K1: Date fin (plan) | L1: Jours de prestations (estimé) | M1: Jours de prestations (réel)
A2: 1. DATA room | B2: Création Data Room | C2: Data Room Accessible to candidate withNDA | D2: JCHYTECH/STRIGO+Support | E2: 7 | F2: 3 | H2: NDA | I2: À faire
A3: 2. Know how Candidate explained to ex-Dim3 | B3: It is mandatory for IT ex-Dim3 to understand know how of candidate to prepare effciently the next step | C3: Meeting | D3: Coo STRIGO/Support/JCHYTECH | E3: 1 | F3: 1.2 | H3: MANDATORY | I3: À faire
A4: 2.IT Structure / tools / code container | B4: Identification of the IT assets concerned (servers, licenses, data, applications, etc.) | C4: Report of IT assets/Pitfalls and Gap | D4: coo JCHYTECH/STRIGO+Support | E4: 15 | F4: 10 | H4: Report of IT assets/Pitfalls and Gap | I4: À faire | K4: 07/10/2025
B5: The identification of the IT assets concerned is a critical step in ensuring a smooth and transparent transition of technological resources. This process involves compiling a detailed inventory of all relevant components, including servers, software licenses, databases, applications, and associated data. Each asset must be clearly documented to establish ownership, assess its operational status, and determine dependencies with other systems. Such identification not only facilitates effective transfer or integration of infrastructure but also ensures compliance with security, licensing, and data protection requirements. Ultimately, a precise understanding of the IT assets in scope forms the foundation for successful project planning, risk management, and long-term system continuity.
A6: 3.Démo non active & CHU Demo | B6: Clarify understanding of Platform and prepare analyse of data room | C6: Demos done | D6: JCHYTECH | E6: 2 | F6: 2 | I6: À faire
A7: 4. Analysis of strategies markets / sales / business models | C7: Report with prospective BP | D7: Facilytis + Jchytech | E7: 2 | F7: 3 | I7: À faire
A8: 4. Analyse Data Room / Q&A | B8: By Candidate internal a Dim3 analysis & Q&A meetings withex-Dim3 | D8: Facilytis + Jchytech/Strigo | E8: 5 | F8: 2 | H8: Audit express requis avant offre finale | I8: À faire | K8: 08/10/2025
A9: 5. Report on feasability/Swot by Candidate | E9: 5 | I9: À faire
E10: =SUBTOTAL(109,E2:E9) -> 37 | F10: =SUBTOTAL(109,F2:F9) -> 21.2
A11: GO NON GO TWO WAYS | D11: Lisam
A12: 1. Préparation | B12: Maintien opérationnel temporaire des serveurs et services critiques | I12: À faire | K12: Immédiat
A13: 2. Accès et sécurité | B13: Mise en place d’un accès sécurisé et contrôlé aux systèmes (VPN, comptes restreints) | I13: À faire | K13: 09/10/2025
A14: 2. Accès et sécurité | B14: Vérification des droits de propriété et de transfert des licences logicielles | I14: À faire | K14: 10/10/2025
A15: 3. Collaboration avec anciens dirigeants | B15: Organisation de sessions techniques entre ex-CEO / CTO et Facilitys | I15: À faire | K15: 09–12/10/2025
A16: 3. Collaboration avec anciens dirigeants | B16: Préparation d’un protocole de collaboration (ou contrat de prestation) pour les anciens dirigeants | I16: À faire | K16: 12/10/2025
A17: 4. Proposition d’acquisition | B17: Rédaction de la proposition d’achat des actifs IT | I17: À faire | K17: 13/10/2025
A18: 4. Proposition d’acquisition | B18: Transmission officielle de la proposition au liquidateur | I18: À faire | K18: 14/10/2025
A19: 5. Phase de transfert | B19: Validation du protocole de cession et calendrier technique | I19: À faire | K19: 15–18/10/2025
A20: 5. Phase de transfert | B20: Transfert effectif des actifs (données, serveurs, sauvegardes, codes source, etc.) | I20: À faire | K20: 20–25/10/2025
A21: 6. Clôture et redémarrage | B21: Reconnexion des systèmes transférés et test de fonctionnement | I21: À faire | K21: Fin octobre 2025
A22: 6. Clôture et redémarrage | B22: Rédaction d’un rapport de clôture de la reprise IT | I22: À faire | K22: 31/10/2025

Sheet Intervenants
A1: Nom | B1: Rôle | C1: Société | D1: Téléphone | E1: Email | F1: Disponibilité (dates/horaires) | G1: TJM (€) | H1: Jours prévus | I1: Jours réalisés | J1: Coût estimé (€) | K1: Coût réel (€) | L1: Commentaires

Sheet Listes
A1: Etat_list | B1: Priorité_list | C1: Risque_list | D1: GoNoGo_list
A2: À faire | B2: Haute | C2: H | D2: Go
A3: En cours | B3: Moyenne | C3: M | D3: No-Go
A4: Terminé | B4: Basse | C4: B

Sheet Dashboard
A1: Plan de transfert IT – Tableau de bord
A3: Indicateur | B3: Valeur | D3: Statut | E3: Nombre
A4: Total tâches | B4: =COUNTA(Suivi!A2:A22) -> 19 | D4: À faire | E4: =COUNTIF(Suivi!I2:I22,"À faire") -> 18
A5: Tâches terminées | B5: =COUNTIF(Suivi!I2:I22,"Terminé") -> 0 | D5: En cours | E5: =COUNTIF(Suivi!I2:I22,"En cours") -> 0
A6: Tâches en cours | B6: =COUNTIF(Suivi!I2:I22,"En cours") -> 0 | D6: Terminé | E6: =COUNTIF(Suivi!I2:I22,"Terminé") -> 0
A7: Tâches à faire | B7: =COUNTIF(Suivi!I2:I22,"À faire") -> 18
A8: % d’avancement global | B8: =IFERROR(AVERAGE(Suivi!#REF!),0) -> 0
A9: Points Go | B9: =COUNTIF(Suivi!#REF!,"Go") -> #REF! | D9: Risque | E9: Nombre
A10: Points No-Go | B10: =COUNTIF(Suivi!#REF!,"No-Go") -> #REF! | D10: H | E10: =COUNTIF(Suivi!#REF!,"H") -> #REF!
A11: Risques élevés (H) | B11: =COUNTIF(Suivi!#REF!,"H") -> #REF! | D11: M | E11: =COUNTIF(Suivi!#REF!,"M") -> #REF!
A12: Risques moyens (M) | B12: =COUNTIF(Suivi!#REF!,"M") -> #REF! | D12: B | E12: =COUNTIF(Suivi!#REF!,"B") -> #REF!
A13: Risques bas (B) | B13: =COUNTIF(Suivi!#REF!,"B") -> #REF!
A14: Jours de prestations – estimés | B14: =SUM(Suivi!L2:L22) -> 0
A15: Jours de prestations – réels | B15: =SUM(Suivi!M2:M22) -> 0
A16: Coûts internes – estimés (€) | B16: =SUM(Suivi!#REF!) -> #REF!
A17: Coûts internes – réels (€) | B17: =SUM(Suivi!#REF!) -> #REF!
A18: Frais externes – estimés (€) | B18: =SUM(Suivi!#REF!) -> #REF!
A19: Frais externes – réels (€) | B19: =SUM(Suivi!#REF!) -> #REF!
A20: Budget total estimé (€) | B20: =SUM(Suivi!#REF!) -> #REF!
A21: Écart coût total (réel - estimé) | B21: =SUM(Suivi!#REF!)+SUM(Suivi!#REF!)-SUM(Suivi!#REF!)-SUM(Suivi!#REF!) -> #REF!
